Workbook

Sheet README
A1: PATENT PORTFOLIO BUNDLING TEMPLATE
A2: A technical-attribute-based framework for grouping patents into sellable bundles
A4: PURPOSE
A5: Score each patent across technical attributes, then auto-route patents into one or more sellable bundle types based on logical rules. The framework is purely technical — no valuation, no pricing.
A7: SHEETS IN THIS WORKBOOK
A8: 1. README — This page. Overview and instructions.
A9: 2. Attribute Dictionary — Definitions and scoring scales for every attribute.
A10: 3. Patent Portfolio — Master data sheet. One row per patent. Fill this in.
A11: 4. Bundle Rules — The 21 bundle types and the routing rule that qualifies a patent for each.
A12: 5. Bundle Assignment — Auto-computed: which bundles each patent qualifies for.
A13: 6. Bundle Quality Scorecard — Auto-computed: quality indicators per bundle.
A14: 7. Sample Bundles — Worked examples showing how three bundles look in practice.
... A65: v6 ADDITION — PatSeer Import Sheet • New sheet "PatSeer Import" (second sheet, after README). • Zone 1: Column Mapping Table (rows 7-33): maps 25 PatSeer export column headers to v5 attribute codes with transform rules. Edit col A to match your actual PatSeer headers. • Zone 2: Paste Area (cols F-AE, rows 40+): paste your PatSeer Excel export here directly. Supports up to 200 patents. Cols A-E reserved for manual input helpers (row number, notes, E3 Continuation override, E2 override, E5 override). • Zone 3: Mapped Output + Bundle Results (cols AF onwards): auto-populates 42 v5 attributes via transform formulas. Amber cells = manual/AI scoring required. Completeness % column shows how complete each patent record is (0-42 attributes filled). 33 Bundle columns show TRUE/FALSE qualification respecting the active Configuration preset. Total column counts qualifying bundles per patent. • Conditional formatting: TRUE=green, FALSE=light-red in bundle cols; completeness traffic-light (green ≥60%, amber 30-60%, red <30%). • Workflow: paste PatSeer export → review amber cells → score manually or use AI prompts → copy completed rows to Patent Portfolio sheet for full Scorecard analysis.

Sheet PatSeer Import
A1: PATSEER IMPORT — Paste your PatSeer export, get bundle results instantly
A2: v6 Addition · Companion to PatSeer Standard/Premier/Pro X export · Outright sale context — short lifecycle portfolios
A4: Step 1 | B4: In PatSeer, export your portfolio as Excel/CSV. Select these field groups: Bibliographic + Parties + Classifications + Family + Citations + Other/Scores.
A5: Step 2 | B5: In the Paste Area (rows 40+), paste your PatSeer export starting at the correct column headers (row 39). Column order must match row 39.
A6: Step 3 | B6: The Mapped Output (right of paste area) auto-populates attributes derived from PatSeer. Amber-highlighted cells = manual scoring required.
A7: Step 4 | B7: Bundle Results columns show TRUE/FALSE qualification per bundle, respecting the active Configuration preset. Review and copy useful patents to Patent Portfolio.
A8: Step 5 | B8: The Column Mapping Table (rows 7-36 below) maps each PatSeer field to its v5 attribute. Edit col A if your PatSeer headers differ — all formulas update automatically.
A10: COLUMN MAPPING TABLE — Edit Col A if your PatSeer headers differ. All formulas update automatically.
A11: PatSeer Export Column Header | B11: Maps to v5 Attribute | C11: Transform Rule | D11: Notes / Instructions
A12: Publication Number | B12: Patent ID | C12: direct | D12: Use as Patent ID; or create your own ID in col A
A13: Title | B13: A1 (derived) | C13: direct | D13: Patent title — used as Title in Patent Portfolio
A14: Assignee (Current) | B14: — | C14: direct | D14: Current owner — stored in paste area; not a v5 attribute
A15: Inventor Names | B15: — | C15: direct | D15: Inventors — stored in paste area; not a v5 attribute
A16: Filing Date | B16: — | C16: year_from_date | D16: Filing year — informational only
A17: Publication Date | B17: — | C17: year_from_date | D17: Publication year — informational only
A18: Estimated Expiry Date | B18: E4 (derived) | C18: expiry_to_yrs | D18: Converted to remaining term in years from today
A19: Remaining Life (Years) | B19: E4 | C19: numeric | D19: Direct remaining term — preferred over Expiry Date if available
A20: Legal Status | B20: E2 | C20: legal_status_map | D20: Granted / Pending / Expired → maps to E2 Prosecution field
A21: Maintenance Status | B21: E5 | C21: direct | D21: Active / Lapsed / Abandoned → E5 Maint. status
A22: IPC (Main) | B22: A1 (derived) | C22: direct | D22: Main IPC → used to derive A1 Primary domain via CPC→domain lookup
... A35: Kind Code | B35: E3 (derived) | C35: direct | D35: Kind code (B2 / C2 = granted; A1/A2 = application) → E3 hint
A36: PASTE AREA — Paste your PatSeer Excel export here (row 40 onwards). Header row 39 must match your export column names exactly. | AE36: MAPPED OUTPUT — Auto-populated from Paste Area via Column Mapping. Amber = manual scoring required. Bundle columns respect active Configuration preset.
A37: → How to paste: In PatSeer export Excel, select ALL data including header row 1. Copy. Click cell F40 in this sheet. Paste. Then clear row 40 if it duplicated the header. | AE37: 42 Attributes — PatSeer-derived fields auto-fill; AMBER cells need manual / AI scoring (see AI_Prompts_for_Attribute_Scoring.md) | BU37: Complete-ness | BW37: 33 Bundle Qualifications — TRUE = patent qualifies (respects Configuration sheet preset)
A38: → Paste area supports up to 200 patents (rows 40–239). For more, add rows and extend formulas in the Mapped Output zone. | AE38: ID / Title | AG38: A. Technology | AL38: B. Standards | AO38: C. Claims | AS38: D. Detectability | AV38: E. Family/Life | BA38: F. Geography | BD38: G. Strategic | BG38: H. Quality | BQ38: I. Market
A39: # | B39: Your Notes | C39: E3 Continuation (Yes/No) | D39: E2 Prosecution Override | E39: E5 Maint. Status Override | F39: Publication Number | G39: Title | H39: Assignee (Current) | I39: Inventor Names | J39: Filing Date | K39: Publication Date | L39: Estimated Expiry Date | M39: Remaining Life (Years) | N39: Legal Status | O39: Maintenance Status | P39: IPC (Main) | Q39: IPC (All) | R39: CPC (Main) | S39: CPC (All) | T39: Simple Family Size | U39: Simple Family Members | V39: Extended Family Size | W39: Forward Citation Count | X39: Backward Citation Count | Y39: Independent Claim Count | Z39: Abstract | AA39: Technology Domain | AB39: Technology Sub-Domain | AC39: Kind Code | AD39: Litigation / PTAB Flag | AE39: Patent ID | AF39: Title | AG39: A1 | AH39: A2 | AI39: A3 | AJ39: A4 | AK39: A5 | AL39: B1 | AM39: B2 | AN39: B3 | AO39: C1 | AP39: C2 | AQ39: C3 | AR39: C4 | AS39: D1 | AT39: D2 | AU39: D3 | AV39: E1 | AW39: E2 | AX39: E3 | AY39: E4 | AZ39: E5 | BA39: F1 | BB39: F2 | BC39: F3 | BD39: G1 | BE39: G2 | BF39: G3 | BG39: H1 | BH39: H2 | BI39: H3 | BJ39: H4 | BK39: H5 | BL39: H6 | BM39: H7 | BN39: H8 | BO39: H9 | BP39: H10 | BQ39: I1 | BR39: I2 | BS39: I3 | BT39: I4 | BU39: Completeness % | BW39: B1 Tech Domain | BX39: B2 SEP | BY39: B3 Product Arch | BZ39: B4 Stack Layer | CA39: B5 Use-Case | CB39: B6 Mfg/Process | CC39: B7 Materials | CD39: B8 Algorithm | CE39: B9 Interop | CF39: B10 Generational | CG39: B11 Claim-Type | CH39: B12 Detectable | CI39: B13 Geographic | CJ39: B14 Family | CK39: B15 Lifecycle | CL39: B16 Foundational+Impr | CM39: B17 Cross-Industry | CN39: B18 Convergent Theme | CO39: B19 Defensive | CP39: B20 Whitespace | CQ39: B21 Prosecution-Status | CR39: B22 Anchor+Halo | CS39: B23 Picket-Fence | CT39: B24 Strong+Tail | CU39: B25 Continuation-Live | CV39: B26 EoU-Backed | CW39: B27 Battle-Tested | CX39: B28 Clean-Title | CY39: B29 High-Citation | CZ39: B30 Adjacent Re-Read | DA39: B31 Salvage-Volume | DB39: B32 Pre-Expiry | DC39: B33 Provenance | DD39: # Bundles
A40: 1 | AE40: =IFERROR(IF(F40<>"",F40,""),"") | AF40: =IFERROR(IF(G40<>"",G40,""),"") | AG40: =IFERROR(IF(AA40<>"",AA40,IF(R40<>"",R40,"")),"") | AH40: =IFERROR(IF(AB40<>"",AB40,IF(S40<>"",S40,"")),"") | AQ40: =IFERROR(IF(Y40<>"",VALUE(Y40),""),"") | AV40: =IFERROR(IF(T40<>"",VALUE(T40),""),"") | AW40: =IFERROR(IF(N40="","",IF(OR(ISNUMBER(SEARCH("grant",N40)),ISNUMBER(SEARCH("B",AC40))),"Granted",IF(OR(ISNUMBER(SEARCH("pend",N40)),ISNUMBER(SEARCH("A",AC40))),"Pending",IF(ISNUMBER(SEARCH("expir",N40)),"Expired",N40)))),"") | AY40: =IFERROR(IF(M40<>"",ROUND(VALUE(M40),1),IF(L40<>"",ROUND(MAX(0,(DATEVALUE(TEXT(L40,"YYYY-MM-DD"))-TODAY())/365.25),1),"")),"") | AZ40: =IFERROR(IF(O40<>"",O40,""),"") | BA40: =IFERROR(IF(U40<>"",SUBSTITUTE(SUBSTITUTE(U40,"; ",", "),";",","),""),"") | BK40: =IFERROR(IF(W40<>"",VALUE(W40),""),"") | BL40: =IFERROR(IF(X40<>"",VALUE(X40),""),"") | BM40: =IFERROR(IF(AD40="","None",IF(ISNUMBER(SEARCH("surv",AD40)),"Survived",IF(ISNUMBER(SEARCH("pend",AD40)),"Pending",IF(ISNUMBER(SEARCH("yes",AD40)),"Pending","None")))),"None") -> None | BU40: =IFERROR(COUNTA(AE40:BT40)/42,0) -> 0.30952381 | BW40: =IF(Configuration!$C$10="No","",IFERROR(IF(AG40<>"",TRUE(),FALSE()),FALSE())) -> FALSE | BX40: =IF(Configuration!$C$11="No","",IFERROR(IF(AND(N(AL40)>=Configuration!$C$44,AM40<>""),TRUE(),FALSE()),FALSE())) -> FALSE | BY40: =IF(Configuration!$C$12="No","",IFERROR(IF(AJ40<>"",TRUE(),FALSE()),FALSE())) -> FALSE | BZ40: =IF(Configuration!$C$13="No","",IFERROR(IF(AI40<>"",TRUE(),FALSE()),FALSE())) -> FALSE | CA40: =IF(Configuration!$C$14="No","",IFERROR(IF(AK40<>"",TRUE(),FALSE()),FALSE())) -> FALSE | CB40: =IF(Configuration!$C$15="No","",IFERROR(IF(AND(OR(ISNUMBER(SEARCH("process",AG40)),ISNUMBER(SEARCH("fab",AG40)),ISNUMBER(SEARCH("manufac",AG40))),AO40="Method"),TRUE(),FALSE()),FALSE())) -> FALSE | CC40: =IF(Configuration!$C$16="No","",IFERROR(IF(AND(OR(ISNUMBER(SEARCH("material",AG40)),ISNUMBER(SEARCH("chem",AG40)),ISNUMBER(SEARCH("battery",AG40)),ISNUMBER(SEARCH("electrolyte",AG40)),ISNUMBER(SEARCH("polymer",AG40))),OR(AO40="Apparatus",AO40="Method")),TRUE(),FALSE()),FALSE())) -> FALSE | CD40: =IF(Configuration!$C$17="No","",IFERROR(IF(AND(OR(AI40="App",AI40="Middleware",AI40="Cloud"),OR(AO40="Method",AO40="CRM")),TRUE(),FALSE()),FALSE())) -> FALSE | CE40: =IF(Configuration!$C$18="No","",IFERROR(IF(N(AN40)>=Configuration!$C$45,TRUE(),FALSE()),FALSE())) -> FALSE | CF40: =IF(Configuration!$C$19="No","",IFERROR(IF(BE40<>"",TRUE(),FALSE()),FALSE())) -> FALSE | CG40: =IF(Configuration!$C$20="No","",IFERROR(IF(AO40<>"",TRUE(),FALSE()),FALSE())) -> FALSE | CH40: =IF(Configuration!$C$21="No","",IFERROR(IF(OR(N(AS40)>=Configuration!$C$46,N(AT40)>=Configuration!$C$47),TRUE(),FALSE()),FALSE())) -> FALSE | CI40: =IF(Configuration!$C$22="No","",IFERROR(IF(BB40="Yes",TRUE(),FALSE()),FALSE())) -> FALSE | CJ40: =IF(Configuration!$C$23="No","",IFERROR(IF(N(AV40)>=Configuration!$C$48,TRUE(),FALSE()),FALSE())) -> FALSE | CK40: =IF(Configuration!$C$24="No","",IFERROR(IF(N(AY40)>0,TRUE(),FALSE()),FALSE())) -> FALSE | CL40: =IF(Configuration!$C$25="No","",IFERROR(IF(OR(N(AP40)=3,N(AP40)<=1),TRUE(),FALSE()),FALSE())) -> TRUE | CM40: =IF(Configuration!$C$26="No","",IFERROR(IF(N(BF40)>=Configuration!$C$49,TRUE(),FALSE()),FALSE())) -> FALSE | CN40: =IF(Configuration!$C$27="No","",IFERROR(IF(BD40<>"",TRUE(),FALSE()),FALSE())) -> FALSE | CO40: =IF(Configuration!$C$28="No","",IFERROR(IF(N(AU40)>=Configuration!$C$50,TRUE(),FALSE()),FALSE())) -> FALSE | CP40: =IF(Configuration!$C$29="No","",IFERROR(IF(AND(N(AR40)>=Configuration!$C$51,AG40<>""),TRUE(),FALSE()),FALSE())) -> FALSE | CQ40: =IF(Configuration!$C$30="No","",IFERROR(IF(OR(AW40="Pending",AX40="Yes"),TRUE(),FALSE()),FALSE())) -> FALSE | CR40: =IF(Configuration!$C$31="No","",IFERROR(IF(AND(N(BG40)>=Configuration!$C$52,N(AP40)>=1),TRUE(),FALSE()),FALSE())) -> FALSE | CS40: =IF(Configuration!$C$32="No","",IFERROR(IF(AND(N(AR40)>=1,OR(AG40<>"",AM40<>"")),TRUE(),FALSE()),FALSE())) -> FALSE | CT40: =IF(Configuration!$C$33="No","",IFERROR(IF(AG40<>"",TRUE(),FALSE()),FALSE())) -> FALSE | CU40: =IF(Configuration!$C$34="No","",IFERROR(IF(AX40="Yes",TRUE(),FALSE()),FALSE())) -> FALSE | CV40: =IF(Configuration!$C$35="No","",IFERROR(IF(OR(BO40="Partial",BO40="Full"),TRUE(),FALSE()),FALSE())) -> FALSE | CW40: =IF(Configuration!$C$36="No","",IFERROR(IF(BM40="Survived",TRUE(),FALSE()),FALSE())) -> FALSE | CX40: =IF(Configuration!$C$37="No","",IFERROR(IF(AND(BN40="Clean",BP40="None"),TRUE(),FALSE()),FALSE())) -> FALSE | CY40: =IF(Configuration!$C$38="No","",IFERROR(IF(N(BK40)>=Configuration!$C$53,TRUE(),FALSE()),FALSE())) -> FALSE | CZ40: =IF(Configuration!$C$39="No","",IFERROR(IF(AND(N(BS40)>=2,N(BF40)>=2),TRUE(),FALSE()),FALSE())) -> FALSE | DA40: =IF(Configuration!$C$40="No","",IFERROR(IF(OR(N(BG40)<=Configuration!$C$56,N(AY40)<Configuration!$C$57,N(BH40)<=Configuration!$C$58),TRUE(),FALSE()),FALSE())) -> TRUE | DB40: =IF(Configuration!$C$41="No","",IFERROR(IF(AND(N(AY40)>=Configuration!$C$54,N(AY40)<=Configuration!$C$55),TRUE(),FALSE()),FALSE())) -> FALSE | DC40: =IF(Configuration!$C$42="No","",IFERROR(IF(AND(AG40<>"",AJ40<>""),TRUE(),FALSE()),FALSE())) -> FALSE | DD40: =COUNTIF(BW40:DC40,TRUE()) -> 2
A41: 2 | AE41: =IFERROR(IF(F41<>"",F41,""),"") | AF41: =IFERROR(IF(G41<>"",G41,""),"") | AG41: =IFERROR(IF(AA41<>"",AA41,IF(R41<>"",R41,"")),"") | AH41: =IFERROR(IF(AB41<>"",AB41,IF(S41<>"",S41,"")),"") | AQ41: =IFERROR(IF(Y41<>"",VALUE(Y41),""),"") | AV41: =IFERROR(IF(T41<>"",VALUE(T41),""),"") | AW41: =IFERROR(IF(N41="","",IF(OR(ISNUMBER(SEARCH("grant",N41)),ISNUMBER(SEARCH("B",AC41))),"Granted",IF(OR(ISNUMBER(SEARCH("pend",N41)),ISNUMBER(SEARCH("A",AC41))),"Pending",IF(ISNUMBER(SEARCH("expir",N41)),"Expired",N41)))),"") | AY41: =IFERROR(IF(M41<>"",ROUND(VALUE(M41),1),IF(L41<>"",ROUND(MAX(0,(DATEVALUE(TEXT(L41,"YYYY-MM-DD"))-TODAY())/365.25),1),"")),"") | AZ41: =IFERROR(IF(O41<>"",O41,""),"") | BA41: =IFERROR(IF(U41<>"",SUBSTITUTE(SUBSTITUTE(U41,"; ",", "),";",","),""),"") | BK41: =IFERROR(IF(W41<>"",VALUE(W41),""),"") | BL41: =IFERROR(IF(X41<>"",VALUE(X41),""),"") | BM41: =IFERROR(IF(AD41="","None",IF(ISNUMBER(SEARCH("surv",AD41)),"Survived",IF(ISNUMBER(SEARCH("pend",AD41)),"Pending",IF(ISNUMBER(SEARCH("yes",AD41)),"Pending","None")))),"None") -> None | BU41: =IFERROR(COUNTA(AE41:BT41)/42,0) -> 0.30952381 | BW41: =IF(Configuration!$C$10="No","",IFERROR(IF(AG41<>"",TRUE(),FALSE()),FALSE())) -> FALSE | BX41: =IF(Configuration!$C$11="No","",IFERROR(IF(AND(N(AL41)>=Configuration!$C$44,AM41<>""),TRUE(),FALSE()),FALSE())) -> FALSE | BY41: =IF(Configuration!$C$12="No","",IFERROR(IF(AJ41<>"",TRUE(),FALSE()),FALSE())) -> FALSE | BZ41: =IF(Configuration!$C$13="No","",IFERROR(IF(AI41<>"",TRUE(),FALSE()),FALSE())) -> FALSE | CA41: =IF(Configuration!$C$14="No","",IFERROR(IF(AK41<>"",TRUE(),FALSE()),FALSE())) -> FALSE | CB41: =IF(Configuration!$C$15="No","",IFERROR(IF(AND(OR(ISNUMBER(SEARCH("process",AG41)),ISNUMBER(SEARCH("fab",AG41)),ISNUMBER(SEARCH("manufac",AG41))),AO41="Method"),TRUE(),FALSE()),FALSE())) -> FALSE | CC41: =IF(Configuration!$C$16="No","",IFERROR(IF(AND(OR(ISNUMBER(SEARCH("material",AG41)),ISNUMBER(SEARCH("chem",AG41)),ISNUMBER(SEARCH("battery",AG41)),ISNUMBER(SEARCH("electrolyte",AG41)),ISNUMBER(SEARCH("polymer",AG41))),OR(AO41="Apparatus",AO41="Method")),TRUE(),FALSE()),FALSE())) -> FALSE | CD41: =IF(Configuration!$C$17="No","",IFERROR(IF(AND(OR(AI41="App",AI41="Middleware",AI41="Cloud"),OR(AO41="Method",AO41="CRM")),TRUE(),FALSE()),FALSE())) -> FALSE | CE41: =IF(Configuration!$C$18="No","",IFERROR(IF(N(AN41)>=Configuration!$C$45,TRUE(),FALSE()),FALSE())) -> FALSE | CF41: =IF(Configuration!$C$19="No","",IFERROR(IF(BE41<>"",TRUE(),FALSE()),FALSE())) -> FALSE | CG41: =IF(Configuration!$C$20="No","",IFERROR(IF(AO41<>"",TRUE(),FALSE()),FALSE())) -> FALSE | CH41: =IF(Configuration!$C$21="No","",IFERROR(IF(OR(N(AS41)>=Configuration!$C$46,N(AT41)>=Configuration!$C$47),TRUE(),FALSE()),FALSE())) -> FALSE | CI41: =IF(Configuration!$C$22="No","",IFERROR(IF(BB41="Yes",TRUE(),FALSE()),FALSE())) -> FALSE | CJ41: =IF(Configuration!$C$23="No","",IFERROR(IF(N(AV41)>=Configuration!$C$48,TRUE(),FALSE()),FALSE())) -> FALSE | CK41: =IF(Configuration!$C$24="No","",IFERROR(IF(N(AY41)>0,TRUE(),FALSE()),FALSE())) -> FALSE | CL41: =IF(Configuration!$C$25="No","",IFERROR(IF(OR(N(AP41)=3,N(AP41)<=1),TRUE(),FALSE()),FALSE())) -> TRUE | CM41: =IF(Configuration!$C$26="No","",IFERROR(IF(N(BF41)>=Configuration!$C$49,TRUE(),FALSE()),FALSE())) -> FALSE | CN41: =IF(Configuration!$C$27="No","",IFERROR(IF(BD41<>"",TRUE(),FALSE()),FALSE())) -> FALSE | CO41: =IF(Configuration!$C$28="No","",IFERROR(IF(N(AU41)>=Configuration!$C$50,TRUE(),FALSE()),FALSE())) -> FALSE | CP41: =IF(Configuration!$C$29="No","",IFERROR(IF(AND(N(AR41)>=Configuration!$C$51,AG41<>""),TRUE(),FALSE()),FALSE())) -> FALSE | CQ41: =IF(Configuration!$C$30="No","",IFERROR(IF(OR(AW41="Pending",AX41="Yes"),TRUE(),FALSE()),FALSE())) -> FALSE | CR41: =IF(Configuration!$C$31="No","",IFERROR(IF(AND(N(BG41)>=Configuration!$C$52,N(AP41)>=1),TRUE(),FALSE()),FALSE())) -> FALSE | CS41: =IF(Configuration!$C$32="No","",IFERROR(IF(AND(N(AR41)>=1,OR(AG41<>"",AM41<>"")),TRUE(),FALSE()),FALSE())) -> FALSE | CT41: =IF(Configuration!$C$33="No","",IFERROR(IF(AG41<>"",TRUE(),FALSE()),FALSE())) -> FALSE | CU41: =IF(Configuration!$C$34="No","",IFERROR(IF(AX41="Yes",TRUE(),FALSE()),FALSE())) -> FALSE | CV41: =IF(Configuration!$C$35="No","",IFERROR(IF(OR(BO41="Partial",BO41="Full"),TRUE(),FALSE()),FALSE())) -> FALSE | CW41: =IF(Configuration!$C$36="No","",IFERROR(IF(BM41="Survived",TRUE(),FALSE()),FALSE())) -> FALSE | CX41: =IF(Configuration!$C$37="No","",IFERROR(IF(AND(BN41="Clean",BP41="None"),TRUE(),FALSE()),FALSE())) -> FALSE | CY41: =IF(Configuration!$C$38="No","",IFERROR(IF(N(BK41)>=Configuration!$C$53,TRUE(),FALSE()),FALSE())) -> FALSE | CZ41: =IF(Configuration!$C$39="No","",IFERROR(IF(AND(N(BS41)>=2,N(BF41)>=2),TRUE(),FALSE()),FALSE())) -> FALSE | DA41: =IF(Configuration!$C$40="No","",IFERROR(IF(OR(N(BG41)<=Configuration!$C$56,N(AY41)<Configuration!$C$57,N(BH41)<=Configuration!$C$58),TRUE(),FALSE()),FALSE())) -> TRUE | DB41: =IF(Configuration!$C$41="No","",IFERROR(IF(AND(N(AY41)>=Configuration!$C$54,N(AY41)<=Configuration!$C$55),TRUE(),FALSE()),FALSE())) -> FALSE | DC41: =IF(Configuration!$C$42="No","",IFERROR(IF(AND(AG41<>"",AJ41<>""),TRUE(),FALSE()),FALSE())) -> FALSE | DD41: =COUNTIF(BW41:DC41,TRUE()) -> 2
A42: 3 | AE42: =IFERROR(IF(F42<>"",F42,""),"") | AF42: =IFERROR(IF(G42<>"",G42,""),"") | AG42: =IFERROR(IF(AA42<>"",AA42,IF(R42<>"",R42,"")),"") | AH42: =IFERROR(IF(AB42<>"",AB42,IF(S42<>"",S42,"")),"") | AQ42: =IFERROR(IF(Y42<>"",VALUE(Y42),""),"") | AV42: =IFERROR(IF(T42<>"",VALUE(T42),""),"") | AW42: =IFERROR(IF(N42="","",IF(OR(ISNUMBER(SEARCH("grant",N42)),ISNUMBER(SEARCH("B",AC42))),"Granted",IF(OR(ISNUMBER(SEARCH("pend",N42)),ISNUMBER(SEARCH("A",AC42))),"Pending",IF(ISNUMBER(SEARCH("expir",N42)),"Expired",N42)))),"") | AY42: =IFERROR(IF(M42<>"",ROUND(VALUE(M42),1),IF(L42<>"",ROUND(MAX(0,(DATEVALUE(TEXT(L42,"YYYY-MM-DD"))-TODAY())/365.25),1),"")),"") | AZ42: =IFERROR(IF(O42<>"",O42,""),"") | BA42: =IFERROR(IF(U42<>"",SUBSTITUTE(SUBSTITUTE(U42,"; ",", "),";",","),""),"") | BK42: =IFERROR(IF(W42<>"",VALUE(W42),""),"") | BL42: =IFERROR(IF(X42<>"",VALUE(X42),""),"") | BM42: =IFERROR(IF(AD42="","None",IF(ISNUMBER(SEARCH("surv",AD42)),"Survived",IF(ISNUMBER(SEARCH("pend",AD42)),"Pending",IF(ISNUMBER(SEARCH("yes",AD42)),"Pending","None")))),"None") -> None | BU42: =IFERROR(COUNTA(AE42:BT42)/42,0) -> 0.30952381 | BW42: =IF(Configuration!$C$10="No","",IFERROR(IF(AG42<>"",TRUE(),FALSE()),FALSE())) -> FALSE | BX42: =IF(Configuration!$C$11="No","",IFERROR(IF(AND(N(AL42)>=Configuration!$C$44,AM42<>""),TRUE(),FALSE()),FALSE())) -> FALSE | BY42: =IF(Configuration!$C$12="No","",IFERROR(IF(AJ42<>"",TRUE(),FALSE()),FALSE())) -> FALSE | BZ42: =IF(Configuration!$C$13="No","",IFERROR(IF(AI42<>"",TRUE(),FALSE()),FALSE())) -> FALSE | CA42: =IF(Configuration!$C$14="No","",IFERROR(IF(AK42<>"",TRUE(),FALSE()),FALSE())) -> FALSE | CB42: =IF(Configuration!$C$15="No","",IFERROR(IF(AND(OR(ISNUMBER(SEARCH("process",AG42)),ISNUMBER(SEARCH("fab",AG42)),ISNUMBER(SEARCH("manufac",AG42))),AO42="Method"),TRUE(),FALSE()),FALSE())) -> FALSE | CC42: =IF(Configuration!$C$16="No","",IFERROR(IF(AND(OR(ISNUMBER(SEARCH("material",AG42)),ISNUMBER(SEARCH("chem",AG42)),ISNUMBER(SEARCH("battery",AG42)),ISNUMBER(SEARCH("electrolyte",AG42)),ISNUMBER(SEARCH("polymer",AG42))),OR(AO42="Apparatus",AO42="Method")),TRUE(),FALSE()),FALSE())) -> FALSE | CD42: =IF(Configuration!$C$17="No","",IFERROR(IF(AND(OR(AI42="App",AI42="Middleware",AI42="Cloud"),OR(AO42="Method",AO42="CRM")),TRUE(),FALSE()),FALSE())) -> FALSE | CE42: =IF(Configuration!$C$18="No","",IFERROR(IF(N(AN42)>=Configuration!$C$45,TRUE(),FALSE()),FALSE())) -> FALSE | CF42: =IF(Configuration!$C$19="No","",IFERROR(IF(BE42<>"",TRUE(),FALSE()),FALSE())) -> FALSE | CG42: =IF(Configuration!$C$20="No","",IFERROR(IF(AO42<>"",TRUE(),FALSE()),FALSE())) -> FALSE | CH42: =IF(Configuration!$C$21="No","",IFERROR(IF(OR(N(AS42)>=Configuration!$C$46,N(AT42)>=Configuration!$C$47),TRUE(),FALSE()),FALSE())) -> FALSE | CI42: =IF(Configuration!$C$22="No","",IFERROR(IF(BB42="Yes",TRUE(),FALSE()),FALSE())) -> FALSE | CJ42: =IF(Configuration!$C$23="No","",IFERROR(IF(N(AV42)>=Configuration!$C$48,TRUE(),FALSE()),FALSE())) -> FALSE | CK42: =IF(Configuration!$C$24="No","",IFERROR(IF(N(AY42)>0,TRUE(),FALSE()),FALSE())) -> FALSE | CL42: =IF(Configuration!$C$25="No","",IFERROR(IF(OR(N(AP42)=3,N(AP42)<=1),TRUE(),FALSE()),FALSE())) -> TRUE | CM42: =IF(Configuration!$C$26="No","",IFERROR(IF(N(BF42)>=Configuration!$C$49,TRUE(),FALSE()),FALSE())) -> FALSE | CN42: =IF(Configuration!$C$27="No","",IFERROR(IF(BD42<>"",TRUE(),FALSE()),FALSE())) -> FALSE | CO42: =IF(Configuration!$C$28="No","",IFERROR(IF(N(AU42)>=Configuration!$C$50,TRUE(),FALSE()),FALSE())) -> FALSE | CP42: =IF(Configuration!$C$29="No","",IFERROR(IF(AND(N(AR42)>=Configuration!$C$51,AG42<>""),TRUE(),FALSE()),FALSE())) -> FALSE | CQ42: =IF(Configuration!$C$30="No","",IFERROR(IF(OR(AW42="Pending",AX42="Yes"),TRUE(),FALSE()),FALSE())) -> FALSE | CR42: =IF(Configuration!$C$31="No","",IFERROR(IF(AND(N(BG42)>=Configuration!$C$52,N(AP42)>=1),TRUE(),FALSE()),FALSE())) -> FALSE | CS42: =IF(Configuration!$C$32="No","",IFERROR(IF(AND(N(AR42)>=1,OR(AG42<>"",AM42<>"")),TRUE(),FALSE()),FALSE())) -> FALSE | CT42: =IF(Configuration!$C$33="No","",IFERROR(IF(AG42<>"",TRUE(),FALSE()),FALSE())) -> FALSE | CU42: =IF(Configuration!$C$34="No","",IFERROR(IF(AX42="Yes",TRUE(),FALSE()),FALSE())) -> FALSE | CV42: =IF(Configuration!$C$35="No","",IFERROR(IF(OR(BO42="Partial",BO42="Full"),TRUE(),FALSE()),FALSE())) -> FALSE | CW42: =IF(Configuration!$C$36="No","",IFERROR(IF(BM42="Survived",TRUE(),FALSE()),FALSE())) -> FALSE | CX42: =IF(Configuration!$C$37="No","",IFERROR(IF(AND(BN42="Clean",BP42="None"),TRUE(),FALSE()),FALSE())) -> FALSE | CY42: =IF(Configuration!$C$38="No","",IFERROR(IF(N(BK42)>=Configuration!$C$53,TRUE(),FALSE()),FALSE())) -> FALSE | CZ42: =IF(Configuration!$C$39="No","",IFERROR(IF(AND(N(BS42)>=2,N(BF42)>=2),TRUE(),FALSE()),FALSE())) -> FALSE | DA42: =IF(Configuration!$C$40="No","",IFERROR(IF(OR(N(BG42)<=Configuration!$C$56,N(AY42)<Configuration!$C$57,N(BH42)<=Configuration!$C$58),TRUE(),FALSE()),FALSE())) -> TRUE | DB42: =IF(Configuration!$C$41="No","",IFERROR(IF(AND(N(AY42)>=Configuration!$C$54,N(AY42)<=Configuration!$C$55),TRUE(),FALSE()),FALSE())) -> FALSE | DC42: =IF(Configuration!$C$42="No","",IFERROR(IF(AND(AG42<>"",AJ42<>""),TRUE(),FALSE()),FALSE())) -> FALSE | DD42: =COUNTIF(BW42:DC42,TRUE()) -> 2
A43: 4 | AE43: =IFERROR(IF(F43<>"",F43,""),"") | AF43: =IFERROR(IF(G43<>"",G43,""),"") | AG43: =IFERROR(IF(AA43<>"",AA43,IF(R43<>"",R43,"")),"") | AH43: =IFERROR(IF(AB43<>"",AB43,IF(S43<>"",S43,"")),"") | AQ43: =IFERROR(IF(Y43<>"",VALUE(Y43),""),"") | AV43: =IFERROR(IF(T43<>"",VALUE(T43),""),"") | AW43: =IFERROR(IF(N43="","",IF(OR(ISNUMBER(SEARCH("grant",N43)),ISNUMBER(SEARCH("B",AC43))),"Granted",IF(OR(ISNUMBER(SEARCH("pend",N43)),ISNUMBER(SEARCH("A",AC43))),"Pending",IF(ISNUMBER(SEARCH("expir",N43)),"Expired",N43)))),"") | AY43: =IFERROR(IF(M43<>"",ROUND(VALUE(M43),1),IF(L43<>"",ROUND(MAX(0,(DATEVALUE(TEXT(L43,"YYYY-MM-DD"))-TODAY())/365.25),1),"")),"") | AZ43: =IFERROR(IF(O43<>"",O43,""),"") | BA43: =IFERROR(IF(U43<>"",SUBSTITUTE(SUBSTITUTE(U43,"; ",", "),";",","),""),"") | BK43: =IFERROR(IF(W43<>"",VALUE(W43),""),"") | BL43: =IFERROR(IF(X43<>"",VALUE(X43),""),"") | BM43: =IFERROR(IF(AD43="","None",IF(ISNUMBER(SEARCH("surv",AD43)),"Survived",IF(ISNUMBER(SEARCH("pend",AD43)),"Pending",IF(ISNUMBER(SEARCH("yes",AD43)),"Pending","None")))),"None") -> None | BU43: =IFERROR(COUNTA(AE43:BT43)/42,0) -> 0.30952381 | BW43: =IF(Configuration!$C$10="No","",IFERROR(IF(AG43<>"",TRUE(),FALSE()),FALSE())) -> FALSE | BX43: =IF(Configuration!$C$11="No","",IFERROR(IF(AND(N(AL43)>=Configuration!$C$44,AM43<>""),TRUE(),FALSE()),FALSE())) -> FALSE | BY43: =IF(Configuration!$C$12="No","",IFERROR(IF(AJ43<>"",TRUE(),FALSE()),FALSE())) -> FALSE | BZ43: =IF(Configuration!$C$13="No","",IFERROR(IF(AI43<>"",TRUE(),FALSE()),FALSE())) -> FALSE | CA43: =IF(Configuration!$C$14="No","",IFERROR(IF(AK43<>"",TRUE(),FALSE()),FALSE())) -> FALSE | CB43: =IF(Configuration!$C$15="No","",IFERROR(IF(AND(OR(ISNUMBER(SEARCH("process",AG43)),ISNUMBER(SEARCH("fab",AG43)),ISNUMBER(SEARCH("manufac",AG43))),AO43="Method"),TRUE(),FALSE()),FALSE())) -> FALSE | CC43: =IF(Configuration!$C$16="No","",IFERROR(IF(AND(OR(ISNUMBER(SEARCH("material",AG43)),ISNUMBER(SEARCH("chem",AG43)),ISNUMBER(SEARCH("battery",AG43)),ISNUMBER(SEARCH("electrolyte",AG43)),ISNUMBER(SEARCH("polymer",AG43))),OR(AO43="Apparatus",AO43="Method")),TRUE(),FALSE()),FALSE())) -> FALSE | CD43: =IF(Configuration!$C$17="No","",IFERROR(IF(AND(OR(AI43="App",AI43="Middleware",AI43="Cloud"),OR(AO43="Method",AO43="CRM")),TRUE(),FALSE()),FALSE())) -> FALSE | CE43: =IF(Configuration!$C$18="No","",IFERROR(IF(N(AN43)>=Configuration!$C$45,TRUE(),FALSE()),FALSE())) -> FALSE | CF43: =IF(Configuration!$C$19="No","",IFERROR(IF(BE43<>"",TRUE(),FALSE()),FALSE())) -> FALSE | CG43: =IF(Configuration!$C$20="No","",IFERROR(IF(AO43<>"",TRUE(),FALSE()),FALSE())) -> FALSE | CH43: =IF(Configuration!$C$21="No","",IFERROR(IF(OR(N(AS43)>=Configuration!$C$46,N(AT43)>=Configuration!$C$47),TRUE(),FALSE()),FALSE())) -> FALSE | CI43: =IF(Configuration!$C$22="No","",IFERROR(IF(BB43="Yes",TRUE(),FALSE()),FALSE())) -> FALSE | CJ43: =IF(Configuration!$C$23="No","",IFERROR(IF(N(AV43)>=Configuration!$C$48,TRUE(),FALSE()),FALSE())) -> FALSE | CK43: =IF(Configuration!$C$24="No","",IFERROR(IF(N(AY43)>0,TRUE(),FALSE()),FALSE())) -> FALSE | CL43: =IF(Configuration!$C$25="No","",IFERROR(IF(OR(N(AP43)=3,N(AP43)<=1),TRUE(),FALSE()),FALSE())) -> TRUE | CM43: =IF(Configuration!$C$26="No","",IFERROR(IF(N(BF43)>=Configuration!$C$49,TRUE(),FALSE()),FALSE())) -> FALSE | CN43: =IF(Configuration!$C$27="No","",IFERROR(IF(BD43<>"",TRUE(),FALSE()),FALSE())) -> FALSE | CO43: =IF(Configuration!$C$28="No","",IFERROR(IF(N(AU43)>=Configuration!$C$50,TRUE(),FALSE()),FALSE())) -> FALSE | CP43: =IF(Configuration!$C$29="No","",IFERROR(IF(AND(N(AR43)>=Configuration!$C$51,AG43<>""),TRUE(),FALSE()),FALSE())) -> FALSE | CQ43: =IF(Configuration!$C$30="No","",IFERROR(IF(OR(AW43="Pending",AX43="Yes"),TRUE(),FALSE()),FALSE())) -> FALSE | CR43: =IF(Configuration!$C$31="No","",IFERROR(IF(AND(N(BG43)>=Configuration!$C$52,N(AP43)>=1),TRUE(),FALSE()),FALSE())) -> FALSE | CS43: =IF(Configuration!$C$32="No","",IFERROR(IF(AND(N(AR43)>=1,OR(AG43<>"",AM43<>"")),TRUE(),FALSE()),FALSE())) -> FALSE | CT43: =IF(Configuration!$C$33="No","",IFERROR(IF(AG43<>"",TRUE(),FALSE()),FALSE())) -> FALSE | CU43: =IF(Configuration!$C$34="No","",IFERROR(IF(AX43="Yes",TRUE(),FALSE()),FALSE())) -> FALSE | CV43: =IF(Configuration!$C$35="No","",IFERROR(IF(OR(BO43="Partial",BO43="Full"),TRUE(),FALSE()),FALSE())) -> FALSE | CW43: =IF(Configuration!$C$36="No","",IFERROR(IF(BM43="Survived",TRUE(),FALSE()),FALSE())) -> FALSE | CX43: =IF(Configuration!$C$37="No","",IFERROR(IF(AND(BN43="Clean",BP43="None"),TRUE(),FALSE()),FALSE())) -> FALSE | CY43: =IF(Configuration!$C$38="No","",IFERROR(IF(N(BK43)>=Configuration!$C$53,TRUE(),FALSE()),FALSE())) -> FALSE | CZ43: =IF(Configuration!$C$39="No","",IFERROR(IF(AND(N(BS43)>=2,N(BF43)>=2),TRUE(),FALSE()),FALSE())) -> FALSE | DA43: =IF(Configuration!$C$40="No","",IFERROR(IF(OR(N(BG43)<=Configuration!$C$56,N(AY43)<Configuration!$C$57,N(BH43)<=Configuration!$C$58),TRUE(),FALSE()),FALSE())) -> TRUE | DB43: =IF(Configuration!$C$41="No","",IFERROR(IF(AND(N(AY43)>=Configuration!$C$54,N(AY43)<=Configuration!$C$55),TRUE(),FALSE()),FALSE())) -> FALSE | DC43: =IF(Configuration!$C$42="No","",IFERROR(IF(AND(AG43<>"",AJ43<>""),TRUE(),FALSE()),FALSE())) -> FALSE | DD43: =COUNTIF(BW43:DC43,TRUE()) -> 2
A44: 5 | AE44: =IFERROR(IF(F44<>"",F44,""),"") | AF44: =IFERROR(IF(G44<>"",G44,""),"") | AG44: =IFERROR(IF(AA44<>"",AA44,IF(R44<>"",R44,"")),"") | AH44: =IFERROR(IF(AB44<>"",AB44,IF(S44<>"",S44,"")),"") | AQ44: =IFERROR(IF(Y44<>"",VALUE(Y44),""),"") | AV44: =IFERROR(IF(T44<>"",VALUE(T44),""),"") | AW44: =IFERROR(IF(N44="","",IF(OR(ISNUMBER(SEARCH("grant",N44)),ISNUMBER(SEARCH("B",AC44))),"Granted",IF(OR(ISNUMBER(SEARCH("pend",N44)),ISNUMBER(SEARCH("A",AC44))),"Pending",IF(ISNUMBER(SEARCH("expir",N44)),"Expired",N44)))),"") | AY44: =IFERROR(IF(M44<>"",ROUND(VALUE(M44),1),IF(L44<>"",ROUND(MAX(0,(DATEVALUE(TEXT(L44,"YYYY-MM-DD"))-TODAY())/365.25),1),"")),"") | AZ44: =IFERROR(IF(O44<>"",O44,""),"") | BA44: =IFERROR(IF(U44<>"",SUBSTITUTE(SUBSTITUTE(U44,"; ",", "),";",","),""),"") | BK44: =IFERROR(IF(W44<>"",VALUE(W44),""),"") | BL44: =IFERROR(IF(X44<>"",VALUE(X44),""),"") | BM44: =IFERROR(IF(AD44="","None",IF(ISNUMBER(SEARCH("surv",AD44)),"Survived",IF(ISNUMBER(SEARCH("pend",AD44)),"Pending",IF(ISNUMBER(SEARCH("yes",AD44)),"Pending","None")))),"None") -> None | BU44: =IFERROR(COUNTA(AE44:BT44)/42,0) -> 0.30952381 | BW44: =IF(Configuration!$C$10="No","",IFERROR(IF(AG44<>"",TRUE(),FALSE()),FALSE())) -> FALSE | BX44: =IF(Configuration!$C$11="No","",IFERROR(IF(AND(N(AL44)>=Configuration!$C$44,AM44<>""),TRUE(),FALSE()),FALSE())) -> FALSE | BY44: =IF(Configuration!$C$12="No","",IFERROR(IF(AJ44<>"",TRUE(),FALSE()),FALSE())) -> FALSE | BZ44: =IF(Configuration!$C$13="No","",IFERROR(IF(AI44<>"",TRUE(),FALSE()),FALSE())) -> FALSE | CA44: =IF(Configuration!$C$14="No","",IFERROR(IF(AK44<>"",TRUE(),FALSE()),FALSE())) -> FALSE | CB44: =IF(Configuration!$C$15="No","",IFERROR(IF(AND(OR(ISNUMBER(SEARCH("process",AG44)),ISNUMBER(SEARCH("fab",AG44)),ISNUMBER(SEARCH("manufac",AG44))),AO44="Method"),TRUE(),FALSE()),FALSE())) -> FALSE | CC44: =IF(Configuration!$C$16="No","",IFERROR(IF(AND(OR(ISNUMBER(SEARCH("material",AG44)),ISNUMBER(SEARCH("chem",AG44)),ISNUMBER(SEARCH("battery",AG44)),ISNUMBER(SEARCH("electrolyte",AG44)),ISNUMBER(SEARCH("polymer",AG44))),OR(AO44="Apparatus",AO44="Method")),TRUE(),FALSE()),FALSE())) -> FALSE | CD44: =IF(Configuration!$C$17="No","",IFERROR(IF(AND(OR(AI44="App",AI44="Middleware",AI44="Cloud"),OR(AO44="Method",AO44="CRM")),TRUE(),FALSE()),FALSE())) -> FALSE | CE44: =IF(Configuration!$C$18="No","",IFERROR(IF(N(AN44)>=Configuration!$C$45,TRUE(),FALSE()),FALSE())) -> FALSE | CF44: =IF(Configuration!$C$19="No","",IFERROR(IF(BE44<>"",TRUE(),FALSE()),FALSE())) -> FALSE | CG44: =IF(Configuration!$C$20="No","",IFERROR(IF(AO44<>"",TRUE(),FALSE()),FALSE())) -> FALSE | CH44: =IF(Configuration!$C$21="No","",IFERROR(IF(OR(N(AS44)>=Configuration!$C$46,N(AT44)>=Configuration!$C$47),TRUE(),FALSE()),FALSE())) -> FALSE | CI44: =IF(Configuration!$C$22="No","",IFERROR(IF(BB44="Yes",TRUE(),FALSE()),FALSE())) -> FALSE | CJ44: =IF(Configuration!$C$23="No","",IFERROR(IF(N(AV44)>=Configuration!$C$48,TRUE(),FALSE()),FALSE())) -> FALSE | CK44: =IF(Configuration!$C$24="No","",IFERROR(IF(N(AY44)>0,TRUE(),FALSE()),FALSE())) -> FALSE | CL44: =IF(Configuration!$C$25="No","",IFERROR(IF(OR(N(AP44)=3,N(AP44)<=1),TRUE(),FALSE()),FALSE())) -> TRUE | CM44: =IF(Configuration!$C$26="No","",IFERROR(IF(N(BF44)>=Configuration!$C$49,TRUE(),FALSE()),FALSE())) -> FALSE | CN44: =IF(Configuration!$C$27="No","",IFERROR(IF(BD44<>"",TRUE(),FALSE()),FALSE())) -> FALSE | CO44: =IF(Configuration!$C$28="No","",IFERROR(IF(N(AU44)>=Configuration!$C$50,TRUE(),FALSE()),FALSE())) -> FALSE | CP44: =IF(Configuration!$C$29="No","",IFERROR(IF(AND(N(AR44)>=Configuration!$C$51,AG44<>""),TRUE(),FALSE()),FALSE())) -> FALSE | CQ44: =IF(Configuration!$C$30="No","",IFERROR(IF(OR(AW44="Pending",AX44="Yes"),TRUE(),FALSE()),FALSE())) -> FALSE | CR44: =IF(Configuration!$C$31="No","",IFERROR(IF(AND(N(BG44)>=Configuration!$C$52,N(AP44)>=1),TRUE(),FALSE()),FALSE())) -> FALSE | CS44: =IF(Configuration!$C$32="No","",IFERROR(IF(AND(N(AR44)>=1,OR(AG44<>"",AM44<>"")),TRUE(),FALSE()),FALSE())) -> FALSE | CT44: =IF(Configuration!$C$33="No","",IFERROR(IF(AG44<>"",TRUE(),FALSE()),FALSE())) -> FALSE | CU44: =IF(Configuration!$C$34="No","",IFERROR(IF(AX44="Yes",TRUE(),FALSE()),FALSE())) -> FALSE | CV44: =IF(Configuration!$C$35="No","",IFERROR(IF(OR(BO44="Partial",BO44="Full"),TRUE(),FALSE()),FALSE())) -> FALSE | CW44: =IF(Configuration!$C$36="No","",IFERROR(IF(BM44="Survived",TRUE(),FALSE()),FALSE())) -> FALSE | CX44: =IF(Configuration!$C$37="No","",IFERROR(IF(AND(BN44="Clean",BP44="None"),TRUE(),FALSE()),FALSE())) -> FALSE | CY44: =IF(Configuration!$C$38="No","",IFERROR(IF(N(BK44)>=Configuration!$C$53,TRUE(),FALSE()),FALSE())) -> FALSE | CZ44: =IF(Configuration!$C$39="No","",IFERROR(IF(AND(N(BS44)>=2,N(BF44)>=2),TRUE(),FALSE()),FALSE())) -> FALSE | DA44: =IF(Configuration!$C$40="No","",IFERROR(IF(OR(N(BG44)<=Configuration!$C$56,N(AY44)<Configuration!$C$57,N(BH44)<=Configuration!$C$58),TRUE(),FALSE()),FALSE())) -> TRUE | DB44: =IF(Configuration!$C$41="No","",IFERROR(IF(AND(N(AY44)>=Configuration!$C$54,N(AY44)<=Configuration!$C$55),TRUE(),FALSE()),FALSE())) -> FALSE | DC44: =IF(Configuration!$C$42="No","",IFERROR(IF(AND(AG44<>"",AJ44<>""),TRUE(),FALSE()),FALSE())) -> FALSE | DD44: =COUNTIF(BW44:DC44,TRUE()) -> 2
A45: 6 | AE45: =IFERROR(IF(F45<>"",F45,""),"") | AF45: =IFERROR(IF(G45<>"",G45,""),"") | AG45: =IFERROR(IF(AA45<>"",AA45,IF(R45<>"",R45,"")),"") | AH45: =IFERROR(IF(AB45<>"",AB45,IF(S45<>"",S45,"")),"") | AQ45: =IFERROR(IF(Y45<>"",VALUE(Y45),""),"") | AV45: =IFERROR(IF(T45<>"",VALUE(T45),""),"") | AW45: =IFERROR(IF(N45="","",IF(OR(ISNUMBER(SEARCH("grant",N45)),ISNUMBER(SEARCH("B",AC45))),"Granted",IF(OR(ISNUMBER(SEARCH("pend",N45)),ISNUMBER(SEARCH("A",AC45))),"Pending",IF(ISNUMBER(SEARCH("expir",N45)),"Expired",N45)))),"") | AY45: =IFERROR(IF(M45<>"",ROUND(VALUE(M45),1),IF(L45<>"",ROUND(MAX(0,(DATEVALUE(TEXT(L45,"YYYY-MM-DD"))-TODAY())/365.25),1),"")),"") | AZ45: =IFERROR(IF(O45<>"",O45,""),"") | BA45: =IFERROR(IF(U45<>"",SUBSTITUTE(SUBSTITUTE(U45,"; ",", "),";",","),""),"") | BK45: =IFERROR(IF(W45<>"",VALUE(W45),""),"") | BL45: =IFERROR(IF(X45<>"",VALUE(X45),""),"") | BM45: =IFERROR(IF(AD45="","None",IF(ISNUMBER(SEARCH("surv",AD45)),"Survived",IF(ISNUMBER(SEARCH("pend",AD45)),"Pending",IF(ISNUMBER(SEARCH("yes",AD45)),"Pending","None")))),"None") -> None | BU45: =IFERROR(COUNTA(AE45:BT45)/42,0) -> 0.30952381 | BW45: =IF(Configuration!$C$10="No","",IFERROR(IF(AG45<>"",TRUE(),FALSE()),FALSE())) -> FALSE | BX45: =IF(Configuration!$C$11="No","",IFERROR(IF(AND(N(AL45)>=Configuration!$C$44,AM45<>""),TRUE(),FALSE()),FALSE())) -> FALSE | BY45: =IF(Configuration!$C$12="No","",IFERROR(IF(AJ45<>"",TRUE(),FALSE()),FALSE())) -> FALSE | BZ45: =IF(Configuration!$C$13="No","",IFERROR(IF(AI45<>"",TRUE(),FALSE()),FALSE())) -> FALSE | CA45: =IF(Configuration!$C$14="No","",IFERROR(IF(AK45<>"",TRUE(),FALSE()),FALSE())) -> FALSE | CB45: =IF(Configuration!$C$15="No","",IFERROR(IF(AND(OR(ISNUMBER(SEARCH("process",AG45)),ISNUMBER(SEARCH("fab",AG45)),ISNUMBER(SEARCH("manufac",AG45))),AO45="Method"),TRUE(),FALSE()),FALSE())) -> FALSE | CC45: =IF(Configuration!$C$16="No","",IFERROR(IF(AND(OR(ISNUMBER(SEARCH("material",AG45)),ISNUMBER(SEARCH("chem",AG45)),ISNUMBER(SEARCH("battery",AG45)),ISNUMBER(SEARCH("electrolyte",AG45)),ISNUMBER(SEARCH("polymer",AG45))),OR(AO45="Apparatus",AO45="Method")),TRUE(),FALSE()),FALSE())) -> FALSE | CD45: =IF(Configuration!$C$17="No","",IFERROR(IF(AND(OR(AI45="App",AI45="Middleware",AI45="Cloud"),OR(AO45="Method",AO45="CRM")),TRUE(),FALSE()),FALSE())) -> FALSE | CE45: =IF(Configuration!$C$18="No","",IFERROR(IF(N(AN45)>=Configuration!$C$45,TRUE(),FALSE()),FALSE())) -> FALSE | CF45: =IF(Configuration!$C$19="No","",IFERROR(IF(BE45<>"",TRUE(),FALSE()),FALSE())) -> FALSE | CG45: =IF(Configuration!$C$20="No","",IFERROR(IF(AO45<>"",TRUE(),FALSE()),FALSE())) -> FALSE | CH45: =IF(Configuration!$C$21="No","",IFERROR(IF(OR(N(AS45)>=Configuration!$C$46,N(AT45)>=Configuration!$C$47),TRUE(),FALSE()),FALSE())) -> FALSE | CI45: =IF(Configuration!$C$22="No","",IFERROR(IF(BB45="Yes",TRUE(),FALSE()),FALSE())) -> FALSE | CJ45: =IF(Configuration!$C$23="No","",IFERROR(IF(N(AV45)>=Configuration!$C$48,TRUE(),FALSE()),FALSE())) -> FALSE | CK45: =IF(Configuration!$C$24="No","",IFERROR(IF(N(AY45)>0,TRUE(),FALSE()),FALSE())) -> FALSE | CL45: =IF(Configuration!$C$25="No","",IFERROR(IF(OR(N(AP45)=3,N(AP45)<=1),TRUE(),FALSE()),FALSE())) -> TRUE | CM45: =IF(Configuration!$C$26="No","",IFERROR(IF(N(BF45)>=Configuration!$C$49,TRUE(),FALSE()),FALSE())) -> FALSE | CN45: =IF(Configuration!$C$27="No","",IFERROR(IF(BD45<>"",TRUE(),FALSE()),FALSE())) -> FALSE | CO45: =IF(Configuration!$C$28="No","",IFERROR(IF(N(AU45)>=Configuration!$C$50,TRUE(),FALSE()),FALSE())) -> FALSE | CP45: =IF(Configuration!$C$29="No","",IFERROR(IF(AND(N(AR45)>=Configuration!$C$51,AG45<>""),TRUE(),FALSE()),FALSE())) -> FALSE | CQ45: =IF(Configuration!$C$30="No","",IFERROR(IF(OR(AW45="Pending",AX45="Yes"),TRUE(),FALSE()),FALSE())) -> FALSE | CR45: =IF(Configuration!$C$31="No","",IFERROR(IF(AND(N(BG45)>=Configuration!$C$52,N(AP45)>=1),TRUE(),FALSE()),FALSE())) -> FALSE | CS45: =IF(Configuration!$C$32="No","",IFERROR(IF(AND(N(AR45)>=1,OR(AG45<>"",AM45<>"")),TRUE(),FALSE()),FALSE())) -> FALSE | CT45: =IF(Configuration!$C$33="No","",IFERROR(IF(AG45<>"",TRUE(),FALSE()),FALSE())) -> FALSE | CU45: =IF(Configuration!$C$34="No","",IFERROR(IF(AX45="Yes",TRUE(),FALSE()),FALSE())) -> FALSE | CV45: =IF(Configuration!$C$35="No","",IFERROR(IF(OR(BO45="Partial",BO45="Full"),TRUE(),FALSE()),FALSE())) -> FALSE | CW45: =IF(Configuration!$C$36="No","",IFERROR(IF(BM45="Survived",TRUE(),FALSE()),FALSE())) -> FALSE | CX45: =IF(Configuration!$C$37="No","",IFERROR(IF(AND(BN45="Clean",BP45="None"),TRUE(),FALSE()),FALSE())) -> FALSE | CY45: =IF(Configuration!$C$38="No","",IFERROR(IF(N(BK45)>=Configuration!$C$53,TRUE(),FALSE()),FALSE())) -> FALSE | CZ45: =IF(Configuration!$C$39="No","",IFERROR(IF(AND(N(BS45)>=2,N(BF45)>=2),TRUE(),FALSE()),FALSE())) -> FALSE | DA45: =IF(Configuration!$C$40="No","",IFERROR(IF(OR(N(BG45)<=Configuration!$C$56,N(AY45)<Configuration!$C$57,N(BH45)<=Configuration!$C$58),TRUE(),FALSE()),FALSE())) -> TRUE | DB45: =IF(Configuration!$C$41="No","",IFERROR(IF(AND(N(AY45)>=Configuration!$C$54,N(AY45)<=Configuration!$C$55),TRUE(),FALSE()),FALSE())) -> FALSE | DC45: =IF(Configuration!$C$42="No","",IFERROR(IF(AND(AG45<>"",AJ45<>""),TRUE(),FALSE()),FALSE())) -> FALSE | DD45: =COUNTIF(BW45:DC45,TRUE()) -> 2
A46: 7 | AE46: =IFERROR(IF(F46<>"",F46,""),"") | AF46: =IFERROR(IF(G46<>"",G46,""),"") | AG46: =IFERROR(IF(AA46<>"",AA46,IF(R46<>"",R46,"")),"") | AH46: =IFERROR(IF(AB46<>"",AB46,IF(S46<>"",S46,"")),"") | AQ46: =IFERROR(IF(Y46<>"",VALUE(Y46),""),"") | AV46: =IFERROR(IF(T46<>"",VALUE(T46),""),"") | AW46: =IFERROR(IF(N46="","",IF(OR(ISNUMBER(SEARCH("grant",N46)),ISNUMBER(SEARCH("B",AC46))),"Granted",IF(OR(ISNUMBER(SEARCH("pend",N46)),ISNUMBER(SEARCH("A",AC46))),"Pending",IF(ISNUMBER(SEARCH("expir",N46)),"Expired",N46)))),"") | AY46: =IFERROR(IF(M46<>"",ROUND(VALUE(M46),1),IF(L46<>"",ROUND(MAX(0,(DATEVALUE(TEXT(L46,"YYYY-MM-DD"))-TODAY())/365.25),1),"")),"") | AZ46: =IFERROR(IF(O46<>"",O46,""),"") | BA46: =IFERROR(IF(U46<>"",SUBSTITUTE(SUBSTITUTE(U46,"; ",", "),";",","),""),"") | BK46: =IFERROR(IF(W46<>"",VALUE(W46),""),"") | BL46: =IFERROR(IF(X46<>"",VALUE(X46),""),"") | BM46: =IFERROR(IF(AD46="","None",IF(ISNUMBER(SEARCH("surv",AD46)),"Survived",IF(ISNUMBER(SEARCH("pend",AD46)),"Pending",IF(ISNUMBER(SEARCH("yes",AD46)),"Pending","None")))),"None") -> None | BU46: =IFERROR(COUNTA(AE46:BT46)/42,0) -> 0.30952381 | BW46: =IF(Configuration!$C$10="No","",IFERROR(IF(AG46<>"",TRUE(),FALSE()),FALSE())) -> FALSE | BX46: =IF(Configuration!$C$11="No","",IFERROR(IF(AND(N(AL46)>=Configuration!$C$44,AM46<>""),TRUE(),FALSE()),FALSE())) -> FALSE | BY46: =IF(Configuration!$C$12="No","",IFERROR(IF(AJ46<>"",TRUE(),FALSE()),FALSE())) -> FALSE | BZ46: =IF(Configuration!$C$13="No","",IFERROR(IF(AI46<>"",TRUE(),FALSE()),FALSE())) -> FALSE | CA46: =IF(Configuration!$C$14="No","",IFERROR(IF(AK46<>"",TRUE(),FALSE()),FALSE())) -> FALSE | CB46: =IF(Configuration!$C$15="No","",IFERROR(IF(AND(OR(ISNUMBER(SEARCH("process",AG46)),ISNUMBER(SEARCH("fab",AG46)),ISNUMBER(SEARCH("manufac",AG46))),AO46="Method"),TRUE(),FALSE()),FALSE())) -> FALSE | CC46: =IF(Configuration!$C$16="No","",IFERROR(IF(AND(OR(ISNUMBER(SEARCH("material",AG46)),ISNUMBER(SEARCH("chem",AG46)),ISNUMBER(SEARCH("battery",AG46)),ISNUMBER(SEARCH("electrolyte",AG46)),ISNUMBER(SEARCH("polymer",AG46))),OR(AO46="Apparatus",AO46="Method")),TRUE(),FALSE()),FALSE())) -> FALSE | CD46: =IF(Configuration!$C$17="No","",IFERROR(IF(AND(OR(AI46="App",AI46="Middleware",AI46="Cloud"),OR(AO46="Method",AO46="CRM")),TRUE(),FALSE()),FALSE())) -> FALSE | CE46: =IF(Configuration!$C$18="No","",IFERROR(IF(N(AN46)>=Configuration!$C$45,TRUE(),FALSE()),FALSE())) -> FALSE | CF46: =IF(Configuration!$C$19="No","",IFERROR(IF(BE46<>"",TRUE(),FALSE()),FALSE())) -> FALSE | CG46: =IF(Configuration!$C$20="No","",IFERROR(IF(AO46<>"",TRUE(),FALSE()),FALSE())) -> FALSE | CH46: =IF(Configuration!$C$21="No","",IFERROR(IF(OR(N(AS46)>=Configuration!$C$46,N(AT46)>=Configuration!$C$47),TRUE(),FALSE()),FALSE())) -> FALSE | CI46: =IF(Configuration!$C$22="No","",IFERROR(IF(BB46="Yes",TRUE(),FALSE()),FALSE())) -> FALSE | CJ46: =IF(Configuration!$C$23="No","",IFERROR(IF(N(AV46)>=Configuration!$C$48,TRUE(),FALSE()),FALSE())) -> FALSE | CK46: =IF(Configuration!$C$24="No","",IFERROR(IF(N(AY46)>0,TRUE(),FALSE()),FALSE())) -> FALSE | CL46: =IF(Configuration!$C$25="No","",IFERROR(IF(OR(N(AP46)=3,N(AP46)<=1),TRUE(),FALSE()),FALSE())) -> TRUE | CM46: =IF(Configuration!$C$26="No","",IFERROR(IF(N(BF46)>=Configuration!$C$49,TRUE(),FALSE()),FALSE())) -> FALSE | CN46: =IF(Configuration!$C$27="No","",IFERROR(IF(BD46<>"",TRUE(),FALSE()),FALSE())) -> FALSE | CO46: =IF(Configuration!$C$28="No","",IFERROR(IF(N(AU46)>=Configuration!$C$50,TRUE(),FALSE()),FALSE())) -> FALSE | CP46: =IF(Configuration!$C$29="No","",IFERROR(IF(AND(N(AR46)>=Configuration!$C$51,AG46<>""),TRUE(),FALSE()),FALSE())) -> FALSE | CQ46: =IF(Configuration!$C$30="No","",IFERROR(IF(OR(AW46="Pending",AX46="Yes"),TRUE(),FALSE()),FALSE())) -> FALSE | CR46: =IF(Configuration!$C$31="No","",IFERROR(IF(AND(N(BG46)>=Configuration!$C$52,N(AP46)>=1),TRUE(),FALSE()),FALSE())) -> FALSE | CS46: =IF(Configuration!$C$32="No","",IFERROR(IF(AND(N(AR46)>=1,OR(AG46<>"",AM46<>"")),TRUE(),FALSE()),FALSE())) -> FALSE | CT46: =IF(Configuration!$C$33="No","",IFERROR(IF(AG46<>"",TRUE(),FALSE()),FALSE())) -> FALSE | CU46: =IF(Configuration!$C$34="No","",IFERROR(IF(AX46="Yes",TRUE(),FALSE()),FALSE())) -> FALSE | CV46: =IF(Configuration!$C$35="No","",IFERROR(IF(OR(BO46="Partial",BO46="Full"),TRUE(),FALSE()),FALSE())) -> FALSE | CW46: =IF(Configuration!$C$36="No","",IFERROR(IF(BM46="Survived",TRUE(),FALSE()),FALSE())) -> FALSE | CX46: =IF(Configuration!$C$37="No","",IFERROR(IF(AND(BN46="Clean",BP46="None"),TRUE(),FALSE()),FALSE())) -> FALSE | CY46: =IF(Configuration!$C$38="No","",IFERROR(IF(N(BK46)>=Configuration!$C$53,TRUE(),FALSE()),FALSE())) -> FALSE | CZ46: =IF(Configuration!$C$39="No","",IFERROR(IF(AND(N(BS46)>=2,N(BF46)>=2),TRUE(),FALSE()),FALSE())) -> FALSE | DA46: =IF(Configuration!$C$40="No","",IFERROR(IF(OR(N(BG46)<=Configuration!$C$56,N(AY46)<Configuration!$C$57,N(BH46)<=Configuration!$C$58),TRUE(),FALSE()),FALSE())) -> TRUE | DB46: =IF(Configuration!$C$41="No","",IFERROR(IF(AND(N(AY46)>=Configuration!$C$54,N(AY46)<=Configuration!$C$55),TRUE(),FALSE()),FALSE())) -> FALSE | DC46: =IF(Configuration!$C$42="No","",IFERROR(IF(AND(AG46<>"",AJ46<>""),TRUE(),FALSE()),FALSE())) -> FALSE | DD46: =COUNTIF(BW46:DC46,TRUE()) -> 2
A47: 8 | AE47: =IFERROR(IF(F47<>"",F47,""),"") | AF47: =IFERROR(IF(G47<>"",G47,""),"") | AG47: =IFERROR(IF(AA47<>"",AA47,IF(R47<>"",R47,"")),"") | AH47: =IFERROR(IF(AB47<>"",AB47,IF(S47<>"",S47,"")),"") | AQ47: =IFERROR(IF(Y47<>"",VALUE(Y47),""),"") | AV47: =IFERROR(IF(T47<>"",VALUE(T47),""),"") | AW47: =IFERROR(IF(N47="","",IF(OR(ISNUMBER(SEARCH("grant",N47)),ISNUMBER(SEARCH("B",AC47))),"Granted",IF(OR(ISNUMBER(SEARCH("pend",N47)),ISNUMBER(SEARCH("A",AC47))),"Pending",IF(ISNUMBER(SEARCH("expir",N47)),"Expired",N47)))),"") | AY47: =IFERROR(IF(M47<>"",ROUND(VALUE(M47),1),IF(L47<>"",ROUND(MAX(0,(DATEVALUE(TEXT(L47,"YYYY-MM-DD"))-TODAY())/365.25),1),"")),"") | AZ47: =IFERROR(IF(O47<>"",O47,""),"") | BA47: =IFERROR(IF(U47<>"",SUBSTITUTE(SUBSTITUTE(U47,"; ",", "),";",","),""),"") | BK47: =IFERROR(IF(W47<>"",VALUE(W47),""),"") | BL47: =IFERROR(IF(X47<>"",VALUE(X47),""),"") | BM47: =IFERROR(IF(AD47="","None",IF(ISNUMBER(SEARCH("surv",AD47)),"Survived",IF(ISNUMBER(SEARCH("pend",AD47)),"Pending",IF(ISNUMBER(SEARCH("yes",AD47)),"Pending","None")))),"None") -> None | BU47: =IFERROR(COUNTA(AE47:BT47)/42,0) -> 0.30952381 | BW47: =IF(Configuration!$C$10="No","",IFERROR(IF(AG47<>"",TRUE(),FALSE()),FALSE())) -> FALSE | BX47: =IF(Configuration!$C$11="No","",IFERROR(IF(AND(N(AL47)>=Configuration!$C$44,AM47<>""),TRUE(),FALSE()),FALSE())) -> FALSE | BY47: =IF(Configuration!$C$12="No","",IFERROR(IF(AJ47<>"",TRUE(),FALSE()),FALSE())) -> FALSE | BZ47: =IF(Configuration!$C$13="No","",IFERROR(IF(AI47<>"",TRUE(),FALSE()),FALSE())) -> FALSE | CA47: =IF(Configuration!$C$14="No","",IFERROR(IF(AK47<>"",TRUE(),FALSE()),FALSE())) -> FALSE | CB47: =IF(Configuration!$C$15="No","",IFERROR(IF(AND(OR(ISNUMBER(SEARCH("process",AG47)),ISNUMBER(SEARCH("fab",AG47)),ISNUMBER(SEARCH("manufac",AG47))),AO47="Method"),TRUE(),FALSE()),FALSE())) -> FALSE | CC47: =IF(Configuration!$C$16="No","",IFERROR(IF(AND(OR(ISNUMBER(SEARCH("material",AG47)),ISNUMBER(SEARCH("chem",AG47)),ISNUMBER(SEARCH("battery",AG47)),ISNUMBER(SEARCH("electrolyte",AG47)),ISNUMBER(SEARCH("polymer",AG47))),OR(AO47="Apparatus",AO47="Method")),TRUE(),FALSE()),FALSE())) -> FALSE | CD47: =IF(Configuration!$C$17="No","",IFERROR(IF(AND(OR(AI47="App",AI47="Middleware",AI47="Cloud"),OR(AO47="Method",AO47="CRM")),TRUE(),FALSE()),FALSE())) -> FALSE | CE47: =IF(Configuration!$C$18="No","",IFERROR(IF(N(AN47)>=Configuration!$C$45,TRUE(),FALSE()),FALSE())) -> FALSE | CF47: =IF(Configuration!$C$19="No","",IFERROR(IF(BE47<>"",TRUE(),FALSE()),FALSE())) -> FALSE | CG47: =IF(Configuration!$C$20="No","",IFERROR(IF(AO47<>"",TRUE(),FALSE()),FALSE())) -> FALSE | CH47: =IF(Configuration!$C$21="No","",IFERROR(IF(OR(N(AS47)>=Configuration!$C$46,N(AT47)>=Configuration!$C$47),TRUE(),FALSE()),FALSE())) -> FALSE | CI47: =IF(Configuration!$C$22="No","",IFERROR(IF(BB47="Yes",TRUE(),FALSE()),FALSE())) -> FALSE | CJ47: =IF(Configuration!$C$23="No","",IFERROR(IF(N(AV47)>=Configuration!$C$48,TRUE(),FALSE()),FALSE())) -> FALSE | CK47: =IF(Configuration!$C$24="No","",IFERROR(IF(N(AY47)>0,TRUE(),FALSE()),FALSE())) -> FALSE | CL47: =IF(Configuration!$C$25="No","",IFERROR(IF(OR(N(AP47)=3,N(AP47)<=1),TRUE(),FALSE()),FALSE())) -> TRUE | CM47: =IF(Configuration!$C$26="No","",IFERROR(IF(N(BF47)>=Configuration!$C$49,TRUE(),FALSE()),FALSE())) -> FALSE | CN47: =IF(Configuration!$C$27="No","",IFERROR(IF(BD47<>"",TRUE(),FALSE()),FALSE())) -> FALSE | CO47: =IF(Configuration!$C$28="No","",IFERROR(IF(N(AU47)>=Configuration!$C$50,TRUE(),FALSE()),FALSE())) -> FALSE | CP47: =IF(Configuration!$C$29="No","",IFERROR(IF(AND(N(AR47)>=Configuration!$C$51,AG47<>""),TRUE(),FALSE()),FALSE())) -> FALSE | CQ47: =IF(Configuration!$C$30="No","",IFERROR(IF(OR(AW47="Pending",AX47="Yes"),TRUE(),FALSE()),FALSE())) -> FALSE | CR47: =IF(Configuration!$C$31="No","",IFERROR(IF(AND(N(BG47)>=Configuration!$C$52,N(AP47)>=1),TRUE(),FALSE()),FALSE())) -> FALSE | CS47: =IF(Configuration!$C$32="No","",IFERROR(IF(AND(N(AR47)>=1,OR(AG47<>"",AM47<>"")),TRUE(),FALSE()),FALSE())) -> FALSE | CT47: =IF(Configuration!$C$33="No","",IFERROR(IF(AG47<>"",TRUE(),FALSE()),FALSE())) -> FALSE | CU47: =IF(Configuration!$C$34="No","",IFERROR(IF(AX47="Yes",TRUE(),FALSE()),FALSE())) -> FALSE | CV47: =IF(Configuration!$C$35="No","",IFERROR(IF(OR(BO47="Partial",BO47="Full"),TRUE(),FALSE()),FALSE())) -> FALSE | CW47: =IF(Configuration!$C$36="No","",IFERROR(IF(BM47="Survived",TRUE(),FALSE()),FALSE())) -> FALSE | CX47: =IF(Configuration!$C$37="No","",IFERROR(IF(AND(BN47="Clean",BP47="None"),TRUE(),FALSE()),FALSE())) -> FALSE | CY47: =IF(Configuration!$C$38="No","",IFERROR(IF(N(BK47)>=Configuration!$C$53,TRUE(),FALSE()),FALSE())) -> FALSE | CZ47: =IF(Configuration!$C$39="No","",IFERROR(IF(AND(N(BS47)>=2,N(BF47)>=2),TRUE(),FALSE()),FALSE())) -> FALSE | DA47: =IF(Configuration!$C$40="No","",IFERROR(IF(OR(N(BG47)<=Configuration!$C$56,N(AY47)<Configuration!$C$57,N(BH47)<=Configuration!$C$58),TRUE(),FALSE()),FALSE())) -> TRUE | DB47: =IF(Configuration!$C$41="No","",IFERROR(IF(AND(N(AY47)>=Configuration!$C$54,N(AY47)<=Configuration!$C$55),TRUE(),FALSE()),FALSE())) -> FALSE | DC47: =IF(Configuration!$C$42="No","",IFERROR(IF(AND(AG47<>"",AJ47<>""),TRUE(),FALSE()),FALSE())) -> FALSE | DD47: =COUNTIF(BW47:DC47,TRUE()) -> 2
A48: 9 | AE48: =IFERROR(IF(F48<>"",F48,""),"") | AF48: =IFERROR(IF(G48<>"",G48,""),"") | AG48: =IFERROR(IF(AA48<>"",AA48,IF(R48<>"",R48,"")),"") | AH48: =IFERROR(IF(AB48<>"",AB48,IF(S48<>"",S48,"")),"") | AQ48: =IFERROR(IF(Y48<>"",VALUE(Y48),""),"") | AV48: =IFERROR(IF(T48<>"",VALUE(T48),""),"") | AW48: =IFERROR(IF(N48="","",IF(OR(ISNUMBER(SEARCH("grant",N48)),ISNUMBER(SEARCH("B",AC48))),"Granted",IF(OR(ISNUMBER(SEARCH("pend",N48)),ISNUMBER(SEARCH("A",AC48))),"Pending",IF(ISNUMBER(SEARCH("expir",N48)),"Expired",N48)))),"") | AY48: =IFERROR(IF(M48<>"",ROUND(VALUE(M48),1),IF(L48<>"",ROUND(MAX(0,(DATEVALUE(TEXT(L48,"YYYY-MM-DD"))-TODAY())/365.25),1),"")),"") | AZ48: =IFERROR(IF(O48<>"",O48,""),"") | BA48: =IFERROR(IF(U48<>"",SUBSTITUTE(SUBSTITUTE(U48,"; ",", "),";",","),""),"") | BK48: =IFERROR(IF(W48<>"",VALUE(W48),""),"") | BL48: =IFERROR(IF(X48<>"",VALUE(X48),""),"") | BM48: =IFERROR(IF(AD48="","None",IF(ISNUMBER(SEARCH("surv",AD48)),"Survived",IF(ISNUMBER(SEARCH("pend",AD48)),"Pending",IF(ISNUMBER(SEARCH("yes",AD48)),"Pending","None")))),"None") -> None | BU48: =IFERROR(COUNTA(AE48:BT48)/42,0) -> 0.30952381 | BW48: =IF(Configuration!$C$10="No","",IFERROR(IF(AG48<>"",TRUE(),FALSE()),FALSE())) -> FALSE | BX48: =IF(Configuration!$C$11="No","",IFERROR(IF(AND(N(AL48)>=Configuration!$C$44,AM48<>""),TRUE(),FALSE()),FALSE())) -> FALSE | BY48: =IF(Configuration!$C$12="No","",IFERROR(IF(AJ48<>"",TRUE(),FALSE()),FALSE())) -> FALSE | BZ48: =IF(Configuration!$C$13="No","",IFERROR(IF(AI48<>"",TRUE(),FALSE()),FALSE())) -> FALSE | CA48: =IF(Configuration!$C$14="No","",IFERROR(IF(AK48<>"",TRUE(),FALSE()),FALSE())) -> FALSE | CB48: =IF(Configuration!$C$15="No","",IFERROR(IF(AND(OR(ISNUMBER(SEARCH("process",AG48)),ISNUMBER(SEARCH("fab",AG48)),ISNUMBER(SEARCH("manufac",AG48))),AO48="Method"),TRUE(),FALSE()),FALSE())) -> FALSE | CC48: =IF(Configuration!$C$16="No","",IFERROR(IF(AND(OR(ISNUMBER(SEARCH("material",AG48)),ISNUMBER(SEARCH("chem",AG48)),ISNUMBER(SEARCH("battery",AG48)),ISNUMBER(SEARCH("electrolyte",AG48)),ISNUMBER(SEARCH("polymer",AG48))),OR(AO48="Apparatus",AO48="Method")),TRUE(),FALSE()),FALSE())) -> FALSE | CD48: =IF(Configuration!$C$17="No","",IFERROR(IF(AND(OR(AI48="App",AI48="Middleware",AI48="Cloud"),OR(AO48="Method",AO48="CRM")),TRUE(),FALSE()),FALSE())) -> FALSE | CE48: =IF(Configuration!$C$18="No","",IFERROR(IF(N(AN48)>=Configuration!$C$45,TRUE(),FALSE()),FALSE())) -> FALSE | CF48: =IF(Configuration!$C$19="No","",IFERROR(IF(BE48<>"",TRUE(),FALSE()),FALSE())) -> FALSE | CG48: =IF(Configuration!$C$20="No","",IFERROR(IF(AO48<>"",TRUE(),FALSE()),FALSE())) -> FALSE | CH48: =IF(Configuration!$C$21="No","",IFERROR(IF(OR(N(AS48)>=Configuration!$C$46,N(AT48)>=Configuration!$C$47),TRUE(),FALSE()),FALSE())) -> FALSE | CI48: =IF(Configuration!$C$22="No","",IFERROR(IF(BB48="Yes",TRUE(),FALSE()),FALSE())) -> FALSE | CJ48: =IF(Configuration!$C$23="No","",IFERROR(IF(N(AV48)>=Configuration!$C$48,TRUE(),FALSE()),FALSE())) -> FALSE | CK48: =IF(Configuration!$C$24="No","",IFERROR(IF(N(AY48)>0,TRUE(),FALSE()),FALSE())) -> FALSE | CL48: =IF(Configuration!$C$25="No","",IFERROR(IF(OR(N(AP48)=3,N(AP48)<=1),TRUE(),FALSE()),FALSE())) -> TRUE | CM48: =IF(Configuration!$C$26="No","",IFERROR(IF(N(BF48)>=Configuration!$C$49,TRUE(),FALSE()),FALSE())) -> FALSE | CN48: =IF(Configuration!$C$27="No","",IFERROR(IF(BD48<>"",TRUE(),FALSE()),FALSE())) -> FALSE | CO48: =IF(Configuration!$C$28="No","",IFERROR(IF(N(AU48)>=Configuration!$C$50,TRUE(),FALSE()),FALSE())) -> FALSE | CP48: =IF(Configuration!$C$29="No","",IFERROR(IF(AND(N(AR48)>=Configuration!$C$51,AG48<>""),TRUE(),FALSE()),FALSE())) -> FALSE | CQ48: =IF(Configuration!$C$30="No","",IFERROR(IF(OR(AW48="Pending",AX48="Yes"),TRUE(),FALSE()),FALSE())) -> FALSE | CR48: =IF(Configuration!$C$31="No","",IFERROR(IF(AND(N(BG48)>=Configuration!$C$52,N(AP48)>=1),TRUE(),FALSE()),FALSE())) -> FALSE | CS48: =IF(Configuration!$C$32="No","",IFERROR(IF(AND(N(AR48)>=1,OR(AG48<>"",AM48<>"")),TRUE(),FALSE()),FALSE())) -> FALSE | CT48: =IF(Configuration!$C$33="No","",IFERROR(IF(AG48<>"",TRUE(),FALSE()),FALSE())) -> FALSE | CU48: =IF(Configuration!$C$34="No","",IFERROR(IF(AX48="Yes",TRUE(),FALSE()),FALSE())) -> FALSE | CV48: =IF(Configuration!$C$35="No","",IFERROR(IF(OR(BO48="Partial",BO48="Full"),TRUE(),FALSE()),FALSE())) -> FALSE | CW48: =IF(Configuration!$C$36="No","",IFERROR(IF(BM48="Survived",TRUE(),FALSE()),FALSE())) -> FALSE | CX48: =IF(Configuration!$C$37="No","",IFERROR(IF(AND(BN48="Clean",BP48="None"),TRUE(),FALSE()),FALSE())) -> FALSE | CY48: =IF(Configuration!$C$38="No","",IFERROR(IF(N(BK48)>=Configuration!$C$53,TRUE(),FALSE()),FALSE())) -> FALSE | CZ48: =IF(Configuration!$C$39="No","",IFERROR(IF(AND(N(BS48)>=2,N(BF48)>=2),TRUE(),FALSE()),FALSE())) -> FALSE | DA48: =IF(Configuration!$C$40="No","",IFERROR(IF(OR(N(BG48)<=Configuration!$C$56,N(AY48)<Configuration!$C$57,N(BH48)<=Configuration!$C$58),TRUE(),FALSE()),FALSE())) -> TRUE | DB48: =IF(Configuration!$C$41="No","",IFERROR(IF(AND(N(AY48)>=Configuration!$C$54,N(AY48)<=Configuration!$C$55),TRUE(),FALSE()),FALSE())) -> FALSE | DC48: =IF(Configuration!$C$42="No","",IFERROR(IF(AND(AG48<>"",AJ48<>""),TRUE(),FALSE()),FALSE())) -> FALSE | DD48: =COUNTIF(BW48:DC48,TRUE()) -> 2
A49: 10 | AE49: =IFERROR(IF(F49<>"",F49,""),"") | AF49: =IFERROR(IF(G49<>"",G49,""),"") | AG49: =IFERROR(IF(AA49<>"",AA49,IF(R49<>"",R49,"")),"") | AH49: =IFERROR(IF(AB49<>"",AB49,IF(S49<>"",S49,"")),"") | AQ49: =IFERROR(IF(Y49<>"",VALUE(Y49),""),"") | AV49: =IFERROR(IF(T49<>"",VALUE(T49),""),"") | AW49: =IFERROR(IF(N49="","",IF(OR(ISNUMBER(SEARCH("grant",N49)),ISNUMBER(SEARCH("B",AC49))),"Granted",IF(OR(ISNUMBER(SEARCH("pend",N49)),ISNUMBER(SEARCH("A",AC49))),"Pending",IF(ISNUMBER(SEARCH("expir",N49)),"Expired",N49)))),"") | AY49: =IFERROR(IF(M49<>"",ROUND(VALUE(M49),1),IF(L49<>"",ROUND(MAX(0,(DATEVALUE(TEXT(L49,"YYYY-MM-DD"))-TODAY())/365.25),1),"")),"") | AZ49: =IFERROR(IF(O49<>"",O49,""),"") | BA49: =IFERROR(IF(U49<>"",SUBSTITUTE(SUBSTITUTE(U49,"; ",", "),";",","),""),"") | BK49: =IFERROR(IF(W49<>"",VALUE(W49),""),"") | BL49: =IFERROR(IF(X49<>"",VALUE(X49),""),"") | BM49: =IFERROR(IF(AD49="","None",IF(ISNUMBER(SEARCH("surv",AD49)),"Survived",IF(ISNUMBER(SEARCH("pend",AD49)),"Pending",IF(ISNUMBER(SEARCH("yes",AD49)),"Pending","None")))),"None") -> None | BU49: =IFERROR(COUNTA(AE49:BT49)/42,0) -> 0.30952381 | BW49: =IF(Configuration!$C$10="No","",IFERROR(IF(AG49<>"",TRUE(),FALSE()),FALSE())) -> FALSE | BX49: =IF(Configuration!$C$11="No","",IFERROR(IF(AND(N(AL49)>=Configuration!$C$44,AM49<>""),TRUE(),FALSE()),FALSE())) -> FALSE | BY49: =IF(Configuration!$C$12="No","",IFERROR(IF(AJ49<>"",TRUE(),FALSE()),FALSE())) -> FALSE | BZ49: =IF(Configuration!$C$13="No","",IFERROR(IF(AI49<>"",TRUE(),FALSE()),FALSE())) -> FALSE | CA49: =IF(Configuration!$C$14="No","",IFERROR(IF(AK49<>"",TRUE(),FALSE()),FALSE())) -> FALSE | CB49: =IF(Configuration!$C$15="No","",IFERROR(IF(AND(OR(ISNUMBER(SEARCH("process",AG49)),ISNUMBER(SEARCH("fab",AG49)),ISNUMBER(SEARCH("manufac",AG49))),AO49="Method"),TRUE(),FALSE()),FALSE())) -> FALSE | CC49: =IF(Configuration!$C$16="No","",IFERROR(IF(AND(OR(ISNUMBER(SEARCH("material",AG49)),ISNUMBER(SEARCH("chem",AG49)),ISNUMBER(SEARCH("battery",AG49)),ISNUMBER(SEARCH("electrolyte",AG49)),ISNUMBER(SEARCH("polymer",AG49))),OR(AO49="Apparatus",AO49="Method")),TRUE(),FALSE()),FALSE())) -> FALSE | CD49: =IF(Configuration!$C$17="No","",IFERROR(IF(AND(OR(AI49="App",AI49="Middleware",AI49="Cloud"),OR(AO49="Method",AO49="CRM")),TRUE(),FALSE()),FALSE())) -> FALSE | CE49: =IF(Configuration!$C$18="No","",IFERROR(IF(N(AN49)>=Configuration!$C$45,TRUE(),FALSE()),FALSE())) -> FALSE | CF49: =IF(Configuration!$C$19="No","",IFERROR(IF(BE49<>"",TRUE(),FALSE()),FALSE())) -> FALSE | CG49: =IF(Configuration!$C$20="No","",IFERROR(IF(AO49<>"",TRUE(),FALSE()),FALSE())) -> FALSE | CH49: =IF(Configuration!$C$21="No","",IFERROR(IF(OR(N(AS49)>=Configuration!$C$46,N(AT49)>=Configuration!$C$47),TRUE(),FALSE()),FALSE())) -> FALSE | CI49: =IF(Configuration!$C$22="No","",IFERROR(IF(BB49="Yes",TRUE(),FALSE()),FALSE())) -> FALSE | CJ49: =IF(Configuration!$C$23="No","",IFERROR(IF(N(AV49)>=Configuration!$C$48,TRUE(),FALSE()),FALSE())) -> FALSE | CK49: =IF(Configuration!$C$24="No","",IFERROR(IF(N(AY49)>0,TRUE(),FALSE()),FALSE())) -> FALSE | CL49: =IF(Configuration!$C$25="No","",IFERROR(IF(OR(N(AP49)=3,N(AP49)<=1),TRUE(),FALSE()),FALSE())) -> TRUE | CM49: =IF(Configuration!$C$26="No","",IFERROR(IF(N(BF49)>=Configuration!$C$49,TRUE(),FALSE()),FALSE())) -> FALSE | CN49: =IF(Configuration!$C$27="No","",IFERROR(IF(BD49<>"",TRUE(),FALSE()),FALSE())) -> FALSE | CO49: =IF(Configuration!$C$28="No","",IFERROR(IF(N(AU49)>=Configuration!$C$50,TRUE(),FALSE()),FALSE())) -> FALSE | CP49: =IF(Configuration!$C$29="No","",IFERROR(IF(AND(N(AR49)>=Configuration!$C$51,AG49<>""),TRUE(),FALSE()),FALSE())) -> FALSE | CQ49: =IF(Configuration!$C$30="No","",IFERROR(IF(OR(AW49="Pending",AX49="Yes"),TRUE(),FALSE()),FALSE())) -> FALSE | CR49: =IF(Configuration!$C$31="No","",IFERROR(IF(AND(N(BG49)>=Configuration!$C$52,N(AP49)>=1),TRUE(),FALSE()),FALSE())) -> FALSE | CS49: =IF(Configuration!$C$32="No","",IFERROR(IF(AND(N(AR49)>=1,OR(AG49<>"",AM49<>"")),TRUE(),FALSE()),FALSE())) -> FALSE | CT49: =IF(Configuration!$C$33="No","",IFERROR(IF(AG49<>"",TRUE(),FALSE()),FALSE())) -> FALSE | CU49: =IF(Configuration!$C$34="No","",IFERROR(IF(AX49="Yes",TRUE(),FALSE()),FALSE())) -> FALSE | CV49: =IF(Configuration!$C$35="No","",IFERROR(IF(OR(BO49="Partial",BO49="Full"),TRUE(),FALSE()),FALSE())) -> FALSE | CW49: =IF(Configuration!$C$36="No","",IFERROR(IF(BM49="Survived",TRUE(),FALSE()),FALSE())) -> FALSE | CX49: =IF(Configuration!$C$37="No","",IFERROR(IF(AND(BN49="Clean",BP49="None"),TRUE(),FALSE()),FALSE())) -> FALSE | CY49: =IF(Configuration!$C$38="No","",IFERROR(IF(N(BK49)>=Configuration!$C$53,TRUE(),FALSE()),FALSE())) -> FALSE | CZ49: =IF(Configuration!$C$39="No","",IFERROR(IF(AND(N(BS49)>=2,N(BF49)>=2),TRUE(),FALSE()),FALSE())) -> FALSE | DA49: =IF(Configuration!$C$40="No","",IFERROR(IF(OR(N(BG49)<=Configuration!$C$56,N(AY49)<Configuration!$C$57,N(BH49)<=Configuration!$C$58),TRUE(),FALSE()),FALSE())) -> TRUE | DB49: =IF(Configuration!$C$41="No","",IFERROR(IF(AND(N(AY49)>=Configuration!$C$54,N(AY49)<=Configuration!$C$55),TRUE(),FALSE()),FALSE())) -> FALSE | DC49: =IF(Configuration!$C$42="No","",IFERROR(IF(AND(AG49<>"",AJ49<>""),TRUE(),FALSE()),FALSE())) -> FALSE | DD49: =COUNTIF(BW49:DC49,TRUE()) -> 2
A50: 11 | AE50: =IFERROR(IF(F50<>"",F50,""),"") | AF50: =IFERROR(IF(G50<>"",G50,""),"") | AG50: =IFERROR(IF(AA50<>"",AA50,IF(R50<>"",R50,"")),"") | AH50: =IFERROR(IF(AB50<>"",AB50,IF(S50<>"",S50,"")),"") | AQ50: =IFERROR(IF(Y50<>"",VALUE(Y50),""),"") | AV50: =IFERROR(IF(T50<>"",VALUE(T50),""),"") | AW50: =IFERROR(IF(N50="","",IF(OR(ISNUMBER(SEARCH("grant",N50)),ISNUMBER(SEARCH("B",AC50))),"Granted",IF(OR(ISNUMBER(SEARCH("pend",N50)),ISNUMBER(SEARCH("A",AC50))),"Pending",IF(ISNUMBER(SEARCH("expir",N50)),"Expired",N50)))),"") | AY50: =IFERROR(IF(M50<>"",ROUND(VALUE(M50),1),IF(L50<>"",ROUND(MAX(0,(DATEVALUE(TEXT(L50,"YYYY-MM-DD"))-TODAY())/365.25),1),"")),"") | AZ50: =IFERROR(IF(O50<>"",O50,""),"") | BA50: =IFERROR(IF(U50<>"",SUBSTITUTE(SUBSTITUTE(U50,"; ",", "),";",","),""),"") | BK50: =IFERROR(IF(W50<>"",VALUE(W50),""),"") | BL50: =IFERROR(IF(X50<>"",VALUE(X50),""),"") | BM50: =IFERROR(IF(AD50="","None",IF(ISNUMBER(SEARCH("surv",AD50)),"Survived",IF(ISNUMBER(SEARCH("pend",AD50)),"Pending",IF(ISNUMBER(SEARCH("yes",AD50)),"Pending","None")))),"None") -> None | BU50: =IFERROR(COUNTA(AE50:BT50)/42,0) -> 0.30952381 | BW50: =IF(Configuration!$C$10="No","",IFERROR(IF(AG50<>"",TRUE(),FALSE()),FALSE())) -> FALSE | BX50: =IF(Configuration!$C$11="No","",IFERROR(IF(AND(N(AL50)>=Configuration!$C$44,AM50<>""),TRUE(),FALSE()),FALSE())) -> FALSE | BY50: =IF(Configuration!$C$12="No","",IFERROR(IF(AJ50<>"",TRUE(),FALSE()),FALSE())) -> FALSE | BZ50: =IF(Configuration!$C$13="No","",IFERROR(IF(AI50<>"",TRUE(),FALSE()),FALSE())) -> FALSE | CA50: =IF(Configuration!$C$14="No","",IFERROR(IF(AK50<>"",TRUE(),FALSE()),FALSE())) -> FALSE | CB50: =IF(Configuration!$C$15="No","",IFERROR(IF(AND(OR(ISNUMBER(SEARCH("process",AG50)),ISNUMBER(SEARCH("fab",AG50)),ISNUMBER(SEARCH("manufac",AG50))),AO50="Method"),TRUE(),FALSE()),FALSE())) -> FALSE | CC50: =IF(Configuration!$C$16="No","",IFERROR(IF(AND(OR(ISNUMBER(SEARCH("material",AG50)),ISNUMBER(SEARCH("chem",AG50)),ISNUMBER(SEARCH("battery",AG50)),ISNUMBER(SEARCH("electrolyte",AG50)),ISNUMBER(SEARCH("polymer",AG50))),OR(AO50="Apparatus",AO50="Method")),TRUE(),FALSE()),FALSE())) -> FALSE | CD50: =IF(Configuration!$C$17="No","",IFERROR(IF(AND(OR(AI50="App",AI50="Middleware",AI50="Cloud"),OR(AO50="Method",AO50="CRM")),TRUE(),FALSE()),FALSE())) -> FALSE | CE50: =IF(Configuration!$C$18="No","",IFERROR(IF(N(AN50)>=Configuration!$C$45,TRUE(),FALSE()),FALSE())) -> FALSE | CF50: =IF(Configuration!$C$19="No","",IFERROR(IF(BE50<>"",TRUE(),FALSE()),FALSE())) -> FALSE | CG50: =IF(Configuration!$C$20="No","",IFERROR(IF(AO50<>"",TRUE(),FALSE()),FALSE())) -> FALSE | CH50: =IF(Configuration!$C$21="No","",IFERROR(IF(OR(N(AS50)>=Configuration!$C$46,N(AT50)>=Configuration!$C$47),TRUE(),FALSE()),FALSE())) -> FALSE | CI50: =IF(Configuration!$C$22="No","",IFERROR(IF(BB50="Yes",TRUE(),FALSE()),FALSE())) -> FALSE | CJ50: =IF(Configuration!$C$23="No","",IFERROR(IF(N(AV50)>=Configuration!$C$48,TRUE(),FALSE()),FALSE())) -> FALSE | CK50: =IF(Configuration!$C$24="No","",IFERROR(IF(N(AY50)>0,TRUE(),FALSE()),FALSE())) -> FALSE | CL50: =IF(Configuration!$C$25="No","",IFERROR(IF(OR(N(AP50)=3,N(AP50)<=1),TRUE(),FALSE()),FALSE())) -> TRUE | CM50: =IF(Configuration!$C$26="No","",IFERROR(IF(N(BF50)>=Configuration!$C$49,TRUE(),FALSE()),FALSE())) -> FALSE | CN50: =IF(Configuration!$C$27="No","",IFERROR(IF(BD50<>"",TRUE(),FALSE()),FALSE())) -> FALSE | CO50: =IF(Configuration!$C$28="No","",IFERROR(IF(N(AU50)>=Configuration!$C$50,TRUE(),FALSE()),FALSE())) -> FALSE | CP50: =IF(Configuration!$C$29="No","",IFERROR(IF(AND(N(AR50)>=Configuration!$C$51,AG50<>""),TRUE(),FALSE()),FALSE())) -> FALSE | CQ50: =IF(Configuration!$C$30="No","",IFERROR(IF(OR(AW50="Pending",AX50="Yes"),TRUE(),FALSE()),FALSE())) -> FALSE | CR50: =IF(Configuration!$C$31="No","",IFERROR(IF(AND(N(BG50)>=Configuration!$C$52,N(AP50)>=1),TRUE(),FALSE()),FALSE())) -> FALSE | CS50: =IF(Configuration!$C$32="No","",IFERROR(IF(AND(N(AR50)>=1,OR(AG50<>"",AM50<>"")),TRUE(),FALSE()),FALSE())) -> FALSE | CT50: =IF(Configuration!$C$33="No","",IFERROR(IF(AG50<>"",TRUE(),FALSE()),FALSE())) -> FALSE | CU50: =IF(Configuration!$C$34="No","",IFERROR(IF(AX50="Yes",TRUE(),FALSE()),FALSE())) -> FALSE | CV50: =IF(Configuration!$C$35="No","",IFERROR(IF(OR(BO50="Partial",BO50="Full"),TRUE(),FALSE()),FALSE())) -> FALSE | CW50: =IF(Configuration!$C$36="No","",IFERROR(IF(BM50="Survived",TRUE(),FALSE()),FALSE())) -> FALSE | CX50: =IF(Configuration!$C$37="No","",IFERROR(IF(AND(BN50="Clean",BP50="None"),TRUE(),FALSE()),FALSE())) -> FALSE | CY50: =IF(Configuration!$C$38="No","",IFERROR(IF(N(BK50)>=Configuration!$C$53,TRUE(),FALSE()),FALSE())) -> FALSE | CZ50: =IF(Configuration!$C$39="No","",IFERROR(IF(AND(N(BS50)>=2,N(BF50)>=2),TRUE(),FALSE()),FALSE())) -> FALSE | DA50: =IF(Configuration!$C$40="No","",IFERROR(IF(OR(N(BG50)<=Configuration!$C$56,N(AY50)<Configuration!$C$57,N(BH50)<=Configuration!$C$58),TRUE(),FALSE()),FALSE())) -> TRUE | DB50: =IF(Configuration!$C$41="No","",IFERROR(IF(AND(N(AY50)>=Configuration!$C$54,N(AY50)<=Configuration!$C$55),TRUE(),FALSE()),FALSE())) -> FALSE | DC50: =IF(Configuration!$C$42="No","",IFERROR(IF(AND(AG50<>"",AJ50<>""),TRUE(),FALSE()),FALSE())) -> FALSE | DD50: =COUNTIF(BW50:DC50,TRUE()) -> 2
A51: 12 | AE51: =IFERROR(IF(F51<>"",F51,""),"") | AF51: =IFERROR(IF(G51<>"",G51,""),"") | AG51: =IFERROR(IF(AA51<>"",AA51,IF(R51<>"",R51,"")),"") | AH51: =IFERROR(IF(AB51<>"",AB51,IF(S51<>"",S51,"")),"") | AQ51: =IFERROR(IF(Y51<>"",VALUE(Y51),""),"") | AV51: =IFERROR(IF(T51<>"",VALUE(T51),""),"") | AW51: =IFERROR(IF(N51="","",IF(OR(ISNUMBER(SEARCH("grant",N51)),ISNUMBER(SEARCH("B",AC51))),"Granted",IF(OR(ISNUMBER(SEARCH("pend",N51)),ISNUMBER(SEARCH("A",AC51))),"Pending",IF(ISNUMBER(SEARCH("expir",N51)),"Expired",N51)))),"") | AY51: =IFERROR(IF(M51<>"",ROUND(VALUE(M51),1),IF(L51<>"",ROUND(MAX(0,(DATEVALUE(TEXT(L51,"YYYY-MM-DD"))-TODAY())/365.25),1),"")),"") | AZ51: =IFERROR(IF(O51<>"",O51,""),"") | BA51: =IFERROR(IF(U51<>"",SUBSTITUTE(SUBSTITUTE(U51,"; ",", "),";",","),""),"") | BK51: =IFERROR(IF(W51<>"",VALUE(W51),""),"") | BL51: =IFERROR(IF(X51<>"",VALUE(X51),""),"") | BM51: =IFERROR(IF(AD51="","None",IF(ISNUMBER(SEARCH("surv",AD51)),"Survived",IF(ISNUMBER(SEARCH("pend",AD51)),"Pending",IF(ISNUMBER(SEARCH("yes",AD51)),"Pending","None")))),"None") -> None | BU51: =IFERROR(COUNTA(AE51:BT51)/42,0) -> 0.30952381 | BW51: =IF(Configuration!$C$10="No","",IFERROR(IF(AG51<>"",TRUE(),FALSE()),FALSE())) -> FALSE | BX51: =IF(Configuration!$C$11="No","",IFERROR(IF(AND(N(AL51)>=Configuration!$C$44,AM51<>""),TRUE(),FALSE()),FALSE())) -> FALSE | BY51: =IF(Configuration!$C$12="No","",IFERROR(IF(AJ51<>"",TRUE(),FALSE()),FALSE())) -> FALSE | BZ51: =IF(Configuration!$C$13="No","",IFERROR(IF(AI51<>"",TRUE(),FALSE()),FALSE())) -> FALSE | CA51: =IF(Configuration!$C$14="No","",IFERROR(IF(AK51<>"",TRUE(),FALSE()),FALSE())) -> FALSE | CB51: =IF(Configuration!$C$15="No","",IFERROR(IF(AND(OR(ISNUMBER(SEARCH("process",AG51)),ISNUMBER(SEARCH("fab",AG51)),ISNUMBER(SEARCH("manufac",AG51))),AO51="Method"),TRUE(),FALSE()),FALSE())) -> FALSE | CC51: =IF(Configuration!$C$16="No","",IFERROR(IF(AND(OR(ISNUMBER(SEARCH("material",AG51)),ISNUMBER(SEARCH("chem",AG51)),ISNUMBER(SEARCH("battery",AG51)),ISNUMBER(SEARCH("electrolyte",AG51)),ISNUMBER(SEARCH("polymer",AG51))),OR(AO51="Apparatus",AO51="Method")),TRUE(),FALSE()),FALSE())) -> FALSE | CD51: =IF(Configuration!$C$17="No","",IFERROR(IF(AND(OR(AI51="App",AI51="Middleware",AI51="Cloud"),OR(AO51="Method",AO51="CRM")),TRUE(),FALSE()),FALSE())) -> FALSE | CE51: =IF(Configuration!$C$18="No","",IFERROR(IF(N(AN51)>=Configuration!$C$45,TRUE(),FALSE()),FALSE())) -> FALSE | CF51: =IF(Configuration!$C$19="No","",IFERROR(IF(BE51<>"",TRUE(),FALSE()),FALSE())) -> FALSE | CG51: =IF(Configuration!$C$20="No","",IFERROR(IF(AO51<>"",TRUE(),FALSE()),FALSE())) -> FALSE | CH51: =IF(Configuration!$C$21="No","",IFERROR(IF(OR(N(AS51)>=Configuration!$C$46,N(AT51)>=Configuration!$C$47),TRUE(),FALSE()),FALSE())) -> FALSE | CI51: =IF(Configuration!$C$22="No","",IFERROR(IF(BB51="Yes",TRUE(),FALSE()),FALSE())) -> FALSE | CJ51: =IF(Configuration!$C$23="No","",IFERROR(IF(N(AV51)>=Configuration!$C$48,TRUE(),FALSE()),FALSE())) -> FALSE | CK51: =IF(Configuration!$C$24="No","",IFERROR(IF(N(AY51)>0,TRUE(),FALSE()),FALSE())) -> FALSE | CL51: =IF(Configuration!$C$25="No","",IFERROR(IF(OR(N(AP51)=3,N(AP51)<=1),TRUE(),FALSE()),FALSE())) -> TRUE | CM51: =IF(Configuration!$C$26="No","",IFERROR(IF(N(BF51)>=Configuration!$C$49,TRUE(),FALSE()),FALSE())) -> FALSE | CN51: =IF(Configuration!$C$27="No","",IFERROR(IF(BD51<>"",TRUE(),FALSE()),FALSE())) -> FALSE | CO51: =IF(Configuration!$C$28="No","",IFERROR(IF(N(AU51)>=Configuration!$C$50,TRUE(),FALSE()),FALSE())) -> FALSE | CP51: =IF(Configuration!$C$29="No","",IFERROR(IF(AND(N(AR51)>=Configuration!$C$51,AG51<>""),TRUE(),FALSE()),FALSE())) -> FALSE | CQ51: =IF(Configuration!$C$30="No","",IFERROR(IF(OR(AW51="Pending",AX51="Yes"),TRUE(),FALSE()),FALSE())) -> FALSE | CR51: =IF(Configuration!$C$31="No","",IFERROR(IF(AND(N(BG51)>=Configuration!$C$52,N(AP51)>=1),TRUE(),FALSE()),FALSE())) -> FALSE | CS51: =IF(Configuration!$C$32="No","",IFERROR(IF(AND(N(AR51)>=1,OR(AG51<>"",AM51<>"")),TRUE(),FALSE()),FALSE())) -> FALSE | CT51: =IF(Configuration!$C$33="No","",IFERROR(IF(AG51<>"",TRUE(),FALSE()),FALSE())) -> FALSE | CU51: =IF(Configuration!$C$34="No","",IFERROR(IF(AX51="Yes",TRUE(),FALSE()),FALSE())) -> FALSE | CV51: =IF(Configuration!$C$35="No","",IFERROR(IF(OR(BO51="Partial",BO51="Full"),TRUE(),FALSE()),FALSE())) -> FALSE | CW51: =IF(Configuration!$C$36="No","",IFERROR(IF(BM51="Survived",TRUE(),FALSE()),FALSE())) -> FALSE | CX51: =IF(Configuration!$C$37="No","",IFERROR(IF(AND(BN51="Clean",BP51="None"),TRUE(),FALSE()),FALSE())) -> FALSE | CY51: =IF(Configuration!$C$38="No","",IFERROR(IF(N(BK51)>=Configuration!$C$53,TRUE(),FALSE()),FALSE())) -> FALSE | CZ51: =IF(Configuration!$C$39="No","",IFERROR(IF(AND(N(BS51)>=2,N(BF51)>=2),TRUE(),FALSE()),FALSE())) -> FALSE | DA51: =IF(Configuration!$C$40="No","",IFERROR(IF(OR(N(BG51)<=Configuration!$C$56,N(AY51)<Configuration!$C$57,N(BH51)<=Configuration!$C$58),TRUE(),FALSE()),FALSE())) -> TRUE | DB51: =IF(Configuration!$C$41="No","",IFERROR(IF(AND(N(AY51)>=Configuration!$C$54,N(AY51)<=Configuration!$C$55),TRUE(),FALSE()),FALSE())) -> FALSE | DC51: =IF(Configuration!$C$42="No","",IFERROR(IF(AND(AG51<>"",AJ51<>""),TRUE(),FALSE()),FALSE())) -> FALSE | DD51: =COUNTIF(BW51:DC51,TRUE()) -> 2
... A239: 200 | AE239: =IFERROR(IF(F239<>"",F239,""),"") | AF239: =IFERROR(IF(G239<>"",G239,""),"") | AG239: =IFERROR(IF(AA239<>"",AA239,IF(R239<>"",R239,"")),"") | AH239: =IFERROR(IF(AB239<>"",AB239,IF(S239<>"",S239,"")),"") | AQ239: =IFERROR(IF(Y239<>"",VALUE(Y239),""),"") | AV239: =IFERROR(IF(T239<>"",VALUE(T239),""),"") | AW239: =IFERROR(IF(N239="","",IF(OR(ISNUMBER(SEARCH("grant",N239)),ISNUMBER(SEARCH("B",AC239))),"Granted",IF(OR(ISNUMBER(SEARCH("pend",N239)),ISNUMBER(SEARCH("A",AC239))),"Pending",IF(ISNUMBER(SEARCH("expir",N239)),"Expired",N239)))),"") | AY239: =IFERROR(IF(M239<>"",ROUND(VALUE(M239),1),IF(L239<>"",ROUND(MAX(0,(DATEVALUE(TEXT(L239,"YYYY-MM-DD"))-TODAY())/365.25),1),"")),"") | AZ239: =IFERROR(IF(O239<>"",O239,""),"") | BA239: =IFERROR(IF(U239<>"",SUBSTITUTE(SUBSTITUTE(U239,"; ",", "),";",","),""),"") | BK239: =IFERROR(IF(W239<>"",VALUE(W239),""),"") | BL239: =IFERROR(IF(X239<>"",VALUE(X239),""),"") | BM239: =IFERROR(IF(AD239="","None",IF(ISNUMBER(SEARCH("surv",AD239)),"Survived",IF(ISNUMBER(SEARCH("pend",AD239)),"Pending",IF(ISNUMBER(SEARCH("yes",AD239)),"Pending","None")))),"None") -> None | BU239: =IFERROR(COUNTA(AE239:BT239)/42,0) -> 0.30952381 | BW239: =IF(Configuration!$C$10="No","",IFERROR(IF(AG239<>"",TRUE(),FALSE()),FALSE())) -> FALSE | BX239: =IF(Configuration!$C$11="No","",IFERROR(IF(AND(N(AL239)>=Configuration!$C$44,AM239<>""),TRUE(),FALSE()),FALSE())) -> FALSE | BY239: =IF(Configuration!$C$12="No","",IFERROR(IF(AJ239<>"",TRUE(),FALSE()),FALSE())) -> FALSE | BZ239: =IF(Configuration!$C$13="No","",IFERROR(IF(AI239<>"",TRUE(),FALSE()),FALSE())) -> FALSE | CA239: =IF(Configuration!$C$14="No","",IFERROR(IF(AK239<>"",TRUE(),FALSE()),FALSE())) -> FALSE | CB239: =IF(Configuration!$C$15="No","",IFERROR(IF(AND(OR(ISNUMBER(SEARCH("process",AG239)),ISNUMBER(SEARCH("fab",AG239)),ISNUMBER(SEARCH("manufac",AG239))),AO239="Method"),TRUE(),FALSE()),FALSE())) -> FALSE | CC239: =IF(Configuration!$C$16="No","",IFERROR(IF(AND(OR(ISNUMBER(SEARCH("material",AG239)),ISNUMBER(SEARCH("chem",AG239)),ISNUMBER(SEARCH("battery",AG239)),ISNUMBER(SEARCH("electrolyte",AG239)),ISNUMBER(SEARCH("polymer",AG239))),OR(AO239="Apparatus",AO239="Method")),TRUE(),FALSE()),FALSE())) -> FALSE | CD239: =IF(Configuration!$C$17="No","",IFERROR(IF(AND(OR(AI239="App",AI239="Middleware",AI239="Cloud"),OR(AO239="Method",AO239="CRM")),TRUE(),FALSE()),FALSE())) -> FALSE | CE239: =IF(Configuration!$C$18="No","",IFERROR(IF(N(AN239)>=Configuration!$C$45,TRUE(),FALSE()),FALSE())) -> FALSE | CF239: =IF(Configuration!$C$19="No","",IFERROR(IF(BE239<>"",TRUE(),FALSE()),FALSE())) -> FALSE | CG239: =IF(Configuration!$C$20="No","",IFERROR(IF(AO239<>"",TRUE(),FALSE()),FALSE())) -> FALSE | CH239: =IF(Configuration!$C$21="No","",IFERROR(IF(OR(N(AS239)>=Configuration!$C$46,N(AT239)>=Configuration!$C$47),TRUE(),FALSE()),FALSE())) -> FALSE | CI239: =IF(Configuration!$C$22="No","",IFERROR(IF(BB239="Yes",TRUE(),FALSE()),FALSE())) -> FALSE | CJ239: =IF(Configuration!$C$23="No","",IFERROR(IF(N(AV239)>=Configuration!$C$48,TRUE(),FALSE()),FALSE())) -> FALSE | CK239: =IF(Configuration!$C$24="No","",IFERROR(IF(N(AY239)>0,TRUE(),FALSE()),FALSE())) -> FALSE | CL239: =IF(Configuration!$C$25="No","",IFERROR(IF(OR(N(AP239)=3,N(AP239)<=1),TRUE(),FALSE()),FALSE())) -> TRUE | CM239: =IF(Configuration!$C$26="No","",IFERROR(IF(N(BF239)>=Configuration!$C$49,TRUE(),FALSE()),FALSE())) -> FALSE | CN239: =IF(Configuration!$C$27="No","",IFERROR(IF(BD239<>"",TRUE(),FALSE()),FALSE())) -> FALSE | CO239: =IF(Configuration!$C$28="No","",IFERROR(IF(N(AU239)>=Configuration!$C$50,TRUE(),FALSE()),FALSE())) -> FALSE | CP239: =IF(Configuration!$C$29="No","",IFERROR(IF(AND(N(AR239)>=Configuration!$C$51,AG239<>""),TRUE(),FALSE()),FALSE())) -> FALSE | CQ239: =IF(Configuration!$C$30="No","",IFERROR(IF(OR(AW239="Pending",AX239="Yes"),TRUE(),FALSE()),FALSE())) -> FALSE | CR239: =IF(Configuration!$C$31="No","",IFERROR(IF(AND(N(BG239)>=Configuration!$C$52,N(AP239)>=1),TRUE(),FALSE()),FALSE())) -> FALSE | CS239: =IF(Configuration!$C$32="No","",IFERROR(IF(AND(N(AR239)>=1,OR(AG239<>"",AM239<>"")),TRUE(),FALSE()),FALSE())) -> FALSE | CT239: =IF(Configuration!$C$33="No","",IFERROR(IF(AG239<>"",TRUE(),FALSE()),FALSE())) -> FALSE | CU239: =IF(Configuration!$C$34="No","",IFERROR(IF(AX239="Yes",TRUE(),FALSE()),FALSE())) -> FALSE | CV239: =IF(Configuration!$C$35="No","",IFERROR(IF(OR(BO239="Partial",BO239="Full"),TRUE(),FALSE()),FALSE())) -> FALSE | CW239: =IF(Configuration!$C$36="No","",IFERROR(IF(BM239="Survived",TRUE(),FALSE()),FALSE())) -> FALSE | CX239: =IF(Configuration!$C$37="No","",IFERROR(IF(AND(BN239="Clean",BP239="None"),TRUE(),FALSE()),FALSE())) -> FALSE | CY239: =IF(Configuration!$C$38="No","",IFERROR(IF(N(BK239)>=Configuration!$C$53,TRUE(),FALSE()),FALSE())) -> FALSE | CZ239: =IF(Configuration!$C$39="No","",IFERROR(IF(AND(N(BS239)>=2,N(BF239)>=2),TRUE(),FALSE()),FALSE())) -> FALSE | DA239: =IF(Configuration!$C$40="No","",IFERROR(IF(OR(N(BG239)<=Configuration!$C$56,N(AY239)<Configuration!$C$57,N(BH239)<=Configuration!$C$58),TRUE(),FALSE()),FALSE())) -> TRUE | DB239: =IF(Configuration!$C$41="No","",IFERROR(IF(AND(N(AY239)>=Configuration!$C$54,N(AY239)<=Configuration!$C$55),TRUE(),FALSE()),FALSE())) -> FALSE | DC239: =IF(Configuration!$C$42="No","",IFERROR(IF(AND(AG239<>"",AJ239<>""),TRUE(),FALSE()),FALSE())) -> FALSE | DD239: =COUNTIF(BW239:DC239,TRUE()) -> 2

Sheet Configuration
A1: CONFIGURATION
A2: Pick a preset, or switch to Edit Mode to override individual values. All Bundle Assignment and Scorecard formulas read from this sheet.
A4: Active Preset: | B4: All ON (default) | E4: ← Pick from Presets sheet. Changing this updates all Active Values below.
A5: Edit Mode: | B5: No | E5: ← Yes = use Manual Override column. No = use selected preset.
A6: Summary: | B6: ="Bundles active: "&COUNTIF(C10:C42,"Yes")&" of 33 | Gates active: "&COUNTIF(C63:C67,"Yes")&" of 5 | "&IF($B$5="Yes","EDIT MODE — using Manual Override values","Using preset: "&$B$4) -> Bundles active: 33 of 33 | Gates active: 5 of 5 | Using preset: All ON (default)
A8: Parameter | B8: Description | C8: Active Value (use this in formulas) | D8: From Preset | E8: Manual Override
A9: BUNDLE TOGGLES (Yes = bundle is active in this analysis)
A10: B1_enabled | B10: Bundle 1 — Tech Domain | C10: =IF($B$5="Yes",E10,D10) -> Yes | D10: =INDEX(Presets!$C$4:$L$4,MATCH($B$4,Presets!$C$1:$L$1,0)) -> Yes | E10: Yes
A11: B2_enabled | B11: Bundle 2 — SEP | C11: =IF($B$5="Yes",E11,D11) -> Yes | D11: =INDEX(Presets!$C$5:$L$5,MATCH($B$4,Presets!$C$1:$L$1,0)) -> Yes | E11: Yes
A12: B3_enabled | B12: Bundle 3 — Product Architecture | C12: =IF($B$5="Yes",E12,D12) -> Yes | D12: =INDEX(Presets!$C$6:$L$6,MATCH($B$4,Presets!$C$1:$L$1,0)) -> Yes | E12: Yes
A13: B4_enabled | B13: Bundle 4 — Stack Layer | C13: =IF($B$5="Yes",E13,D13) -> Yes | D13: =INDEX(Presets!$C$7:$L$7,MATCH($B$4,Presets!$C$1:$L$1,0)) -> Yes | E13: Yes
A14: B5_enabled | B14: Bundle 5 — Use-Case | C14: =IF($B$5="Yes",E14,D14) -> Yes | D14: =INDEX(Presets!$C$8:$L$8,MATCH($B$4,Presets!$C$1:$L$1,0)) -> Yes | E14: Yes
A15: B6_enabled | B15: Bundle 6 — Manufacturing / Process | C15: =IF($B$5="Yes",E15,D15) -> Yes | D15: =INDEX(Presets!$C$9:$L$9,MATCH($B$4,Presets!$C$1:$L$1,0)) -> Yes | E15: Yes
A16: B7_enabled | B16: Bundle 7 — Materials & Chemistry | C16: =IF($B$5="Yes",E16,D16) -> Yes | D16: =INDEX(Presets!$C$10:$L$10,MATCH($B$4,Presets!$C$1:$L$1,0)) -> Yes | E16: Yes
A17: B8_enabled | B17: Bundle 8 — Algorithm / Software | C17: =IF($B$5="Yes",E17,D17) -> Yes | D17: =INDEX(Presets!$C$11:$L$11,MATCH($B$4,Presets!$C$1:$L$1,0)) -> Yes | E17: Yes
A18: B9_enabled | B18: Bundle 9 — Interoperability | C18: =IF($B$5="Yes",E18,D18) -> Yes | D18: =INDEX(Presets!$C$12:$L$12,MATCH($B$4,Presets!$C$1:$L$1,0)) -> Yes | E18: Yes
A19: B10_enabled | B19: Bundle 10 — Generational Roadmap | C19: =IF($B$5="Yes",E19,D19) -> Yes | D19: =INDEX(Presets!$C$13:$L$13,MATCH($B$4,Presets!$C$1:$L$1,0)) -> Yes | E19: Yes
A20: B11_enabled | B20: Bundle 11 — Claim-Type | C20: =IF($B$5="Yes",E20,D20) -> Yes | D20: =INDEX(Presets!$C$14:$L$14,MATCH($B$4,Presets!$C$1:$L$1,0)) -> Yes | E20: Yes
A21: B12_enabled | B21: Bundle 12 — Detectability | C21: =IF($B$5="Yes",E21,D21) -> Yes | D21: =INDEX(Presets!$C$15:$L$15,MATCH($B$4,Presets!$C$1:$L$1,0)) -> Yes | E21: Yes
A22: B13_enabled | B22: Bundle 13 — Geographic | C22: =IF($B$5="Yes",E22,D22) -> Yes | D22: =INDEX(Presets!$C$16:$L$16,MATCH($B$4,Presets!$C$1:$L$1,0)) -> Yes | E22: Yes
A23: B14_enabled | B23: Bundle 14 — Family-Tree | C23: =IF($B$5="Yes",E23,D23) -> Yes | D23: =INDEX(Presets!$C$17:$L$17,MATCH($B$4,Presets!$C$1:$L$1,0)) -> Yes | E23: Yes
A24: B15_enabled | B24: Bundle 15 — Lifecycle / Term | C24: =IF($B$5="Yes",E24,D24) -> Yes | D24: =INDEX(Presets!$C$18:$L$18,MATCH($B$4,Presets!$C$1:$L$1,0)) -> Yes | E24: Yes
A25: B16_enabled | B25: Bundle 16 — Foundational + Improvement | C25: =IF($B$5="Yes",E25,D25) -> Yes | D25: =INDEX(Presets!$C$19:$L$19,MATCH($B$4,Presets!$C$1:$L$1,0)) -> Yes | E25: Yes
A26: B17_enabled | B26: Bundle 17 — Cross-Industry | C26: =IF($B$5="Yes",E26,D26) -> Yes | D26: =INDEX(Presets!$C$20:$L$20,MATCH($B$4,Presets!$C$1:$L$1,0)) -> Yes | E26: Yes
A27: B18_enabled | B27: Bundle 18 — Convergent Theme | C27: =IF($B$5="Yes",E27,D27) -> Yes | D27: =INDEX(Presets!$C$21:$L$21,MATCH($B$4,Presets!$C$1:$L$1,0)) -> Yes | E27: Yes
A28: B19_enabled | B28: Bundle 19 — Defensive / Counter-Assert. | C28: =IF($B$5="Yes",E28,D28) -> Yes | D28: =INDEX(Presets!$C$22:$L$22,MATCH($B$4,Presets!$C$1:$L$1,0)) -> Yes | E28: Yes
A29: B20_enabled | B29: Bundle 20 — Whitespace / Design-Around | C29: =IF($B$5="Yes",E29,D29) -> Yes | D29: =INDEX(Presets!$C$23:$L$23,MATCH($B$4,Presets!$C$1:$L$1,0)) -> Yes | E29: Yes
A30: B21_enabled | B30: Bundle 21 — Prosecution-Status | C30: =IF($B$5="Yes",E30,D30) -> Yes | D30: =INDEX(Presets!$C$24:$L$24,MATCH($B$4,Presets!$C$1:$L$1,0)) -> Yes | E30: Yes
A31: B22_enabled | B31: Bundle 22 — Anchor-and-Halo | C31: =IF($B$5="Yes",E31,D31) -> Yes | D31: =INDEX(Presets!$C$25:$L$25,MATCH($B$4,Presets!$C$1:$L$1,0)) -> Yes | E31: Yes
A32: B23_enabled | B32: Bundle 23 — Picket-Fence | C32: =IF($B$5="Yes",E32,D32) -> Yes | D32: =INDEX(Presets!$C$26:$L$26,MATCH($B$4,Presets!$C$1:$L$1,0)) -> Yes | E32: Yes
A33: B24_enabled | B33: Bundle 24 — Strong-Core + Tail | C33: =IF($B$5="Yes",E33,D33) -> Yes | D33: =INDEX(Presets!$C$27:$L$27,MATCH($B$4,Presets!$C$1:$L$1,0)) -> Yes | E33: Yes
A34: B25_enabled | B34: Bundle 25 — Continuation-Live | C34: =IF($B$5="Yes",E34,D34) -> Yes | D34: =INDEX(Presets!$C$28:$L$28,MATCH($B$4,Presets!$C$1:$L$1,0)) -> Yes | E34: Yes
A35: B26_enabled | B35: Bundle 26 — EoU-Backed | C35: =IF($B$5="Yes",E35,D35) -> Yes | D35: =INDEX(Presets!$C$29:$L$29,MATCH($B$4,Presets!$C$1:$L$1,0)) -> Yes | E35: Yes
A36: B27_enabled | B36: Bundle 27 — Battle-Tested | C36: =IF($B$5="Yes",E36,D36) -> Yes | D36: =INDEX(Presets!$C$30:$L$30,MATCH($B$4,Presets!$C$1:$L$1,0)) -> Yes | E36: Yes
A37: B28_enabled | B37: Bundle 28 — Clean-Title | C37: =IF($B$5="Yes",E37,D37) -> Yes | D37: =INDEX(Presets!$C$31:$L$31,MATCH($B$4,Presets!$C$1:$L$1,0)) -> Yes | E37: Yes
A38: B29_enabled | B38: Bundle 29 — High-Citation | C38: =IF($B$5="Yes",E38,D38) -> Yes | D38: =INDEX(Presets!$C$32:$L$32,MATCH($B$4,Presets!$C$1:$L$1,0)) -> Yes | E38: Yes
A39: B30_enabled | B39: Bundle 30 — Adjacent Re-Read | C39: =IF($B$5="Yes",E39,D39) -> Yes | D39: =INDEX(Presets!$C$33:$L$33,MATCH($B$4,Presets!$C$1:$L$1,0)) -> Yes | E39: Yes
A40: B31_enabled | B40: Bundle 31 — Salvage / Volume Lot | C40: =IF($B$5="Yes",E40,D40) -> Yes | D40: =INDEX(Presets!$C$34:$L$34,MATCH($B$4,Presets!$C$1:$L$1,0)) -> Yes | E40: Yes
A41: B32_enabled | B41: Bundle 32 — Pre-Expiry | C41: =IF($B$5="Yes",E41,D41) -> Yes | D41: =INDEX(Presets!$C$35:$L$35,MATCH($B$4,Presets!$C$1:$L$1,0)) -> Yes | E41: Yes
A42: B33_enabled | B42: Bundle 33 — Provenance-Coherent | C42: =IF($B$5="Yes",E42,D42) -> Yes | D42: =INDEX(Presets!$C$36:$L$36,MATCH($B$4,Presets!$C$1:$L$1,0)) -> Yes | E42: Yes
A43: THRESHOLDS (numeric values referenced in routing rules)
A44: SEP_B1_cutoff | B44: B2 SEP bundle: minimum B1 SEP potential (default 2) | C44: =IF($B$5="Yes",E44,D44) -> 2 | D44: =INDEX(Presets!$C$38:$L$38,MATCH($B$4,Presets!$C$1:$L$1,0)) -> 2 | E44: 2
A45: Interface_B3_cutoff | B45: B9 Interop bundle: minimum B3 interface role (default 2) | C45: =IF($B$5="Yes",E45,D45) -> 2 | D45: =INDEX(Presets!$C$39:$L$39,MATCH($B$4,Presets!$C$1:$L$1,0)) -> 2 | E45: 2
A46: Detect_D1_cutoff | B46: B12 Detectability: D1 external-detect cutoff (default 2) | C46: =IF($B$5="Yes",E46,D46) -> 2 | D46: =INDEX(Presets!$C$40:$L$40,MATCH($B$4,Presets!$C$1:$L$1,0)) -> 2 | E46: 2
A47: Detect_D2_cutoff | B47: B12 Detectability: D2 teardown cutoff (default 2) | C47: =IF($B$5="Yes",E47,D47) -> 2 | D47: =INDEX(Presets!$C$41:$L$41,MATCH($B$4,Presets!$C$1:$L$1,0)) -> 2 | E47: 2
A48: Family_E1_min | B48: B14 Family bundle: minimum E1 family size (default 2) | C48: =IF($B$5="Yes",E48,D48) -> 2 | D48: =INDEX(Presets!$C$42:$L$42,MATCH($B$4,Presets!$C$1:$L$1,0)) -> 2 | E48: 2
A49: CrossIndustry_G3_cutoff | B49: B17 Cross-Industry: minimum G3 cross-industry score (default 2) | C49: =IF($B$5="Yes",E49,D49) -> 2 | D49: =INDEX(Presets!$C$43:$L$43,MATCH($B$4,Presets!$C$1:$L$1,0)) -> 2 | E49: 2
A50: Defensive_D3_cutoff | B50: B19 Defensive: minimum D3 reads-on-products (default 2) | C50: =IF($B$5="Yes",E50,D50) -> 2 | D50: =INDEX(Presets!$C$44:$L$44,MATCH($B$4,Presets!$C$1:$L$1,0)) -> 2 | E50: 2
A51: Whitespace_C4_cutoff | B51: B20 Whitespace: minimum C4 design-around difficulty (default 2) | C51: =IF($B$5="Yes",E51,D51) -> 2 | D51: =INDEX(Presets!$C$45:$L$45,MATCH($B$4,Presets!$C$1:$L$1,0)) -> 2 | E51: 2
A52: Anchor_H1_cutoff | B52: B22 Anchor+Halo: minimum H1 claim strength for anchor (default 2) | C52: =IF($B$5="Yes",E52,D52) -> 2 | D52: =INDEX(Presets!$C$46:$L$46,MATCH($B$4,Presets!$C$1:$L$1,0)) -> 2 | E52: 2
A53: HighCitation_H5_min | B53: B29 High-Citation: minimum H5 forward citations (default 15) | C53: =IF($B$5="Yes",E53,D53) -> 15 | D53: =INDEX(Presets!$C$47:$L$47,MATCH($B$4,Presets!$C$1:$L$1,0)) -> 15 | E53: 15
A54: PreExpiry_min_years | B54: B32 Pre-Expiry: minimum remaining term in years (default 1) | C54: =IF($B$5="Yes",E54,D54) -> 1 | D54: =INDEX(Presets!$C$48:$L$48,MATCH($B$4,Presets!$C$1:$L$1,0)) -> 1 | E54: 1
A55: PreExpiry_max_years | B55: B32 Pre-Expiry: maximum remaining term in years (default 4) | C55: =IF($B$5="Yes",E55,D55) -> 4 | D55: =INDEX(Presets!$C$49:$L$49,MATCH($B$4,Presets!$C$1:$L$1,0)) -> 4 | E55: 4
A56: Salvage_H1_max | B56: B31 Salvage: maximum H1 (default 1) | C56: =IF($B$5="Yes",E56,D56) -> 1 | D56: =INDEX(Presets!$C$50:$L$50,MATCH($B$4,Presets!$C$1:$L$1,0)) -> 1 | E56: 1
A57: Salvage_E4_max | B57: B31 Salvage: maximum remaining term in years (default 5) | C57: =IF($B$5="Yes",E57,D57) -> 5 | D57: =INDEX(Presets!$C$51:$L$51,MATCH($B$4,Presets!$C$1:$L$1,0)) -> 5 | E57: 5
A58: Salvage_H2_max | B58: B31 Salvage: maximum H2 prior-art exposure (default 1) | C58: =IF($B$5="Yes",E58,D58) -> 1 | D58: =INDEX(Presets!$C$52:$L$52,MATCH($B$4,Presets!$C$1:$L$1,0)) -> 1 | E58: 1
A59: Strength_depth_min | B59: Scorecard STRONG flag: minimum coverage depth (default 4) | C59: =IF($B$5="Yes",E59,D59) -> 4 | D59: =INDEX(Presets!$C$53:$L$53,MATCH($B$4,Presets!$C$1:$L$1,0)) -> 4 | E59: 4
A60: Strength_detect_min | B60: Scorecard STRONG flag: minimum avg detectability (default 2) | C60: =IF($B$5="Yes",E60,D60) -> 2 | D60: =INDEX(Presets!$C$54:$L$54,MATCH($B$4,Presets!$C$1:$L$1,0)) -> 2 | E60: 2
A61: Strength_term_min | B61: Scorecard STRONG flag: minimum avg remaining term (default 10) | C61: =IF($B$5="Yes",E61,D61) -> 10 | D61: =INDEX(Presets!$C$55:$L$55,MATCH($B$4,Presets!$C$1:$L$1,0)) -> 10 | E61: 10
A62: QUALITY GATES (Yes = gate column shown on Scorecard)
A63: Gate_WeakestH1 | B63: Show "Weakest H1 in bundle" column | C63: =IF($B$5="Yes",E63,D63) -> Yes | D63: =INDEX(Presets!$C$57:$L$57,MATCH($B$4,Presets!$C$1:$L$1,0)) -> Yes | E63: Yes
A64: Gate_InvalidityExposure | B64: Show "Invalidity exposure %" column | C64: =IF($B$5="Yes",E64,D64) -> Yes | D64: =INDEX(Presets!$C$58:$L$58,MATCH($B$4,Presets!$C$1:$L$1,0)) -> Yes | E64: Yes
A65: Gate_EoUReady | B65: Show "EoU-ready %" column | C65: =IF($B$5="Yes",E65,D65) -> Yes | D65: =INDEX(Presets!$C$59:$L$59,MATCH($B$4,Presets!$C$1:$L$1,0)) -> Yes | E65: Yes
A66: Gate_Survived | B66: Show "Survived %" column | C66: =IF($B$5="Yes",E66,D66) -> Yes | D66: =INDEX(Presets!$C$60:$L$60,MATCH($B$4,Presets!$C$1:$L$1,0)) -> Yes | E66: Yes
A67: Gate_ContOptionality | B67: Show "Continuation-optionality %" column | C67: =IF($B$5="Yes",E67,D67) -> Yes | D67: =INDEX(Presets!$C$61:$L$61,MATCH($B$4,Presets!$C$1:$L$1,0)) -> Yes | E67: Yes

Sheet Portfolio Context Guide
A1: PORTFOLIO CONTEXT GUIDE — Short-Lifecycle Assets (≤8 Years Remaining Term)
A2: v5 Addition · Companion to Presets: Short Lifecycle — Critical (1-2yr) / Monetization (3-5yr) / Strategic (6-8yr) · For outright patent sales
A4: 1. TERM BAND OVERVIEW
A5: Dimension | B5: Critical Window | C5: Monetization Window | D5: Strategic Window
A6: Remaining term | B6: 1 – 2 years | C6: 3 – 5 years | D6: 6 – 8 years
A7: Preset to use | B7: Short Lifecycle — Critical | C7: Short Lifecycle — Monetization | D7: Short Lifecycle — Strategic
A8: Primary buyers | B8: NPE-LIT, LIT-FIN | C8: NPE-LIT, LIT-FIN, NPE-LIC | D8: OC-DEF, NPE-LIC, IP-FUND
A9: Secondary buyers | B9: DEF-AGG (weak assets) | C9: DEF-AGG, OC-DEF (borderline) | D9: DEF-AGG, STD-LIC
A10: Core value driver | B10: EoU chart + named defendant | C10: Enforcement window + broad claims | D10: Coverage depth + product mapping
A11: Urgency framing | B11: "Last enforcement window" | C11: "Campaign horizon: 3–5yr" | D11: "Full product-gen coverage"
A12: Sample portfolios | B12: SL-001 to SL-010 | C12: SL-011 to SL-020 | D12: SL-021 to SL-030
A14: 2. HOW TO USE THESE PRESETS WITH THE WORKBOOK
A15: Step 1 | B15: Go to the Configuration sheet. In cell B4 (Active Preset dropdown), select the preset that matches your portfolio term band.
A16: Step 2 | B16: The Bundle Assignment and Bundle Quality Scorecard sheets recompute automatically. Disabled bundle columns show [DISABLED] and are grayed out.
A17: Step 3 | B17: Review the Scorecard. For Critical and Monetization bands, look for bundles with EoU-ready % > 50% and Survived % > 0. For Strategic, focus on coverage depth and Weakest H1.
A18: Step 4 | B18: To fine-tune: set Edit Mode (B5) to Yes. You can then override individual thresholds in the Manual Override column without affecting the preset.
A19: Step 5 | B19: The 30 sample patents (SL-001 to SL-030) in the Patent Portfolio sheet are pre-scored for this scenario. Review them to understand how the routing logic differs across bands.
A20: Step 6 | B20: When pitching to buyers, match the IAM Market language register to the term band. Use the "Buyer Fit" and "Positioning Strategy" columns on this sheet as a reference.
A22: 3. CRITICAL SIGNALS BY TERM BAND (Attributes driving sale success)
A23: Signal / Attribute | B23: Critical (1-2yr) | C23: Monetization (3-5yr) | D23: Strategic (6-8yr) | E23: Notes
A24: H9 EoU available | B24: MUST HAVE — Full chart required | C24: Must-have for NPE-LIT, nice-to-have for NPE-LIC | D24: Nice-to-have; OC-DEF doesn't require it | E24: Full chart = ready to file; Partial = 60-90d prep needed
A25: H7 Survived challenge | B25: MUST HAVE — IPR filed day 1 | C25: Strong premium; validates claim integrity | D25: Important for OC-OFF and IP-FUND | E25: Reduces invalidity risk for all buyers
A26: D1 External detectability | B26: MUST HAVE — no discovery time | C26: Must-have; no time for forensic analysis | D26: Required for OC-DEF product mapping | E26: H1+D1 is the enforcement readiness pair
A27: H1 Claim strength | B27: Min 3 — must survive IPR | C27: Min 2 — IPR risk manageable | D27: Min 2 — OC buyers vet every claim | E27: Weakest H1 gate on Scorecard shows bundle floor
A28: H4 Divided infringement | B28: 3 = single-actor (essential) | C28: 3 preferred; 2 acceptable with careful drafting | D28: 2+ acceptable; OC-DEF less sensitive | E28: H4≤1 kills litigation route entirely
A29: E4 Remaining term | B29: 1-2yr: urgency is the asset | C29: 3-5yr: full campaign window | D29: 6-8yr: product lifecycle coverage | E29: Pre-Expiry bundle threshold is set per band
A30: C2 Claim breadth | B30: 2+ helpful for damages scope | C30: 2+ for multi-target licensing pool | D30: 2+ for OC blocking and NPE-LIC programs | E30: C2=3 (pioneer) is highest premium signal
A31: H8 Chain of title | B31: Clean: fast close essential | C31: Clean: standard requirement | D31: Clean: OC buyers are strictest on title | E31: Any gap doubles due diligence timeline
A32: G3 Cross-industry | B32: Marginal — no time for program | C32: 2+ opens NPE-LIC secondary market | D32: 2+ opens IP-FUND and DEF-AGG buyers | E32: B30 Adjacent Re-Read bundle leverages this
A33: H5 Forward citations | B33: Low weight at this term | C33: Moderate: helps IP-FUND if ≥10 | D33: High weight: IP-FUND and CORP-VC key signal | E33: B29 High-Citation bundle threshold = 10 (lowered from 15 in short-lifecycle presets)
A35: 4. DEAL KILLERS — ROUTE TO SALVAGE OR REMOVE FROM SALE PACKAGE
A36: Deal Killer (Attribute value) | B36: Impact & recommended action | E36: Applies to
A37: E4 < 1yr at close | B37: Unsellable — case cannot be filed and resolved before expiry. Remove from package. | E37: All bands
A38: H4 ≤ 1 (divided infringement) | B38: Kills litigation route. OC-DEF still possible but at heavy discount. Salvage lot or remove. | E38: All bands
A39: H10 ≠ None (FRAND/encumbrance) | B39: Restricts who can be targeted and caps royalty rates. Must disclose; kills many deals outright. | E39: All bands
A40: H2 = 0 (very high invalidity) | B40: Critical and Monetization bands: IPR filed immediately, terminates campaign. Strategic: OC-DEF will pass. | E40: Critical, Monetization
A41: H9 = None (no EoU) | B41: Critical band: removes from primary sale tier, route to Salvage. Monetization: reduces price significantly. | E41: Critical, Monetization
A42: H8 = Clouded title | B42: Doubles due diligence timeline. OC buyers will walk. Must resolve pre-sale or heavily discount. | E42: All bands
A43: H7 = Pending (IPR active) | B43: Outcome uncertainty is a deal-stopper for NPE-LIT and LIT-FIN. Wait for resolution or route to Salvage. | E43: Critical, Monetization
A44: E3 = No AND H1 ≤ 1 | B44: No continuation option + weak claims = no future value. IP-FUND and OC-OFF will pass. Salvage or lot pricing only. | E44: Strategic
A46: 5. IAM MARKET LANGUAGE REGISTER BY TERM BAND
A47: Language element | B47: Critical (1-2yr) | C47: Monetization (3-5yr) | D47: Strategic (6-8yr)
A48: Term framing | B48: "Enforcement window open through [date]" | C48: "3–5yr campaign horizon; two full licensing rounds" | D48: "Seven years of enforceable coverage; full product gen"
A49: Value hook | B49: "Case economics: damages exposure >> acquisition cost" | C49: "Assertion-ready; EoU charts prepared for [category]" | D49: "FTO depth across [tech domain]; clean title, immediate transfer"
A50: Urgency language | B50: Use urgency explicitly — window is the asset | C50: Frame as: "act before the window closes" | D50: Avoid urgency; use coverage and blocking language
A51: Buyer language | B51: "Assertion vehicle", "defendant-mapped", "case file" | C51: "Licensing program", "royalty base", "detectable infringement" | D51: "FTO coverage", "design-around blocking", "portfolio depth"
A52: Avoid | B52: "Long-term strategic value" — overclaims | C52: "Expiring soon" — sounds apologetic; flip to "last window" | D52: "Enforcement ready" without EoU support — needs evidence
A54: 6. 3-TIER COMPOSITION WITHIN ANY TERM BAND
A55: Tier | B55: Qualifying criteria | C55: Positioning & recommended bundles
A56: Tier A (Premium) | B56: EoU-Backed + Survived-Challenge anchors | C56: Lead with these. Price to reflect assertion readiness. NPE-LIT and LIT-FIN buyers will pay a premium. Bundle using B26 + B27 + B22.
A57: Tier B (Standard) | B57: Detectability ≥ 2, no full EoU chart yet | C57: Position as "program-starter" lots: 60-90 days of claim charting needed before campaign launch. Discount from Tier A. Bundle using B12 + B22 + B28.
A58: Tier C (Volume / Salvage) | B58: Weak H1 or high invalidity exposure | C58: Route to Salvage/Volume Lot bundle (B31). Price to clear. Target DEF-AGG buyers only. Never mix with Tier A or B in the same IAM listing.
A60: 7. SAMPLE PATENT INDEX (SL-001 to SL-030 on Patent Portfolio sheet)
A61: Patent ID | B61: Title | C61: Term Band | D61: Key buyer signal(s) | E61: Tier
A62: SL-001 | B62: LTE handover parameter optimization | C62: Critical (1-2yr) | D62: Full EoU + Survived IPR + H4=3 | E62: Tier A
A63: SL-002 | B63: Touch haptic feedback encoding | C63: Critical (1-2yr) | D63: Full EoU + Survived + H4=3 | E63: Tier A
A64: SL-003 | B64: Low-power wake-word detection MCU | C64: Critical (1-2yr) | D64: Full EoU; H1=2 — tight case | E64: Tier A
A65: SL-004 | B65: Fingerprint anti-spoofing impedance | C65: Critical (1-2yr) | D65: Full EoU + Survived + Broad claims | E65: Tier A
A66: SL-005 | B66: DRAM refresh power optimization | C66: Critical (1-2yr) | D66: Partial EoU + Survived + H4=3 | E66: Tier A
A67: SL-006 | B67: Packet classification TCAM | C67: Critical (1-2yr) | D67: Full EoU + D1=3; no survived | E67: Tier B
A68: SL-007 | B68: EV charging session auth PLC | C68: Critical (1-2yr) | D68: Full EoU; H2=3 low invalidity risk | E68: Tier B
A69: SL-008 | B69: Predictive BMS cell balancing ML | C69: Critical (1-2yr) | D69: Full EoU + Survived; narrow term | E69: Tier A
A70: SL-009 | B70: UWB indoor localization ranging | C70: Critical (1-2yr) | D70: Full EoU + D1=3 + H1=3 | E70: Tier A
A71: SL-010 | B71: Adaptive video codec rate control | C71: Critical (1-2yr) | D71: Full EoU + broad claims; minor title gap → B | E71: Tier B
A72: SL-011 | B72: 5G NR HARQ-ACK timing control | C72: Monetization (3-5yr) | D72: Partial EoU + 5G NR SEP potential | E72: Tier B
... A91: SL-030 | B91: GaN power amplifier 5G base stations | C91: Strategic (6-8yr) | D91: Partial EoU + trilateral + OC-DEF viable | E91: Tier B
A94: Patent Portfolio Bundling Template v5 · Portfolio Context Guide · Companion: Patent_Buyer_Profiles_v1.docx & Value_Proposition_Framework_v3.md

Sheet Presets
A1: Parameter | B1: Description | C1: All ON (default) | D1: NPE / Counter-Assertion | E1: Operating Company / FTO | F1: Defensive Aggregator | G1: Standards Licensee | H1: EV Powertrain Sale | I1: Custom Preset 1 | J1: Custom Preset 2 | K1: Custom Preset 3 | L1: Custom Preset 4 | M1: Short Lifecycle — Critical (1-2yr) | N1: Short Lifecycle — Monetization (3-5yr) | O1: Short Lifecycle — Strategic (6-8yr)
A2: _description | B2: Short description of the preset | C2: Every bundle and gate enabled, all thresholds at default. Baseline view. | D2: Focus on assertion-ready assets: detectability, EoU, survived challenges, defensive reads, salvage lots. | E2: Focus on subsystem coverage, interfaces, claim breadth, continuation optionality. Skips litigation-focused bundles. | F2: Volume-driven: salvage, geographic breadth, claim-type variety, prosecution mix. | G2: Tight focus on standards-essential, interoperability, generational, geographic, battle-tested assets. | H2: EV-focused: subsystems, materials, manufacturing, thermal, generational. Skips wireless/SEP/AI bundles. | I2: (empty — overwrite this column with your own configuration) | J2: (empty — overwrite this column with your own configuration) | K2: (empty — overwrite this column with your own configuration) | L2: (empty — overwrite this column with your own configuration) | M2: Last-window enforcement: EoU-backed, battle-tested, detectable. Pre-Expiry window set 1-2yr. Disables continuation, prosecution-status, and long-horizon bundles. | N2: Primary enforcement & licensing window. EoU-backed, detectable, anchor+halo core. Pre-Expiry 3-5yr. Adds claim-type and use-case bundles. Defensive aggregator secondary. | O2: Broadest buyer pool for short-lifecycle portfolios. OC-DEF viable. Adds tech-domain, defensive, cross-industry, provenance bundles. Pre-Expiry 6-8yr. Strength_term_min reduced to 6.
A3: BUNDLE TOGGLES (Yes = enabled, No = disabled)
A4: B1_enabled | B4: Bundle 1 — Tech Domain | C4: Yes | D4: No | E4: Yes | F4: Yes | G4: No | H4: Yes | I4: Yes | J4: Yes | K4: Yes | L4: Yes | M4: No | N4: No | O4: Yes
A5: B2_enabled | B5: Bundle 2 — SEP | C5: Yes | D5: Yes | E5: No | F5: No | G5: Yes | H5: No | I5: Yes | J5: Yes | K5: Yes | L5: Yes | M5: No | N5: No | O5: No
A6: B3_enabled | B6: Bundle 3 — Product Architecture | C6: Yes | D6: No | E6: Yes | F6: No | G6: No | H6: Yes | I6: Yes | J6: Yes | K6: Yes | L6: Yes | M6: No | N6: No | O6: Yes
A7: B4_enabled | B7: Bundle 4 — Stack Layer | C7: Yes | D7: No | E7: Yes | F7: Yes | G7: No | H7: Yes | I7: Yes | J7: Yes | K7: Yes | L7: Yes | M7: No | N7: No | O7: No
A8: B5_enabled | B8: Bundle 5 — Use-Case | C8: Yes | D8: Yes | E8: Yes | F8: No | G8: No | H8: Yes | I8: Yes | J8: Yes | K8: Yes | L8: Yes | M8: No | N8: Yes | O8: Yes
A9: B6_enabled | B9: Bundle 6 — Manufacturing / Process | C9: Yes | D9: No | E9: Yes | F9: No | G9: No | H9: Yes | I9: Yes | J9: Yes | K9: Yes | L9: Yes | M9: No | N9: No | O9: No
A10: B7_enabled | B10: Bundle 7 — Materials & Chemistry | C10: Yes | D10: No | E10: Yes | F10: No | G10: No | H10: Yes | I10: Yes | J10: Yes | K10: Yes | L10: Yes | M10: No | N10: No | O10: No
A11: B8_enabled | B11: Bundle 8 — Algorithm / Software | C11: Yes | D11: No | E11: Yes | F11: No | G11: No | H11: No | I11: Yes | J11: Yes | K11: Yes | L11: Yes | M11: No | N11: No | O11: No
A12: B9_enabled | B12: Bundle 9 — Interoperability | C12: Yes | D12: Yes | E12: Yes | F12: No | G12: Yes | H12: No | I12: Yes | J12: Yes | K12: Yes | L12: Yes | M12: No | N12: No | O12: No
A13: B10_enabled | B13: Bundle 10 — Generational Roadmap | C13: Yes | D13: No | E13: No | F13: Yes | G13: Yes | H13: Yes | I13: Yes | J13: Yes | K13: Yes | L13: Yes | M13: No | N13: No | O13: No
A14: B11_enabled | B14: Bundle 11 — Claim-Type | C14: Yes | D14: Yes | E14: No | F14: Yes | G14: No | H14: No | I14: Yes | J14: Yes | K14: Yes | L14: Yes | M14: Yes | N14: Yes | O14: Yes
A15: B12_enabled | B15: Bundle 12 — Detectability | C15: Yes | D15: Yes | E15: No | F15: No | G15: Yes | H15: No | I15: Yes | J15: Yes | K15: Yes | L15: Yes | M15: Yes | N15: Yes | O15: Yes
... A36: B33_enabled | B36: Bundle 33 — Provenance-Coherent | C36: Yes | D36: No | E36: Yes | F36: No | G36: No | H36: Yes | I36: Yes | J36: Yes | K36: Yes | L36: Yes | M36: No | N36: No | O36: Yes
A37: THRESHOLDS (numeric values used in routing rules)
A38: SEP_B1_cutoff | B38: B2 SEP bundle: minimum B1 SEP potential (default 2) | C38: 2 | D38: 2 | E38: 2 | F38: 2 | G38: 2 | H38: 2 | I38: 2 | J38: 2 | K38: 2 | L38: 2 | M38: 2 | N38: 2 | O38: 2
A39: Interface_B3_cutoff | B39: B9 Interop bundle: minimum B3 interface role (default 2) | C39: 2 | D39: 2 | E39: 2 | F39: 2 | G39: 2 | H39: 2 | I39: 2 | J39: 2 | K39: 2 | L39: 2 | M39: 2 | N39: 2 | O39: 2
A40: Detect_D1_cutoff | B40: B12 Detectability: D1 external-detect cutoff (default 2) | C40: 2 | D40: 2 | E40: 2 | F40: 2 | G40: 2 | H40: 2 | I40: 2 | J40: 2 | K40: 2 | L40: 2 | M40: 2 | N40: 2 | O40: 2
A41: Detect_D2_cutoff | B41: B12 Detectability: D2 teardown cutoff (default 2) | C41: 2 | D41: 2 | E41: 2 | F41: 2 | G41: 2 | H41: 2 | I41: 2 | J41: 2 | K41: 2 | L41: 2 | M41: 2 | N41: 2 | O41: 2
A42: Family_E1_min | B42: B14 Family bundle: minimum E1 family size (default 2) | C42: 2 | D42: 2 | E42: 3 | F42: 2 | G42: 2 | H42: 2 | I42: 2 | J42: 2 | K42: 2 | L42: 2 | M42: 2 | N42: 2 | O42: 2
A43: CrossIndustry_G3_cutoff | B43: B17 Cross-Industry: minimum G3 cross-industry score (default 2) | C43: 2 | D43: 2 | E43: 2 | F43: 2 | G43: 2 | H43: 2 | I43: 2 | J43: 2 | K43: 2 | L43: 2 | M43: 2 | N43: 2 | O43: 2
A44: Defensive_D3_cutoff | B44: B19 Defensive: minimum D3 reads-on-products (default 2) | C44: 2 | D44: 2 | E44: 2 | F44: 2 | G44: 2 | H44: 2 | I44: 2 | J44: 2 | K44: 2 | L44: 2 | M44: 2 | N44: 2 | O44: 2
A45: Whitespace_C4_cutoff | B45: B20 Whitespace: minimum C4 design-around difficulty (default 2) | C45: 2 | D45: 2 | E45: 2 | F45: 2 | G45: 2 | H45: 2 | I45: 2 | J45: 2 | K45: 2 | L45: 2 | M45: 2 | N45: 2 | O45: 2
A46: Anchor_H1_cutoff | B46: B22 Anchor+Halo: minimum H1 claim strength for anchor (default 2) | C46: 2 | D46: 2 | E46: 2 | F46: 2 | G46: 2 | H46: 2 | I46: 2 | J46: 2 | K46: 2 | L46: 2 | M46: 3 | N46: 2 | O46: 2
A47: HighCitation_H5_min | B47: B29 High-Citation: minimum H5 forward citations (default 15) | C47: 15 | D47: 10 | E47: 15 | F47: 15 | G47: 15 | H47: 15 | I47: 15 | J47: 15 | K47: 15 | L47: 15 | M47: 10 | N47: 10 | O47: 10
A48: PreExpiry_min_years | B48: B32 Pre-Expiry: minimum remaining term in years (default 1) | C48: 1 | D48: 1 | E48: 1 | F48: 1 | G48: 1 | H48: 1 | I48: 1 | J48: 1 | K48: 1 | L48: 1 | M48: 1 | N48: 3 | O48: 6
A49: PreExpiry_max_years | B49: B32 Pre-Expiry: maximum remaining term in years (default 4) | C49: 4 | D49: 4 | E49: 4 | F49: 4 | G49: 4 | H49: 4 | I49: 4 | J49: 4 | K49: 4 | L49: 4 | M49: 2 | N49: 5 | O49: 8
... A55: Strength_term_min | B55: Scorecard STRONG flag: minimum avg remaining term (default 10) | C55: 10 | D55: 10 | E55: 10 | F55: 10 | G55: 10 | H55: 10 | I55: 10 | J55: 10 | K55: 10 | L55: 10 | M55: 1 | N55: 3 | O55: 6
A56: QUALITY GATES (Yes = column shown on Scorecard, No = column blanked)
A57: Gate_WeakestH1 | B57: Show "Weakest H1 in bundle" column | C57: Yes | D57: Yes | E57: Yes | F57: No | G57: Yes | H57: Yes | I57: Yes | J57: Yes | K57: Yes | L57: Yes | M57: Yes | N57: Yes | O57: Yes
A58: Gate_InvalidityExposure | B58: Show "Invalidity exposure %" column | C58: Yes | D58: Yes | E58: Yes | F58: Yes | G58: Yes | H58: Yes | I58: Yes | J58: Yes | K58: Yes | L58: Yes | M58: Yes | N58: Yes | O58: Yes
A59: Gate_EoUReady | B59: Show "EoU-ready %" column | C59: Yes | D59: Yes | E59: No | F59: No | G59: Yes | H59: No | I59: Yes | J59: Yes | K59: Yes | L59: Yes | M59: Yes | N59: Yes | O59: Yes
A60: Gate_Survived | B60: Show "Survived %" column | C60: Yes | D60: Yes | E60: No | F60: No | G60: Yes | H60: No | I60: Yes | J60: Yes | K60: Yes | L60: Yes | M60: Yes | N60: Yes | O60: Yes
A61: Gate_ContOptionality | B61: Show "Continuation-optionality %" column | C61: Yes | D61: No | E61: Yes | F61: No | G61: Yes | H61: Yes | I61: Yes | J61: Yes | K61: Yes | L61: Yes | M61: No | N61: No | O61: Yes
A64: HOW TO USE THE PRESETS SHEET
A65: • The "Active Preset" dropdown on the Configuration sheet picks one column from this sheet.
A66: • Columns C-H are starter presets — useful as-is or as templates.
A67: • Columns I-L are empty "Custom Preset" slots — overwrite their values to define your own.
A68: • To rename a preset: edit row 1 of its column. The dropdown on the Configuration sheet updates automatically.
A69: • To save your current Configuration as a new preset:
A70: 1. On the Configuration sheet, set Edit Mode = Yes and configure all toggles/thresholds the way you want.
A71: 2. Come back to this sheet. In the Custom Preset column you want to use, paste-special each value section by section, or type values directly.
A72: 3. Rename the column header (row 1) to your preset name.
A73: 4. Back on Configuration: set Edit Mode = No and select your new preset from the dropdown.
A74: • You can add more preset columns by extending to columns M onward — just update the dropdown range on the Configuration sheet.

Sheet Attribute Dictionary
A1: Group | B1: Code | C1: Attribute | D1: Description | E1: Scale / Values | F1: Example
A2: A. Technology Classification | B2: A1 | C2: Primary technology domain | D2: Main CPC/IPC classification or internal taxonomy tag. | E2: Categorical text | F2: Wireless PHY
A3: A. Technology Classification | B3: A2 | C3: Secondary domains | D3: Cross-applicable technical areas the patent also touches. | E3: Comma-separated tags | F3: Beamforming, MIMO
A4: A. Technology Classification | B4: A3 | C4: Stack layer | D4: Horizontal layer of the technology stack. | E4: Hardware / Firmware / OS / Middleware / App / Cloud / UI | F4: Hardware
A5: A. Technology Classification | B5: A4 | C5: Product subsystem | D5: Which subsystem(s) of an end-product it covers. | E5: Free-text / list | F5: Battery management
A6: A. Technology Classification | B6: A5 | C6: Use-case | D6: Real-world problem(s) it solves. | E6: Free-text / list | F6: Indoor positioning
A7: B. Standards & Ecosystem | B7: B1 | C7: SEP potential | D7: Standard-essential potential. | E7: 0 (none) → 3 (declared/strong mapping) | F7: 3
A8: B. Standards & Ecosystem | B8: B2 | C8: Standard tagged | D8: Specific standard(s) the patent maps to. | E8: Categorical text | F8: 3GPP 5G NR
A9: B. Standards & Ecosystem | B9: B3 | C9: Interface role | D9: Role as an interoperability/interface technology. | E9: 0 (internal only) → 3 (mandatory interface) | F9: 2
A10: C. Claim & Scope | B10: C1 | C10: Claim type | D10: Dominant claim type. | E10: Apparatus / Method / System / CRM / Design | F10: Method
A11: C. Claim & Scope | B11: C2 | C11: Claim breadth | D11: How broad/foundational the independent claims are. | E11: 0 (narrow) → 3 (foundational/pioneer) | F11: 2
A12: C. Claim & Scope | B12: C3 | C12: Independent claim count | D12: Number of independent claims. | E12: Integer | F12: 3
... A41: I. Market/Buyer Signals | B41: I4 | C41: Workaround complexity | D41: Engineering effort needed for a competitor to design around the claims. | E41: 0 (trivial) → 3 (deep redesign) | F41: 3

Sheet Attribute Procedure
A1: ATTRIBUTE DERIVATION PROCEDURE
A2: A field-by-field procedure for populating the 40-attribute scoring model from raw patent data. Sits alongside the Attribute Dictionary as the long-form reference.
A3: TYPE LEGEND
A4: Direct lookup | B4: Pull the value straight from a patent document field or database; no judgment required.
A5: Computed | B5: Apply an arithmetic formula or boolean rule to other already-collected fields.
A6: Derived (rubric) | B6: Apply a scoring rubric to claim text or specification language. Requires reading and judgment.
A7: Derived (rubric + SME) | B7: Rubric-based but should be cross-checked with a domain expert or patent counsel.
A9: RECOMMENDED WORKFLOW — 10 steps (run in order; steps 1-3 mostly automatable, steps 4-10 require reading & judgment)
A10: # | B10: Step | C10: What to do | F10: Fields populated
A11: 1 | B11: Pull bibliographic & family data | C11: For each patent: get the front page, claims, abstract, family tree, citations, assignments, and prosecution status. Use Google Patents + Espacenet + USPTO Patent Center. | F11: A1, A2, C1, C3, E1–E5, F1, H5, H6, H8
A12: 2 | B12: Read claims and specification | C12: Read the first independent claim of each patent + the Background / Field-of-Invention. This is the irreplaceable manual step. | F12: A3, A4, A5, C2, C4, B3
A13: 3 | B13: Check SEP declarations | C13: For wireless / video / connectivity patents: check ETSI IPR, IEEE-SA, ITU declarations against the family. | F13: B1, B2
A14: 4 | B14: Score detectability | C14: For each claim, judge external vs. teardown detectability with the rubric. Cross-check teardowns where available. | F14: D1, D2
A15: 5 | B15: Map to products | C15: Identify which commercial products read on each patent. Build a quick read-on list. This is the highest-leverage step for buyer value. | F15: D3, I1
A16: 6 | B16: Compute geography | C16: From the family list, derive trilateral flag and major-market score. | F16: F2, F3 (auto from F1)
A17: 7 | B17: Tag themes and generations | C17: Apply your convergence-theme dictionary and generation labels. | F17: G1, G2, G3
A18: 8 | B18: Quality & vulnerability review | C18: Patent-counsel-grade review: claim strength, prior-art exposure, prosecution estoppel, divided-infringement, litigation history. Most labor-intensive but most decisive for buyer due diligence. | F18: H1, H2, H3, H4, H7
A19: 9 | B19: EoU & encumbrance audit | C19: Check internal claim-chart library; check encumbrance records. | F19: H9, H10
A20: 10 | B20: Market signals review | C20: Implementation maturity (was it productized?), adjacent re-read potential, workaround complexity. SME-driven. | F20: I2, I3, I4
A23: MASTER ATTRIBUTE PROCEDURE TABLE — one row per attribute (40 attributes total)
A24: Grp | B24: Code | C24: Attribute | D24: Type | E24: Where to find | F24: How to derive / compute | G24: Best data source
A25: A | B25: A1 | C25: Primary technology domain | D25: Direct lookup | E25: Front page of the patent: CPC main classification (most specific subgroup), or IPC. Also check the title and abstract for confirmation. | F25: Take the CPC main code and translate it to a human-readable domain tag using a fixed taxonomy (e.g., CPC H04W → "Wireless networking"; CPC H01M → "Battery cells"). Maintain a CPC→tag mapping spreadsheet so values stay consistent across the portfolio. | G25: Google Patents, USPTO PatentsView, Espacenet, EPO Open Patent Services, Lens.org. CPC scheme reference: cpc.uspto.gov
A26: A | B26: A2 | C26: Secondary domains | D26: Direct lookup | E26: CPC classifications other than the main one (front page lists multiple). Also pull keywords from the abstract and the first independent claim. | F26: List every additional CPC subgroup beyond A1. Optionally enrich with 2-3 keyword tags drawn from the abstract (e.g., "MIMO", "beamforming", "edge inference"). | G26: Google Patents, Espacenet, Lens.org. For keyword extraction at scale: use a simple TF-IDF over the abstract against the rest of your portfolio.
A27: A | B27: A3 | C27: Stack layer | D27: Derived (rubric) | E27: Read the first independent claim and the "Field of the Invention" / "Background" section. | F27: Apply a 7-bucket rubric. Hardware: physical device, circuit, or material composition. Firmware: low-level code embedded in hardware. OS: kernel/driver level. Middleware: protocol stacks, libraries, frameworks. App: end-user application logic. Cloud: server-side service or backend. UI: visual interface or interaction pattern. Pick the dominant layer; if the claim mixes layers, pick where the novelty lives. | G27: Patent specification. No external database — judgment-based against the rubric.
A28: A | B28: A4 | C28: Product subsystem | D28: Derived (rubric) | E28: Read the first independent claim, the "Detailed Description" preamble, and any "Embodiments" section listing real-world products. | F28: Map the claim subject matter to a subsystem of an identifiable end product. Example: for an EV — "battery cell", "battery pack", "BMS", "traction inverter", "thermal mgmt", "charging port", "motor", "regen brake controller". Maintain a per-industry subsystem dictionary so tags are consistent. | G28: Patent specification + product architecture knowledge (engineering team / SME input).
A29: A | B29: A5 | C29: Use-case | D29: Derived (rubric) | E29: "Field of the Invention", "Background", and the "Detailed Description" — look for problem statements ("there is a need to...", "addresses the problem of..."). | F29: Phrase the use-case as a customer-facing problem (e.g., "indoor positioning", "battery fast-charging", "fraud detection in payments", "low-latency video streaming"). Maintain a portfolio-wide use-case dictionary; reuse tags rather than coining new ones for each patent. | G29: Patent specification. Use natural-language extraction from the Background section. Cross-check against market reports if needed.
A30: B | B30: B1 | C30: SEP potential | D30: Derived (rubric) | E30: Check (a) SEP databases for any declaration on this family, (b) the claim language for standards-spec phrasing, (c) any prior 3GPP / IEEE / ITU letters of assurance. | F30: Score 0-3. 3: declared SEP in an SSO database, OR claim language directly mirrors a normative spec section. 2: claim reads on a specific clause of a known standard but no formal declaration. 1: standard-adjacent but normative essentiality is debatable. 0: no standard tie. For 5G/Wi-Fi/Bluetooth/USB-C/H.26x patents, always run a claim-vs-spec mapping before assigning ≥2. | G30: ETSI IPR Online Database (search.ipr.etsi.org), IEEE-SA, ITU, IETF declarations, Unified Patents SEP database, IPlytics, Amplified.ai. Pair with claim-charts where available.
A31: B | B31: B2 | C31: Standard tagged | D31: Direct lookup | E31: Same sources as B1. Read the actual SSO declaration if one exists. | F31: Record the exact standard identifier (e.g., "3GPP TS 38.211 (5G NR PHY)", "IEEE 802.11be (Wi-Fi 7)", "USB PD 3.1", "ITU-T H.266/VVC"). If multiple standards are implicated, list all. Blank if B1 = 0. | G31: ETSI IPR database (full declaration text usually names the spec). Otherwise infer from claim text + standards expert review.
A32: B | B32: B3 | C32: Interface role | D32: Derived (rubric) | E32: Read the first independent claim. Look for protocol/handshake/format/connector language. | F32: Score 0-3. 3: claim sits at a mandatory interface between two systems (e.g., wire protocol, connector pinout, RPC format). 2: claim covers a widely-used interoperability mechanism that is not technically mandatory but is de-facto standard. 1: claim involves an interface but the interface is internal to one product. 0: no interface dimension. | G32: Patent specification + SME interpretation. Cross-check whether the interface is named in any public spec.
A33: C | B33: C1 | C33: Claim type | D33: Direct lookup | E33: Read the preamble of each independent claim. | F33: Classify the dominant independent claim type. Apparatus: "an apparatus comprising…", "a device comprising…". Method: "a method comprising the steps of…". System: "a system for X comprising…". CRM: "a non-transitory computer-readable medium storing instructions that, when executed…". Design: design patents (D-numbered, drawings only). If mixed, pick the most enforceable type given the product target. | G33: Patent claims section (always front-of-patent in granted patents).
A34: C | B34: C2 | C34: Claim breadth | D34: Derived (rubric) | E34: Read each independent claim. Count words, count specific limitations, look for "wherein" clauses. | F34: Score 0-3. 3 (pioneer/foundational): few elements, abstract/general language, no narrowing wherein clauses, broad genus. 2 (broad): moderate element count, some structural narrowing. 1 (narrow): many specific element constraints, specific value ranges, named structural features. 0 (very narrow/picture claim): tied to one specific implementation. Rule of thumb: shorter independent claims with fewer limitations are usually broader. | G34: Patent claims + judgment. Tools like ClaimMaster, LexisNexis PatentAdvisor, or simple word-count heuristics can prefilter.
A35: C | B35: C3 | C35: Independent claim count | D35: Direct lookup (count) | E35: Claims section. Independent claims are those that do not refer to another claim ("a method comprising…" rather than "the method of claim 1, wherein…"). | F35: Simple count. Look for claims whose first word is not "The" referring back to a prior claim. | G35: Patent claims section. Most patent APIs (PatentsView, EPO OPS) return claim text in structured form.
... A64: I | B64: I4 | C64: Workaround complexity | D64: Derived (rubric + engineering SME) | E64: Read the claim. Ask an engineer: "If a competitor needed to ship a competing product without infringing, how much redesign is needed?" | F64: Score 0-3. 3: deep redesign — claim covers the natural/efficient approach; alternatives are expensive or technically inferior. 2: significant redesign — alternatives exist but are commercially undesirable. 1: minor redesign — straightforward alternative is available. 0: trivial workaround — designers can easily substitute. Strongly correlates with C4 design-around difficulty but considered separately because C4 is about claim language whereas I4 is about commercial impact. | G64: Patent claims + engineering SME review. The most reliable answer comes from an engineer who has actually shipped products in the space.
A67: DATA SOURCE REFERENCE — free and paid sources used across the procedure
A68: Tier | B68: Source | C68: URL | E68: What it gives you
A69: Free | B69: Google Patents | C69: patents.google.com | E69: Bibliographic, family, citations, claims, full text. Best free starting point.
A70: Free | B70: Espacenet | C70: worldwide.espacenet.com | E70: EPO's global patent search; best for family view (INPADOC).
A71: Free | B71: USPTO Patent Center | C71: patentcenter.uspto.gov | E71: US file wrapper, prosecution history, maintenance fees, assignments.
A72: Free | B72: PatentsView | C72: patentsview.org | E72: USPTO bulk data API. Excellent for programmatic scoring across a portfolio.
A73: Free | B73: Lens.org | C73: lens.org | E73: Free patent + scholarly search; good for forward-citation analysis.
A74: Free | B74: EPO Register | C74: register.epo.org | E74: EP file wrapper, oppositions, renewals.
A75: Free | B75: USPTO PTAB Database | C75: developer.uspto.gov/ptab-api | E75: IPR/PGR/CBM filings and outcomes.
A76: Free | B76: ETSI IPR Database | C76: ipr.etsi.org | E76: SEP declarations for 3GPP / ETSI standards.
A77: Free | B77: USPTO Assignment Search | C77: assignment.uspto.gov | E77: Chain of title for US patents.
A78: Paid | B78: Patsnap | C78: patsnap.com | E78: Integrated platform: family, citations, litigation, valuation. Strong for portfolio-scale analysis.
A79: Paid | B79: Derwent Innovation (Clarivate) | C79: clarivate.com | E79: Premium curated abstracts and family data; strong for prior art.
... A87: Paid | B87: iFixit | C87: ifixit.com | E87: Consumer product teardowns (free + paid tiers).
A90: PRACTICAL NOTES
A91: Scoring consistency
A92: For every 0-3 rubric attribute, calibrate by scoring 5-10 sample patents first as a team, then locking the calibration before processing the rest. Otherwise scores drift across reviewers. Maintain a portfolio-specific data dictionary for A1, A4, A5, G1 so tags are reused rather than re-coined for each patent. Inconsistent tags break the routing rules.
A93: Time and effort allocation
A94: On a 50-patent portfolio: Steps 1-3 (data pull) take ~1 hour total when automated. Steps 4-7 (claim reading, rubric scoring) take ~30 min per patent. Step 8 (quality and vulnerability) takes ~45 min per patent and benefits from patent-counsel involvement. Step 9 (EoU and encumbrance) varies wildly — anywhere from 5 min to several hours depending on internal artifact availability.
A95: Where to invest in claim charts
A96: Don't build EoU claim charts for the whole portfolio. Build them for: anchor patents (H1=3), patents likely to land in EoU-Backed (Bundle 26) or Battle-Tested (Bundle 27), and anything destined for the Premium tier. Charts are expensive — invest them where they shift bundle value the most.
A97: Automation pointers
A98: PatentsView API + Espacenet OPS API together cover ~80% of the Direct Lookup fields programmatically. A simple Python script can populate A1, A2, B2, C1, C3, E1-E5, F1, H5, H6, H8 across the entire Patent Portfolio sheet in one batch. Reserve manual work for the rubric-based and SME-based attributes.
A99: Threshold calibration warning
A100: The numeric thresholds on the Configuration sheet (SEP cutoff, citation minimum, etc.) only make sense if your 0-3 scores are calibrated. If two reviewers would give the same patent different H1 scores, the threshold-based routing produces noise. Run a calibration session before bulk scoring.

Sheet Patent Portfolio
A1: Identification | C1: A. Technology Classification | H1: B. Standards | K1: C. Claim & Scope | O1: D. Detectability | R1: E. Family & Lifecycle | W1: F. Geographic | Z1: G. Strategic | AC1: H. Patent Quality & Vulnerability | AM1: I. Market/Buyer Signals
A2: Patent ID | B2: Title | C2: A1 Primary domain | D2: A2 Secondary domains | E2: A3 Stack layer | F2: A4 Subsystem | G2: A5 Use-case | H2: B1 SEP potential (0-3) | I2: B2 Standard | J2: B3 Interface role (0-3) | K2: C1 Claim type | L2: C2 Claim breadth (0-3) | M2: C3 Indep. claim count | N2: C4 Design-around diff. (0-3) | O2: D1 External detect. (0-3) | P2: D2 Teardown detect. (0-3) | Q2: D3 Reads-on-products (0-3) | R2: E1 Family size | S2: E2 Prosecution | T2: E3 Continuation | U2: E4 Remaining term (yrs) | V2: E5 Maint. status | W2: F1 Jurisdictions | X2: F2 Trilateral (Y/N) | Y2: F3 Major-market score (0-3) | Z2: G1 Convergence theme | AA2: G2 Generation | AB2: G3 Cross-industry (0-3) | AC2: H1 Claim strength (0-3) | AD2: H2 Prior-art exposure (0-3) | AE2: H3 Prosecution risk (0-3) | AF2: H4 Divided-infrgmnt (0-3) | AG2: H5 Fwd citations | AH2: H6 Bwd citations | AI2: H7 Lit/PTAB history | AJ2: H8 Chain-of-title | AK2: H9 EoU available | AL2: H10 Encumbrance | AM2: I1 Product-map conf. (0-3) | AN2: I2 Impl. maturity | AO2: I3 Adjacent re-read (0-3) | AP2: I4 Workaround complex. (0-3)
A3: P-001 | B3: Beamforming pilot signaling for 5G NR | C3: Wireless PHY | D3: MIMO, beamforming | E3: Hardware | F3: Radio frontend | G3: Cellular comms | H3: 3 | I3: 3GPP 5G NR | J3: 3 | K3: Method | L3: 2 | M3: 3 | N3: 3 | O3: 1 | P3: 3 | Q3: 3 | R3: 8 | S3: Granted | T3: Yes | U3: 14 | V3: Active | W3: US, EP, CN, JP, KR | X3: Yes | Y3: 3 | AA3: Current | AB3: 1 | AC3: 3 | AD3: 3 | AE3: 2 | AF3: 3 | AG3: 28 | AH3: 42 | AI3: Survived | AJ3: Clean | AK3: Full | AL3: None | AM3: 3 | AN3: Productized | AO3: 1 | AP3: 3
A4: P-002 | B4: Polar code decoder architecture | C4: Wireless PHY | D4: Error correction | E4: Hardware | F4: Baseband processor | G4: Cellular comms | H4: 3 | I4: 3GPP 5G NR | J4: 2 | K4: Apparatus | L4: 2 | M4: 2 | N4: 2 | O4: 0 | P4: 3 | Q4: 3 | R4: 5 | S4: Granted | T4: No | U4: 13 | V4: Active | W4: US, EP, CN, KR | X4: Yes | Y4: 3 | AA4: Current | AB4: 1 | AC4: 2 | AD4: 2 | AE4: 2 | AF4: 3 | AG4: 18 | AH4: 31 | AI4: None | AJ4: Clean | AK4: Partial | AL4: None | AM4: 3 | AN4: Productized | AO4: 1 | AP4: 2
A5: P-003 | B5: Adaptive Wi-Fi 7 channel sounding | C5: Wireless PHY | D5: OFDMA | E5: Firmware | F5: WLAN module | G5: Indoor connectivity | H5: 2 | I5: IEEE 802.11be | J5: 3 | K5: Method | L5: 1 | M5: 2 | N5: 2 | O5: 1 | P5: 2 | Q5: 2 | R5: 4 | S5: Mixed | T5: Yes | U5: 17 | V5: Active | W5: US, EP, CN | X5: Yes | Y5: 2 | AA5: Next-gen | AB5: 2 | AC5: 2 | AD5: 3 | AE5: 3 | AF5: 2 | AG5: 4 | AH5: 22 | AI5: None | AJ5: Clean | AK5: None | AL5: None | AM5: 2 | AN5: Prototyped | AO5: 2 | AP5: 2
A6: P-004 | B6: Solid-state electrolyte composition for EV batteries | C6: Battery materials | D6: Solid-state, ionics | E6: Hardware | F6: Battery cell | G6: EV propulsion | H6: 0 | J6: 0 | K6: Apparatus | L6: 3 | M6: 4 | N6: 3 | O6: 0 | P6: 3 | Q6: 2 | R6: 6 | S6: Granted | T6: Yes | U6: 17 | V6: Active | W6: US, EP, CN, JP, KR | X6: Yes | Y6: 3 | AA6: Next-gen | AB6: 2 | AC6: 3 | AD6: 3 | AE6: 3 | AF6: 3 | AG6: 35 | AH6: 48 | AI6: None | AJ6: Clean | AK6: Partial | AL6: None | AM6: 2 | AN6: Prototyped | AO6: 3 | AP6: 3
A7: P-005 | B7: Battery thermal management with phase-change material | C7: Thermal mgmt | D7: BMS, materials | E7: Hardware | F7: Battery pack | G7: EV propulsion | H7: 0 | J7: 1 | K7: System | L7: 2 | M7: 3 | N7: 2 | O7: 1 | P7: 3 | Q7: 2 | R7: 3 | S7: Granted | T7: No | U7: 11 | V7: Active | W7: US, EP, CN | X7: Yes | Y7: 2 | AA7: Current | AB7: 2 | AC7: 2 | AD7: 2 | AE7: 2 | AF7: 3 | AG7: 14 | AH7: 27 | AI7: None | AJ7: Clean | AK7: None | AL7: Non-exclusive licensed | AM7: 2 | AN7: Productized | AO7: 2 | AP7: 2
A8: P-006 | B8: SiC MOSFET inverter control method | C8: Power electronics | D8: Wide-bandgap | E8: Firmware | F8: Traction inverter | G8: EV propulsion | H8: 0 | J8: 1 | K8: Method | L8: 2 | M8: 2 | N8: 2 | O8: 1 | P8: 3 | Q8: 3 | R8: 4 | S8: Granted | T8: No | U8: 12 | V8: Active | W8: US, EP, CN, JP | X8: Yes | Y8: 3 | AA8: Current | AB8: 2 | AC8: 2 | AD8: 2 | AE8: 2 | AF8: 3 | AG8: 16 | AH8: 33 | AI8: None | AJ8: Minor gaps | AK8: Partial | AL8: None | AM8: 3 | AN8: Productized | AO8: 2 | AP8: 2
A9: P-007 | B9: On-device CNN quantization for low-power inference | C9: CV algorithm | D9: Edge AI, ML | E9: App | F9: Vision pipeline | G9: Smart cameras | H9: 0 | J9: 0 | K9: CRM | L9: 2 | M9: 3 | N9: 2 | O9: 2 | P9: 1 | Q9: 2 | R9: 5 | S9: Granted | T9: Yes | U9: 15 | V9: Active | W9: US, EP, CN | X9: Yes | Y9: 2 | Z9: Edge AI | AA9: Current | AB9: 3 | AC9: 2 | AD9: 1 | AE9: 2 | AF9: 2 | AG9: 47 | AH9: 26 | AI9: Pending | AJ9: Clean | AK9: Partial | AL9: None | AM9: 2 | AN9: Productized | AO9: 3 | AP9: 2
A10: P-008 | B10: Transformer attention pruning for vision models | C10: CV algorithm | D10: AI optimization | E10: App | F10: Inference engine | G10: Visual analytics | H10: 0 | J10: 0 | K10: Method | L10: 1 | M10: 2 | N10: 1 | O10: 2 | P10: 0 | Q10: 2 | R10: 3 | S10: Pending | T10: Yes | U10: 19 | V10: Active | W10: US, EP | X10: No | Y10: 1 | Z10: Edge AI, AI+health | AA10: Next-gen | AB10: 3 | AC10: 1 | AD10: 1 | AE10: 1 | AF10: 1 | AG10: 8 | AH10: 19 | AI10: None | AJ10: Clean | AK10: None | AL10: None | AM10: 1 | AN10: Idea-only | AO10: 3 | AP10: 1
A11: P-009 | B11: Visual SLAM for indoor robot navigation | C11: Robotics SW | D11: SLAM, CV | E11: Middleware | F11: Navigation stack | G11: Indoor positioning | H11: 0 | J11: 1 | K11: System | L11: 2 | M11: 2 | N11: 2 | O11: 2 | P11: 1 | Q11: 2 | R11: 4 | S11: Granted | T11: No | U11: 10 | V11: Active | W11: US, EP, JP | X11: Yes | Y11: 2 | Z11: Robotics, edge AI | AA11: Current | AB11: 3 | AC11: 2 | AD11: 2 | AE11: 2 | AF11: 2 | AG11: 22 | AH11: 34 | AI11: None | AJ11: Clean | AK11: Partial | AL11: None | AM11: 2 | AN11: Prototyped | AO11: 2 | AP11: 2
A12: P-010 | B12: USB-C power delivery handshake extension | C12: Interconnect | D12: Power delivery | E12: Firmware | F12: Charging interface | G12: Universal charging | H12: 2 | I12: USB PD 3.x | J12: 3 | K12: Method | L12: 1 | M12: 2 | N12: 2 | O12: 3 | P12: 3 | Q12: 3 | R12: 5 | S12: Granted | T12: No | U12: 9 | V12: Active | W12: US, EP, CN, JP, KR | X12: Yes | Y12: 3 | AA12: Current | AB12: 3 | AC12: 2 | AD12: 3 | AE12: 2 | AF12: 3 | AG12: 25 | AH12: 39 | AI12: Survived | AJ12: Clean | AK12: Full | AL12: None | AM12: 3 | AN12: Productized | AO12: 2 | AP12: 2
A13: P-011 | B13: Atomic layer deposition recipe for high-k dielectric | C13: Semiconductor process | D13: ALD, fab | E13: Hardware | F13: Front-end-of-line | G13: IC manufacturing | H13: 0 | J13: 1 | K13: Method | L13: 2 | M13: 3 | N13: 3 | O13: 0 | P13: 1 | Q13: 1 | R13: 6 | S13: Granted | T13: Yes | U13: 13 | V13: Active | W13: US, EP, CN, JP, KR, TW | X13: Yes | Y13: 3 | AA13: Current | AB13: 1 | AC13: 3 | AD13: 2 | AE13: 3 | AF13: 3 | AG13: 19 | AH13: 41 | AI13: None | AJ13: Clean | AK13: None | AL13: None | AM13: 1 | AN13: Productized | AO13: 1 | AP13: 3
A14: P-012 | B14: Predictive maintenance ML for industrial pumps | C14: Industrial AI | D14: Predictive analytics | E14: Cloud | F14: Asset monitoring | G14: Predictive maintenance | H14: 0 | J14: 1 | K14: CRM | L14: 1 | M14: 2 | N14: 1 | O14: 2 | P14: 0 | Q14: 1 | R14: 2 | S14: Granted | T14: No | U14: 8 | V14: Active | W14: US, EP | X14: No | Y14: 1 | Z14: AI+industrial | AA14: Current | AB14: 3 | AC14: 1 | AD14: 1 | AE14: 2 | AF14: 1 | AG14: 5 | AH14: 12 | AI14: None | AJ14: Minor gaps | AK14: None | AL14: None | AM14: 1 | AN14: Idea-only | AO14: 2 | AP14: 1
A23: BAND A — Critical Window (1–2 years remaining) · Buyer targets: NPE-LIT, LIT-FIN · Preset: Short Lifecycle — Critical (1-2yr)
A24: SL-001 | B24: LTE handover parameter optimization method | C24: Wireless PHY | D24: Handover, mobility | E24: Firmware | F24: Baseband processor | G24: Network handover | H24: 3 | I24: 3GPP LTE | J24: 3 | K24: Method | L24: 2 | M24: 3 | N24: 2 | O24: 3 | P24: 2 | Q24: 3 | R24: 4 | S24: Granted | T24: No | U24: 2 | V24: Active | W24: US, EP, CN | X24: Yes | Y24: 3 | AA24: Legacy | AB24: 1 | AC24: 3 | AD24: 3 | AE24: 3 | AF24: 3 | AG24: 31 | AH24: 18 | AI24: Survived | AJ24: Clean | AK24: Full | AL24: None | AM24: 3 | AN24: Productized | AO24: 1 | AP24: 3
A25: SL-002 | B25: Touch haptic feedback encoding for mobile UI | C25: UI/UX | D25: Haptics, touch | E25: App | F25: Touch controller | G25: Mobile UX | H25: 0 | J25: 1 | K25: Method | L25: 2 | M25: 2 | N25: 2 | O25: 3 | P25: 1 | Q25: 3 | R25: 3 | S25: Granted | T25: No | U25: 2 | V25: Active | W25: US, EP | X25: No | Y25: 2 | AA25: Current | AB25: 2 | AC25: 2 | AD25: 2 | AE25: 3 | AF25: 2 | AG25: 12 | AH25: 9 | AI25: Survived | AJ25: Clean | AK25: Full | AL25: None | AM25: 3 | AN25: Productized | AO25: 2 | AP25: 2
A26: SL-003 | B26: Low-power wake-word detection on microcontrollers | C26: Edge AI | D26: TinyML, audio | E26: Firmware | F26: MCU core | G26: Voice interface | H26: 0 | J26: 0 | K26: CRM | L26: 2 | M26: 2 | N26: 1 | O26: 2 | P26: 1 | Q26: 3 | R26: 2 | S26: Granted | T26: No | U26: 1 | V26: Active | W26: US | X26: No | Y26: 1 | Z26: Edge AI | AA26: Current | AB26: 2 | AC26: 2 | AD26: 2 | AE26: 2 | AF26: 2 | AG26: 8 | AH26: 14 | AI26: None | AJ26: Clean | AK26: Full | AL26: None | AM26: 3 | AN26: Productized | AO26: 2 | AP26: 2
A27: SL-004 | B27: Fingerprint sensor anti-spoofing via impedance spectroscopy | C27: Biometrics | D27: Sensor, security | E27: Hardware | F27: Fingerprint sensor | G27: Identity auth | H27: 0 | J27: 1 | K27: Apparatus | L27: 3 | M27: 2 | N27: 3 | O27: 3 | P27: 2 | Q27: 3 | R27: 3 | S27: Granted | T27: No | U27: 2 | V27: Active | W27: US, EP, CN | X27: Yes | Y27: 2 | AA27: Current | AB27: 3 | AC27: 3 | AD27: 3 | AE27: 3 | AF27: 3 | AG27: 22 | AH27: 11 | AI27: Survived | AJ27: Clean | AK27: Full | AL27: None | AM27: 3 | AN27: Productized | AO27: 2 | AP27: 3
A28: SL-005 | B28: DRAM refresh power optimization algorithm | C28: Memory | D28: DRAM, power | E28: Firmware | F28: Memory controller | G28: Low-power memory | H28: 0 | J28: 0 | K28: Method | L28: 2 | M28: 3 | N28: 2 | O28: 2 | P28: 3 | Q28: 3 | R28: 4 | S28: Granted | T28: No | U28: 1 | V28: Active | W28: US, KR | X28: No | Y28: 2 | AA28: Legacy | AB28: 2 | AC28: 2 | AD28: 2 | AE28: 3 | AF28: 2 | AG28: 16 | AH28: 20 | AI28: Survived | AJ28: Clean | AK28: Partial | AL28: None | AM28: 3 | AN28: Productized | AO28: 1 | AP28: 2
A29: SL-006 | B29: Packet classification with ternary content-addressable memory | C29: Networking | D29: TCAM, SDN | E29: Hardware | F29: Network ASIC | G29: Traffic routing | H29: 0 | J29: 2 | K29: Apparatus | L29: 2 | M29: 2 | N29: 2 | O29: 3 | P29: 2 | Q29: 2 | R29: 3 | S29: Granted | T29: No | U29: 2 | V29: Active | W29: US, EP | X29: No | Y29: 2 | AA29: Current | AB29: 2 | AC29: 2 | AD29: 3 | AE29: 2 | AF29: 3 | AG29: 14 | AH29: 17 | AI29: None | AJ29: Clean | AK29: Full | AL29: None | AM29: 3 | AN29: Productized | AO29: 2 | AP29: 2
A30: SL-007 | B30: EV charging session authentication via PLC | C30: EV charging | D30: PLC, V2G | E30: Middleware | F30: Charging port | G30: EV charging auth | H30: 0 | J30: 2 | K30: Method | L30: 2 | M30: 2 | N30: 2 | O30: 3 | P30: 1 | Q30: 3 | R30: 3 | S30: Granted | T30: No | U30: 2 | V30: Active | W30: US, EP, CN | X30: Yes | Y30: 2 | Z30: EV/Energy | AA30: Current | AB30: 2 | AC30: 2 | AD30: 3 | AE30: 2 | AF30: 3 | AG30: 9 | AH30: 12 | AI30: None | AJ30: Clean | AK30: Full | AL30: None | AM30: 2 | AN30: Productized | AO30: 2 | AP30: 2
A31: SL-008 | B31: Predictive battery cell balancing using ML | C31: Battery mgmt | D31: BMS, ML | E31: App | F31: Battery pack | G31: Battery longevity | H31: 0 | J31: 0 | K31: Method | L31: 2 | M31: 2 | N31: 2 | O31: 2 | P31: 1 | Q31: 3 | R31: 3 | S31: Granted | T31: No | U31: 1 | V31: Active | W31: US, EP | X31: No | Y31: 2 | Z31: Edge AI | AA31: Current | AB31: 2 | AC31: 2 | AD31: 2 | AE31: 3 | AF31: 2 | AG31: 10 | AH31: 15 | AI31: Survived | AJ31: Clean | AK31: Full | AL31: None | AM31: 3 | AN31: Productized | AO31: 2 | AP31: 2
A32: SL-009 | B32: Ultra-wideband indoor localization ranging method | C32: Wireless PHY | D32: UWB, ranging | E32: Hardware | F32: RF module | G32: Indoor positioning | H32: 2 | I32: IEEE 802.15.4a | J32: 2 | K32: Method | L32: 2 | M32: 2 | N32: 3 | O32: 3 | P32: 2 | Q32: 3 | R32: 3 | S32: Granted | T32: No | U32: 2 | V32: Active | W32: US, EP | X32: No | Y32: 2 | AA32: Current | AB32: 3 | AC32: 2 | AD32: 2 | AE32: 2 | AF32: 3 | AG32: 11 | AH32: 8 | AI32: None | AJ32: Clean | AK32: Full | AL32: None | AM32: 3 | AN32: Productized | AO32: 2 | AP32: 2
A33: SL-010 | B33: Adaptive video codec rate control for lossy networks | C33: Video compression | D33: AVC, codec | E33: App | F33: Video pipeline | G33: Streaming QoE | H33: 1 | I33: H.264/AVC | J33: 2 | K33: Method | L33: 3 | M33: 3 | N33: 3 | O33: 3 | P33: 0 | Q33: 2 | R33: 3 | S33: Granted | T33: No | U33: 2 | V33: Active | W33: US, EP, CN | X33: Yes | Y33: 2 | AA33: Legacy | AB33: 2 | AC33: 3 | AD33: 3 | AE33: 3 | AF33: 3 | AG33: 18 | AH33: 21 | AI33: None | AJ33: Minor gaps | AK33: Full | AL33: None | AM33: 2 | AN33: Productized | AO33: 2 | AP33: 3
A34: BAND B — Monetization Window (3–5 years remaining) · Buyer targets: NPE-LIT, LIT-FIN, NPE-LIC · Preset: Short Lifecycle — Monetization (3-5yr)
A35: SL-011 | B35: 5G NR downlink HARQ-ACK timing control | C35: Wireless PHY | D35: HARQ, 5G NR | E35: Firmware | F35: Baseband processor | G35: Cellular comms | H35: 3 | I35: 3GPP 5G NR | J35: 3 | K35: Method | L35: 2 | M35: 3 | N35: 2 | O35: 2 | P35: 3 | Q35: 3 | R35: 5 | S35: Granted | T35: No | U35: 4 | V35: Active | W35: US, EP, CN, JP, KR | X35: Yes | Y35: 3 | AA35: Current | AB35: 1 | AC35: 2 | AD35: 2 | AE35: 3 | AF35: 2 | AG35: 14 | AH35: 16 | AI35: None | AJ35: Clean | AK35: Partial | AL35: None | AM35: 3 | AN35: Productized | AO35: 1 | AP35: 2
A36: SL-012 | B36: OLED pixel compensation circuit for burn-in prevention | C36: Display | D36: OLED, pixel | E36: Hardware | F36: Display panel | G36: Display quality | H36: 0 | J36: 1 | K36: Apparatus | L36: 2 | M36: 2 | N36: 3 | O36: 2 | P36: 2 | Q36: 3 | R36: 4 | S36: Granted | T36: No | U36: 3 | V36: Active | W36: US, EP, KR | X36: No | Y36: 3 | AA36: Current | AB36: 2 | AC36: 2 | AD36: 2 | AE36: 2 | AF36: 2 | AG36: 16 | AH36: 11 | AI36: Survived | AJ36: Clean | AK36: Partial | AL36: None | AM36: 3 | AN36: Productized | AO36: 1 | AP36: 2
A37: SL-013 | B37: Object detection acceleration with sparse convolution | C37: CV algorithm | D37: Sparse conv, ML | E37: App | F37: Inference engine | G37: Autonomous perception | H37: 0 | J37: 0 | K37: CRM | L37: 2 | M37: 3 | N37: 2 | O37: 2 | P37: 1 | Q37: 2 | R37: 4 | S37: Granted | T37: Yes | U37: 4 | V37: Active | W37: US, EP, CN | X37: Yes | Y37: 3 | Z37: Edge AI | AA37: Current | AB37: 3 | AC37: 2 | AD37: 2 | AE37: 2 | AF37: 3 | AG37: 21 | AH37: 18 | AI37: None | AJ37: Clean | AK37: Partial | AL37: None | AM37: 2 | AN37: Prototyped | AO37: 3 | AP37: 2
A38: SL-014 | B38: Lithium-sulfur battery electrolyte stabilization | C38: Battery materials | D38: Li-S, electrolyte | E38: Hardware | F38: Battery cell | G38: Energy density | H38: 0 | J38: 0 | K38: Apparatus | L38: 3 | M38: 3 | N38: 3 | O38: 0 | P38: 2 | Q38: 2 | R38: 3 | S38: Granted | T38: Yes | U38: 4 | V38: Active | W38: US, EP, CN, JP | X38: Yes | Y38: 3 | Z38: EV/Energy | AA38: Next-gen | AB38: 3 | AC38: 3 | AD38: 3 | AE38: 3 | AF38: 3 | AG38: 24 | AH38: 29 | AI38: None | AJ38: Clean | AK38: Partial | AL38: None | AM38: 2 | AN38: Prototyped | AO38: 3 | AP38: 3
A39: SL-015 | B39: Private 5G network slice orchestration method | C39: Networking | D39: Network slicing, 5G | E39: Cloud | F39: RAN controller | G39: Private 5G | H39: 2 | I39: 3GPP 5G Core | J39: 2 | K39: Method | L39: 2 | M39: 2 | N39: 2 | O39: 2 | P39: 0 | Q39: 2 | R39: 3 | S39: Granted | T39: No | U39: 3 | V39: Active | W39: US, EP, CN | X39: Yes | Y39: 2 | AA39: Current | AB39: 2 | AC39: 2 | AD39: 2 | AE39: 3 | AF39: 2 | AG39: 12 | AH39: 14 | AI39: None | AJ39: Clean | AK39: Partial | AL39: None | AM39: 3 | AN39: Productized | AO39: 2 | AP39: 2
A40: SL-016 | B40: Secure enclave key derivation for IoT devices | C40: Security | D40: HSM, TEE | E40: Hardware | F40: Secure element | G40: Device security | H40: 0 | J40: 1 | K40: Apparatus | L40: 2 | M40: 2 | N40: 2 | O40: 2 | P40: 2 | Q40: 3 | R40: 3 | S40: Granted | T40: No | U40: 3 | V40: Active | W40: US, EP | X40: No | Y40: 2 | AA40: Current | AB40: 2 | AC40: 3 | AD40: 3 | AE40: 3 | AF40: 2 | AG40: 9 | AH40: 13 | AI40: Survived | AJ40: Clean | AK40: Full | AL40: None | AM40: 3 | AN40: Productized | AO40: 2 | AP40: 2
A41: SL-017 | B41: Multilayer ceramic capacitor dielectric formulation | C41: Electronic materials | D41: MLCC, ceramics | E41: Hardware | F41: Passive component | G41: Signal filtering | H41: 0 | J41: 0 | K41: Apparatus | L41: 3 | M41: 2 | N41: 3 | O41: 0 | P41: 3 | Q41: 2 | R41: 5 | S41: Granted | T41: Yes | U41: 5 | V41: Active | W41: US, EP, JP, KR, CN | X41: Yes | Y41: 3 | AA41: Current | AB41: 3 | AC41: 2 | AD41: 2 | AE41: 3 | AF41: 2 | AG41: 19 | AH41: 38 | AI41: None | AJ41: Clean | AK41: None | AL41: None | AM41: 2 | AN41: Productized | AO41: 2 | AP41: 3
A42: SL-018 | B42: Cooperative MIMO precoding in distributed antenna systems | C42: Wireless PHY | D42: C-RAN, MIMO | E42: Hardware | F42: Radio frontend | G42: Cellular comms | H42: 2 | I42: 3GPP 5G NR | J42: 3 | K42: Method | L42: 2 | M42: 2 | N42: 2 | O42: 3 | P42: 2 | Q42: 3 | R42: 4 | S42: Granted | T42: No | U42: 5 | V42: Active | W42: US, EP, CN, KR | X42: Yes | Y42: 3 | AA42: Current | AB42: 1 | AC42: 3 | AD42: 3 | AE42: 3 | AF42: 3 | AG42: 13 | AH42: 19 | AI42: None | AJ42: Clean | AK42: Partial | AL42: None | AM42: 3 | AN42: Productized | AO42: 1 | AP42: 2
A43: SL-019 | B43: Real-time LiDAR point cloud compression for autonomous driving | C43: Sensors | D43: LiDAR, point cloud | E43: Middleware | F43: Sensor fusion | G43: Autonomous driving | H43: 0 | J43: 0 | K43: Method | L43: 2 | M43: 2 | N43: 2 | O43: 2 | P43: 2 | Q43: 3 | R43: 3 | S43: Granted | T43: Yes | U43: 4 | V43: Active | W43: US, EP, CN | X43: Yes | Y43: 2 | AA43: Current | AB43: 3 | AC43: 2 | AD43: 3 | AE43: 2 | AF43: 3 | AG43: 17 | AH43: 14 | AI43: None | AJ43: Clean | AK43: Partial | AL43: None | AM43: 2 | AN43: Prototyped | AO43: 3 | AP43: 2
A44: SL-020 | B44: Thermal interface material with anisotropic conductivity | C44: Thermal mgmt | D44: TIM, materials | E44: Hardware | F44: Thermal module | G44: Electronics cooling | H44: 0 | J44: 0 | K44: Apparatus | L44: 2 | M44: 2 | N44: 3 | O44: 0 | P44: 3 | Q44: 2 | R44: 3 | S44: Granted | T44: No | U44: 3 | V44: Active | W44: US, EP, CN | X44: Yes | Y44: 2 | Z44: EV/Energy | AA44: Current | AB44: 2 | AC44: 3 | AD44: 3 | AE44: 3 | AF44: 3 | AG44: 11 | AH44: 22 | AI44: None | AJ44: Clean | AK44: None | AL44: None | AM44: 2 | AN44: Productized | AO44: 3 | AP44: 3
A45: BAND C — Strategic Window (6–8 years remaining) · Buyer targets: OC-DEF, NPE-LIC, IP-FUND · Preset: Short Lifecycle — Strategic (6-8yr)
A46: SL-021 | B46: Wi-Fi 6E multi-BSS OFDMA resource scheduling | C46: Wireless PHY | D46: OFDMA, Wi-Fi | E46: Firmware | F46: WLAN module | G46: Indoor connectivity | H46: 2 | I46: IEEE 802.11ax | J46: 3 | K46: Method | L46: 2 | M46: 3 | N46: 2 | O46: 2 | P46: 2 | Q46: 3 | R46: 5 | S46: Granted | T46: Yes | U46: 7 | V46: Active | W46: US, EP, CN, JP, KR | X46: Yes | Y46: 3 | AA46: Current | AB46: 2 | AC46: 2 | AD46: 2 | AE46: 3 | AF46: 2 | AG46: 11 | AH46: 14 | AI46: Survived | AJ46: Clean | AK46: Partial | AL46: None | AM46: 3 | AN46: Productized | AO46: 2 | AP46: 2
A47: SL-022 | B47: Solid-state LiDAR MEMS mirror resonance control | C47: Sensors | D47: MEMS, LiDAR | E47: Hardware | F47: LiDAR scanner | G47: Autonomous sensing | H47: 0 | J47: 1 | K47: Apparatus | L47: 3 | M47: 2 | N47: 3 | O47: 2 | P47: 2 | Q47: 3 | R47: 4 | S47: Granted | T47: Yes | U47: 7 | V47: Active | W47: US, EP, CN | X47: Yes | Y47: 3 | AA47: Current | AB47: 3 | AC47: 3 | AD47: 3 | AE47: 3 | AF47: 3 | AG47: 28 | AH47: 17 | AI47: None | AJ47: Clean | AK47: Partial | AL47: None | AM47: 2 | AN47: Prototyped | AO47: 3 | AP47: 3
A48: SL-023 | B48: In-memory computing architecture for DNN inference | C48: Memory | D48: CIM, neuromorphic | E48: Hardware | F48: Memory controller | G48: AI acceleration | H48: 0 | J48: 0 | K48: Apparatus | L48: 3 | M48: 3 | N48: 2 | O48: 1 | P48: 2 | Q48: 2 | R48: 4 | S48: Granted | T48: Yes | U48: 8 | V48: Active | W48: US, EP, CN | X48: Yes | Y48: 3 | Z48: Edge AI | AA48: Next-gen | AB48: 3 | AC48: 3 | AD48: 2 | AE48: 3 | AF48: 3 | AG48: 33 | AH48: 22 | AI48: None | AJ48: Clean | AK48: None | AL48: None | AM48: 2 | AN48: Prototyped | AO48: 3 | AP48: 2
A49: SL-024 | B49: Perovskite solar cell stability enhancement method | C49: Photovoltaics | D49: Perovskite, PV | E49: Hardware | F49: Solar cell | G49: Energy generation | H49: 0 | J49: 0 | K49: Method | L49: 2 | M49: 3 | N49: 2 | O49: 0 | P49: 2 | Q49: 2 | R49: 4 | S49: Granted | T49: Yes | U49: 7 | V49: Active | W49: US, EP | X49: No | Y49: 2 | Z49: EV/Energy | AA49: Next-gen | AB49: 2 | AC49: 2 | AD49: 3 | AE49: 3 | AF49: 3 | AG49: 19 | AH49: 31 | AI49: None | AJ49: Clean | AK49: None | AL49: None | AM49: 1 | AN49: Prototyped | AO49: 2 | AP49: 3
A50: SL-025 | B50: Network traffic anomaly detection via federated learning | C50: Security | D50: FL, anomaly | E50: Cloud | F50: Security platform | G50: Threat detection | H50: 0 | J50: 0 | K50: Method | L50: 2 | M50: 2 | N50: 2 | O50: 2 | P50: 0 | Q50: 2 | R50: 3 | S50: Granted | T50: No | U50: 6 | V50: Active | W50: US, EP | X50: No | Y50: 2 | Z50: Edge AI | AA50: Current | AB50: 2 | AC50: 2 | AD50: 2 | AE50: 3 | AF50: 2 | AG50: 14 | AH50: 11 | AI50: None | AJ50: Clean | AK50: None | AL50: None | AM50: 2 | AN50: Productized | AO50: 3 | AP50: 2
A51: SL-026 | B51: Carbon nanotube field-effect transistor fabrication process | C51: Semiconductors | D51: CNT, nano | E51: Hardware | F51: Logic gate | G51: Post-silicon computing | H51: 0 | J51: 0 | K51: Method | L51: 3 | M51: 2 | N51: 3 | O51: 0 | P51: 2 | Q51: 1 | R51: 3 | S51: Granted | T51: Yes | U51: 8 | V51: Active | W51: US, EP, JP | X51: No | Y51: 3 | AA51: Next-gen | AB51: 2 | AC51: 3 | AD51: 3 | AE51: 3 | AF51: 3 | AG51: 22 | AH51: 44 | AI51: None | AJ51: Clean | AK51: None | AL51: None | AM51: 1 | AN51: Prototyped | AO51: 2 | AP51: 3
A52: SL-027 | B52: Dynamic spectrum sharing between 5G NR and LTE coexistence | C52: Wireless PHY | D52: DSS, coexistence | E52: Firmware | F52: Baseband processor | G52: Spectrum efficiency | H52: 2 | I52: 3GPP Rel-16 | J52: 3 | K52: Method | L52: 2 | M52: 2 | N52: 2 | O52: 3 | P52: 2 | Q52: 3 | R52: 5 | S52: Granted | T52: No | U52: 7 | V52: Active | W52: US, EP, CN, KR | X52: Yes | Y52: 3 | AA52: Current | AB52: 1 | AC52: 2 | AD52: 2 | AE52: 3 | AF52: 2 | AG52: 13 | AH52: 17 | AI52: None | AJ52: Clean | AK52: Partial | AL52: None | AM52: 3 | AN52: Productized | AO52: 2 | AP52: 2
A53: SL-028 | B53: Adaptive noise cancellation for over-ear headphones | C53: Audio | D53: ANC, signal proc | E53: Hardware | F53: Audio SoC | G53: Active noise cancellation | H53: 0 | J53: 1 | K53: System | L53: 2 | M53: 2 | N53: 2 | O53: 3 | P53: 1 | Q53: 3 | R53: 4 | S53: Granted | T53: No | U53: 6 | V53: Active | W53: US, EP, CN | X53: Yes | Y53: 2 | AA53: Current | AB53: 3 | AC53: 2 | AD53: 2 | AE53: 3 | AF53: 2 | AG53: 16 | AH53: 12 | AI53: Survived | AJ53: Clean | AK53: Full | AL53: None | AM53: 3 | AN53: Productized | AO53: 2 | AP53: 2
A54: SL-029 | B54: Blockchain-based supply chain provenance verification | C54: Blockchain | D54: DLT, provenance | E54: Cloud | F54: Smart contract | G54: Supply chain trust | H54: 0 | J54: 1 | K54: Method | L54: 2 | M54: 2 | N54: 1 | O54: 1 | P54: 0 | Q54: 2 | R54: 3 | S54: Granted | T54: No | U54: 7 | V54: Active | W54: US, EP | X54: No | Y54: 1 | AA54: Current | AB54: 2 | AC54: 1 | AD54: 1 | AE54: 3 | AF54: 1 | AG54: 6 | AH54: 9 | AI54: None | AJ54: Clean | AK54: None | AL54: None | AM54: 2 | AN54: Prototyped | AO54: 3 | AP54: 1
A55: SL-030 | B55: High-efficiency GaN power amplifier for 5G base stations | C55: Power electronics | D55: GaN, RF power | E55: Hardware | F55: RF frontend | G55: Cellular base station | H55: 1 | I55: 3GPP 5G NR | J55: 2 | K55: Apparatus | L55: 2 | M55: 2 | N55: 2 | O55: 2 | P55: 2 | Q55: 3 | R55: 4 | S55: Granted | T55: No | U55: 8 | V55: Active | W55: US, EP, CN, JP | X55: Yes | Y55: 3 | AA55: Current | AB55: 1 | AC55: 2 | AD55: 2 | AE55: 3 | AF55: 2 | AG55: 15 | AH55: 19 | AI55: None | AJ55: Clean | AK55: Partial | AL55: None | AM55: 3 | AN55: Productized | AO55: 2 | AP55: 2

Sheet Bundle Rules
A1: # | B1: Bundle Type | C1: Value Proposition | D1: Routing Rule (technical qualification) | E1: Primary attributes used
A2: 1 | B2: Technology Domain | C2: Concentrated coverage in one technical field; useful for entering or fortifying a domain position. | D2: Patents share the same A1 (primary domain) tag. | E2: A1
A3: 2 | B3: Standard-Essential (SEP) | C3: Bundle of assets every implementer of the standard must license or design around. | D3: B1 ≥ 2 AND share same B2 standard. | E3: B1, B2
A4: 3 | B4: Product Architecture | C4: "Build a product" kit — full vertical coverage across subsystems of one end-product. | D4: Collectively span ≥ 3 distinct A4 subsystems of one product family. | E4: A4
A5: 4 | B5: Stack Layer | C5: Targets buyers operating at a specific layer of the technology stack. | D5: Patents share the same A3 (stack layer). | E5: A3
A6: 5 | B6: Use-Case / Application | C6: All tools to address one customer problem, even if underlying tech is heterogeneous. | D6: Patents share at least one A5 (use-case) tag. | E6: A5
A7: 6 | B7: Manufacturing / Process | C7: Targets fabs, contract manufacturers, equipment makers needing freedom to operate on production methods. | D7: A1 is a "process" / manufacturing domain (e.g., contains "process" or "fab") AND C1 = Method. | E7: A1, C1
A8: 7 | B8: Materials & Chemistry | C8: Focused IP shield around composition, synthesis, and use of a material system. | D8: A1 is a materials/chemistry domain AND C1 ∈ {Apparatus, Method}. | E8: A1, C1
A9: 8 | B9: Algorithm / Software Method | C9: Implementation-agnostic methods deployable across many products. | D9: A3 ∈ {App, Middleware, Cloud} AND C1 ∈ {Method, CRM}. | E9: A3, C1
A10: 9 | B10: Interoperability / Interface | C10: Critical chokepoints for any player whose product must talk to others. | D10: B3 ≥ 2. | E10: B3
A11: 10 | B11: Generational Roadmap | C11: Buyer picks legacy (cheap defensive) or next-gen (forward-looking offensive). | D11: Group by G2 (Legacy / Current / Next-gen). | E11: G2
A12: 11 | B12: Claim-Type | C12: Different enforcement profiles; buyers pick by litigation/licensing strategy. | D12: Group by C1. | E12: C1
A13: 12 | B13: Detectability | C13: Litigation-ready bundle — infringement is easy to spot. | D13: D1 ≥ 2 OR D2 ≥ 2. | E13: D1, D2
... A34: 33 | B34: Provenance-Coherent | C34: Patents originating from the same R&D program, inventor group, or acquired sub-business. Shared specifications and consistent terminology reduce claim-construction risk. | D34: Patents share A1 AND share A4 (proxy for common provenance in this template). | E34: A1, A4

Sheet Bundle Assignment
A1: Patent | C1: Bundle Qualification (TRUE = patent qualifies for this bundle) | AJ1: Total
A2: Patent ID | B2: Title | C2: =IF(Configuration!$C$10="No","[DISABLED] B1 Tech Domain","B1 Tech Domain") -> B1 Tech Domain | D2: =IF(Configuration!$C$11="No","[DISABLED] B2 SEP","B2 SEP") -> B2 SEP | E2: =IF(Configuration!$C$12="No","[DISABLED] B3 Product Arch","B3 Product Arch") -> B3 Product Arch | F2: =IF(Configuration!$C$13="No","[DISABLED] B4 Stack Layer","B4 Stack Layer") -> B4 Stack Layer | G2: =IF(Configuration!$C$14="No","[DISABLED] B5 Use-Case","B5 Use-Case") -> B5 Use-Case | H2: =IF(Configuration!$C$15="No","[DISABLED] B6 Mfg/Process","B6 Mfg/Process") -> B6 Mfg/Process | I2: =IF(Configuration!$C$16="No","[DISABLED] B7 Materials","B7 Materials") -> B7 Materials | J2: =IF(Configuration!$C$17="No","[DISABLED] B8 Algorithm","B8 Algorithm") -> B8 Algorithm | K2: =IF(Configuration!$C$18="No","[DISABLED] B9 Interop","B9 Interop") -> B9 Interop | L2: =IF(Configuration!$C$19="No","[DISABLED] B10 Generational","B10 Generational") -> B10 Generational | M2: =IF(Configuration!$C$20="No","[DISABLED] B11 Claim-Type","B11 Claim-Type") -> B11 Claim-Type | N2: =IF(Configuration!$C$21="No","[DISABLED] B12 Detectable","B12 Detectable") -> B12 Detectable | O2: =IF(Configuration!$C$22="No","[DISABLED] B13 Geographic","B13 Geographic") -> B13 Geographic | P2: =IF(Configuration!$C$23="No","[DISABLED] B14 Family","B14 Family") -> B14 Family | Q2: =IF(Configuration!$C$24="No","[DISABLED] B15 Lifecycle","B15 Lifecycle") -> B15 Lifecycle | R2: =IF(Configuration!$C$25="No","[DISABLED] B16 Foundational+Improv.","B16 Foundational+Improv.") -> B16 Foundational+Improv. | S2: =IF(Configuration!$C$26="No","[DISABLED] B17 Cross-Industry","B17 Cross-Industry") -> B17 Cross-Industry | T2: =IF(Configuration!$C$27="No","[DISABLED] B18 Convergent Theme","B18 Convergent Theme") -> B18 Convergent Theme | U2: =IF(Configuration!$C$28="No","[DISABLED] B19 Defensive","B19 Defensive") -> B19 Defensive | V2: =IF(Configuration!$C$29="No","[DISABLED] B20 Whitespace","B20 Whitespace") -> B20 Whitespace | W2: =IF(Configuration!$C$30="No","[DISABLED] B21 Prosecution-Status","B21 Prosecution-Status") -> B21 Prosecution-Status | X2: =IF(Configuration!$C$31="No","[DISABLED] B22 Anchor+Halo","B22 Anchor+Halo") -> B22 Anchor+Halo | Y2: =IF(Configuration!$C$32="No","[DISABLED] B23 Picket-Fence","B23 Picket-Fence") -> B23 Picket-Fence | Z2: =IF(Configuration!$C$33="No","[DISABLED] B24 Strong+Tail","B24 Strong+Tail") -> B24 Strong+Tail | AA2: =IF(Configuration!$C$34="No","[DISABLED] B25 Continuation-Live","B25 Continuation-Live") -> B25 Continuation-Live | AB2: =IF(Configuration!$C$35="No","[DISABLED] B26 EoU-Backed","B26 EoU-Backed") -> B26 EoU-Backed | AC2: =IF(Configuration!$C$36="No","[DISABLED] B27 Battle-Tested","B27 Battle-Tested") -> B27 Battle-Tested | AD2: =IF(Configuration!$C$37="No","[DISABLED] B28 Clean-Title","B28 Clean-Title") -> B28 Clean-Title | AE2: =IF(Configuration!$C$38="No","[DISABLED] B29 High-Citation","B29 High-Citation") -> B29 High-Citation | AF2: =IF(Configuration!$C$39="No","[DISABLED] B30 Adjacent Re-Read","B30 Adjacent Re-Read") -> B30 Adjacent Re-Read | AG2: =IF(Configuration!$C$40="No","[DISABLED] B31 Salvage-Volume","B31 Salvage-Volume") -> B31 Salvage-Volume | AH2: =IF(Configuration!$C$41="No","[DISABLED] B32 Pre-Expiry","B32 Pre-Expiry") -> B32 Pre-Expiry | AI2: =IF(Configuration!$C$42="No","[DISABLED] B33 Provenance","B33 Provenance") -> B33 Provenance | AJ2: # of bundles
A3: ='Patent Portfolio'!A3 -> P-001 | B3: ='Patent Portfolio'!B3 -> Beamforming pilot signaling for 5G NR | C3: =IF(Configuration!$C$10="No","",IFERROR(IF('Patent Portfolio'!C3<>"",TRUE(),FALSE()),FALSE())) -> TRUE | D3: =IF(Configuration!$C$11="No","",IFERROR(IF(AND(N('Patent Portfolio'!H3)>=Configuration!$C$44,'Patent Portfolio'!I3<>""),TRUE(),FALSE()),FALSE())) -> TRUE | E3: =IF(Configuration!$C$12="No","",IFERROR(IF('Patent Portfolio'!F3<>"",TRUE(),FALSE()),FALSE())) -> TRUE | F3: =IF(Configuration!$C$13="No","",IFERROR(IF('Patent Portfolio'!E3<>"",TRUE(),FALSE()),FALSE())) -> TRUE | G3: =IF(Configuration!$C$14="No","",IFERROR(IF('Patent Portfolio'!G3<>"",TRUE(),FALSE()),FALSE())) -> TRUE | H3: =IF(Configuration!$C$15="No","",IFERROR(IF(AND(OR(ISNUMBER(SEARCH("process",'Patent Portfolio'!C3)),ISNUMBER(SEARCH("fab",'Patent Portfolio'!C3)),ISNUMBER(SEARCH("manufac",'Patent Portfolio'!C3))),'Patent Portfolio'!K3="Method"),TRUE(),FALSE()),FALSE())) -> FALSE | I3: =IF(Configuration!$C$16="No","",IFERROR(IF(AND(OR(ISNUMBER(SEARCH("material",'Patent Portfolio'!C3)),ISNUMBER(SEARCH("chem",'Patent Portfolio'!C3)),ISNUMBER(SEARCH("battery",'Patent Portfolio'!C3)),ISNUMBER(SEARCH("electrolyte",'Patent Portfolio'!C3)),ISNUMBER(SEARCH("polymer",'Patent Portfolio'!C3))),OR('Patent Portfolio'!K3="Apparatus",'Patent Portfolio'!K3="Method")),TRUE(),FALSE()),FALSE())) -> FALSE | J3: =IF(Configuration!$C$17="No","",IFERROR(IF(AND(OR('Patent Portfolio'!E3="App",'Patent Portfolio'!E3="Middleware",'Patent Portfolio'!E3="Cloud"),OR('Patent Portfolio'!K3="Method",'Patent Portfolio'!K3="CRM")),TRUE(),FALSE()),FALSE())) -> FALSE | K3: =IF(Configuration!$C$18="No","",IFERROR(IF(N('Patent Portfolio'!J3)>=Configuration!$C$45,TRUE(),FALSE()),FALSE())) -> TRUE | L3: =IF(Configuration!$C$19="No","",IFERROR(IF('Patent Portfolio'!AA3<>"",TRUE(),FALSE()),FALSE())) -> TRUE | M3: =IF(Configuration!$C$20="No","",IFERROR(IF('Patent Portfolio'!K3<>"",TRUE(),FALSE()),FALSE())) -> TRUE | N3: =IF(Configuration!$C$21="No","",IFERROR(IF(OR(N('Patent Portfolio'!O3)>=Configuration!$C$46,N('Patent Portfolio'!P3)>=Configuration!$C$47),TRUE(),FALSE()),FALSE())) -> TRUE | O3: =IF(Configuration!$C$22="No","",IFERROR(IF('Patent Portfolio'!X3="Yes",TRUE(),FALSE()),FALSE())) -> TRUE | P3: =IF(Configuration!$C$23="No","",IFERROR(IF(N('Patent Portfolio'!R3)>=Configuration!$C$48,TRUE(),FALSE()),FALSE())) -> TRUE | Q3: =IF(Configuration!$C$24="No","",IFERROR(IF(N('Patent Portfolio'!U3)>0,TRUE(),FALSE()),FALSE())) -> TRUE | R3: =IF(Configuration!$C$25="No","",IFERROR(IF(OR(N('Patent Portfolio'!L3)=3,N('Patent Portfolio'!L3)<=1),TRUE(),FALSE()),FALSE())) -> FALSE | S3: =IF(Configuration!$C$26="No","",IFERROR(IF(N('Patent Portfolio'!AB3)>=Configuration!$C$49,TRUE(),FALSE()),FALSE())) -> FALSE | T3: =IF(Configuration!$C$27="No","",IFERROR(IF('Patent Portfolio'!Z3<>"",TRUE(),FALSE()),FALSE())) -> FALSE | U3: =IF(Configuration!$C$28="No","",IFERROR(IF(N('Patent Portfolio'!Q3)>=Configuration!$C$50,TRUE(),FALSE()),FALSE())) -> TRUE | V3: =IF(Configuration!$C$29="No","",IFERROR(IF(AND(N('Patent Portfolio'!N3)>=Configuration!$C$51,'Patent Portfolio'!C3<>""),TRUE(),FALSE()),FALSE())) -> TRUE | W3: =IF(Configuration!$C$30="No","",IFERROR(IF(OR('Patent Portfolio'!S3="Pending",'Patent Portfolio'!T3="Yes"),TRUE(),FALSE()),FALSE())) -> TRUE | X3: =IF(Configuration!$C$31="No","",IFERROR(IF(AND(N('Patent Portfolio'!AC3)>=Configuration!$C$52,N('Patent Portfolio'!L3)>=1),TRUE(),FALSE()),FALSE())) -> TRUE | Y3: =IF(Configuration!$C$32="No","",IFERROR(IF(AND(N('Patent Portfolio'!N3)>=1,OR('Patent Portfolio'!C3<>"",'Patent Portfolio'!I3<>"")),TRUE(),FALSE()),FALSE())) -> TRUE | Z3: =IF(Configuration!$C$33="No","",IFERROR(IF('Patent Portfolio'!C3<>"",TRUE(),FALSE()),FALSE())) -> TRUE | AA3: =IF(Configuration!$C$34="No","",IFERROR(IF('Patent Portfolio'!T3="Yes",TRUE(),FALSE()),FALSE())) -> TRUE | AB3: =IF(Configuration!$C$35="No","",IFERROR(IF(OR('Patent Portfolio'!AK3="Partial",'Patent Portfolio'!AK3="Full"),TRUE(),FALSE()),FALSE())) -> TRUE | AC3: =IF(Configuration!$C$36="No","",IFERROR(IF('Patent Portfolio'!AI3="Survived",TRUE(),FALSE()),FALSE())) -> TRUE | AD3: =IF(Configuration!$C$37="No","",IFERROR(IF(AND('Patent Portfolio'!AJ3="Clean",'Patent Portfolio'!AL3="None"),TRUE(),FALSE()),FALSE())) -> TRUE | AE3: =IF(Configuration!$C$38="No","",IFERROR(IF(N('Patent Portfolio'!AG3)>=Configuration!$C$53,TRUE(),FALSE()),FALSE())) -> TRUE | AF3: =IF(Configuration!$C$39="No","",IFERROR(IF(AND(N('Patent Portfolio'!AO3)>=2,N('Patent Portfolio'!AB3)>=2),TRUE(),FALSE()),FALSE())) -> FALSE | AG3: =IF(Configuration!$C$40="No","",IFERROR(IF(OR(N('Patent Portfolio'!AC3)<=Configuration!$C$56,N('Patent Portfolio'!U3)<Configuration!$C$57,N('Patent Portfolio'!AD3)<=Configuration!$C$58),TRUE(),FALSE()),FALSE())) -> FALSE | AH3: =IF(Configuration!$C$41="No","",IFERROR(IF(AND(N('Patent Portfolio'!U3)>=Configuration!$C$54,N('Patent Portfolio'!U3)<=Configuration!$C$55),TRUE(),FALSE()),FALSE())) -> FALSE | AI3: =IF(Configuration!$C$42="No","",IFERROR(IF(AND('Patent Portfolio'!C3<>"",'Patent Portfolio'!F3<>""),TRUE(),FALSE()),FALSE())) -> TRUE | AJ3: =COUNTIF(C3:AI3,TRUE()) -> 24
A4: ='Patent Portfolio'!A4 -> P-002 | B4: ='Patent Portfolio'!B4 -> Polar code decoder architecture | C4: =IF(Configuration!$C$10="No","",IFERROR(IF('Patent Portfolio'!C4<>"",TRUE(),FALSE()),FALSE())) -> TRUE | D4: =IF(Configuration!$C$11="No","",IFERROR(IF(AND(N('Patent Portfolio'!H4)>=Configuration!$C$44,'Patent Portfolio'!I4<>""),TRUE(),FALSE()),FALSE())) -> TRUE | E4: =IF(Configuration!$C$12="No","",IFERROR(IF('Patent Portfolio'!F4<>"",TRUE(),FALSE()),FALSE())) -> TRUE | F4: =IF(Configuration!$C$13="No","",IFERROR(IF('Patent Portfolio'!E4<>"",TRUE(),FALSE()),FALSE())) -> TRUE | G4: =IF(Configuration!$C$14="No","",IFERROR(IF('Patent Portfolio'!G4<>"",TRUE(),FALSE()),FALSE())) -> TRUE | H4: =IF(Configuration!$C$15="No","",IFERROR(IF(AND(OR(ISNUMBER(SEARCH("process",'Patent Portfolio'!C4)),ISNUMBER(SEARCH("fab",'Patent Portfolio'!C4)),ISNUMBER(SEARCH("manufac",'Patent Portfolio'!C4))),'Patent Portfolio'!K4="Method"),TRUE(),FALSE()),FALSE())) -> FALSE | I4: =IF(Configuration!$C$16="No","",IFERROR(IF(AND(OR(ISNUMBER(SEARCH("material",'Patent Portfolio'!C4)),ISNUMBER(SEARCH("chem",'Patent Portfolio'!C4)),ISNUMBER(SEARCH("battery",'Patent Portfolio'!C4)),ISNUMBER(SEARCH("electrolyte",'Patent Portfolio'!C4)),ISNUMBER(SEARCH("polymer",'Patent Portfolio'!C4))),OR('Patent Portfolio'!K4="Apparatus",'Patent Portfolio'!K4="Method")),TRUE(),FALSE()),FALSE())) -> FALSE | J4: =IF(Configuration!$C$17="No","",IFERROR(IF(AND(OR('Patent Portfolio'!E4="App",'Patent Portfolio'!E4="Middleware",'Patent Portfolio'!E4="Cloud"),OR('Patent Portfolio'!K4="Method",'Patent Portfolio'!K4="CRM")),TRUE(),FALSE()),FALSE())) -> FALSE | K4: =IF(Configuration!$C$18="No","",IFERROR(IF(N('Patent Portfolio'!J4)>=Configuration!$C$45,TRUE(),FALSE()),FALSE())) -> TRUE | L4: =IF(Configuration!$C$19="No","",IFERROR(IF('Patent Portfolio'!AA4<>"",TRUE(),FALSE()),FALSE())) -> TRUE | M4: =IF(Configuration!$C$20="No","",IFERROR(IF('Patent Portfolio'!K4<>"",TRUE(),FALSE()),FALSE())) -> TRUE | N4: =IF(Configuration!$C$21="No","",IFERROR(IF(OR(N('Patent Portfolio'!O4)>=Configuration!$C$46,N('Patent Portfolio'!P4)>=Configuration!$C$47),TRUE(),FALSE()),FALSE())) -> TRUE | O4: =IF(Configuration!$C$22="No","",IFERROR(IF('Patent Portfolio'!X4="Yes",TRUE(),FALSE()),FALSE())) -> TRUE | P4: =IF(Configuration!$C$23="No","",IFERROR(IF(N('Patent Portfolio'!R4)>=Configuration!$C$48,TRUE(),FALSE()),FALSE())) -> TRUE | Q4: =IF(Configuration!$C$24="No","",IFERROR(IF(N('Patent Portfolio'!U4)>0,TRUE(),FALSE()),FALSE())) -> TRUE | R4: =IF(Configuration!$C$25="No","",IFERROR(IF(OR(N('Patent Portfolio'!L4)=3,N('Patent Portfolio'!L4)<=1),TRUE(),FALSE()),FALSE())) -> FALSE | S4: =IF(Configuration!$C$26="No","",IFERROR(IF(N('Patent Portfolio'!AB4)>=Configuration!$C$49,TRUE(),FALSE()),FALSE())) -> FALSE | T4: =IF(Configuration!$C$27="No","",IFERROR(IF('Patent Portfolio'!Z4<>"",TRUE(),FALSE()),FALSE())) -> FALSE | U4: =IF(Configuration!$C$28="No","",IFERROR(IF(N('Patent Portfolio'!Q4)>=Configuration!$C$50,TRUE(),FALSE()),FALSE())) -> TRUE | V4: =IF(Configuration!$C$29="No","",IFERROR(IF(AND(N('Patent Portfolio'!N4)>=Configuration!$C$51,'Patent Portfolio'!C4<>""),TRUE(),FALSE()),FALSE())) -> TRUE | W4: =IF(Configuration!$C$30="No","",IFERROR(IF(OR('Patent Portfolio'!S4="Pending",'Patent Portfolio'!T4="Yes"),TRUE(),FALSE()),FALSE())) -> FALSE | X4: =IF(Configuration!$C$31="No","",IFERROR(IF(AND(N('Patent Portfolio'!AC4)>=Configuration!$C$52,N('Patent Portfolio'!L4)>=1),TRUE(),FALSE()),FALSE())) -> TRUE | Y4: =IF(Configuration!$C$32="No","",IFERROR(IF(AND(N('Patent Portfolio'!N4)>=1,OR('Patent Portfolio'!C4<>"",'Patent Portfolio'!I4<>"")),TRUE(),FALSE()),FALSE())) -> TRUE | Z4: =IF(Configuration!$C$33="No","",IFERROR(IF('Patent Portfolio'!C4<>"",TRUE(),FALSE()),FALSE())) -> TRUE | AA4: =IF(Configuration!$C$34="No","",IFERROR(IF('Patent Portfolio'!T4="Yes",TRUE(),FALSE()),FALSE())) -> FALSE | AB4: =IF(Configuration!$C$35="No","",IFERROR(IF(OR('Patent Portfolio'!AK4="Partial",'Patent Portfolio'!AK4="Full"),TRUE(),FALSE()),FALSE())) -> TRUE | AC4: =IF(Configuration!$C$36="No","",IFERROR(IF('Patent Portfolio'!AI4="Survived",TRUE(),FALSE()),FALSE())) -> FALSE | AD4: =IF(Configuration!$C$37="No","",IFERROR(IF(AND('Patent Portfolio'!AJ4="Clean",'Patent Portfolio'!AL4="None"),TRUE(),FALSE()),FALSE())) -> TRUE | AE4: =IF(Configuration!$C$38="No","",IFERROR(IF(N('Patent Portfolio'!AG4)>=Configuration!$C$53,TRUE(),FALSE()),FALSE())) -> TRUE | AF4: =IF(Configuration!$C$39="No","",IFERROR(IF(AND(N('Patent Portfolio'!AO4)>=2,N('Patent Portfolio'!AB4)>=2),TRUE(),FALSE()),FALSE())) -> FALSE | AG4: =IF(Configuration!$C$40="No","",IFERROR(IF(OR(N('Patent Portfolio'!AC4)<=Configuration!$C$56,N('Patent Portfolio'!U4)<Configuration!$C$57,N('Patent Portfolio'!AD4)<=Configuration!$C$58),TRUE(),FALSE()),FALSE())) -> FALSE | AH4: =IF(Configuration!$C$41="No","",IFERROR(IF(AND(N('Patent Portfolio'!U4)>=Configuration!$C$54,N('Patent Portfolio'!U4)<=Configuration!$C$55),TRUE(),FALSE()),FALSE())) -> FALSE | AI4: =IF(Configuration!$C$42="No","",IFERROR(IF(AND('Patent Portfolio'!C4<>"",'Patent Portfolio'!F4<>""),TRUE(),FALSE()),FALSE())) -> TRUE | AJ4: =COUNTIF(C4:AI4,TRUE()) -> 21
A5: ='Patent Portfolio'!A5 -> P-003 | B5: ='Patent Portfolio'!B5 -> Adaptive Wi-Fi 7 channel sounding | C5: =IF(Configuration!$C$10="No","",IFERROR(IF('Patent Portfolio'!C5<>"",TRUE(),FALSE()),FALSE())) -> TRUE | D5: =IF(Configuration!$C$11="No","",IFERROR(IF(AND(N('Patent Portfolio'!H5)>=Configuration!$C$44,'Patent Portfolio'!I5<>""),TRUE(),FALSE()),FALSE())) -> TRUE | E5: =IF(Configuration!$C$12="No","",IFERROR(IF('Patent Portfolio'!F5<>"",TRUE(),FALSE()),FALSE())) -> TRUE | F5: =IF(Configuration!$C$13="No","",IFERROR(IF('Patent Portfolio'!E5<>"",TRUE(),FALSE()),FALSE())) -> TRUE | G5: =IF(Configuration!$C$14="No","",IFERROR(IF('Patent Portfolio'!G5<>"",TRUE(),FALSE()),FALSE())) -> TRUE | H5: =IF(Configuration!$C$15="No","",IFERROR(IF(AND(OR(ISNUMBER(SEARCH("process",'Patent Portfolio'!C5)),ISNUMBER(SEARCH("fab",'Patent Portfolio'!C5)),ISNUMBER(SEARCH("manufac",'Patent Portfolio'!C5))),'Patent Portfolio'!K5="Method"),TRUE(),FALSE()),FALSE())) -> FALSE | I5: =IF(Configuration!$C$16="No","",IFERROR(IF(AND(OR(ISNUMBER(SEARCH("material",'Patent Portfolio'!C5)),ISNUMBER(SEARCH("chem",'Patent Portfolio'!C5)),ISNUMBER(SEARCH("battery",'Patent Portfolio'!C5)),ISNUMBER(SEARCH("electrolyte",'Patent Portfolio'!C5)),ISNUMBER(SEARCH("polymer",'Patent Portfolio'!C5))),OR('Patent Portfolio'!K5="Apparatus",'Patent Portfolio'!K5="Method")),TRUE(),FALSE()),FALSE())) -> FALSE | J5: =IF(Configuration!$C$17="No","",IFERROR(IF(AND(OR('Patent Portfolio'!E5="App",'Patent Portfolio'!E5="Middleware",'Patent Portfolio'!E5="Cloud"),OR('Patent Portfolio'!K5="Method",'Patent Portfolio'!K5="CRM")),TRUE(),FALSE()),FALSE())) -> FALSE | K5: =IF(Configuration!$C$18="No","",IFERROR(IF(N('Patent Portfolio'!J5)>=Configuration!$C$45,TRUE(),FALSE()),FALSE())) -> TRUE | L5: =IF(Configuration!$C$19="No","",IFERROR(IF('Patent Portfolio'!AA5<>"",TRUE(),FALSE()),FALSE())) -> TRUE | M5: =IF(Configuration!$C$20="No","",IFERROR(IF('Patent Portfolio'!K5<>"",TRUE(),FALSE()),FALSE())) -> TRUE | N5: =IF(Configuration!$C$21="No","",IFERROR(IF(OR(N('Patent Portfolio'!O5)>=Configuration!$C$46,N('Patent Portfolio'!P5)>=Configuration!$C$47),TRUE(),FALSE()),FALSE())) -> TRUE | O5: =IF(Configuration!$C$22="No","",IFERROR(IF('Patent Portfolio'!X5="Yes",TRUE(),FALSE()),FALSE())) -> TRUE | P5: =IF(Configuration!$C$23="No","",IFERROR(IF(N('Patent Portfolio'!R5)>=Configuration!$C$48,TRUE(),FALSE()),FALSE())) -> TRUE | Q5: =IF(Configuration!$C$24="No","",IFERROR(IF(N('Patent Portfolio'!U5)>0,TRUE(),FALSE()),FALSE())) -> TRUE | R5: =IF(Configuration!$C$25="No","",IFERROR(IF(OR(N('Patent Portfolio'!L5)=3,N('Patent Portfolio'!L5)<=1),TRUE(),FALSE()),FALSE())) -> TRUE | S5: =IF(Configuration!$C$26="No","",IFERROR(IF(N('Patent Portfolio'!AB5)>=Configuration!$C$49,TRUE(),FALSE()),FALSE())) -> TRUE | T5: =IF(Configuration!$C$27="No","",IFERROR(IF('Patent Portfolio'!Z5<>"",TRUE(),FALSE()),FALSE())) -> FALSE | U5: =IF(Configuration!$C$28="No","",IFERROR(IF(N('Patent Portfolio'!Q5)>=Configuration!$C$50,TRUE(),FALSE()),FALSE())) -> TRUE | V5: =IF(Configuration!$C$29="No","",IFERROR(IF(AND(N('Patent Portfolio'!N5)>=Configuration!$C$51,'Patent Portfolio'!C5<>""),TRUE(),FALSE()),FALSE())) -> TRUE | W5: =IF(Configuration!$C$30="No","",IFERROR(IF(OR('Patent Portfolio'!S5="Pending",'Patent Portfolio'!T5="Yes"),TRUE(),FALSE()),FALSE())) -> TRUE | X5: =IF(Configuration!$C$31="No","",IFERROR(IF(AND(N('Patent Portfolio'!AC5)>=Configuration!$C$52,N('Patent Portfolio'!L5)>=1),TRUE(),FALSE()),FALSE())) -> TRUE | Y5: =IF(Configuration!$C$32="No","",IFERROR(IF(AND(N('Patent Portfolio'!N5)>=1,OR('Patent Portfolio'!C5<>"",'Patent Portfolio'!I5<>"")),TRUE(),FALSE()),FALSE())) -> TRUE | Z5: =IF(Configuration!$C$33="No","",IFERROR(IF('Patent Portfolio'!C5<>"",TRUE(),FALSE()),FALSE())) -> TRUE | AA5: =IF(Configuration!$C$34="No","",IFERROR(IF('Patent Portfolio'!T5="Yes",TRUE(),FALSE()),FALSE())) -> TRUE | AB5: =IF(Configuration!$C$35="No","",IFERROR(IF(OR('Patent Portfolio'!AK5="Partial",'Patent Portfolio'!AK5="Full"),TRUE(),FALSE()),FALSE())) -> FALSE | AC5: =IF(Configuration!$C$36="No","",IFERROR(IF('Patent Portfolio'!AI5="Survived",TRUE(),FALSE()),FALSE())) -> FALSE | AD5: =IF(Configuration!$C$37="No","",IFERROR(IF(AND('Patent Portfolio'!AJ5="Clean",'Patent Portfolio'!AL5="None"),TRUE(),FALSE()),FALSE())) -> TRUE | AE5: =IF(Configuration!$C$38="No","",IFERROR(IF(N('Patent Portfolio'!AG5)>=Configuration!$C$53,TRUE(),FALSE()),FALSE())) -> FALSE | AF5: =IF(Configuration!$C$39="No","",IFERROR(IF(AND(N('Patent Portfolio'!AO5)>=2,N('Patent Portfolio'!AB5)>=2),TRUE(),FALSE()),FALSE())) -> TRUE | AG5: =IF(Configuration!$C$40="No","",IFERROR(IF(OR(N('Patent Portfolio'!AC5)<=Configuration!$C$56,N('Patent Portfolio'!U5)<Configuration!$C$57,N('Patent Portfolio'!AD5)<=Configuration!$C$58),TRUE(),FALSE()),FALSE())) -> FALSE | AH5: =IF(Configuration!$C$41="No","",IFERROR(IF(AND(N('Patent Portfolio'!U5)>=Configuration!$C$54,N('Patent Portfolio'!U5)<=Configuration!$C$55),TRUE(),FALSE()),FALSE())) -> FALSE | AI5: =IF(Configuration!$C$42="No","",IFERROR(IF(AND('Patent Portfolio'!C5<>"",'Patent Portfolio'!F5<>""),TRUE(),FALSE()),FALSE())) -> TRUE | AJ5: =COUNTIF(C5:AI5,TRUE()) -> 24
A6: ='Patent Portfolio'!A6 -> P-004 | B6: ='Patent Portfolio'!B6 -> Solid-state electrolyte composition for EV batteries | C6: =IF(Configuration!$C$10="No","",IFERROR(IF('Patent Portfolio'!C6<>"",TRUE(),FALSE()),FALSE())) -> TRUE | D6: =IF(Configuration!$C$11="No","",IFERROR(IF(AND(N('Patent Portfolio'!H6)>=Configuration!$C$44,'Patent Portfolio'!I6<>""),TRUE(),FALSE()),FALSE())) -> FALSE | E6: =IF(Configuration!$C$12="No","",IFERROR(IF('Patent Portfolio'!F6<>"",TRUE(),FALSE()),FALSE())) -> TRUE | F6: =IF(Configuration!$C$13="No","",IFERROR(IF('Patent Portfolio'!E6<>"",TRUE(),FALSE()),FALSE())) -> TRUE | G6: =IF(Configuration!$C$14="No","",IFERROR(IF('Patent Portfolio'!G6<>"",TRUE(),FALSE()),FALSE())) -> TRUE | H6: =IF(Configuration!$C$15="No","",IFERROR(IF(AND(OR(ISNUMBER(SEARCH("process",'Patent Portfolio'!C6)),ISNUMBER(SEARCH("fab",'Patent Portfolio'!C6)),ISNUMBER(SEARCH("manufac",'Patent Portfolio'!C6))),'Patent Portfolio'!K6="Method"),TRUE(),FALSE()),FALSE())) -> FALSE | I6: =IF(Configuration!$C$16="No","",IFERROR(IF(AND(OR(ISNUMBER(SEARCH("material",'Patent Portfolio'!C6)),ISNUMBER(SEARCH("chem",'Patent Portfolio'!C6)),ISNUMBER(SEARCH("battery",'Patent Portfolio'!C6)),ISNUMBER(SEARCH("electrolyte",'Patent Portfolio'!C6)),ISNUMBER(SEARCH("polymer",'Patent Portfolio'!C6))),OR('Patent Portfolio'!K6="Apparatus",'Patent Portfolio'!K6="Method")),TRUE(),FALSE()),FALSE())) -> TRUE | J6: =IF(Configuration!$C$17="No","",IFERROR(IF(AND(OR('Patent Portfolio'!E6="App",'Patent Portfolio'!E6="Middleware",'Patent Portfolio'!E6="Cloud"),OR('Patent Portfolio'!K6="Method",'Patent Portfolio'!K6="CRM")),TRUE(),FALSE()),FALSE())) -> FALSE | K6: =IF(Configuration!$C$18="No","",IFERROR(IF(N('Patent Portfolio'!J6)>=Configuration!$C$45,TRUE(),FALSE()),FALSE())) -> FALSE | L6: =IF(Configuration!$C$19="No","",IFERROR(IF('Patent Portfolio'!AA6<>"",TRUE(),FALSE()),FALSE())) -> TRUE | M6: =IF(Configuration!$C$20="No","",IFERROR(IF('Patent Portfolio'!K6<>"",TRUE(),FALSE()),FALSE())) -> TRUE | N6: =IF(Configuration!$C$21="No","",IFERROR(IF(OR(N('Patent Portfolio'!O6)>=Configuration!$C$46,N('Patent Portfolio'!P6)>=Configuration!$C$47),TRUE(),FALSE()),FALSE())) -> TRUE | O6: =IF(Configuration!$C$22="No","",IFERROR(IF('Patent Portfolio'!X6="Yes",TRUE(),FALSE()),FALSE())) -> TRUE | P6: =IF(Configuration!$C$23="No","",IFERROR(IF(N('Patent Portfolio'!R6)>=Configuration!$C$48,TRUE(),FALSE()),FALSE())) -> TRUE | Q6: =IF(Configuration!$C$24="No","",IFERROR(IF(N('Patent Portfolio'!U6)>0,TRUE(),FALSE()),FALSE())) -> TRUE | R6: =IF(Configuration!$C$25="No","",IFERROR(IF(OR(N('Patent Portfolio'!L6)=3,N('Patent Portfolio'!L6)<=1),TRUE(),FALSE()),FALSE())) -> TRUE | S6: =IF(Configuration!$C$26="No","",IFERROR(IF(N('Patent Portfolio'!AB6)>=Configuration!$C$49,TRUE(),FALSE()),FALSE())) -> TRUE | T6: =IF(Configuration!$C$27="No","",IFERROR(IF('Patent Portfolio'!Z6<>"",TRUE(),FALSE()),FALSE())) -> FALSE | U6: =IF(Configuration!$C$28="No","",IFERROR(IF(N('Patent Portfolio'!Q6)>=Configuration!$C$50,TRUE(),FALSE()),FALSE())) -> TRUE | V6: =IF(Configuration!$C$29="No","",IFERROR(IF(AND(N('Patent Portfolio'!N6)>=Configuration!$C$51,'Patent Portfolio'!C6<>""),TRUE(),FALSE()),FALSE())) -> TRUE | W6: =IF(Configuration!$C$30="No","",IFERROR(IF(OR('Patent Portfolio'!S6="Pending",'Patent Portfolio'!T6="Yes"),TRUE(),FALSE()),FALSE())) -> TRUE | X6: =IF(Configuration!$C$31="No","",IFERROR(IF(AND(N('Patent Portfolio'!AC6)>=Configuration!$C$52,N('Patent Portfolio'!L6)>=1),TRUE(),FALSE()),FALSE())) -> TRUE | Y6: =IF(Configuration!$C$32="No","",IFERROR(IF(AND(N('Patent Portfolio'!N6)>=1,OR('Patent Portfolio'!C6<>"",'Patent Portfolio'!I6<>"")),TRUE(),FALSE()),FALSE())) -> TRUE | Z6: =IF(Configuration!$C$33="No","",IFERROR(IF('Patent Portfolio'!C6<>"",TRUE(),FALSE()),FALSE())) -> TRUE | AA6: =IF(Configuration!$C$34="No","",IFERROR(IF('Patent Portfolio'!T6="Yes",TRUE(),FALSE()),FALSE())) -> TRUE | AB6: =IF(Configuration!$C$35="No","",IFERROR(IF(OR('Patent Portfolio'!AK6="Partial",'Patent Portfolio'!AK6="Full"),TRUE(),FALSE()),FALSE())) -> TRUE | AC6: =IF(Configuration!$C$36="No","",IFERROR(IF('Patent Portfolio'!AI6="Survived",TRUE(),FALSE()),FALSE())) -> FALSE | AD6: =IF(Configuration!$C$37="No","",IFERROR(IF(AND('Patent Portfolio'!AJ6="Clean",'Patent Portfolio'!AL6="None"),TRUE(),FALSE()),FALSE())) -> TRUE | AE6: =IF(Configuration!$C$38="No","",IFERROR(IF(N('Patent Portfolio'!AG6)>=Configuration!$C$53,TRUE(),FALSE()),FALSE())) -> TRUE | AF6: =IF(Configuration!$C$39="No","",IFERROR(IF(AND(N('Patent Portfolio'!AO6)>=2,N('Patent Portfolio'!AB6)>=2),TRUE(),FALSE()),FALSE())) -> TRUE | AG6: =IF(Configuration!$C$40="No","",IFERROR(IF(OR(N('Patent Portfolio'!AC6)<=Configuration!$C$56,N('Patent Portfolio'!U6)<Configuration!$C$57,N('Patent Portfolio'!AD6)<=Configuration!$C$58),TRUE(),FALSE()),FALSE())) -> FALSE | AH6: =IF(Configuration!$C$41="No","",IFERROR(IF(AND(N('Patent Portfolio'!U6)>=Configuration!$C$54,N('Patent Portfolio'!U6)<=Configuration!$C$55),TRUE(),FALSE()),FALSE())) -> FALSE | AI6: =IF(Configuration!$C$42="No","",IFERROR(IF(AND('Patent Portfolio'!C6<>"",'Patent Portfolio'!F6<>""),TRUE(),FALSE()),FALSE())) -> TRUE | AJ6: =COUNTIF(C6:AI6,TRUE()) -> 25
A7: ='Patent Portfolio'!A7 -> P-005 | B7: ='Patent Portfolio'!B7 -> Battery thermal management with phase-change material | C7: =IF(Configuration!$C$10="No","",IFERROR(IF('Patent Portfolio'!C7<>"",TRUE(),FALSE()),FALSE())) -> TRUE | D7: =IF(Configuration!$C$11="No","",IFERROR(IF(AND(N('Patent Portfolio'!H7)>=Configuration!$C$44,'Patent Portfolio'!I7<>""),TRUE(),FALSE()),FALSE())) -> FALSE | E7: =IF(Configuration!$C$12="No","",IFERROR(IF('Patent Portfolio'!F7<>"",TRUE(),FALSE()),FALSE())) -> TRUE | F7: =IF(Configuration!$C$13="No","",IFERROR(IF('Patent Portfolio'!E7<>"",TRUE(),FALSE()),FALSE())) -> TRUE | G7: =IF(Configuration!$C$14="No","",IFERROR(IF('Patent Portfolio'!G7<>"",TRUE(),FALSE()),FALSE())) -> TRUE | H7: =IF(Configuration!$C$15="No","",IFERROR(IF(AND(OR(ISNUMBER(SEARCH("process",'Patent Portfolio'!C7)),ISNUMBER(SEARCH("fab",'Patent Portfolio'!C7)),ISNUMBER(SEARCH("manufac",'Patent Portfolio'!C7))),'Patent Portfolio'!K7="Method"),TRUE(),FALSE()),FALSE())) -> FALSE | I7: =IF(Configuration!$C$16="No","",IFERROR(IF(AND(OR(ISNUMBER(SEARCH("material",'Patent Portfolio'!C7)),ISNUMBER(SEARCH("chem",'Patent Portfolio'!C7)),ISNUMBER(SEARCH("battery",'Patent Portfolio'!C7)),ISNUMBER(SEARCH("electrolyte",'Patent Portfolio'!C7)),ISNUMBER(SEARCH("polymer",'Patent Portfolio'!C7))),OR('Patent Portfolio'!K7="Apparatus",'Patent Portfolio'!K7="Method")),TRUE(),FALSE()),FALSE())) -> FALSE | J7: =IF(Configuration!$C$17="No","",IFERROR(IF(AND(OR('Patent Portfolio'!E7="App",'Patent Portfolio'!E7="Middleware",'Patent Portfolio'!E7="Cloud"),OR('Patent Portfolio'!K7="Method",'Patent Portfolio'!K7="CRM")),TRUE(),FALSE()),FALSE())) -> FALSE | K7: =IF(Configuration!$C$18="No","",IFERROR(IF(N('Patent Portfolio'!J7)>=Configuration!$C$45,TRUE(),FALSE()),FALSE())) -> FALSE | L7: =IF(Configuration!$C$19="No","",IFERROR(IF('Patent Portfolio'!AA7<>"",TRUE(),FALSE()),FALSE())) -> TRUE | M7: =IF(Configuration!$C$20="No","",IFERROR(IF('Patent Portfolio'!K7<>"",TRUE(),FALSE()),FALSE())) -> TRUE | N7: =IF(Configuration!$C$21="No","",IFERROR(IF(OR(N('Patent Portfolio'!O7)>=Configuration!$C$46,N('Patent Portfolio'!P7)>=Configuration!$C$47),TRUE(),FALSE()),FALSE())) -> TRUE | O7: =IF(Configuration!$C$22="No","",IFERROR(IF('Patent Portfolio'!X7="Yes",TRUE(),FALSE()),FALSE())) -> TRUE | P7: =IF(Configuration!$C$23="No","",IFERROR(IF(N('Patent Portfolio'!R7)>=Configuration!$C$48,TRUE(),FALSE()),FALSE())) -> TRUE | Q7: =IF(Configuration!$C$24="No","",IFERROR(IF(N('Patent Portfolio'!U7)>0,TRUE(),FALSE()),FALSE())) -> TRUE | R7: =IF(Configuration!$C$25="No","",IFERROR(IF(OR(N('Patent Portfolio'!L7)=3,N('Patent Portfolio'!L7)<=1),TRUE(),FALSE()),FALSE())) -> FALSE | S7: =IF(Configuration!$C$26="No","",IFERROR(IF(N('Patent Portfolio'!AB7)>=Configuration!$C$49,TRUE(),FALSE()),FALSE())) -> TRUE | T7: =IF(Configuration!$C$27="No","",IFERROR(IF('Patent Portfolio'!Z7<>"",TRUE(),FALSE()),FALSE())) -> FALSE | U7: =IF(Configuration!$C$28="No","",IFERROR(IF(N('Patent Portfolio'!Q7)>=Configuration!$C$50,TRUE(),FALSE()),FALSE())) -> TRUE | V7: =IF(Configuration!$C$29="No","",IFERROR(IF(AND(N('Patent Portfolio'!N7)>=Configuration!$C$51,'Patent Portfolio'!C7<>""),TRUE(),FALSE()),FALSE())) -> TRUE | W7: =IF(Configuration!$C$30="No","",IFERROR(IF(OR('Patent Portfolio'!S7="Pending",'Patent Portfolio'!T7="Yes"),TRUE(),FALSE()),FALSE())) -> FALSE | X7: =IF(Configuration!$C$31="No","",IFERROR(IF(AND(N('Patent Portfolio'!AC7)>=Configuration!$C$52,N('Patent Portfolio'!L7)>=1),TRUE(),FALSE()),FALSE())) -> TRUE | Y7: =IF(Configuration!$C$32="No","",IFERROR(IF(AND(N('Patent Portfolio'!N7)>=1,OR('Patent Portfolio'!C7<>"",'Patent Portfolio'!I7<>"")),TRUE(),FALSE()),FALSE())) -> TRUE | Z7: =IF(Configuration!$C$33="No","",IFERROR(IF('Patent Portfolio'!C7<>"",TRUE(),FALSE()),FALSE())) -> TRUE | AA7: =IF(Configuration!$C$34="No","",IFERROR(IF('Patent Portfolio'!T7="Yes",TRUE(),FALSE()),FALSE())) -> FALSE | AB7: =IF(Configuration!$C$35="No","",IFERROR(IF(OR('Patent Portfolio'!AK7="Partial",'Patent Portfolio'!AK7="Full"),TRUE(),FALSE()),FALSE())) -> FALSE | AC7: =IF(Configuration!$C$36="No","",IFERROR(IF('Patent Portfolio'!AI7="Survived",TRUE(),FALSE()),FALSE())) -> FALSE | AD7: =IF(Configuration!$C$37="No","",IFERROR(IF(AND('Patent Portfolio'!AJ7="Clean",'Patent Portfolio'!AL7="None"),TRUE(),FALSE()),FALSE())) -> FALSE | AE7: =IF(Configuration!$C$38="No","",IFERROR(IF(N('Patent Portfolio'!AG7)>=Configuration!$C$53,TRUE(),FALSE()),FALSE())) -> FALSE | AF7: =IF(Configuration!$C$39="No","",IFERROR(IF(AND(N('Patent Portfolio'!AO7)>=2,N('Patent Portfolio'!AB7)>=2),TRUE(),FALSE()),FALSE())) -> TRUE | AG7: =IF(Configuration!$C$40="No","",IFERROR(IF(OR(N('Patent Portfolio'!AC7)<=Configuration!$C$56,N('Patent Portfolio'!U7)<Configuration!$C$57,N('Patent Portfolio'!AD7)<=Configuration!$C$58),TRUE(),FALSE()),FALSE())) -> FALSE | AH7: =IF(Configuration!$C$41="No","",IFERROR(IF(AND(N('Patent Portfolio'!U7)>=Configuration!$C$54,N('Patent Portfolio'!U7)<=Configuration!$C$55),TRUE(),FALSE()),FALSE())) -> FALSE | AI7: =IF(Configuration!$C$42="No","",IFERROR(IF(AND('Patent Portfolio'!C7<>"",'Patent Portfolio'!F7<>""),TRUE(),FALSE()),FALSE())) -> TRUE | AJ7: =COUNTIF(C7:AI7,TRUE()) -> 18
A8: ='Patent Portfolio'!A8 -> P-006 | B8: ='Patent Portfolio'!B8 -> SiC MOSFET inverter control method | C8: =IF(Configuration!$C$10="No","",IFERROR(IF('Patent Portfolio'!C8<>"",TRUE(),FALSE()),FALSE())) -> TRUE | D8: =IF(Configuration!$C$11="No","",IFERROR(IF(AND(N('Patent Portfolio'!H8)>=Configuration!$C$44,'Patent Portfolio'!I8<>""),TRUE(),FALSE()),FALSE())) -> FALSE | E8: =IF(Configuration!$C$12="No","",IFERROR(IF('Patent Portfolio'!F8<>"",TRUE(),FALSE()),FALSE())) -> TRUE | F8: =IF(Configuration!$C$13="No","",IFERROR(IF('Patent Portfolio'!E8<>"",TRUE(),FALSE()),FALSE())) -> TRUE | G8: =IF(Configuration!$C$14="No","",IFERROR(IF('Patent Portfolio'!G8<>"",TRUE(),FALSE()),FALSE())) -> TRUE | H8: =IF(Configuration!$C$15="No","",IFERROR(IF(AND(OR(ISNUMBER(SEARCH("process",'Patent Portfolio'!C8)),ISNUMBER(SEARCH("fab",'Patent Portfolio'!C8)),ISNUMBER(SEARCH("manufac",'Patent Portfolio'!C8))),'Patent Portfolio'!K8="Method"),TRUE(),FALSE()),FALSE())) -> FALSE | I8: =IF(Configuration!$C$16="No","",IFERROR(IF(AND(OR(ISNUMBER(SEARCH("material",'Patent Portfolio'!C8)),ISNUMBER(SEARCH("chem",'Patent Portfolio'!C8)),ISNUMBER(SEARCH("battery",'Patent Portfolio'!C8)),ISNUMBER(SEARCH("electrolyte",'Patent Portfolio'!C8)),ISNUMBER(SEARCH("polymer",'Patent Portfolio'!C8))),OR('Patent Portfolio'!K8="Apparatus",'Patent Portfolio'!K8="Method")),TRUE(),FALSE()),FALSE())) -> FALSE | J8: =IF(Configuration!$C$17="No","",IFERROR(IF(AND(OR('Patent Portfolio'!E8="App",'Patent Portfolio'!E8="Middleware",'Patent Portfolio'!E8="Cloud"),OR('Patent Portfolio'!K8="Method",'Patent Portfolio'!K8="CRM")),TRUE(),FALSE()),FALSE())) -> FALSE | K8: =IF(Configuration!$C$18="No","",IFERROR(IF(N('Patent Portfolio'!J8)>=Configuration!$C$45,TRUE(),FALSE()),FALSE())) -> FALSE | L8: =IF(Configuration!$C$19="No","",IFERROR(IF('Patent Portfolio'!AA8<>"",TRUE(),FALSE()),FALSE())) -> TRUE | M8: =IF(Configuration!$C$20="No","",IFERROR(IF('Patent Portfolio'!K8<>"",TRUE(),FALSE()),FALSE())) -> TRUE | N8: =IF(Configuration!$C$21="No","",IFERROR(IF(OR(N('Patent Portfolio'!O8)>=Configuration!$C$46,N('Patent Portfolio'!P8)>=Configuration!$C$47),TRUE(),FALSE()),FALSE())) -> TRUE | O8: =IF(Configuration!$C$22="No","",IFERROR(IF('Patent Portfolio'!X8="Yes",TRUE(),FALSE()),FALSE())) -> TRUE | P8: =IF(Configuration!$C$23="No","",IFERROR(IF(N('Patent Portfolio'!R8)>=Configuration!$C$48,TRUE(),FALSE()),FALSE())) -> TRUE | Q8: =IF(Configuration!$C$24="No","",IFERROR(IF(N('Patent Portfolio'!U8)>0,TRUE(),FALSE()),FALSE())) -> TRUE | R8: =IF(Configuration!$C$25="No","",IFERROR(IF(OR(N('Patent Portfolio'!L8)=3,N('Patent Portfolio'!L8)<=1),TRUE(),FALSE()),FALSE())) -> FALSE | S8: =IF(Configuration!$C$26="No","",IFERROR(IF(N('Patent Portfolio'!AB8)>=Configuration!$C$49,TRUE(),FALSE()),FALSE())) -> TRUE | T8: =IF(Configuration!$C$27="No","",IFERROR(IF('Patent Portfolio'!Z8<>"",TRUE(),FALSE()),FALSE())) -> FALSE | U8: =IF(Configuration!$C$28="No","",IFERROR(IF(N('Patent Portfolio'!Q8)>=Configuration!$C$50,TRUE(),FALSE()),FALSE())) -> TRUE | V8: =IF(Configuration!$C$29="No","",IFERROR(IF(AND(N('Patent Portfolio'!N8)>=Configuration!$C$51,'Patent Portfolio'!C8<>""),TRUE(),FALSE()),FALSE())) -> TRUE | W8: =IF(Configuration!$C$30="No","",IFERROR(IF(OR('Patent Portfolio'!S8="Pending",'Patent Portfolio'!T8="Yes"),TRUE(),FALSE()),FALSE())) -> FALSE | X8: =IF(Configuration!$C$31="No","",IFERROR(IF(AND(N('Patent Portfolio'!AC8)>=Configuration!$C$52,N('Patent Portfolio'!L8)>=1),TRUE(),FALSE()),FALSE())) -> TRUE | Y8: =IF(Configuration!$C$32="No","",IFERROR(IF(AND(N('Patent Portfolio'!N8)>=1,OR('Patent Portfolio'!C8<>"",'Patent Portfolio'!I8<>"")),TRUE(),FALSE()),FALSE())) -> TRUE | Z8: =IF(Configuration!$C$33="No","",IFERROR(IF('Patent Portfolio'!C8<>"",TRUE(),FALSE()),FALSE())) -> TRUE | AA8: =IF(Configuration!$C$34="No","",IFERROR(IF('Patent Portfolio'!T8="Yes",TRUE(),FALSE()),FALSE())) -> FALSE | AB8: =IF(Configuration!$C$35="No","",IFERROR(IF(OR('Patent Portfolio'!AK8="Partial",'Patent Portfolio'!AK8="Full"),TRUE(),FALSE()),FALSE())) -> TRUE | AC8: =IF(Configuration!$C$36="No","",IFERROR(IF('Patent Portfolio'!AI8="Survived",TRUE(),FALSE()),FALSE())) -> FALSE | AD8: =IF(Configuration!$C$37="No","",IFERROR(IF(AND('Patent Portfolio'!AJ8="Clean",'Patent Portfolio'!AL8="None"),TRUE(),FALSE()),FALSE())) -> FALSE | AE8: =IF(Configuration!$C$38="No","",IFERROR(IF(N('Patent Portfolio'!AG8)>=Configuration!$C$53,TRUE(),FALSE()),FALSE())) -> TRUE | AF8: =IF(Configuration!$C$39="No","",IFERROR(IF(AND(N('Patent Portfolio'!AO8)>=2,N('Patent Portfolio'!AB8)>=2),TRUE(),FALSE()),FALSE())) -> TRUE | AG8: =IF(Configuration!$C$40="No","",IFERROR(IF(OR(N('Patent Portfolio'!AC8)<=Configuration!$C$56,N('Patent Portfolio'!U8)<Configuration!$C$57,N('Patent Portfolio'!AD8)<=Configuration!$C$58),TRUE(),FALSE()),FALSE())) -> FALSE | AH8: =IF(Configuration!$C$41="No","",IFERROR(IF(AND(N('Patent Portfolio'!U8)>=Configuration!$C$54,N('Patent Portfolio'!U8)<=Configuration!$C$55),TRUE(),FALSE()),FALSE())) -> FALSE | AI8: =IF(Configuration!$C$42="No","",IFERROR(IF(AND('Patent Portfolio'!C8<>"",'Patent Portfolio'!F8<>""),TRUE(),FALSE()),FALSE())) -> TRUE | AJ8: =COUNTIF(C8:AI8,TRUE()) -> 20
A9: ='Patent Portfolio'!A9 -> P-007 | B9: ='Patent Portfolio'!B9 -> On-device CNN quantization for low-power inference | C9: =IF(Configuration!$C$10="No","",IFERROR(IF('Patent Portfolio'!C9<>"",TRUE(),FALSE()),FALSE())) -> TRUE | D9: =IF(Configuration!$C$11="No","",IFERROR(IF(AND(N('Patent Portfolio'!H9)>=Configuration!$C$44,'Patent Portfolio'!I9<>""),TRUE(),FALSE()),FALSE())) -> FALSE | E9: =IF(Configuration!$C$12="No","",IFERROR(IF('Patent Portfolio'!F9<>"",TRUE(),FALSE()),FALSE())) -> TRUE | F9: =IF(Configuration!$C$13="No","",IFERROR(IF('Patent Portfolio'!E9<>"",TRUE(),FALSE()),FALSE())) -> TRUE | G9: =IF(Configuration!$C$14="No","",IFERROR(IF('Patent Portfolio'!G9<>"",TRUE(),FALSE()),FALSE())) -> TRUE | H9: =IF(Configuration!$C$15="No","",IFERROR(IF(AND(OR(ISNUMBER(SEARCH("process",'Patent Portfolio'!C9)),ISNUMBER(SEARCH("fab",'Patent Portfolio'!C9)),ISNUMBER(SEARCH("manufac",'Patent Portfolio'!C9))),'Patent Portfolio'!K9="Method"),TRUE(),FALSE()),FALSE())) -> FALSE | I9: =IF(Configuration!$C$16="No","",IFERROR(IF(AND(OR(ISNUMBER(SEARCH("material",'Patent Portfolio'!C9)),ISNUMBER(SEARCH("chem",'Patent Portfolio'!C9)),ISNUMBER(SEARCH("battery",'Patent Portfolio'!C9)),ISNUMBER(SEARCH("electrolyte",'Patent Portfolio'!C9)),ISNUMBER(SEARCH("polymer",'Patent Portfolio'!C9))),OR('Patent Portfolio'!K9="Apparatus",'Patent Portfolio'!K9="Method")),TRUE(),FALSE()),FALSE())) -> FALSE | J9: =IF(Configuration!$C$17="No","",IFERROR(IF(AND(OR('Patent Portfolio'!E9="App",'Patent Portfolio'!E9="Middleware",'Patent Portfolio'!E9="Cloud"),OR('Patent Portfolio'!K9="Method",'Patent Portfolio'!K9="CRM")),TRUE(),FALSE()),FALSE())) -> TRUE | K9: =IF(Configuration!$C$18="No","",IFERROR(IF(N('Patent Portfolio'!J9)>=Configuration!$C$45,TRUE(),FALSE()),FALSE())) -> FALSE | L9: =IF(Configuration!$C$19="No","",IFERROR(IF('Patent Portfolio'!AA9<>"",TRUE(),FALSE()),FALSE())) -> TRUE | M9: =IF(Configuration!$C$20="No","",IFERROR(IF('Patent Portfolio'!K9<>"",TRUE(),FALSE()),FALSE())) -> TRUE | N9: =IF(Configuration!$C$21="No","",IFERROR(IF(OR(N('Patent Portfolio'!O9)>=Configuration!$C$46,N('Patent Portfolio'!P9)>=Configuration!$C$47),TRUE(),FALSE()),FALSE())) -> TRUE | O9: =IF(Configuration!$C$22="No","",IFERROR(IF('Patent Portfolio'!X9="Yes",TRUE(),FALSE()),FALSE())) -> TRUE | P9: =IF(Configuration!$C$23="No","",IFERROR(IF(N('Patent Portfolio'!R9)>=Configuration!$C$48,TRUE(),FALSE()),FALSE())) -> TRUE | Q9: =IF(Configuration!$C$24="No","",IFERROR(IF(N('Patent Portfolio'!U9)>0,TRUE(),FALSE()),FALSE())) -> TRUE | R9: =IF(Configuration!$C$25="No","",IFERROR(IF(OR(N('Patent Portfolio'!L9)=3,N('Patent Portfolio'!L9)<=1),TRUE(),FALSE()),FALSE())) -> FALSE | S9: =IF(Configuration!$C$26="No","",IFERROR(IF(N('Patent Portfolio'!AB9)>=Configuration!$C$49,TRUE(),FALSE()),FALSE())) -> TRUE | T9: =IF(Configuration!$C$27="No","",IFERROR(IF('Patent Portfolio'!Z9<>"",TRUE(),FALSE()),FALSE())) -> TRUE | U9: =IF(Configuration!$C$28="No","",IFERROR(IF(N('Patent Portfolio'!Q9)>=Configuration!$C$50,TRUE(),FALSE()),FALSE())) -> TRUE | V9: =IF(Configuration!$C$29="No","",IFERROR(IF(AND(N('Patent Portfolio'!N9)>=Configuration!$C$51,'Patent Portfolio'!C9<>""),TRUE(),FALSE()),FALSE())) -> TRUE | W9: =IF(Configuration!$C$30="No","",IFERROR(IF(OR('Patent Portfolio'!S9="Pending",'Patent Portfolio'!T9="Yes"),TRUE(),FALSE()),FALSE())) -> TRUE | X9: =IF(Configuration!$C$31="No","",IFERROR(IF(AND(N('Patent Portfolio'!AC9)>=Configuration!$C$52,N('Patent Portfolio'!L9)>=1),TRUE(),FALSE()),FALSE())) -> TRUE | Y9: =IF(Configuration!$C$32="No","",IFERROR(IF(AND(N('Patent Portfolio'!N9)>=1,OR('Patent Portfolio'!C9<>"",'Patent Portfolio'!I9<>"")),TRUE(),FALSE()),FALSE())) -> TRUE | Z9: =IF(Configuration!$C$33="No","",IFERROR(IF('Patent Portfolio'!C9<>"",TRUE(),FALSE()),FALSE())) -> TRUE | AA9: =IF(Configuration!$C$34="No","",IFERROR(IF('Patent Portfolio'!T9="Yes",TRUE(),FALSE()),FALSE())) -> TRUE | AB9: =IF(Configuration!$C$35="No","",IFERROR(IF(OR('Patent Portfolio'!AK9="Partial",'Patent Portfolio'!AK9="Full"),TRUE(),FALSE()),FALSE())) -> TRUE | AC9: =IF(Configuration!$C$36="No","",IFERROR(IF('Patent Portfolio'!AI9="Survived",TRUE(),FALSE()),FALSE())) -> FALSE | AD9: =IF(Configuration!$C$37="No","",IFERROR(IF(AND('Patent Portfolio'!AJ9="Clean",'Patent Portfolio'!AL9="None"),TRUE(),FALSE()),FALSE())) -> TRUE | AE9: =IF(Configuration!$C$38="No","",IFERROR(IF(N('Patent Portfolio'!AG9)>=Configuration!$C$53,TRUE(),FALSE()),FALSE())) -> TRUE | AF9: =IF(Configuration!$C$39="No","",IFERROR(IF(AND(N('Patent Portfolio'!AO9)>=2,N('Patent Portfolio'!AB9)>=2),TRUE(),FALSE()),FALSE())) -> TRUE | AG9: =IF(Configuration!$C$40="No","",IFERROR(IF(OR(N('Patent Portfolio'!AC9)<=Configuration!$C$56,N('Patent Portfolio'!U9)<Configuration!$C$57,N('Patent Portfolio'!AD9)<=Configuration!$C$58),TRUE(),FALSE()),FALSE())) -> TRUE | AH9: =IF(Configuration!$C$41="No","",IFERROR(IF(AND(N('Patent Portfolio'!U9)>=Configuration!$C$54,N('Patent Portfolio'!U9)<=Configuration!$C$55),TRUE(),FALSE()),FALSE())) -> FALSE | AI9: =IF(Configuration!$C$42="No","",IFERROR(IF(AND('Patent Portfolio'!C9<>"",'Patent Portfolio'!F9<>""),TRUE(),FALSE()),FALSE())) -> TRUE | AJ9: =COUNTIF(C9:AI9,TRUE()) -> 26
A10: ='Patent Portfolio'!A10 -> P-008 | B10: ='Patent Portfolio'!B10 -> Transformer attention pruning for vision models | C10: =IF(Configuration!$C$10="No","",IFERROR(IF('Patent Portfolio'!C10<>"",TRUE(),FALSE()),FALSE())) -> TRUE | D10: =IF(Configuration!$C$11="No","",IFERROR(IF(AND(N('Patent Portfolio'!H10)>=Configuration!$C$44,'Patent Portfolio'!I10<>""),TRUE(),FALSE()),FALSE())) -> FALSE | E10: =IF(Configuration!$C$12="No","",IFERROR(IF('Patent Portfolio'!F10<>"",TRUE(),FALSE()),FALSE())) -> TRUE | F10: =IF(Configuration!$C$13="No","",IFERROR(IF('Patent Portfolio'!E10<>"",TRUE(),FALSE()),FALSE())) -> TRUE | G10: =IF(Configuration!$C$14="No","",IFERROR(IF('Patent Portfolio'!G10<>"",TRUE(),FALSE()),FALSE())) -> TRUE | H10: =IF(Configuration!$C$15="No","",IFERROR(IF(AND(OR(ISNUMBER(SEARCH("process",'Patent Portfolio'!C10)),ISNUMBER(SEARCH("fab",'Patent Portfolio'!C10)),ISNUMBER(SEARCH("manufac",'Patent Portfolio'!C10))),'Patent Portfolio'!K10="Method"),TRUE(),FALSE()),FALSE())) -> FALSE | I10: =IF(Configuration!$C$16="No","",IFERROR(IF(AND(OR(ISNUMBER(SEARCH("material",'Patent Portfolio'!C10)),ISNUMBER(SEARCH("chem",'Patent Portfolio'!C10)),ISNUMBER(SEARCH("battery",'Patent Portfolio'!C10)),ISNUMBER(SEARCH("electrolyte",'Patent Portfolio'!C10)),ISNUMBER(SEARCH("polymer",'Patent Portfolio'!C10))),OR('Patent Portfolio'!K10="Apparatus",'Patent Portfolio'!K10="Method")),TRUE(),FALSE()),FALSE())) -> FALSE | J10: =IF(Configuration!$C$17="No","",IFERROR(IF(AND(OR('Patent Portfolio'!E10="App",'Patent Portfolio'!E10="Middleware",'Patent Portfolio'!E10="Cloud"),OR('Patent Portfolio'!K10="Method",'Patent Portfolio'!K10="CRM")),TRUE(),FALSE()),FALSE())) -> TRUE | K10: =IF(Configuration!$C$18="No","",IFERROR(IF(N('Patent Portfolio'!J10)>=Configuration!$C$45,TRUE(),FALSE()),FALSE())) -> FALSE | L10: =IF(Configuration!$C$19="No","",IFERROR(IF('Patent Portfolio'!AA10<>"",TRUE(),FALSE()),FALSE())) -> TRUE | M10: =IF(Configuration!$C$20="No","",IFERROR(IF('Patent Portfolio'!K10<>"",TRUE(),FALSE()),FALSE())) -> TRUE | N10: =IF(Configuration!$C$21="No","",IFERROR(IF(OR(N('Patent Portfolio'!O10)>=Configuration!$C$46,N('Patent Portfolio'!P10)>=Configuration!$C$47),TRUE(),FALSE()),FALSE())) -> TRUE | O10: =IF(Configuration!$C$22="No","",IFERROR(IF('Patent Portfolio'!X10="Yes",TRUE(),FALSE()),FALSE())) -> FALSE | P10: =IF(Configuration!$C$23="No","",IFERROR(IF(N('Patent Portfolio'!R10)>=Configuration!$C$48,TRUE(),FALSE()),FALSE())) -> TRUE | Q10: =IF(Configuration!$C$24="No","",IFERROR(IF(N('Patent Portfolio'!U10)>0,TRUE(),FALSE()),FALSE())) -> TRUE | R10: =IF(Configuration!$C$25="No","",IFERROR(IF(OR(N('Patent Portfolio'!L10)=3,N('Patent Portfolio'!L10)<=1),TRUE(),FALSE()),FALSE())) -> TRUE | S10: =IF(Configuration!$C$26="No","",IFERROR(IF(N('Patent Portfolio'!AB10)>=Configuration!$C$49,TRUE(),FALSE()),FALSE())) -> TRUE | T10: =IF(Configuration!$C$27="No","",IFERROR(IF('Patent Portfolio'!Z10<>"",TRUE(),FALSE()),FALSE())) -> TRUE | U10: =IF(Configuration!$C$28="No","",IFERROR(IF(N('Patent Portfolio'!Q10)>=Configuration!$C$50,TRUE(),FALSE()),FALSE())) -> TRUE | V10: =IF(Configuration!$C$29="No","",IFERROR(IF(AND(N('Patent Portfolio'!N10)>=Configuration!$C$51,'Patent Portfolio'!C10<>""),TRUE(),FALSE()),FALSE())) -> FALSE | W10: =IF(Configuration!$C$30="No","",IFERROR(IF(OR('Patent Portfolio'!S10="Pending",'Patent Portfolio'!T10="Yes"),TRUE(),FALSE()),FALSE())) -> TRUE | X10: =IF(Configuration!$C$31="No","",IFERROR(IF(AND(N('Patent Portfolio'!AC10)>=Configuration!$C$52,N('Patent Portfolio'!L10)>=1),TRUE(),FALSE()),FALSE())) -> FALSE | Y10: =IF(Configuration!$C$32="No","",IFERROR(IF(AND(N('Patent Portfolio'!N10)>=1,OR('Patent Portfolio'!C10<>"",'Patent Portfolio'!I10<>"")),TRUE(),FALSE()),FALSE())) -> TRUE | Z10: =IF(Configuration!$C$33="No","",IFERROR(IF('Patent Portfolio'!C10<>"",TRUE(),FALSE()),FALSE())) -> TRUE | AA10: =IF(Configuration!$C$34="No","",IFERROR(IF('Patent Portfolio'!T10="Yes",TRUE(),FALSE()),FALSE())) -> TRUE | AB10: =IF(Configuration!$C$35="No","",IFERROR(IF(OR('Patent Portfolio'!AK10="Partial",'Patent Portfolio'!AK10="Full"),TRUE(),FALSE()),FALSE())) -> FALSE | AC10: =IF(Configuration!$C$36="No","",IFERROR(IF('Patent Portfolio'!AI10="Survived",TRUE(),FALSE()),FALSE())) -> FALSE | AD10: =IF(Configuration!$C$37="No","",IFERROR(IF(AND('Patent Portfolio'!AJ10="Clean",'Patent Portfolio'!AL10="None"),TRUE(),FALSE()),FALSE())) -> TRUE | AE10: =IF(Configuration!$C$38="No","",IFERROR(IF(N('Patent Portfolio'!AG10)>=Configuration!$C$53,TRUE(),FALSE()),FALSE())) -> FALSE | AF10: =IF(Configuration!$C$39="No","",IFERROR(IF(AND(N('Patent Portfolio'!AO10)>=2,N('Patent Portfolio'!AB10)>=2),TRUE(),FALSE()),FALSE())) -> TRUE | AG10: =IF(Configuration!$C$40="No","",IFERROR(IF(OR(N('Patent Portfolio'!AC10)<=Configuration!$C$56,N('Patent Portfolio'!U10)<Configuration!$C$57,N('Patent Portfolio'!AD10)<=Configuration!$C$58),TRUE(),FALSE()),FALSE())) -> TRUE | AH10: =IF(Configuration!$C$41="No","",IFERROR(IF(AND(N('Patent Portfolio'!U10)>=Configuration!$C$54,N('Patent Portfolio'!U10)<=Configuration!$C$55),TRUE(),FALSE()),FALSE())) -> FALSE | AI10: =IF(Configuration!$C$42="No","",IFERROR(IF(AND('Patent Portfolio'!C10<>"",'Patent Portfolio'!F10<>""),TRUE(),FALSE()),FALSE())) -> TRUE | AJ10: =COUNTIF(C10:AI10,TRUE()) -> 22
