Workbook

Sheet README
A1: PATENT PORTFOLIO BUNDLING TEMPLATE
A2: A technical-attribute-based framework for grouping patents into sellable bundles
A4: PURPOSE
A5: Score each patent across technical attributes, then auto-route patents into one or more sellable bundle types based on logical rules. The framework is purely technical — no valuation, no pricing.
A7: SHEETS IN THIS WORKBOOK
A8: 1. README — This page. Overview and instructions.
A9: 2. Attribute Dictionary — Definitions and scoring scales for every attribute.
A10: 3. Patent Portfolio — Master data sheet. One row per patent. Fill this in.
A11: 4. Bundle Rules — The 21 bundle types and the routing rule that qualifies a patent for each.
A12: 5. Bundle Assignment — Auto-computed: which bundles each patent qualifies for.
A13: 6. Bundle Quality Scorecard — Auto-computed: quality indicators per bundle.
A14: 7. Sample Bundles — Worked examples showing how three bundles look in practice.
... A42: New "Bundle Composition Strategy" sheet — tiered structure, anchor-first, storyline, complementary-weakness, modular, carve-in/out, reserve, buyer-profile, continuation-optionality overlays.

Sheet Attribute Dictionary
A1: Group | B1: Code | C1: Attribute | D1: Description | E1: Scale / Values | F1: Example
A2: A. Technology Classification | B2: A1 | C2: Primary technology domain | D2: Main CPC/IPC classification or internal taxonomy tag. | E2: Categorical text | F2: Wireless PHY
A3: A. Technology Classification | B3: A2 | C3: Secondary domains | D3: Cross-applicable technical areas the patent also touches. | E3: Comma-separated tags | F3: Beamforming, MIMO
A4: A. Technology Classification | B4: A3 | C4: Stack layer | D4: Horizontal layer of the technology stack. | E4: Hardware / Firmware / OS / Middleware / App / Cloud / UI | F4: Hardware
A5: A. Technology Classification | B5: A4 | C5: Product subsystem | D5: Which subsystem(s) of an end-product it covers. | E5: Free-text / list | F5: Battery management
A6: A. Technology Classification | B6: A5 | C6: Use-case | D6: Real-world problem(s) it solves. | E6: Free-text / list | F6: Indoor positioning
A7: B. Standards & Ecosystem | B7: B1 | C7: SEP potential | D7: Standard-essential potential. | E7: 0 (none) → 3 (declared/strong mapping) | F7: 3
A8: B. Standards & Ecosystem | B8: B2 | C8: Standard tagged | D8: Specific standard(s) the patent maps to. | E8: Categorical text | F8: 3GPP 5G NR
A9: B. Standards & Ecosystem | B9: B3 | C9: Interface role | D9: Role as an interoperability/interface technology. | E9: 0 (internal only) → 3 (mandatory interface) | F9: 2
A10: C. Claim & Scope | B10: C1 | C10: Claim type | D10: Dominant claim type. | E10: Apparatus / Method / System / CRM / Design | F10: Method
A11: C. Claim & Scope | B11: C2 | C11: Claim breadth | D11: How broad/foundational the independent claims are. | E11: 0 (narrow) → 3 (foundational/pioneer) | F11: 2
A12: C. Claim & Scope | B12: C3 | C12: Independent claim count | D12: Number of independent claims. | E12: Integer | F12: 3
... A41: I. Market/Buyer Signals | B41: I4 | C41: Workaround complexity | D41: Engineering effort needed for a competitor to design around the claims. | E41: 0 (trivial) → 3 (deep redesign) | F41: 3

Sheet Patent Portfolio
A1: Identification | C1: A. Technology Classification | H1: B. Standards | K1: C. Claim & Scope | O1: D. Detectability | R1: E. Family & Lifecycle | W1: F. Geographic | Z1: G. Strategic | AC1: H. Patent Quality & Vulnerability | AM1: I. Market/Buyer Signals
A2: Patent ID | B2: Title | C2: A1 Primary domain | D2: A2 Secondary domains | E2: A3 Stack layer | F2: A4 Subsystem | G2: A5 Use-case | H2: B1 SEP potential (0-3) | I2: B2 Standard | J2: B3 Interface role (0-3) | K2: C1 Claim type | L2: C2 Claim breadth (0-3) | M2: C3 Indep. claim count | N2: C4 Design-around diff. (0-3) | O2: D1 External detect. (0-3) | P2: D2 Teardown detect. (0-3) | Q2: D3 Reads-on-products (0-3) | R2: E1 Family size | S2: E2 Prosecution | T2: E3 Continuation | U2: E4 Remaining term (yrs) | V2: E5 Maint. status | W2: F1 Jurisdictions | X2: F2 Trilateral (Y/N) | Y2: F3 Major-market score (0-3) | Z2: G1 Convergence theme | AA2: G2 Generation | AB2: G3 Cross-industry (0-3) | AC2: H1 Claim strength (0-3) | AD2: H2 Prior-art exposure (0-3) | AE2: H3 Prosecution risk (0-3) | AF2: H4 Divided-infrgmnt (0-3) | AG2: H5 Fwd citations | AH2: H6 Bwd citations | AI2: H7 Lit/PTAB history | AJ2: H8 Chain-of-title | AK2: H9 EoU available | AL2: H10 Encumbrance | AM2: I1 Product-map conf. (0-3) | AN2: I2 Impl. maturity | AO2: I3 Adjacent re-read (0-3) | AP2: I4 Workaround complex. (0-3)
A3: P-001 | B3: Beamforming pilot signaling for 5G NR | C3: Wireless PHY | D3: MIMO, beamforming | E3: Hardware | F3: Radio frontend | G3: Cellular comms | H3: 3 | I3: 3GPP 5G NR | J3: 3 | K3: Method | L3: 2 | M3: 3 | N3: 3 | O3: 1 | P3: 3 | Q3: 3 | R3: 8 | S3: Granted | T3: Yes | U3: 14 | V3: Active | W3: US, EP, CN, JP, KR | X3: Yes | Y3: 3 | AA3: Current | AB3: 1 | AC3: 3 | AD3: 3 | AE3: 2 | AF3: 3 | AG3: 28 | AH3: 42 | AI3: Survived | AJ3: Clean | AK3: Full | AL3: None | AM3: 3 | AN3: Productized | AO3: 1 | AP3: 3
A4: P-002 | B4: Polar code decoder architecture | C4: Wireless PHY | D4: Error correction | E4: Hardware | F4: Baseband processor | G4: Cellular comms | H4: 3 | I4: 3GPP 5G NR | J4: 2 | K4: Apparatus | L4: 2 | M4: 2 | N4: 2 | O4: 0 | P4: 3 | Q4: 3 | R4: 5 | S4: Granted | T4: No | U4: 13 | V4: Active | W4: US, EP, CN, KR | X4: Yes | Y4: 3 | AA4: Current | AB4: 1 | AC4: 2 | AD4: 2 | AE4: 2 | AF4: 3 | AG4: 18 | AH4: 31 | AI4: None | AJ4: Clean | AK4: Partial | AL4: None | AM4: 3 | AN4: Productized | AO4: 1 | AP4: 2
A5: P-003 | B5: Adaptive Wi-Fi 7 channel sounding | C5: Wireless PHY | D5: OFDMA | E5: Firmware | F5: WLAN module | G5: Indoor connectivity | H5: 2 | I5: IEEE 802.11be | J5: 3 | K5: Method | L5: 1 | M5: 2 | N5: 2 | O5: 1 | P5: 2 | Q5: 2 | R5: 4 | S5: Mixed | T5: Yes | U5: 17 | V5: Active | W5: US, EP, CN | X5: Yes | Y5: 2 | AA5: Next-gen | AB5: 2 | AC5: 2 | AD5: 3 | AE5: 3 | AF5: 2 | AG5: 4 | AH5: 22 | AI5: None | AJ5: Clean | AK5: None | AL5: None | AM5: 2 | AN5: Prototyped | AO5: 2 | AP5: 2
A6: P-004 | B6: Solid-state electrolyte composition for EV batteries | C6: Battery materials | D6: Solid-state, ionics | E6: Hardware | F6: Battery cell | G6: EV propulsion | H6: 0 | J6: 0 | K6: Apparatus | L6: 3 | M6: 4 | N6: 3 | O6: 0 | P6: 3 | Q6: 2 | R6: 6 | S6: Granted | T6: Yes | U6: 17 | V6: Active | W6: US, EP, CN, JP, KR | X6: Yes | Y6: 3 | AA6: Next-gen | AB6: 2 | AC6: 3 | AD6: 3 | AE6: 3 | AF6: 3 | AG6: 35 | AH6: 48 | AI6: None | AJ6: Clean | AK6: Partial | AL6: None | AM6: 2 | AN6: Prototyped | AO6: 3 | AP6: 3
A7: P-005 | B7: Battery thermal management with phase-change material | C7: Thermal mgmt | D7: BMS, materials | E7: Hardware | F7: Battery pack | G7: EV propulsion | H7: 0 | J7: 1 | K7: System | L7: 2 | M7: 3 | N7: 2 | O7: 1 | P7: 3 | Q7: 2 | R7: 3 | S7: Granted | T7: No | U7: 11 | V7: Active | W7: US, EP, CN | X7: Yes | Y7: 2 | AA7: Current | AB7: 2 | AC7: 2 | AD7: 2 | AE7: 2 | AF7: 3 | AG7: 14 | AH7: 27 | AI7: None | AJ7: Clean | AK7: None | AL7: Non-exclusive licensed | AM7: 2 | AN7: Productized | AO7: 2 | AP7: 2
A8: P-006 | B8: SiC MOSFET inverter control method | C8: Power electronics | D8: Wide-bandgap | E8: Firmware | F8: Traction inverter | G8: EV propulsion | H8: 0 | J8: 1 | K8: Method | L8: 2 | M8: 2 | N8: 2 | O8: 1 | P8: 3 | Q8: 3 | R8: 4 | S8: Granted | T8: No | U8: 12 | V8: Active | W8: US, EP, CN, JP | X8: Yes | Y8: 3 | AA8: Current | AB8: 2 | AC8: 2 | AD8: 2 | AE8: 2 | AF8: 3 | AG8: 16 | AH8: 33 | AI8: None | AJ8: Minor gaps | AK8: Partial | AL8: None | AM8: 3 | AN8: Productized | AO8: 2 | AP8: 2
A9: P-007 | B9: On-device CNN quantization for low-power inference | C9: CV algorithm | D9: Edge AI, ML | E9: App | F9: Vision pipeline | G9: Smart cameras | H9: 0 | J9: 0 | K9: CRM | L9: 2 | M9: 3 | N9: 2 | O9: 2 | P9: 1 | Q9: 2 | R9: 5 | S9: Granted | T9: Yes | U9: 15 | V9: Active | W9: US, EP, CN | X9: Yes | Y9: 2 | Z9: Edge AI | AA9: Current | AB9: 3 | AC9: 2 | AD9: 1 | AE9: 2 | AF9: 2 | AG9: 47 | AH9: 26 | AI9: Pending | AJ9: Clean | AK9: Partial | AL9: None | AM9: 2 | AN9: Productized | AO9: 3 | AP9: 2
A10: P-008 | B10: Transformer attention pruning for vision models | C10: CV algorithm | D10: AI optimization | E10: App | F10: Inference engine | G10: Visual analytics | H10: 0 | J10: 0 | K10: Method | L10: 1 | M10: 2 | N10: 1 | O10: 2 | P10: 0 | Q10: 2 | R10: 3 | S10: Pending | T10: Yes | U10: 19 | V10: Active | W10: US, EP | X10: No | Y10: 1 | Z10: Edge AI, AI+health | AA10: Next-gen | AB10: 3 | AC10: 1 | AD10: 1 | AE10: 1 | AF10: 1 | AG10: 8 | AH10: 19 | AI10: None | AJ10: Clean | AK10: None | AL10: None | AM10: 1 | AN10: Idea-only | AO10: 3 | AP10: 1
A11: P-009 | B11: Visual SLAM for indoor robot navigation | C11: Robotics SW | D11: SLAM, CV | E11: Middleware | F11: Navigation stack | G11: Indoor positioning | H11: 0 | J11: 1 | K11: System | L11: 2 | M11: 2 | N11: 2 | O11: 2 | P11: 1 | Q11: 2 | R11: 4 | S11: Granted | T11: No | U11: 10 | V11: Active | W11: US, EP, JP | X11: Yes | Y11: 2 | Z11: Robotics, edge AI | AA11: Current | AB11: 3 | AC11: 2 | AD11: 2 | AE11: 2 | AF11: 2 | AG11: 22 | AH11: 34 | AI11: None | AJ11: Clean | AK11: Partial | AL11: None | AM11: 2 | AN11: Prototyped | AO11: 2 | AP11: 2
A12: P-010 | B12: USB-C power delivery handshake extension | C12: Interconnect | D12: Power delivery | E12: Firmware | F12: Charging interface | G12: Universal charging | H12: 2 | I12: USB PD 3.x | J12: 3 | K12: Method | L12: 1 | M12: 2 | N12: 2 | O12: 3 | P12: 3 | Q12: 3 | R12: 5 | S12: Granted | T12: No | U12: 9 | V12: Active | W12: US, EP, CN, JP, KR | X12: Yes | Y12: 3 | AA12: Current | AB12: 3 | AC12: 2 | AD12: 3 | AE12: 2 | AF12: 3 | AG12: 25 | AH12: 39 | AI12: Survived | AJ12: Clean | AK12: Full | AL12: None | AM12: 3 | AN12: Productized | AO12: 2 | AP12: 2
A13: P-011 | B13: Atomic layer deposition recipe for high-k dielectric | C13: Semiconductor process | D13: ALD, fab | E13: Hardware | F13: Front-end-of-line | G13: IC manufacturing | H13: 0 | J13: 1 | K13: Method | L13: 2 | M13: 3 | N13: 3 | O13: 0 | P13: 1 | Q13: 1 | R13: 6 | S13: Granted | T13: Yes | U13: 13 | V13: Active | W13: US, EP, CN, JP, KR, TW | X13: Yes | Y13: 3 | AA13: Current | AB13: 1 | AC13: 3 | AD13: 2 | AE13: 3 | AF13: 3 | AG13: 19 | AH13: 41 | AI13: None | AJ13: Clean | AK13: None | AL13: None | AM13: 1 | AN13: Productized | AO13: 1 | AP13: 3
A14: P-012 | B14: Predictive maintenance ML for industrial pumps | C14: Industrial AI | D14: Predictive analytics | E14: Cloud | F14: Asset monitoring | G14: Predictive maintenance | H14: 0 | J14: 1 | K14: CRM | L14: 1 | M14: 2 | N14: 1 | O14: 2 | P14: 0 | Q14: 1 | R14: 2 | S14: Granted | T14: No | U14: 8 | V14: Active | W14: US, EP | X14: No | Y14: 1 | Z14: AI+industrial | AA14: Current | AB14: 3 | AC14: 1 | AD14: 1 | AE14: 2 | AF14: 1 | AG14: 5 | AH14: 12 | AI14: None | AJ14: Minor gaps | AK14: None | AL14: None | AM14: 1 | AN14: Idea-only | AO14: 2 | AP14: 1

Sheet Bundle Rules
A1: # | B1: Bundle Type | C1: Value Proposition | D1: Routing Rule (technical qualification) | E1: Primary attributes used
A2: 1 | B2: Technology Domain | C2: Concentrated coverage in one technical field; useful for entering or fortifying a domain position. | D2: Patents share the same A1 (primary domain) tag. | E2: A1
A3: 2 | B3: Standard-Essential (SEP) | C3: Bundle of assets every implementer of the standard must license or design around. | D3: B1 ≥ 2 AND share same B2 standard. | E3: B1, B2
A4: 3 | B4: Product Architecture | C4: "Build a product" kit — full vertical coverage across subsystems of one end-product. | D4: Collectively span ≥ 3 distinct A4 subsystems of one product family. | E4: A4
A5: 4 | B5: Stack Layer | C5: Targets buyers operating at a specific layer of the technology stack. | D5: Patents share the same A3 (stack layer). | E5: A3
A6: 5 | B6: Use-Case / Application | C6: All tools to address one customer problem, even if underlying tech is heterogeneous. | D6: Patents share at least one A5 (use-case) tag. | E6: A5
A7: 6 | B7: Manufacturing / Process | C7: Targets fabs, contract manufacturers, equipment makers needing freedom to operate on production methods. | D7: A1 is a "process" / manufacturing domain (e.g., contains "process" or "fab") AND C1 = Method. | E7: A1, C1
A8: 7 | B8: Materials & Chemistry | C8: Focused IP shield around composition, synthesis, and use of a material system. | D8: A1 is a materials/chemistry domain AND C1 ∈ {Apparatus, Method}. | E8: A1, C1
A9: 8 | B9: Algorithm / Software Method | C9: Implementation-agnostic methods deployable across many products. | D9: A3 ∈ {App, Middleware, Cloud} AND C1 ∈ {Method, CRM}. | E9: A3, C1
A10: 9 | B10: Interoperability / Interface | C10: Critical chokepoints for any player whose product must talk to others. | D10: B3 ≥ 2. | E10: B3
A11: 10 | B11: Generational Roadmap | C11: Buyer picks legacy (cheap defensive) or next-gen (forward-looking offensive). | D11: Group by G2 (Legacy / Current / Next-gen). | E11: G2
A12: 11 | B12: Claim-Type | C12: Different enforcement profiles; buyers pick by litigation/licensing strategy. | D12: Group by C1. | E12: C1
A13: 12 | B13: Detectability | C13: Litigation-ready bundle — infringement is easy to spot. | D13: D1 ≥ 2 OR D2 ≥ 2. | E13: D1, D2
... A34: 33 | B34: Provenance-Coherent | C34: Patents originating from the same R&D program, inventor group, or acquired sub-business. Shared specifications and consistent terminology reduce claim-construction risk. | D34: Patents share A1 AND share A4 (proxy for common provenance in this template). | E34: A1, A4

Sheet Bundle Assignment
A1: Patent | C1: Bundle Qualification (TRUE = patent qualifies for this bundle) | AJ1: Total
A2: Patent ID | B2: Title | C2: B1 Tech Domain | D2: B2 SEP | E2: B3 Product Arch | F2: B4 Stack Layer | G2: B5 Use-Case | H2: B6 Mfg/Process | I2: B7 Materials | J2: B8 Algorithm | K2: B9 Interop | L2: B10 Generational | M2: B11 Claim-Type | N2: B12 Detectable | O2: B13 Geographic | P2: B14 Family | Q2: B15 Lifecycle | R2: B16 Foundational+Improvement | S2: B17 Cross-Industry | T2: B18 Convergent Theme | U2: B19 Defensive | V2: B20 Whitespace | W2: B21 Prosecution-Status | X2: B22 Anchor+Halo | Y2: B23 Picket-Fence | Z2: B24 Strong+Tail | AA2: B25 Continuation-Live | AB2: B26 EoU-Backed | AC2: B27 Battle-Tested | AD2: B28 Clean-Title | AE2: B29 High-Citation | AF2: B30 Adjacent Re-Read | AG2: B31 Salvage-Volume | AH2: B32 Pre-Expiry | AI2: B33 Provenance | AJ2: # of bundles
A3: ='Patent Portfolio'!A3 -> P-001 | B3: ='Patent Portfolio'!B3 -> Beamforming pilot signaling for 5G NR | C3: =IFERROR(IF('Patent Portfolio'!C3<>"",TRUE(),FALSE()),FALSE()) -> TRUE | D3: =IFERROR(IF(AND(N('Patent Portfolio'!H3)>=2,'Patent Portfolio'!I3<>""),TRUE(),FALSE()),FALSE()) -> TRUE | E3: =IFERROR(IF('Patent Portfolio'!F3<>"",TRUE(),FALSE()),FALSE()) -> TRUE | F3: =IFERROR(IF('Patent Portfolio'!E3<>"",TRUE(),FALSE()),FALSE()) -> TRUE | G3: =IFERROR(IF('Patent Portfolio'!G3<>"",TRUE(),FALSE()),FALSE()) -> TRUE | H3: =IFERROR(IF(AND(OR(ISNUMBER(SEARCH("process",'Patent Portfolio'!C3)),ISNUMBER(SEARCH("fab",'Patent Portfolio'!C3)),ISNUMBER(SEARCH("manufac",'Patent Portfolio'!C3))),'Patent Portfolio'!K3="Method"),TRUE(),FALSE()),FALSE()) -> FALSE | I3: =IFERROR(IF(AND(OR(ISNUMBER(SEARCH("material",'Patent Portfolio'!C3)),ISNUMBER(SEARCH("chem",'Patent Portfolio'!C3)),ISNUMBER(SEARCH("battery",'Patent Portfolio'!C3)),ISNUMBER(SEARCH("electrolyte",'Patent Portfolio'!C3)),ISNUMBER(SEARCH("polymer",'Patent Portfolio'!C3))),OR('Patent Portfolio'!K3="Apparatus",'Patent Portfolio'!K3="Method")),TRUE(),FALSE()),FALSE()) -> FALSE | J3: =IFERROR(IF(AND(OR('Patent Portfolio'!E3="App",'Patent Portfolio'!E3="Middleware",'Patent Portfolio'!E3="Cloud"),OR('Patent Portfolio'!K3="Method",'Patent Portfolio'!K3="CRM")),TRUE(),FALSE()),FALSE()) -> FALSE | K3: =IFERROR(IF(N('Patent Portfolio'!J3)>=2,TRUE(),FALSE()),FALSE()) -> TRUE | L3: =IFERROR(IF('Patent Portfolio'!AA3<>"",TRUE(),FALSE()),FALSE()) -> TRUE | M3: =IFERROR(IF('Patent Portfolio'!K3<>"",TRUE(),FALSE()),FALSE()) -> TRUE | N3: =IFERROR(IF(OR(N('Patent Portfolio'!O3)>=2,N('Patent Portfolio'!P3)>=2),TRUE(),FALSE()),FALSE()) -> TRUE | O3: =IFERROR(IF('Patent Portfolio'!X3="Yes",TRUE(),FALSE()),FALSE()) -> TRUE | P3: =IFERROR(IF(N('Patent Portfolio'!R3)>=2,TRUE(),FALSE()),FALSE()) -> TRUE | Q3: =IFERROR(IF(N('Patent Portfolio'!U3)>0,TRUE(),FALSE()),FALSE()) -> TRUE | R3: =IFERROR(IF(OR(N('Patent Portfolio'!L3)=3,N('Patent Portfolio'!L3)<=1),TRUE(),FALSE()),FALSE()) -> FALSE | S3: =IFERROR(IF(N('Patent Portfolio'!AB3)>=2,TRUE(),FALSE()),FALSE()) -> FALSE | T3: =IFERROR(IF('Patent Portfolio'!Z3<>"",TRUE(),FALSE()),FALSE()) -> FALSE | U3: =IFERROR(IF(N('Patent Portfolio'!Q3)>=2,TRUE(),FALSE()),FALSE()) -> TRUE | V3: =IFERROR(IF(AND(N('Patent Portfolio'!N3)>=2,'Patent Portfolio'!C3<>""),TRUE(),FALSE()),FALSE()) -> TRUE | W3: =IFERROR(IF(OR('Patent Portfolio'!S3="Pending",'Patent Portfolio'!T3="Yes"),TRUE(),FALSE()),FALSE()) -> TRUE | X3: =IFERROR(IF(AND(N('Patent Portfolio'!AC3)>=2,N('Patent Portfolio'!L3)>=1),TRUE(),FALSE()),FALSE()) -> TRUE | Y3: =IFERROR(IF(AND(N('Patent Portfolio'!N3)>=1,OR('Patent Portfolio'!C3<>"",'Patent Portfolio'!I3<>"")),TRUE(),FALSE()),FALSE()) -> TRUE | Z3: =IFERROR(IF('Patent Portfolio'!C3<>"",TRUE(),FALSE()),FALSE()) -> TRUE | AA3: =IFERROR(IF('Patent Portfolio'!T3="Yes",TRUE(),FALSE()),FALSE()) -> TRUE | AB3: =IFERROR(IF(OR('Patent Portfolio'!AK3="Partial",'Patent Portfolio'!AK3="Full"),TRUE(),FALSE()),FALSE()) -> TRUE | AC3: =IFERROR(IF('Patent Portfolio'!AI3="Survived",TRUE(),FALSE()),FALSE()) -> TRUE | AD3: =IFERROR(IF(AND('Patent Portfolio'!AJ3="Clean",'Patent Portfolio'!AL3="None"),TRUE(),FALSE()),FALSE()) -> TRUE | AE3: =IFERROR(IF(N('Patent Portfolio'!AG3)>=15,TRUE(),FALSE()),FALSE()) -> TRUE | AF3: =IFERROR(IF(AND(N('Patent Portfolio'!AO3)>=2,N('Patent Portfolio'!AB3)>=2),TRUE(),FALSE()),FALSE()) -> FALSE | AG3: =IFERROR(IF(OR(N('Patent Portfolio'!AC3)<=1,N('Patent Portfolio'!U3)<5,N('Patent Portfolio'!AD3)<=1),TRUE(),FALSE()),FALSE()) -> FALSE | AH3: =IFERROR(IF(AND(N('Patent Portfolio'!U3)>=1,N('Patent Portfolio'!U3)<=4),TRUE(),FALSE()),FALSE()) -> FALSE | AI3: =IFERROR(IF(AND('Patent Portfolio'!C3<>"",'Patent Portfolio'!F3<>""),TRUE(),FALSE()),FALSE()) -> TRUE | AJ3: =COUNTIF(C3:AI3,TRUE()) -> 24
A4: ='Patent Portfolio'!A4 -> P-002 | B4: ='Patent Portfolio'!B4 -> Polar code decoder architecture | C4: =IFERROR(IF('Patent Portfolio'!C4<>"",TRUE(),FALSE()),FALSE()) -> TRUE | D4: =IFERROR(IF(AND(N('Patent Portfolio'!H4)>=2,'Patent Portfolio'!I4<>""),TRUE(),FALSE()),FALSE()) -> TRUE | E4: =IFERROR(IF('Patent Portfolio'!F4<>"",TRUE(),FALSE()),FALSE()) -> TRUE | F4: =IFERROR(IF('Patent Portfolio'!E4<>"",TRUE(),FALSE()),FALSE()) -> TRUE | G4: =IFERROR(IF('Patent Portfolio'!G4<>"",TRUE(),FALSE()),FALSE()) -> TRUE | H4: =IFERROR(IF(AND(OR(ISNUMBER(SEARCH("process",'Patent Portfolio'!C4)),ISNUMBER(SEARCH("fab",'Patent Portfolio'!C4)),ISNUMBER(SEARCH("manufac",'Patent Portfolio'!C4))),'Patent Portfolio'!K4="Method"),TRUE(),FALSE()),FALSE()) -> FALSE | I4: =IFERROR(IF(AND(OR(ISNUMBER(SEARCH("material",'Patent Portfolio'!C4)),ISNUMBER(SEARCH("chem",'Patent Portfolio'!C4)),ISNUMBER(SEARCH("battery",'Patent Portfolio'!C4)),ISNUMBER(SEARCH("electrolyte",'Patent Portfolio'!C4)),ISNUMBER(SEARCH("polymer",'Patent Portfolio'!C4))),OR('Patent Portfolio'!K4="Apparatus",'Patent Portfolio'!K4="Method")),TRUE(),FALSE()),FALSE()) -> FALSE | J4: =IFERROR(IF(AND(OR('Patent Portfolio'!E4="App",'Patent Portfolio'!E4="Middleware",'Patent Portfolio'!E4="Cloud"),OR('Patent Portfolio'!K4="Method",'Patent Portfolio'!K4="CRM")),TRUE(),FALSE()),FALSE()) -> FALSE | K4: =IFERROR(IF(N('Patent Portfolio'!J4)>=2,TRUE(),FALSE()),FALSE()) -> TRUE | L4: =IFERROR(IF('Patent Portfolio'!AA4<>"",TRUE(),FALSE()),FALSE()) -> TRUE | M4: =IFERROR(IF('Patent Portfolio'!K4<>"",TRUE(),FALSE()),FALSE()) -> TRUE | N4: =IFERROR(IF(OR(N('Patent Portfolio'!O4)>=2,N('Patent Portfolio'!P4)>=2),TRUE(),FALSE()),FALSE()) -> TRUE | O4: =IFERROR(IF('Patent Portfolio'!X4="Yes",TRUE(),FALSE()),FALSE()) -> TRUE | P4: =IFERROR(IF(N('Patent Portfolio'!R4)>=2,TRUE(),FALSE()),FALSE()) -> TRUE | Q4: =IFERROR(IF(N('Patent Portfolio'!U4)>0,TRUE(),FALSE()),FALSE()) -> TRUE | R4: =IFERROR(IF(OR(N('Patent Portfolio'!L4)=3,N('Patent Portfolio'!L4)<=1),TRUE(),FALSE()),FALSE()) -> FALSE | S4: =IFERROR(IF(N('Patent Portfolio'!AB4)>=2,TRUE(),FALSE()),FALSE()) -> FALSE | T4: =IFERROR(IF('Patent Portfolio'!Z4<>"",TRUE(),FALSE()),FALSE()) -> FALSE | U4: =IFERROR(IF(N('Patent Portfolio'!Q4)>=2,TRUE(),FALSE()),FALSE()) -> TRUE | V4: =IFERROR(IF(AND(N('Patent Portfolio'!N4)>=2,'Patent Portfolio'!C4<>""),TRUE(),FALSE()),FALSE()) -> TRUE | W4: =IFERROR(IF(OR('Patent Portfolio'!S4="Pending",'Patent Portfolio'!T4="Yes"),TRUE(),FALSE()),FALSE()) -> FALSE | X4: =IFERROR(IF(AND(N('Patent Portfolio'!AC4)>=2,N('Patent Portfolio'!L4)>=1),TRUE(),FALSE()),FALSE()) -> TRUE | Y4: =IFERROR(IF(AND(N('Patent Portfolio'!N4)>=1,OR('Patent Portfolio'!C4<>"",'Patent Portfolio'!I4<>"")),TRUE(),FALSE()),FALSE()) -> TRUE | Z4: =IFERROR(IF('Patent Portfolio'!C4<>"",TRUE(),FALSE()),FALSE()) -> TRUE | AA4: =IFERROR(IF('Patent Portfolio'!T4="Yes",TRUE(),FALSE()),FALSE()) -> FALSE | AB4: =IFERROR(IF(OR('Patent Portfolio'!AK4="Partial",'Patent Portfolio'!AK4="Full"),TRUE(),FALSE()),FALSE()) -> TRUE | AC4: =IFERROR(IF('Patent Portfolio'!AI4="Survived",TRUE(),FALSE()),FALSE()) -> FALSE | AD4: =IFERROR(IF(AND('Patent Portfolio'!AJ4="Clean",'Patent Portfolio'!AL4="None"),TRUE(),FALSE()),FALSE()) -> TRUE | AE4: =IFERROR(IF(N('Patent Portfolio'!AG4)>=15,TRUE(),FALSE()),FALSE()) -> TRUE | AF4: =IFERROR(IF(AND(N('Patent Portfolio'!AO4)>=2,N('Patent Portfolio'!AB4)>=2),TRUE(),FALSE()),FALSE()) -> FALSE | AG4: =IFERROR(IF(OR(N('Patent Portfolio'!AC4)<=1,N('Patent Portfolio'!U4)<5,N('Patent Portfolio'!AD4)<=1),TRUE(),FALSE()),FALSE()) -> FALSE | AH4: =IFERROR(IF(AND(N('Patent Portfolio'!U4)>=1,N('Patent Portfolio'!U4)<=4),TRUE(),FALSE()),FALSE()) -> FALSE | AI4: =IFERROR(IF(AND('Patent Portfolio'!C4<>"",'Patent Portfolio'!F4<>""),TRUE(),FALSE()),FALSE()) -> TRUE | AJ4: =COUNTIF(C4:AI4,TRUE()) -> 21
A5: ='Patent Portfolio'!A5 -> P-003 | B5: ='Patent Portfolio'!B5 -> Adaptive Wi-Fi 7 channel sounding | C5: =IFERROR(IF('Patent Portfolio'!C5<>"",TRUE(),FALSE()),FALSE()) -> TRUE | D5: =IFERROR(IF(AND(N('Patent Portfolio'!H5)>=2,'Patent Portfolio'!I5<>""),TRUE(),FALSE()),FALSE()) -> TRUE | E5: =IFERROR(IF('Patent Portfolio'!F5<>"",TRUE(),FALSE()),FALSE()) -> TRUE | F5: =IFERROR(IF('Patent Portfolio'!E5<>"",TRUE(),FALSE()),FALSE()) -> TRUE | G5: =IFERROR(IF('Patent Portfolio'!G5<>"",TRUE(),FALSE()),FALSE()) -> TRUE | H5: =IFERROR(IF(AND(OR(ISNUMBER(SEARCH("process",'Patent Portfolio'!C5)),ISNUMBER(SEARCH("fab",'Patent Portfolio'!C5)),ISNUMBER(SEARCH("manufac",'Patent Portfolio'!C5))),'Patent Portfolio'!K5="Method"),TRUE(),FALSE()),FALSE()) -> FALSE | I5: =IFERROR(IF(AND(OR(ISNUMBER(SEARCH("material",'Patent Portfolio'!C5)),ISNUMBER(SEARCH("chem",'Patent Portfolio'!C5)),ISNUMBER(SEARCH("battery",'Patent Portfolio'!C5)),ISNUMBER(SEARCH("electrolyte",'Patent Portfolio'!C5)),ISNUMBER(SEARCH("polymer",'Patent Portfolio'!C5))),OR('Patent Portfolio'!K5="Apparatus",'Patent Portfolio'!K5="Method")),TRUE(),FALSE()),FALSE()) -> FALSE | J5: =IFERROR(IF(AND(OR('Patent Portfolio'!E5="App",'Patent Portfolio'!E5="Middleware",'Patent Portfolio'!E5="Cloud"),OR('Patent Portfolio'!K5="Method",'Patent Portfolio'!K5="CRM")),TRUE(),FALSE()),FALSE()) -> FALSE | K5: =IFERROR(IF(N('Patent Portfolio'!J5)>=2,TRUE(),FALSE()),FALSE()) -> TRUE | L5: =IFERROR(IF('Patent Portfolio'!AA5<>"",TRUE(),FALSE()),FALSE()) -> TRUE | M5: =IFERROR(IF('Patent Portfolio'!K5<>"",TRUE(),FALSE()),FALSE()) -> TRUE | N5: =IFERROR(IF(OR(N('Patent Portfolio'!O5)>=2,N('Patent Portfolio'!P5)>=2),TRUE(),FALSE()),FALSE()) -> TRUE | O5: =IFERROR(IF('Patent Portfolio'!X5="Yes",TRUE(),FALSE()),FALSE()) -> TRUE | P5: =IFERROR(IF(N('Patent Portfolio'!R5)>=2,TRUE(),FALSE()),FALSE()) -> TRUE | Q5: =IFERROR(IF(N('Patent Portfolio'!U5)>0,TRUE(),FALSE()),FALSE()) -> TRUE | R5: =IFERROR(IF(OR(N('Patent Portfolio'!L5)=3,N('Patent Portfolio'!L5)<=1),TRUE(),FALSE()),FALSE()) -> TRUE | S5: =IFERROR(IF(N('Patent Portfolio'!AB5)>=2,TRUE(),FALSE()),FALSE()) -> TRUE | T5: =IFERROR(IF('Patent Portfolio'!Z5<>"",TRUE(),FALSE()),FALSE()) -> FALSE | U5: =IFERROR(IF(N('Patent Portfolio'!Q5)>=2,TRUE(),FALSE()),FALSE()) -> TRUE | V5: =IFERROR(IF(AND(N('Patent Portfolio'!N5)>=2,'Patent Portfolio'!C5<>""),TRUE(),FALSE()),FALSE()) -> TRUE | W5: =IFERROR(IF(OR('Patent Portfolio'!S5="Pending",'Patent Portfolio'!T5="Yes"),TRUE(),FALSE()),FALSE()) -> TRUE | X5: =IFERROR(IF(AND(N('Patent Portfolio'!AC5)>=2,N('Patent Portfolio'!L5)>=1),TRUE(),FALSE()),FALSE()) -> TRUE | Y5: =IFERROR(IF(AND(N('Patent Portfolio'!N5)>=1,OR('Patent Portfolio'!C5<>"",'Patent Portfolio'!I5<>"")),TRUE(),FALSE()),FALSE()) -> TRUE | Z5: =IFERROR(IF('Patent Portfolio'!C5<>"",TRUE(),FALSE()),FALSE()) -> TRUE | AA5: =IFERROR(IF('Patent Portfolio'!T5="Yes",TRUE(),FALSE()),FALSE()) -> TRUE | AB5: =IFERROR(IF(OR('Patent Portfolio'!AK5="Partial",'Patent Portfolio'!AK5="Full"),TRUE(),FALSE()),FALSE()) -> FALSE | AC5: =IFERROR(IF('Patent Portfolio'!AI5="Survived",TRUE(),FALSE()),FALSE()) -> FALSE | AD5: =IFERROR(IF(AND('Patent Portfolio'!AJ5="Clean",'Patent Portfolio'!AL5="None"),TRUE(),FALSE()),FALSE()) -> TRUE | AE5: =IFERROR(IF(N('Patent Portfolio'!AG5)>=15,TRUE(),FALSE()),FALSE()) -> FALSE | AF5: =IFERROR(IF(AND(N('Patent Portfolio'!AO5)>=2,N('Patent Portfolio'!AB5)>=2),TRUE(),FALSE()),FALSE()) -> TRUE | AG5: =IFERROR(IF(OR(N('Patent Portfolio'!AC5)<=1,N('Patent Portfolio'!U5)<5,N('Patent Portfolio'!AD5)<=1),TRUE(),FALSE()),FALSE()) -> FALSE | AH5: =IFERROR(IF(AND(N('Patent Portfolio'!U5)>=1,N('Patent Portfolio'!U5)<=4),TRUE(),FALSE()),FALSE()) -> FALSE | AI5: =IFERROR(IF(AND('Patent Portfolio'!C5<>"",'Patent Portfolio'!F5<>""),TRUE(),FALSE()),FALSE()) -> TRUE | AJ5: =COUNTIF(C5:AI5,TRUE()) -> 24
A6: ='Patent Portfolio'!A6 -> P-004 | B6: ='Patent Portfolio'!B6 -> Solid-state electrolyte composition for EV batteries | C6: =IFERROR(IF('Patent Portfolio'!C6<>"",TRUE(),FALSE()),FALSE()) -> TRUE | D6: =IFERROR(IF(AND(N('Patent Portfolio'!H6)>=2,'Patent Portfolio'!I6<>""),TRUE(),FALSE()),FALSE()) -> FALSE | E6: =IFERROR(IF('Patent Portfolio'!F6<>"",TRUE(),FALSE()),FALSE()) -> TRUE | F6: =IFERROR(IF('Patent Portfolio'!E6<>"",TRUE(),FALSE()),FALSE()) -> TRUE | G6: =IFERROR(IF('Patent Portfolio'!G6<>"",TRUE(),FALSE()),FALSE()) -> TRUE | H6: =IFERROR(IF(AND(OR(ISNUMBER(SEARCH("process",'Patent Portfolio'!C6)),ISNUMBER(SEARCH("fab",'Patent Portfolio'!C6)),ISNUMBER(SEARCH("manufac",'Patent Portfolio'!C6))),'Patent Portfolio'!K6="Method"),TRUE(),FALSE()),FALSE()) -> FALSE | I6: =IFERROR(IF(AND(OR(ISNUMBER(SEARCH("material",'Patent Portfolio'!C6)),ISNUMBER(SEARCH("chem",'Patent Portfolio'!C6)),ISNUMBER(SEARCH("battery",'Patent Portfolio'!C6)),ISNUMBER(SEARCH("electrolyte",'Patent Portfolio'!C6)),ISNUMBER(SEARCH("polymer",'Patent Portfolio'!C6))),OR('Patent Portfolio'!K6="Apparatus",'Patent Portfolio'!K6="Method")),TRUE(),FALSE()),FALSE()) -> TRUE | J6: =IFERROR(IF(AND(OR('Patent Portfolio'!E6="App",'Patent Portfolio'!E6="Middleware",'Patent Portfolio'!E6="Cloud"),OR('Patent Portfolio'!K6="Method",'Patent Portfolio'!K6="CRM")),TRUE(),FALSE()),FALSE()) -> FALSE | K6: =IFERROR(IF(N('Patent Portfolio'!J6)>=2,TRUE(),FALSE()),FALSE()) -> FALSE | L6: =IFERROR(IF('Patent Portfolio'!AA6<>"",TRUE(),FALSE()),FALSE()) -> TRUE | M6: =IFERROR(IF('Patent Portfolio'!K6<>"",TRUE(),FALSE()),FALSE()) -> TRUE | N6: =IFERROR(IF(OR(N('Patent Portfolio'!O6)>=2,N('Patent Portfolio'!P6)>=2),TRUE(),FALSE()),FALSE()) -> TRUE | O6: =IFERROR(IF('Patent Portfolio'!X6="Yes",TRUE(),FALSE()),FALSE()) -> TRUE | P6: =IFERROR(IF(N('Patent Portfolio'!R6)>=2,TRUE(),FALSE()),FALSE()) -> TRUE | Q6: =IFERROR(IF(N('Patent Portfolio'!U6)>0,TRUE(),FALSE()),FALSE()) -> TRUE | R6: =IFERROR(IF(OR(N('Patent Portfolio'!L6)=3,N('Patent Portfolio'!L6)<=1),TRUE(),FALSE()),FALSE()) -> TRUE | S6: =IFERROR(IF(N('Patent Portfolio'!AB6)>=2,TRUE(),FALSE()),FALSE()) -> TRUE | T6: =IFERROR(IF('Patent Portfolio'!Z6<>"",TRUE(),FALSE()),FALSE()) -> FALSE | U6: =IFERROR(IF(N('Patent Portfolio'!Q6)>=2,TRUE(),FALSE()),FALSE()) -> TRUE | V6: =IFERROR(IF(AND(N('Patent Portfolio'!N6)>=2,'Patent Portfolio'!C6<>""),TRUE(),FALSE()),FALSE()) -> TRUE | W6: =IFERROR(IF(OR('Patent Portfolio'!S6="Pending",'Patent Portfolio'!T6="Yes"),TRUE(),FALSE()),FALSE()) -> TRUE | X6: =IFERROR(IF(AND(N('Patent Portfolio'!AC6)>=2,N('Patent Portfolio'!L6)>=1),TRUE(),FALSE()),FALSE()) -> TRUE | Y6: =IFERROR(IF(AND(N('Patent Portfolio'!N6)>=1,OR('Patent Portfolio'!C6<>"",'Patent Portfolio'!I6<>"")),TRUE(),FALSE()),FALSE()) -> TRUE | Z6: =IFERROR(IF('Patent Portfolio'!C6<>"",TRUE(),FALSE()),FALSE()) -> TRUE | AA6: =IFERROR(IF('Patent Portfolio'!T6="Yes",TRUE(),FALSE()),FALSE()) -> TRUE | AB6: =IFERROR(IF(OR('Patent Portfolio'!AK6="Partial",'Patent Portfolio'!AK6="Full"),TRUE(),FALSE()),FALSE()) -> TRUE | AC6: =IFERROR(IF('Patent Portfolio'!AI6="Survived",TRUE(),FALSE()),FALSE()) -> FALSE | AD6: =IFERROR(IF(AND('Patent Portfolio'!AJ6="Clean",'Patent Portfolio'!AL6="None"),TRUE(),FALSE()),FALSE()) -> TRUE | AE6: =IFERROR(IF(N('Patent Portfolio'!AG6)>=15,TRUE(),FALSE()),FALSE()) -> TRUE | AF6: =IFERROR(IF(AND(N('Patent Portfolio'!AO6)>=2,N('Patent Portfolio'!AB6)>=2),TRUE(),FALSE()),FALSE()) -> TRUE | AG6: =IFERROR(IF(OR(N('Patent Portfolio'!AC6)<=1,N('Patent Portfolio'!U6)<5,N('Patent Portfolio'!AD6)<=1),TRUE(),FALSE()),FALSE()) -> FALSE | AH6: =IFERROR(IF(AND(N('Patent Portfolio'!U6)>=1,N('Patent Portfolio'!U6)<=4),TRUE(),FALSE()),FALSE()) -> FALSE | AI6: =IFERROR(IF(AND('Patent Portfolio'!C6<>"",'Patent Portfolio'!F6<>""),TRUE(),FALSE()),FALSE()) -> TRUE | AJ6: =COUNTIF(C6:AI6,TRUE()) -> 25
A7: ='Patent Portfolio'!A7 -> P-005 | B7: ='Patent Portfolio'!B7 -> Battery thermal management with phase-change material | C7: =IFERROR(IF('Patent Portfolio'!C7<>"",TRUE(),FALSE()),FALSE()) -> TRUE | D7: =IFERROR(IF(AND(N('Patent Portfolio'!H7)>=2,'Patent Portfolio'!I7<>""),TRUE(),FALSE()),FALSE()) -> FALSE | E7: =IFERROR(IF('Patent Portfolio'!F7<>"",TRUE(),FALSE()),FALSE()) -> TRUE | F7: =IFERROR(IF('Patent Portfolio'!E7<>"",TRUE(),FALSE()),FALSE()) -> TRUE | G7: =IFERROR(IF('Patent Portfolio'!G7<>"",TRUE(),FALSE()),FALSE()) -> TRUE | H7: =IFERROR(IF(AND(OR(ISNUMBER(SEARCH("process",'Patent Portfolio'!C7)),ISNUMBER(SEARCH("fab",'Patent Portfolio'!C7)),ISNUMBER(SEARCH("manufac",'Patent Portfolio'!C7))),'Patent Portfolio'!K7="Method"),TRUE(),FALSE()),FALSE()) -> FALSE | I7: =IFERROR(IF(AND(OR(ISNUMBER(SEARCH("material",'Patent Portfolio'!C7)),ISNUMBER(SEARCH("chem",'Patent Portfolio'!C7)),ISNUMBER(SEARCH("battery",'Patent Portfolio'!C7)),ISNUMBER(SEARCH("electrolyte",'Patent Portfolio'!C7)),ISNUMBER(SEARCH("polymer",'Patent Portfolio'!C7))),OR('Patent Portfolio'!K7="Apparatus",'Patent Portfolio'!K7="Method")),TRUE(),FALSE()),FALSE()) -> FALSE | J7: =IFERROR(IF(AND(OR('Patent Portfolio'!E7="App",'Patent Portfolio'!E7="Middleware",'Patent Portfolio'!E7="Cloud"),OR('Patent Portfolio'!K7="Method",'Patent Portfolio'!K7="CRM")),TRUE(),FALSE()),FALSE()) -> FALSE | K7: =IFERROR(IF(N('Patent Portfolio'!J7)>=2,TRUE(),FALSE()),FALSE()) -> FALSE | L7: =IFERROR(IF('Patent Portfolio'!AA7<>"",TRUE(),FALSE()),FALSE()) -> TRUE | M7: =IFERROR(IF('Patent Portfolio'!K7<>"",TRUE(),FALSE()),FALSE()) -> TRUE | N7: =IFERROR(IF(OR(N('Patent Portfolio'!O7)>=2,N('Patent Portfolio'!P7)>=2),TRUE(),FALSE()),FALSE()) -> TRUE | O7: =IFERROR(IF('Patent Portfolio'!X7="Yes",TRUE(),FALSE()),FALSE()) -> TRUE | P7: =IFERROR(IF(N('Patent Portfolio'!R7)>=2,TRUE(),FALSE()),FALSE()) -> TRUE | Q7: =IFERROR(IF(N('Patent Portfolio'!U7)>0,TRUE(),FALSE()),FALSE()) -> TRUE | R7: =IFERROR(IF(OR(N('Patent Portfolio'!L7)=3,N('Patent Portfolio'!L7)<=1),TRUE(),FALSE()),FALSE()) -> FALSE | S7: =IFERROR(IF(N('Patent Portfolio'!AB7)>=2,TRUE(),FALSE()),FALSE()) -> TRUE | T7: =IFERROR(IF('Patent Portfolio'!Z7<>"",TRUE(),FALSE()),FALSE()) -> FALSE | U7: =IFERROR(IF(N('Patent Portfolio'!Q7)>=2,TRUE(),FALSE()),FALSE()) -> TRUE | V7: =IFERROR(IF(AND(N('Patent Portfolio'!N7)>=2,'Patent Portfolio'!C7<>""),TRUE(),FALSE()),FALSE()) -> TRUE | W7: =IFERROR(IF(OR('Patent Portfolio'!S7="Pending",'Patent Portfolio'!T7="Yes"),TRUE(),FALSE()),FALSE()) -> FALSE | X7: =IFERROR(IF(AND(N('Patent Portfolio'!AC7)>=2,N('Patent Portfolio'!L7)>=1),TRUE(),FALSE()),FALSE()) -> TRUE | Y7: =IFERROR(IF(AND(N('Patent Portfolio'!N7)>=1,OR('Patent Portfolio'!C7<>"",'Patent Portfolio'!I7<>"")),TRUE(),FALSE()),FALSE()) -> TRUE | Z7: =IFERROR(IF('Patent Portfolio'!C7<>"",TRUE(),FALSE()),FALSE()) -> TRUE | AA7: =IFERROR(IF('Patent Portfolio'!T7="Yes",TRUE(),FALSE()),FALSE()) -> FALSE | AB7: =IFERROR(IF(OR('Patent Portfolio'!AK7="Partial",'Patent Portfolio'!AK7="Full"),TRUE(),FALSE()),FALSE()) -> FALSE | AC7: =IFERROR(IF('Patent Portfolio'!AI7="Survived",TRUE(),FALSE()),FALSE()) -> FALSE | AD7: =IFERROR(IF(AND('Patent Portfolio'!AJ7="Clean",'Patent Portfolio'!AL7="None"),TRUE(),FALSE()),FALSE()) -> FALSE | AE7: =IFERROR(IF(N('Patent Portfolio'!AG7)>=15,TRUE(),FALSE()),FALSE()) -> FALSE | AF7: =IFERROR(IF(AND(N('Patent Portfolio'!AO7)>=2,N('Patent Portfolio'!AB7)>=2),TRUE(),FALSE()),FALSE()) -> TRUE | AG7: =IFERROR(IF(OR(N('Patent Portfolio'!AC7)<=1,N('Patent Portfolio'!U7)<5,N('Patent Portfolio'!AD7)<=1),TRUE(),FALSE()),FALSE()) -> FALSE | AH7: =IFERROR(IF(AND(N('Patent Portfolio'!U7)>=1,N('Patent Portfolio'!U7)<=4),TRUE(),FALSE()),FALSE()) -> FALSE | AI7: =IFERROR(IF(AND('Patent Portfolio'!C7<>"",'Patent Portfolio'!F7<>""),TRUE(),FALSE()),FALSE()) -> TRUE | AJ7: =COUNTIF(C7:AI7,TRUE()) -> 18
A8: ='Patent Portfolio'!A8 -> P-006 | B8: ='Patent Portfolio'!B8 -> SiC MOSFET inverter control method | C8: =IFERROR(IF('Patent Portfolio'!C8<>"",TRUE(),FALSE()),FALSE()) -> TRUE | D8: =IFERROR(IF(AND(N('Patent Portfolio'!H8)>=2,'Patent Portfolio'!I8<>""),TRUE(),FALSE()),FALSE()) -> FALSE | E8: =IFERROR(IF('Patent Portfolio'!F8<>"",TRUE(),FALSE()),FALSE()) -> TRUE | F8: =IFERROR(IF('Patent Portfolio'!E8<>"",TRUE(),FALSE()),FALSE()) -> TRUE | G8: =IFERROR(IF('Patent Portfolio'!G8<>"",TRUE(),FALSE()),FALSE()) -> TRUE | H8: =IFERROR(IF(AND(OR(ISNUMBER(SEARCH("process",'Patent Portfolio'!C8)),ISNUMBER(SEARCH("fab",'Patent Portfolio'!C8)),ISNUMBER(SEARCH("manufac",'Patent Portfolio'!C8))),'Patent Portfolio'!K8="Method"),TRUE(),FALSE()),FALSE()) -> FALSE | I8: =IFERROR(IF(AND(OR(ISNUMBER(SEARCH("material",'Patent Portfolio'!C8)),ISNUMBER(SEARCH("chem",'Patent Portfolio'!C8)),ISNUMBER(SEARCH("battery",'Patent Portfolio'!C8)),ISNUMBER(SEARCH("electrolyte",'Patent Portfolio'!C8)),ISNUMBER(SEARCH("polymer",'Patent Portfolio'!C8))),OR('Patent Portfolio'!K8="Apparatus",'Patent Portfolio'!K8="Method")),TRUE(),FALSE()),FALSE()) -> FALSE | J8: =IFERROR(IF(AND(OR('Patent Portfolio'!E8="App",'Patent Portfolio'!E8="Middleware",'Patent Portfolio'!E8="Cloud"),OR('Patent Portfolio'!K8="Method",'Patent Portfolio'!K8="CRM")),TRUE(),FALSE()),FALSE()) -> FALSE | K8: =IFERROR(IF(N('Patent Portfolio'!J8)>=2,TRUE(),FALSE()),FALSE()) -> FALSE | L8: =IFERROR(IF('Patent Portfolio'!AA8<>"",TRUE(),FALSE()),FALSE()) -> TRUE | M8: =IFERROR(IF('Patent Portfolio'!K8<>"",TRUE(),FALSE()),FALSE()) -> TRUE | N8: =IFERROR(IF(OR(N('Patent Portfolio'!O8)>=2,N('Patent Portfolio'!P8)>=2),TRUE(),FALSE()),FALSE()) -> TRUE | O8: =IFERROR(IF('Patent Portfolio'!X8="Yes",TRUE(),FALSE()),FALSE()) -> TRUE | P8: =IFERROR(IF(N('Patent Portfolio'!R8)>=2,TRUE(),FALSE()),FALSE()) -> TRUE | Q8: =IFERROR(IF(N('Patent Portfolio'!U8)>0,TRUE(),FALSE()),FALSE()) -> TRUE | R8: =IFERROR(IF(OR(N('Patent Portfolio'!L8)=3,N('Patent Portfolio'!L8)<=1),TRUE(),FALSE()),FALSE()) -> FALSE | S8: =IFERROR(IF(N('Patent Portfolio'!AB8)>=2,TRUE(),FALSE()),FALSE()) -> TRUE | T8: =IFERROR(IF('Patent Portfolio'!Z8<>"",TRUE(),FALSE()),FALSE()) -> FALSE | U8: =IFERROR(IF(N('Patent Portfolio'!Q8)>=2,TRUE(),FALSE()),FALSE()) -> TRUE | V8: =IFERROR(IF(AND(N('Patent Portfolio'!N8)>=2,'Patent Portfolio'!C8<>""),TRUE(),FALSE()),FALSE()) -> TRUE | W8: =IFERROR(IF(OR('Patent Portfolio'!S8="Pending",'Patent Portfolio'!T8="Yes"),TRUE(),FALSE()),FALSE()) -> FALSE | X8: =IFERROR(IF(AND(N('Patent Portfolio'!AC8)>=2,N('Patent Portfolio'!L8)>=1),TRUE(),FALSE()),FALSE()) -> TRUE | Y8: =IFERROR(IF(AND(N('Patent Portfolio'!N8)>=1,OR('Patent Portfolio'!C8<>"",'Patent Portfolio'!I8<>"")),TRUE(),FALSE()),FALSE()) -> TRUE | Z8: =IFERROR(IF('Patent Portfolio'!C8<>"",TRUE(),FALSE()),FALSE()) -> TRUE | AA8: =IFERROR(IF('Patent Portfolio'!T8="Yes",TRUE(),FALSE()),FALSE()) -> FALSE | AB8: =IFERROR(IF(OR('Patent Portfolio'!AK8="Partial",'Patent Portfolio'!AK8="Full"),TRUE(),FALSE()),FALSE()) -> TRUE | AC8: =IFERROR(IF('Patent Portfolio'!AI8="Survived",TRUE(),FALSE()),FALSE()) -> FALSE | AD8: =IFERROR(IF(AND('Patent Portfolio'!AJ8="Clean",'Patent Portfolio'!AL8="None"),TRUE(),FALSE()),FALSE()) -> FALSE | AE8: =IFERROR(IF(N('Patent Portfolio'!AG8)>=15,TRUE(),FALSE()),FALSE()) -> TRUE | AF8: =IFERROR(IF(AND(N('Patent Portfolio'!AO8)>=2,N('Patent Portfolio'!AB8)>=2),TRUE(),FALSE()),FALSE()) -> TRUE | AG8: =IFERROR(IF(OR(N('Patent Portfolio'!AC8)<=1,N('Patent Portfolio'!U8)<5,N('Patent Portfolio'!AD8)<=1),TRUE(),FALSE()),FALSE()) -> FALSE | AH8: =IFERROR(IF(AND(N('Patent Portfolio'!U8)>=1,N('Patent Portfolio'!U8)<=4),TRUE(),FALSE()),FALSE()) -> FALSE | AI8: =IFERROR(IF(AND('Patent Portfolio'!C8<>"",'Patent Portfolio'!F8<>""),TRUE(),FALSE()),FALSE()) -> TRUE | AJ8: =COUNTIF(C8:AI8,TRUE()) -> 20
A9: ='Patent Portfolio'!A9 -> P-007 | B9: ='Patent Portfolio'!B9 -> On-device CNN quantization for low-power inference | C9: =IFERROR(IF('Patent Portfolio'!C9<>"",TRUE(),FALSE()),FALSE()) -> TRUE | D9: =IFERROR(IF(AND(N('Patent Portfolio'!H9)>=2,'Patent Portfolio'!I9<>""),TRUE(),FALSE()),FALSE()) -> FALSE | E9: =IFERROR(IF('Patent Portfolio'!F9<>"",TRUE(),FALSE()),FALSE()) -> TRUE | F9: =IFERROR(IF('Patent Portfolio'!E9<>"",TRUE(),FALSE()),FALSE()) -> TRUE | G9: =IFERROR(IF('Patent Portfolio'!G9<>"",TRUE(),FALSE()),FALSE()) -> TRUE | H9: =IFERROR(IF(AND(OR(ISNUMBER(SEARCH("process",'Patent Portfolio'!C9)),ISNUMBER(SEARCH("fab",'Patent Portfolio'!C9)),ISNUMBER(SEARCH("manufac",'Patent Portfolio'!C9))),'Patent Portfolio'!K9="Method"),TRUE(),FALSE()),FALSE()) -> FALSE | I9: =IFERROR(IF(AND(OR(ISNUMBER(SEARCH("material",'Patent Portfolio'!C9)),ISNUMBER(SEARCH("chem",'Patent Portfolio'!C9)),ISNUMBER(SEARCH("battery",'Patent Portfolio'!C9)),ISNUMBER(SEARCH("electrolyte",'Patent Portfolio'!C9)),ISNUMBER(SEARCH("polymer",'Patent Portfolio'!C9))),OR('Patent Portfolio'!K9="Apparatus",'Patent Portfolio'!K9="Method")),TRUE(),FALSE()),FALSE()) -> FALSE | J9: =IFERROR(IF(AND(OR('Patent Portfolio'!E9="App",'Patent Portfolio'!E9="Middleware",'Patent Portfolio'!E9="Cloud"),OR('Patent Portfolio'!K9="Method",'Patent Portfolio'!K9="CRM")),TRUE(),FALSE()),FALSE()) -> TRUE | K9: =IFERROR(IF(N('Patent Portfolio'!J9)>=2,TRUE(),FALSE()),FALSE()) -> FALSE | L9: =IFERROR(IF('Patent Portfolio'!AA9<>"",TRUE(),FALSE()),FALSE()) -> TRUE | M9: =IFERROR(IF('Patent Portfolio'!K9<>"",TRUE(),FALSE()),FALSE()) -> TRUE | N9: =IFERROR(IF(OR(N('Patent Portfolio'!O9)>=2,N('Patent Portfolio'!P9)>=2),TRUE(),FALSE()),FALSE()) -> TRUE | O9: =IFERROR(IF('Patent Portfolio'!X9="Yes",TRUE(),FALSE()),FALSE()) -> TRUE | P9: =IFERROR(IF(N('Patent Portfolio'!R9)>=2,TRUE(),FALSE()),FALSE()) -> TRUE | Q9: =IFERROR(IF(N('Patent Portfolio'!U9)>0,TRUE(),FALSE()),FALSE()) -> TRUE | R9: =IFERROR(IF(OR(N('Patent Portfolio'!L9)=3,N('Patent Portfolio'!L9)<=1),TRUE(),FALSE()),FALSE()) -> FALSE | S9: =IFERROR(IF(N('Patent Portfolio'!AB9)>=2,TRUE(),FALSE()),FALSE()) -> TRUE | T9: =IFERROR(IF('Patent Portfolio'!Z9<>"",TRUE(),FALSE()),FALSE()) -> TRUE | U9: =IFERROR(IF(N('Patent Portfolio'!Q9)>=2,TRUE(),FALSE()),FALSE()) -> TRUE | V9: =IFERROR(IF(AND(N('Patent Portfolio'!N9)>=2,'Patent Portfolio'!C9<>""),TRUE(),FALSE()),FALSE()) -> TRUE | W9: =IFERROR(IF(OR('Patent Portfolio'!S9="Pending",'Patent Portfolio'!T9="Yes"),TRUE(),FALSE()),FALSE()) -> TRUE | X9: =IFERROR(IF(AND(N('Patent Portfolio'!AC9)>=2,N('Patent Portfolio'!L9)>=1),TRUE(),FALSE()),FALSE()) -> TRUE | Y9: =IFERROR(IF(AND(N('Patent Portfolio'!N9)>=1,OR('Patent Portfolio'!C9<>"",'Patent Portfolio'!I9<>"")),TRUE(),FALSE()),FALSE()) -> TRUE | Z9: =IFERROR(IF('Patent Portfolio'!C9<>"",TRUE(),FALSE()),FALSE()) -> TRUE | AA9: =IFERROR(IF('Patent Portfolio'!T9="Yes",TRUE(),FALSE()),FALSE()) -> TRUE | AB9: =IFERROR(IF(OR('Patent Portfolio'!AK9="Partial",'Patent Portfolio'!AK9="Full"),TRUE(),FALSE()),FALSE()) -> TRUE | AC9: =IFERROR(IF('Patent Portfolio'!AI9="Survived",TRUE(),FALSE()),FALSE()) -> FALSE | AD9: =IFERROR(IF(AND('Patent Portfolio'!AJ9="Clean",'Patent Portfolio'!AL9="None"),TRUE(),FALSE()),FALSE()) -> TRUE | AE9: =IFERROR(IF(N('Patent Portfolio'!AG9)>=15,TRUE(),FALSE()),FALSE()) -> TRUE | AF9: =IFERROR(IF(AND(N('Patent Portfolio'!AO9)>=2,N('Patent Portfolio'!AB9)>=2),TRUE(),FALSE()),FALSE()) -> TRUE | AG9: =IFERROR(IF(OR(N('Patent Portfolio'!AC9)<=1,N('Patent Portfolio'!U9)<5,N('Patent Portfolio'!AD9)<=1),TRUE(),FALSE()),FALSE()) -> TRUE | AH9: =IFERROR(IF(AND(N('Patent Portfolio'!U9)>=1,N('Patent Portfolio'!U9)<=4),TRUE(),FALSE()),FALSE()) -> FALSE | AI9: =IFERROR(IF(AND('Patent Portfolio'!C9<>"",'Patent Portfolio'!F9<>""),TRUE(),FALSE()),FALSE()) -> TRUE | AJ9: =COUNTIF(C9:AI9,TRUE()) -> 26
A10: ='Patent Portfolio'!A10 -> P-008 | B10: ='Patent Portfolio'!B10 -> Transformer attention pruning for vision models | C10: =IFERROR(IF('Patent Portfolio'!C10<>"",TRUE(),FALSE()),FALSE()) -> TRUE | D10: =IFERROR(IF(AND(N('Patent Portfolio'!H10)>=2,'Patent Portfolio'!I10<>""),TRUE(),FALSE()),FALSE()) -> FALSE | E10: =IFERROR(IF('Patent Portfolio'!F10<>"",TRUE(),FALSE()),FALSE()) -> TRUE | F10: =IFERROR(IF('Patent Portfolio'!E10<>"",TRUE(),FALSE()),FALSE()) -> TRUE | G10: =IFERROR(IF('Patent Portfolio'!G10<>"",TRUE(),FALSE()),FALSE()) -> TRUE | H10: =IFERROR(IF(AND(OR(ISNUMBER(SEARCH("process",'Patent Portfolio'!C10)),ISNUMBER(SEARCH("fab",'Patent Portfolio'!C10)),ISNUMBER(SEARCH("manufac",'Patent Portfolio'!C10))),'Patent Portfolio'!K10="Method"),TRUE(),FALSE()),FALSE()) -> FALSE | I10: =IFERROR(IF(AND(OR(ISNUMBER(SEARCH("material",'Patent Portfolio'!C10)),ISNUMBER(SEARCH("chem",'Patent Portfolio'!C10)),ISNUMBER(SEARCH("battery",'Patent Portfolio'!C10)),ISNUMBER(SEARCH("electrolyte",'Patent Portfolio'!C10)),ISNUMBER(SEARCH("polymer",'Patent Portfolio'!C10))),OR('Patent Portfolio'!K10="Apparatus",'Patent Portfolio'!K10="Method")),TRUE(),FALSE()),FALSE()) -> FALSE | J10: =IFERROR(IF(AND(OR('Patent Portfolio'!E10="App",'Patent Portfolio'!E10="Middleware",'Patent Portfolio'!E10="Cloud"),OR('Patent Portfolio'!K10="Method",'Patent Portfolio'!K10="CRM")),TRUE(),FALSE()),FALSE()) -> TRUE | K10: =IFERROR(IF(N('Patent Portfolio'!J10)>=2,TRUE(),FALSE()),FALSE()) -> FALSE | L10: =IFERROR(IF('Patent Portfolio'!AA10<>"",TRUE(),FALSE()),FALSE()) -> TRUE | M10: =IFERROR(IF('Patent Portfolio'!K10<>"",TRUE(),FALSE()),FALSE()) -> TRUE | N10: =IFERROR(IF(OR(N('Patent Portfolio'!O10)>=2,N('Patent Portfolio'!P10)>=2),TRUE(),FALSE()),FALSE()) -> TRUE | O10: =IFERROR(IF('Patent Portfolio'!X10="Yes",TRUE(),FALSE()),FALSE()) -> FALSE | P10: =IFERROR(IF(N('Patent Portfolio'!R10)>=2,TRUE(),FALSE()),FALSE()) -> TRUE | Q10: =IFERROR(IF(N('Patent Portfolio'!U10)>0,TRUE(),FALSE()),FALSE()) -> TRUE | R10: =IFERROR(IF(OR(N('Patent Portfolio'!L10)=3,N('Patent Portfolio'!L10)<=1),TRUE(),FALSE()),FALSE()) -> TRUE | S10: =IFERROR(IF(N('Patent Portfolio'!AB10)>=2,TRUE(),FALSE()),FALSE()) -> TRUE | T10: =IFERROR(IF('Patent Portfolio'!Z10<>"",TRUE(),FALSE()),FALSE()) -> TRUE | U10: =IFERROR(IF(N('Patent Portfolio'!Q10)>=2,TRUE(),FALSE()),FALSE()) -> TRUE | V10: =IFERROR(IF(AND(N('Patent Portfolio'!N10)>=2,'Patent Portfolio'!C10<>""),TRUE(),FALSE()),FALSE()) -> FALSE | W10: =IFERROR(IF(OR('Patent Portfolio'!S10="Pending",'Patent Portfolio'!T10="Yes"),TRUE(),FALSE()),FALSE()) -> TRUE | X10: =IFERROR(IF(AND(N('Patent Portfolio'!AC10)>=2,N('Patent Portfolio'!L10)>=1),TRUE(),FALSE()),FALSE()) -> FALSE | Y10: =IFERROR(IF(AND(N('Patent Portfolio'!N10)>=1,OR('Patent Portfolio'!C10<>"",'Patent Portfolio'!I10<>"")),TRUE(),FALSE()),FALSE()) -> TRUE | Z10: =IFERROR(IF('Patent Portfolio'!C10<>"",TRUE(),FALSE()),FALSE()) -> TRUE | AA10: =IFERROR(IF('Patent Portfolio'!T10="Yes",TRUE(),FALSE()),FALSE()) -> TRUE | AB10: =IFERROR(IF(OR('Patent Portfolio'!AK10="Partial",'Patent Portfolio'!AK10="Full"),TRUE(),FALSE()),FALSE()) -> FALSE | AC10: =IFERROR(IF('Patent Portfolio'!AI10="Survived",TRUE(),FALSE()),FALSE()) -> FALSE | AD10: =IFERROR(IF(AND('Patent Portfolio'!AJ10="Clean",'Patent Portfolio'!AL10="None"),TRUE(),FALSE()),FALSE()) -> TRUE | AE10: =IFERROR(IF(N('Patent Portfolio'!AG10)>=15,TRUE(),FALSE()),FALSE()) -> FALSE | AF10: =IFERROR(IF(AND(N('Patent Portfolio'!AO10)>=2,N('Patent Portfolio'!AB10)>=2),TRUE(),FALSE()),FALSE()) -> TRUE | AG10: =IFERROR(IF(OR(N('Patent Portfolio'!AC10)<=1,N('Patent Portfolio'!U10)<5,N('Patent Portfolio'!AD10)<=1),TRUE(),FALSE()),FALSE()) -> TRUE | AH10: =IFERROR(IF(AND(N('Patent Portfolio'!U10)>=1,N('Patent Portfolio'!U10)<=4),TRUE(),FALSE()),FALSE()) -> FALSE | AI10: =IFERROR(IF(AND('Patent Portfolio'!C10<>"",'Patent Portfolio'!F10<>""),TRUE(),FALSE()),FALSE()) -> TRUE | AJ10: =COUNTIF(C10:AI10,TRUE()) -> 22
A11: ='Patent Portfolio'!A11 -> P-009 | B11: ='Patent Portfolio'!B11 -> Visual SLAM for indoor robot navigation | C11: =IFERROR(IF('Patent Portfolio'!C11<>"",TRUE(),FALSE()),FALSE()) -> TRUE | D11: =IFERROR(IF(AND(N('Patent Portfolio'!H11)>=2,'Patent Portfolio'!I11<>""),TRUE(),FALSE()),FALSE()) -> FALSE | E11: =IFERROR(IF('Patent Portfolio'!F11<>"",TRUE(),FALSE()),FALSE()) -> TRUE | F11: =IFERROR(IF('Patent Portfolio'!E11<>"",TRUE(),FALSE()),FALSE()) -> TRUE | G11: =IFERROR(IF('Patent Portfolio'!G11<>"",TRUE(),FALSE()),FALSE()) -> TRUE | H11: =IFERROR(IF(AND(OR(ISNUMBER(SEARCH("process",'Patent Portfolio'!C11)),ISNUMBER(SEARCH("fab",'Patent Portfolio'!C11)),ISNUMBER(SEARCH("manufac",'Patent Portfolio'!C11))),'Patent Portfolio'!K11="Method"),TRUE(),FALSE()),FALSE()) -> FALSE | I11: =IFERROR(IF(AND(OR(ISNUMBER(SEARCH("material",'Patent Portfolio'!C11)),ISNUMBER(SEARCH("chem",'Patent Portfolio'!C11)),ISNUMBER(SEARCH("battery",'Patent Portfolio'!C11)),ISNUMBER(SEARCH("electrolyte",'Patent Portfolio'!C11)),ISNUMBER(SEARCH("polymer",'Patent Portfolio'!C11))),OR('Patent Portfolio'!K11="Apparatus",'Patent Portfolio'!K11="Method")),TRUE(),FALSE()),FALSE()) -> FALSE | J11: =IFERROR(IF(AND(OR('Patent Portfolio'!E11="App",'Patent Portfolio'!E11="Middleware",'Patent Portfolio'!E11="Cloud"),OR('Patent Portfolio'!K11="Method",'Patent Portfolio'!K11="CRM")),TRUE(),FALSE()),FALSE()) -> FALSE | K11: =IFERROR(IF(N('Patent Portfolio'!J11)>=2,TRUE(),FALSE()),FALSE()) -> FALSE | L11: =IFERROR(IF('Patent Portfolio'!AA11<>"",TRUE(),FALSE()),FALSE()) -> TRUE | M11: =IFERROR(IF('Patent Portfolio'!K11<>"",TRUE(),FALSE()),FALSE()) -> TRUE | N11: =IFERROR(IF(OR(N('Patent Portfolio'!O11)>=2,N('Patent Portfolio'!P11)>=2),TRUE(),FALSE()),FALSE()) -> TRUE | O11: =IFERROR(IF('Patent Portfolio'!X11="Yes",TRUE(),FALSE()),FALSE()) -> TRUE | P11: =IFERROR(IF(N('Patent Portfolio'!R11)>=2,TRUE(),FALSE()),FALSE()) -> TRUE | Q11: =IFERROR(IF(N('Patent Portfolio'!U11)>0,TRUE(),FALSE()),FALSE()) -> TRUE | R11: =IFERROR(IF(OR(N('Patent Portfolio'!L11)=3,N('Patent Portfolio'!L11)<=1),TRUE(),FALSE()),FALSE()) -> FALSE | S11: =IFERROR(IF(N('Patent Portfolio'!AB11)>=2,TRUE(),FALSE()),FALSE()) -> TRUE | T11: =IFERROR(IF('Patent Portfolio'!Z11<>"",TRUE(),FALSE()),FALSE()) -> TRUE | U11: =IFERROR(IF(N('Patent Portfolio'!Q11)>=2,TRUE(),FALSE()),FALSE()) -> TRUE | V11: =IFERROR(IF(AND(N('Patent Portfolio'!N11)>=2,'Patent Portfolio'!C11<>""),TRUE(),FALSE()),FALSE()) -> TRUE | W11: =IFERROR(IF(OR('Patent Portfolio'!S11="Pending",'Patent Portfolio'!T11="Yes"),TRUE(),FALSE()),FALSE()) -> FALSE | X11: =IFERROR(IF(AND(N('Patent Portfolio'!AC11)>=2,N('Patent Portfolio'!L11)>=1),TRUE(),FALSE()),FALSE()) -> TRUE | Y11: =IFERROR(IF(AND(N('Patent Portfolio'!N11)>=1,OR('Patent Portfolio'!C11<>"",'Patent Portfolio'!I11<>"")),TRUE(),FALSE()),FALSE()) -> TRUE | Z11: =IFERROR(IF('Patent Portfolio'!C11<>"",TRUE(),FALSE()),FALSE()) -> TRUE | AA11: =IFERROR(IF('Patent Portfolio'!T11="Yes",TRUE(),FALSE()),FALSE()) -> FALSE | AB11: =IFERROR(IF(OR('Patent Portfolio'!AK11="Partial",'Patent Portfolio'!AK11="Full"),TRUE(),FALSE()),FALSE()) -> TRUE | AC11: =IFERROR(IF('Patent Portfolio'!AI11="Survived",TRUE(),FALSE()),FALSE()) -> FALSE | AD11: =IFERROR(IF(AND('Patent Portfolio'!AJ11="Clean",'Patent Portfolio'!AL11="None"),TRUE(),FALSE()),FALSE()) -> TRUE | AE11: =IFERROR(IF(N('Patent Portfolio'!AG11)>=15,TRUE(),FALSE()),FALSE()) -> TRUE | AF11: =IFERROR(IF(AND(N('Patent Portfolio'!AO11)>=2,N('Patent Portfolio'!AB11)>=2),TRUE(),FALSE()),FALSE()) -> TRUE | AG11: =IFERROR(IF(OR(N('Patent Portfolio'!AC11)<=1,N('Patent Portfolio'!U11)<5,N('Patent Portfolio'!AD11)<=1),TRUE(),FALSE()),FALSE()) -> FALSE | AH11: =IFERROR(IF(AND(N('Patent Portfolio'!U11)>=1,N('Patent Portfolio'!U11)<=4),TRUE(),FALSE()),FALSE()) -> FALSE | AI11: =IFERROR(IF(AND('Patent Portfolio'!C11<>"",'Patent Portfolio'!F11<>""),TRUE(),FALSE()),FALSE()) -> TRUE | AJ11: =COUNTIF(C11:AI11,TRUE()) -> 22
A12: ='Patent Portfolio'!A12 -> P-010 | B12: ='Patent Portfolio'!B12 -> USB-C power delivery handshake extension | C12: =IFERROR(IF('Patent Portfolio'!C12<>"",TRUE(),FALSE()),FALSE()) -> TRUE | D12: =IFERROR(IF(AND(N('Patent Portfolio'!H12)>=2,'Patent Portfolio'!I12<>""),TRUE(),FALSE()),FALSE()) -> TRUE | E12: =IFERROR(IF('Patent Portfolio'!F12<>"",TRUE(),FALSE()),FALSE()) -> TRUE | F12: =IFERROR(IF('Patent Portfolio'!E12<>"",TRUE(),FALSE()),FALSE()) -> TRUE | G12: =IFERROR(IF('Patent Portfolio'!G12<>"",TRUE(),FALSE()),FALSE()) -> TRUE | H12: =IFERROR(IF(AND(OR(ISNUMBER(SEARCH("process",'Patent Portfolio'!C12)),ISNUMBER(SEARCH("fab",'Patent Portfolio'!C12)),ISNUMBER(SEARCH("manufac",'Patent Portfolio'!C12))),'Patent Portfolio'!K12="Method"),TRUE(),FALSE()),FALSE()) -> FALSE | I12: =IFERROR(IF(AND(OR(ISNUMBER(SEARCH("material",'Patent Portfolio'!C12)),ISNUMBER(SEARCH("chem",'Patent Portfolio'!C12)),ISNUMBER(SEARCH("battery",'Patent Portfolio'!C12)),ISNUMBER(SEARCH("electrolyte",'Patent Portfolio'!C12)),ISNUMBER(SEARCH("polymer",'Patent Portfolio'!C12))),OR('Patent Portfolio'!K12="Apparatus",'Patent Portfolio'!K12="Method")),TRUE(),FALSE()),FALSE()) -> FALSE | J12: =IFERROR(IF(AND(OR('Patent Portfolio'!E12="App",'Patent Portfolio'!E12="Middleware",'Patent Portfolio'!E12="Cloud"),OR('Patent Portfolio'!K12="Method",'Patent Portfolio'!K12="CRM")),TRUE(),FALSE()),FALSE()) -> FALSE | K12: =IFERROR(IF(N('Patent Portfolio'!J12)>=2,TRUE(),FALSE()),FALSE()) -> TRUE | L12: =IFERROR(IF('Patent Portfolio'!AA12<>"",TRUE(),FALSE()),FALSE()) -> TRUE | M12: =IFERROR(IF('Patent Portfolio'!K12<>"",TRUE(),FALSE()),FALSE()) -> TRUE | N12: =IFERROR(IF(OR(N('Patent Portfolio'!O12)>=2,N('Patent Portfolio'!P12)>=2),TRUE(),FALSE()),FALSE()) -> TRUE | O12: =IFERROR(IF('Patent Portfolio'!X12="Yes",TRUE(),FALSE()),FALSE()) -> TRUE | P12: =IFERROR(IF(N('Patent Portfolio'!R12)>=2,TRUE(),FALSE()),FALSE()) -> TRUE | Q12: =IFERROR(IF(N('Patent Portfolio'!U12)>0,TRUE(),FALSE()),FALSE()) -> TRUE | R12: =IFERROR(IF(OR(N('Patent Portfolio'!L12)=3,N('Patent Portfolio'!L12)<=1),TRUE(),FALSE()),FALSE()) -> TRUE | S12: =IFERROR(IF(N('Patent Portfolio'!AB12)>=2,TRUE(),FALSE()),FALSE()) -> TRUE | T12: =IFERROR(IF('Patent Portfolio'!Z12<>"",TRUE(),FALSE()),FALSE()) -> FALSE | U12: =IFERROR(IF(N('Patent Portfolio'!Q12)>=2,TRUE(),FALSE()),FALSE()) -> TRUE | V12: =IFERROR(IF(AND(N('Patent Portfolio'!N12)>=2,'Patent Portfolio'!C12<>""),TRUE(),FALSE()),FALSE()) -> TRUE | W12: =IFERROR(IF(OR('Patent Portfolio'!S12="Pending",'Patent Portfolio'!T12="Yes"),TRUE(),FALSE()),FALSE()) -> FALSE | X12: =IFERROR(IF(AND(N('Patent Portfolio'!AC12)>=2,N('Patent Portfolio'!L12)>=1),TRUE(),FALSE()),FALSE()) -> TRUE | Y12: =IFERROR(IF(AND(N('Patent Portfolio'!N12)>=1,OR('Patent Portfolio'!C12<>"",'Patent Portfolio'!I12<>"")),TRUE(),FALSE()),FALSE()) -> TRUE | Z12: =IFERROR(IF('Patent Portfolio'!C12<>"",TRUE(),FALSE()),FALSE()) -> TRUE | AA12: =IFERROR(IF('Patent Portfolio'!T12="Yes",TRUE(),FALSE()),FALSE()) -> FALSE | AB12: =IFERROR(IF(OR('Patent Portfolio'!AK12="Partial",'Patent Portfolio'!AK12="Full"),TRUE(),FALSE()),FALSE()) -> TRUE | AC12: =IFERROR(IF('Patent Portfolio'!AI12="Survived",TRUE(),FALSE()),FALSE()) -> TRUE | AD12: =IFERROR(IF(AND('Patent Portfolio'!AJ12="Clean",'Patent Portfolio'!AL12="None"),TRUE(),FALSE()),FALSE()) -> TRUE | AE12: =IFERROR(IF(N('Patent Portfolio'!AG12)>=15,TRUE(),FALSE()),FALSE()) -> TRUE | AF12: =IFERROR(IF(AND(N('Patent Portfolio'!AO12)>=2,N('Patent Portfolio'!AB12)>=2),TRUE(),FALSE()),FALSE()) -> TRUE | AG12: =IFERROR(IF(OR(N('Patent Portfolio'!AC12)<=1,N('Patent Portfolio'!U12)<5,N('Patent Portfolio'!AD12)<=1),TRUE(),FALSE()),FALSE()) -> FALSE | AH12: =IFERROR(IF(AND(N('Patent Portfolio'!U12)>=1,N('Patent Portfolio'!U12)<=4),TRUE(),FALSE()),FALSE()) -> FALSE | AI12: =IFERROR(IF(AND('Patent Portfolio'!C12<>"",'Patent Portfolio'!F12<>""),TRUE(),FALSE()),FALSE()) -> TRUE | AJ12: =COUNTIF(C12:AI12,TRUE()) -> 25
A13: ='Patent Portfolio'!A13 -> P-011 | B13: ='Patent Portfolio'!B13 -> Atomic layer deposition recipe for high-k dielectric | C13: =IFERROR(IF('Patent Portfolio'!C13<>"",TRUE(),FALSE()),FALSE()) -> TRUE | D13: =IFERROR(IF(AND(N('Patent Portfolio'!H13)>=2,'Patent Portfolio'!I13<>""),TRUE(),FALSE()),FALSE()) -> FALSE | E13: =IFERROR(IF('Patent Portfolio'!F13<>"",TRUE(),FALSE()),FALSE()) -> TRUE | F13: =IFERROR(IF('Patent Portfolio'!E13<>"",TRUE(),FALSE()),FALSE()) -> TRUE | G13: =IFERROR(IF('Patent Portfolio'!G13<>"",TRUE(),FALSE()),FALSE()) -> TRUE | H13: =IFERROR(IF(AND(OR(ISNUMBER(SEARCH("process",'Patent Portfolio'!C13)),ISNUMBER(SEARCH("fab",'Patent Portfolio'!C13)),ISNUMBER(SEARCH("manufac",'Patent Portfolio'!C13))),'Patent Portfolio'!K13="Method"),TRUE(),FALSE()),FALSE()) -> TRUE | I13: =IFERROR(IF(AND(OR(ISNUMBER(SEARCH("material",'Patent Portfolio'!C13)),ISNUMBER(SEARCH("chem",'Patent Portfolio'!C13)),ISNUMBER(SEARCH("battery",'Patent Portfolio'!C13)),ISNUMBER(SEARCH("electrolyte",'Patent Portfolio'!C13)),ISNUMBER(SEARCH("polymer",'Patent Portfolio'!C13))),OR('Patent Portfolio'!K13="Apparatus",'Patent Portfolio'!K13="Method")),TRUE(),FALSE()),FALSE()) -> FALSE | J13: =IFERROR(IF(AND(OR('Patent Portfolio'!E13="App",'Patent Portfolio'!E13="Middleware",'Patent Portfolio'!E13="Cloud"),OR('Patent Portfolio'!K13="Method",'Patent Portfolio'!K13="CRM")),TRUE(),FALSE()),FALSE()) -> FALSE | K13: =IFERROR(IF(N('Patent Portfolio'!J13)>=2,TRUE(),FALSE()),FALSE()) -> FALSE | L13: =IFERROR(IF('Patent Portfolio'!AA13<>"",TRUE(),FALSE()),FALSE()) -> TRUE | M13: =IFERROR(IF('Patent Portfolio'!K13<>"",TRUE(),FALSE()),FALSE()) -> TRUE | N13: =IFERROR(IF(OR(N('Patent Portfolio'!O13)>=2,N('Patent Portfolio'!P13)>=2),TRUE(),FALSE()),FALSE()) -> FALSE | O13: =IFERROR(IF('Patent Portfolio'!X13="Yes",TRUE(),FALSE()),FALSE()) -> TRUE | P13: =IFERROR(IF(N('Patent Portfolio'!R13)>=2,TRUE(),FALSE()),FALSE()) -> TRUE | Q13: =IFERROR(IF(N('Patent Portfolio'!U13)>0,TRUE(),FALSE()),FALSE()) -> TRUE | R13: =IFERROR(IF(OR(N('Patent Portfolio'!L13)=3,N('Patent Portfolio'!L13)<=1),TRUE(),FALSE()),FALSE()) -> FALSE | S13: =IFERROR(IF(N('Patent Portfolio'!AB13)>=2,TRUE(),FALSE()),FALSE()) -> FALSE | T13: =IFERROR(IF('Patent Portfolio'!Z13<>"",TRUE(),FALSE()),FALSE()) -> FALSE | U13: =IFERROR(IF(N('Patent Portfolio'!Q13)>=2,TRUE(),FALSE()),FALSE()) -> FALSE | V13: =IFERROR(IF(AND(N('Patent Portfolio'!N13)>=2,'Patent Portfolio'!C13<>""),TRUE(),FALSE()),FALSE()) -> TRUE | W13: =IFERROR(IF(OR('Patent Portfolio'!S13="Pending",'Patent Portfolio'!T13="Yes"),TRUE(),FALSE()),FALSE()) -> TRUE | X13: =IFERROR(IF(AND(N('Patent Portfolio'!AC13)>=2,N('Patent Portfolio'!L13)>=1),TRUE(),FALSE()),FALSE()) -> TRUE | Y13: =IFERROR(IF(AND(N('Patent Portfolio'!N13)>=1,OR('Patent Portfolio'!C13<>"",'Patent Portfolio'!I13<>"")),TRUE(),FALSE()),FALSE()) -> TRUE | Z13: =IFERROR(IF('Patent Portfolio'!C13<>"",TRUE(),FALSE()),FALSE()) -> TRUE | AA13: =IFERROR(IF('Patent Portfolio'!T13="Yes",TRUE(),FALSE()),FALSE()) -> TRUE | AB13: =IFERROR(IF(OR('Patent Portfolio'!AK13="Partial",'Patent Portfolio'!AK13="Full"),TRUE(),FALSE()),FALSE()) -> FALSE | AC13: =IFERROR(IF('Patent Portfolio'!AI13="Survived",TRUE(),FALSE()),FALSE()) -> FALSE | AD13: =IFERROR(IF(AND('Patent Portfolio'!AJ13="Clean",'Patent Portfolio'!AL13="None"),TRUE(),FALSE()),FALSE()) -> TRUE | AE13: =IFERROR(IF(N('Patent Portfolio'!AG13)>=15,TRUE(),FALSE()),FALSE()) -> TRUE | AF13: =IFERROR(IF(AND(N('Patent Portfolio'!AO13)>=2,N('Patent Portfolio'!AB13)>=2),TRUE(),FALSE()),FALSE()) -> FALSE | AG13: =IFERROR(IF(OR(N('Patent Portfolio'!AC13)<=1,N('Patent Portfolio'!U13)<5,N('Patent Portfolio'!AD13)<=1),TRUE(),FALSE()),FALSE()) -> FALSE | AH13: =IFERROR(IF(AND(N('Patent Portfolio'!U13)>=1,N('Patent Portfolio'!U13)<=4),TRUE(),FALSE()),FALSE()) -> FALSE | AI13: =IFERROR(IF(AND('Patent Portfolio'!C13<>"",'Patent Portfolio'!F13<>""),TRUE(),FALSE()),FALSE()) -> TRUE | AJ13: =COUNTIF(C13:AI13,TRUE()) -> 19
A14: ='Patent Portfolio'!A14 -> P-012 | B14: ='Patent Portfolio'!B14 -> Predictive maintenance ML for industrial pumps | C14: =IFERROR(IF('Patent Portfolio'!C14<>"",TRUE(),FALSE()),FALSE()) -> TRUE | D14: =IFERROR(IF(AND(N('Patent Portfolio'!H14)>=2,'Patent Portfolio'!I14<>""),TRUE(),FALSE()),FALSE()) -> FALSE | E14: =IFERROR(IF('Patent Portfolio'!F14<>"",TRUE(),FALSE()),FALSE()) -> TRUE | F14: =IFERROR(IF('Patent Portfolio'!E14<>"",TRUE(),FALSE()),FALSE()) -> TRUE | G14: =IFERROR(IF('Patent Portfolio'!G14<>"",TRUE(),FALSE()),FALSE()) -> TRUE | H14: =IFERROR(IF(AND(OR(ISNUMBER(SEARCH("process",'Patent Portfolio'!C14)),ISNUMBER(SEARCH("fab",'Patent Portfolio'!C14)),ISNUMBER(SEARCH("manufac",'Patent Portfolio'!C14))),'Patent Portfolio'!K14="Method"),TRUE(),FALSE()),FALSE()) -> FALSE | I14: =IFERROR(IF(AND(OR(ISNUMBER(SEARCH("material",'Patent Portfolio'!C14)),ISNUMBER(SEARCH("chem",'Patent Portfolio'!C14)),ISNUMBER(SEARCH("battery",'Patent Portfolio'!C14)),ISNUMBER(SEARCH("electrolyte",'Patent Portfolio'!C14)),ISNUMBER(SEARCH("polymer",'Patent Portfolio'!C14))),OR('Patent Portfolio'!K14="Apparatus",'Patent Portfolio'!K14="Method")),TRUE(),FALSE()),FALSE()) -> FALSE | J14: =IFERROR(IF(AND(OR('Patent Portfolio'!E14="App",'Patent Portfolio'!E14="Middleware",'Patent Portfolio'!E14="Cloud"),OR('Patent Portfolio'!K14="Method",'Patent Portfolio'!K14="CRM")),TRUE(),FALSE()),FALSE()) -> TRUE | K14: =IFERROR(IF(N('Patent Portfolio'!J14)>=2,TRUE(),FALSE()),FALSE()) -> FALSE | L14: =IFERROR(IF('Patent Portfolio'!AA14<>"",TRUE(),FALSE()),FALSE()) -> TRUE | M14: =IFERROR(IF('Patent Portfolio'!K14<>"",TRUE(),FALSE()),FALSE()) -> TRUE | N14: =IFERROR(IF(OR(N('Patent Portfolio'!O14)>=2,N('Patent Portfolio'!P14)>=2),TRUE(),FALSE()),FALSE()) -> TRUE | O14: =IFERROR(IF('Patent Portfolio'!X14="Yes",TRUE(),FALSE()),FALSE()) -> FALSE | P14: =IFERROR(IF(N('Patent Portfolio'!R14)>=2,TRUE(),FALSE()),FALSE()) -> TRUE | Q14: =IFERROR(IF(N('Patent Portfolio'!U14)>0,TRUE(),FALSE()),FALSE()) -> TRUE | R14: =IFERROR(IF(OR(N('Patent Portfolio'!L14)=3,N('Patent Portfolio'!L14)<=1),TRUE(),FALSE()),FALSE()) -> TRUE | S14: =IFERROR(IF(N('Patent Portfolio'!AB14)>=2,TRUE(),FALSE()),FALSE()) -> TRUE | T14: =IFERROR(IF('Patent Portfolio'!Z14<>"",TRUE(),FALSE()),FALSE()) -> TRUE | U14: =IFERROR(IF(N('Patent Portfolio'!Q14)>=2,TRUE(),FALSE()),FALSE()) -> FALSE | V14: =IFERROR(IF(AND(N('Patent Portfolio'!N14)>=2,'Patent Portfolio'!C14<>""),TRUE(),FALSE()),FALSE()) -> FALSE | W14: =IFERROR(IF(OR('Patent Portfolio'!S14="Pending",'Patent Portfolio'!T14="Yes"),TRUE(),FALSE()),FALSE()) -> FALSE | X14: =IFERROR(IF(AND(N('Patent Portfolio'!AC14)>=2,N('Patent Portfolio'!L14)>=1),TRUE(),FALSE()),FALSE()) -> FALSE | Y14: =IFERROR(IF(AND(N('Patent Portfolio'!N14)>=1,OR('Patent Portfolio'!C14<>"",'Patent Portfolio'!I14<>"")),TRUE(),FALSE()),FALSE()) -> TRUE | Z14: =IFERROR(IF('Patent Portfolio'!C14<>"",TRUE(),FALSE()),FALSE()) -> TRUE | AA14: =IFERROR(IF('Patent Portfolio'!T14="Yes",TRUE(),FALSE()),FALSE()) -> FALSE | AB14: =IFERROR(IF(OR('Patent Portfolio'!AK14="Partial",'Patent Portfolio'!AK14="Full"),TRUE(),FALSE()),FALSE()) -> FALSE | AC14: =IFERROR(IF('Patent Portfolio'!AI14="Survived",TRUE(),FALSE()),FALSE()) -> FALSE | AD14: =IFERROR(IF(AND('Patent Portfolio'!AJ14="Clean",'Patent Portfolio'!AL14="None"),TRUE(),FALSE()),FALSE()) -> FALSE | AE14: =IFERROR(IF(N('Patent Portfolio'!AG14)>=15,TRUE(),FALSE()),FALSE()) -> FALSE | AF14: =IFERROR(IF(AND(N('Patent Portfolio'!AO14)>=2,N('Patent Portfolio'!AB14)>=2),TRUE(),FALSE()),FALSE()) -> TRUE | AG14: =IFERROR(IF(OR(N('Patent Portfolio'!AC14)<=1,N('Patent Portfolio'!U14)<5,N('Patent Portfolio'!AD14)<=1),TRUE(),FALSE()),FALSE()) -> TRUE | AH14: =IFERROR(IF(AND(N('Patent Portfolio'!U14)>=1,N('Patent Portfolio'!U14)<=4),TRUE(),FALSE()),FALSE()) -> FALSE | AI14: =IFERROR(IF(AND('Patent Portfolio'!C14<>"",'Patent Portfolio'!F14<>""),TRUE(),FALSE()),FALSE()) -> TRUE | AJ14: =COUNTIF(C14:AI14,TRUE()) -> 18
... A22: ='Patent Portfolio'!A22 -> 0 | B22: ='Patent Portfolio'!B22 -> 0 | C22: =IFERROR(IF('Patent Portfolio'!C22<>"",TRUE(),FALSE()),FALSE()) -> FALSE | D22: =IFERROR(IF(AND(N('Patent Portfolio'!H22)>=2,'Patent Portfolio'!I22<>""),TRUE(),FALSE()),FALSE()) -> FALSE | E22: =IFERROR(IF('Patent Portfolio'!F22<>"",TRUE(),FALSE()),FALSE()) -> FALSE | F22: =IFERROR(IF('Patent Portfolio'!E22<>"",TRUE(),FALSE()),FALSE()) -> FALSE | G22: =IFERROR(IF('Patent Portfolio'!G22<>"",TRUE(),FALSE()),FALSE()) -> FALSE | H22: =IFERROR(IF(AND(OR(ISNUMBER(SEARCH("process",'Patent Portfolio'!C22)),ISNUMBER(SEARCH("fab",'Patent Portfolio'!C22)),ISNUMBER(SEARCH("manufac",'Patent Portfolio'!C22))),'Patent Portfolio'!K22="Method"),TRUE(),FALSE()),FALSE()) -> FALSE | I22: =IFERROR(IF(AND(OR(ISNUMBER(SEARCH("material",'Patent Portfolio'!C22)),ISNUMBER(SEARCH("chem",'Patent Portfolio'!C22)),ISNUMBER(SEARCH("battery",'Patent Portfolio'!C22)),ISNUMBER(SEARCH("electrolyte",'Patent Portfolio'!C22)),ISNUMBER(SEARCH("polymer",'Patent Portfolio'!C22))),OR('Patent Portfolio'!K22="Apparatus",'Patent Portfolio'!K22="Method")),TRUE(),FALSE()),FALSE()) -> FALSE | J22: =IFERROR(IF(AND(OR('Patent Portfolio'!E22="App",'Patent Portfolio'!E22="Middleware",'Patent Portfolio'!E22="Cloud"),OR('Patent Portfolio'!K22="Method",'Patent Portfolio'!K22="CRM")),TRUE(),FALSE()),FALSE()) -> FALSE | K22: =IFERROR(IF(N('Patent Portfolio'!J22)>=2,TRUE(),FALSE()),FALSE()) -> FALSE | L22: =IFERROR(IF('Patent Portfolio'!AA22<>"",TRUE(),FALSE()),FALSE()) -> FALSE | M22: =IFERROR(IF('Patent Portfolio'!K22<>"",TRUE(),FALSE()),FALSE()) -> FALSE | N22: =IFERROR(IF(OR(N('Patent Portfolio'!O22)>=2,N('Patent Portfolio'!P22)>=2),TRUE(),FALSE()),FALSE()) -> FALSE | O22: =IFERROR(IF('Patent Portfolio'!X22="Yes",TRUE(),FALSE()),FALSE()) -> FALSE | P22: =IFERROR(IF(N('Patent Portfolio'!R22)>=2,TRUE(),FALSE()),FALSE()) -> FALSE | Q22: =IFERROR(IF(N('Patent Portfolio'!U22)>0,TRUE(),FALSE()),FALSE()) -> FALSE | R22: =IFERROR(IF(OR(N('Patent Portfolio'!L22)=3,N('Patent Portfolio'!L22)<=1),TRUE(),FALSE()),FALSE()) -> TRUE | S22: =IFERROR(IF(N('Patent Portfolio'!AB22)>=2,TRUE(),FALSE()),FALSE()) -> FALSE | T22: =IFERROR(IF('Patent Portfolio'!Z22<>"",TRUE(),FALSE()),FALSE()) -> FALSE | U22: =IFERROR(IF(N('Patent Portfolio'!Q22)>=2,TRUE(),FALSE()),FALSE()) -> FALSE | V22: =IFERROR(IF(AND(N('Patent Portfolio'!N22)>=2,'Patent Portfolio'!C22<>""),TRUE(),FALSE()),FALSE()) -> FALSE | W22: =IFERROR(IF(OR('Patent Portfolio'!S22="Pending",'Patent Portfolio'!T22="Yes"),TRUE(),FALSE()),FALSE()) -> FALSE | X22: =IFERROR(IF(AND(N('Patent Portfolio'!AC22)>=2,N('Patent Portfolio'!L22)>=1),TRUE(),FALSE()),FALSE()) -> FALSE | Y22: =IFERROR(IF(AND(N('Patent Portfolio'!N22)>=1,OR('Patent Portfolio'!C22<>"",'Patent Portfolio'!I22<>"")),TRUE(),FALSE()),FALSE()) -> FALSE | Z22: =IFERROR(IF('Patent Portfolio'!C22<>"",TRUE(),FALSE()),FALSE()) -> FALSE | AA22: =IFERROR(IF('Patent Portfolio'!T22="Yes",TRUE(),FALSE()),FALSE()) -> FALSE | AB22: =IFERROR(IF(OR('Patent Portfolio'!AK22="Partial",'Patent Portfolio'!AK22="Full"),TRUE(),FALSE()),FALSE()) -> FALSE | AC22: =IFERROR(IF('Patent Portfolio'!AI22="Survived",TRUE(),FALSE()),FALSE()) -> FALSE | AD22: =IFERROR(IF(AND('Patent Portfolio'!AJ22="Clean",'Patent Portfolio'!AL22="None"),TRUE(),FALSE()),FALSE()) -> FALSE | AE22: =IFERROR(IF(N('Patent Portfolio'!AG22)>=15,TRUE(),FALSE()),FALSE()) -> FALSE | AF22: =IFERROR(IF(AND(N('Patent Portfolio'!AO22)>=2,N('Patent Portfolio'!AB22)>=2),TRUE(),FALSE()),FALSE()) -> FALSE | AG22: =IFERROR(IF(OR(N('Patent Portfolio'!AC22)<=1,N('Patent Portfolio'!U22)<5,N('Patent Portfolio'!AD22)<=1),TRUE(),FALSE()),FALSE()) -> TRUE | AH22: =IFERROR(IF(AND(N('Patent Portfolio'!U22)>=1,N('Patent Portfolio'!U22)<=4),TRUE(),FALSE()),FALSE()) -> FALSE | AI22: =IFERROR(IF(AND('Patent Portfolio'!C22<>"",'Patent Portfolio'!F22<>""),TRUE(),FALSE()),FALSE()) -> FALSE | AJ22: =COUNTIF(C22:AI22,TRUE()) -> 2

Sheet Bundle Quality Scorecard
A1: # | B1: Bundle Type | C1: Coverage depth (# patents) | D1: Avg Detectability (D1+D2)/2 | E1: Avg Remaining Term (E4) | F1: Trilateral % (F2=Yes) | G1: Continuation % (E3=Yes) | H1: % SEP-flagged (B1≥2) | I1: Pioneer count (C2=3) | J1: Strength flag | K1: Weakest H1 (min in bundle) | L1: Invalidity exposure % (H2≤1) | M1: EoU-ready % (H9≠None) | N1: Survived % (H7=Survived) | O1: Continuation-optionality %
A2: 1 | B2: Tech Domain | C2: =COUNTIF('Bundle Assignment'!C3:C22,TRUE()) -> 12 | D2: =IFERROR(SUMPRODUCT(--('Bundle Assignment'!C3:C22=TRUE()),('Patent Portfolio'!O3:O22+'Patent Portfolio'!P3:P22)/2)/COUNTIF('Bundle Assignment'!C3:C22,TRUE()),0) -> 1.5833333 | E2: =IFERROR(SUMPRODUCT(--('Bundle Assignment'!C3:C22=TRUE()),'Patent Portfolio'!U3:U22)/COUNTIF('Bundle Assignment'!C3:C22,TRUE()),0) -> 13.166667 | F2: =IFERROR(SUMPRODUCT(--('Bundle Assignment'!C3:C22=TRUE()),--('Patent Portfolio'!X3:X22="Yes"))/COUNTIF('Bundle Assignment'!C3:C22,TRUE()),0) -> 0.83333333 | G2: =IFERROR(SUMPRODUCT(--('Bundle Assignment'!C3:C22=TRUE()),--('Patent Portfolio'!T3:T22="Yes"))/COUNTIF('Bundle Assignment'!C3:C22,TRUE()),0) -> 0.5 | H2: =IFERROR(SUMPRODUCT(--('Bundle Assignment'!C3:C22=TRUE()),--('Patent Portfolio'!H3:H22>=2))/COUNTIF('Bundle Assignment'!C3:C22,TRUE()),0) -> 0.33333333 | I2: =SUMPRODUCT(--('Bundle Assignment'!C3:C22=TRUE()),--('Patent Portfolio'!L3:L22=3)) -> 1 | J2: =IF(C2<2,"WEAK",IF(AND(C2>=4,D2>=2,E2>=10),"STRONG","MODERATE")) -> MODERATE | K2: =IFERROR(aggregate(5,6,'Patent Portfolio'!AC3:AC22/('Bundle Assignment'!C3:C22=TRUE())),"") | L2: =IFERROR(SUMPRODUCT(--('Bundle Assignment'!C3:C22=TRUE()),--('Patent Portfolio'!AD3:AD22<=1))/COUNTIF('Bundle Assignment'!C3:C22,TRUE()),0) -> 0.25 | M2: =IFERROR(SUMPRODUCT(--('Bundle Assignment'!C3:C22=TRUE()),--('Patent Portfolio'!AK3:AK22<>"None"),--('Patent Portfolio'!AK3:AK22<>""))/COUNTIF('Bundle Assignment'!C3:C22,TRUE()),0) -> 0.58333333 | N2: =IFERROR(SUMPRODUCT(--('Bundle Assignment'!C3:C22=TRUE()),--('Patent Portfolio'!AI3:AI22="Survived"))/COUNTIF('Bundle Assignment'!C3:C22,TRUE()),0) -> 0.16666667 | O2: =IFERROR(SUMPRODUCT(--('Bundle Assignment'!C3:C22=TRUE()),--('Patent Portfolio'!T3:T22="Yes"))/COUNTIF('Bundle Assignment'!C3:C22,TRUE()),0) -> 0.5
A3: 2 | B3: SEP | C3: =COUNTIF('Bundle Assignment'!D3:D22,TRUE()) -> 4 | D3: =IFERROR(SUMPRODUCT(--('Bundle Assignment'!D3:D22=TRUE()),('Patent Portfolio'!O3:O22+'Patent Portfolio'!P3:P22)/2)/COUNTIF('Bundle Assignment'!D3:D22,TRUE()),0) -> 2 | E3: =IFERROR(SUMPRODUCT(--('Bundle Assignment'!D3:D22=TRUE()),'Patent Portfolio'!U3:U22)/COUNTIF('Bundle Assignment'!D3:D22,TRUE()),0) -> 13.25 | F3: =IFERROR(SUMPRODUCT(--('Bundle Assignment'!D3:D22=TRUE()),--('Patent Portfolio'!X3:X22="Yes"))/COUNTIF('Bundle Assignment'!D3:D22,TRUE()),0) -> 1 | G3: =IFERROR(SUMPRODUCT(--('Bundle Assignment'!D3:D22=TRUE()),--('Patent Portfolio'!T3:T22="Yes"))/COUNTIF('Bundle Assignment'!D3:D22,TRUE()),0) -> 0.5 | H3: =IFERROR(SUMPRODUCT(--('Bundle Assignment'!D3:D22=TRUE()),--('Patent Portfolio'!H3:H22>=2))/COUNTIF('Bundle Assignment'!D3:D22,TRUE()),0) -> 1 | I3: =SUMPRODUCT(--('Bundle Assignment'!D3:D22=TRUE()),--('Patent Portfolio'!L3:L22=3)) -> 0 | J3: =IF(C3<2,"WEAK",IF(AND(C3>=4,D3>=2,E3>=10),"STRONG","MODERATE")) -> STRONG | K3: =IFERROR(aggregate(5,6,'Patent Portfolio'!AC3:AC22/('Bundle Assignment'!D3:D22=TRUE())),"") | L3: =IFERROR(SUMPRODUCT(--('Bundle Assignment'!D3:D22=TRUE()),--('Patent Portfolio'!AD3:AD22<=1))/COUNTIF('Bundle Assignment'!D3:D22,TRUE()),0) -> 0 | M3: =IFERROR(SUMPRODUCT(--('Bundle Assignment'!D3:D22=TRUE()),--('Patent Portfolio'!AK3:AK22<>"None"),--('Patent Portfolio'!AK3:AK22<>""))/COUNTIF('Bundle Assignment'!D3:D22,TRUE()),0) -> 0.75 | N3: =IFERROR(SUMPRODUCT(--('Bundle Assignment'!D3:D22=TRUE()),--('Patent Portfolio'!AI3:AI22="Survived"))/COUNTIF('Bundle Assignment'!D3:D22,TRUE()),0) -> 0.5 | O3: =IFERROR(SUMPRODUCT(--('Bundle Assignment'!D3:D22=TRUE()),--('Patent Portfolio'!T3:T22="Yes"))/COUNTIF('Bundle Assignment'!D3:D22,TRUE()),0) -> 0.5
A4: 3 | B4: Product Arch | C4: =COUNTIF('Bundle Assignment'!E3:E22,TRUE()) -> 12 | D4: =IFERROR(SUMPRODUCT(--('Bundle Assignment'!E3:E22=TRUE()),('Patent Portfolio'!O3:O22+'Patent Portfolio'!P3:P22)/2)/COUNTIF('Bundle Assignment'!E3:E22,TRUE()),0) -> 1.5833333 | E4: =IFERROR(SUMPRODUCT(--('Bundle Assignment'!E3:E22=TRUE()),'Patent Portfolio'!U3:U22)/COUNTIF('Bundle Assignment'!E3:E22,TRUE()),0) -> 13.166667 | F4: =IFERROR(SUMPRODUCT(--('Bundle Assignment'!E3:E22=TRUE()),--('Patent Portfolio'!X3:X22="Yes"))/COUNTIF('Bundle Assignment'!E3:E22,TRUE()),0) -> 0.83333333 | G4: =IFERROR(SUMPRODUCT(--('Bundle Assignment'!E3:E22=TRUE()),--('Patent Portfolio'!T3:T22="Yes"))/COUNTIF('Bundle Assignment'!E3:E22,TRUE()),0) -> 0.5 | H4: =IFERROR(SUMPRODUCT(--('Bundle Assignment'!E3:E22=TRUE()),--('Patent Portfolio'!H3:H22>=2))/COUNTIF('Bundle Assignment'!E3:E22,TRUE()),0) -> 0.33333333 | I4: =SUMPRODUCT(--('Bundle Assignment'!E3:E22=TRUE()),--('Patent Portfolio'!L3:L22=3)) -> 1 | J4: =IF(C4<2,"WEAK",IF(AND(C4>=4,D4>=2,E4>=10),"STRONG","MODERATE")) -> MODERATE | K4: =IFERROR(aggregate(5,6,'Patent Portfolio'!AC3:AC22/('Bundle Assignment'!E3:E22=TRUE())),"") | L4: =IFERROR(SUMPRODUCT(--('Bundle Assignment'!E3:E22=TRUE()),--('Patent Portfolio'!AD3:AD22<=1))/COUNTIF('Bundle Assignment'!E3:E22,TRUE()),0) -> 0.25 | M4: =IFERROR(SUMPRODUCT(--('Bundle Assignment'!E3:E22=TRUE()),--('Patent Portfolio'!AK3:AK22<>"None"),--('Patent Portfolio'!AK3:AK22<>""))/COUNTIF('Bundle Assignment'!E3:E22,TRUE()),0) -> 0.58333333 | N4: =IFERROR(SUMPRODUCT(--('Bundle Assignment'!E3:E22=TRUE()),--('Patent Portfolio'!AI3:AI22="Survived"))/COUNTIF('Bundle Assignment'!E3:E22,TRUE()),0) -> 0.16666667 | O4: =IFERROR(SUMPRODUCT(--('Bundle Assignment'!E3:E22=TRUE()),--('Patent Portfolio'!T3:T22="Yes"))/COUNTIF('Bundle Assignment'!E3:E22,TRUE()),0) -> 0.5
A5: 4 | B5: Stack Layer | C5: =COUNTIF('Bundle Assignment'!F3:F22,TRUE()) -> 12 | D5: =IFERROR(SUMPRODUCT(--('Bundle Assignment'!F3:F22=TRUE()),('Patent Portfolio'!O3:O22+'Patent Portfolio'!P3:P22)/2)/COUNTIF('Bundle Assignment'!F3:F22,TRUE()),0) -> 1.5833333 | E5: =IFERROR(SUMPRODUCT(--('Bundle Assignment'!F3:F22=TRUE()),'Patent Portfolio'!U3:U22)/COUNTIF('Bundle Assignment'!F3:F22,TRUE()),0) -> 13.166667 | F5: =IFERROR(SUMPRODUCT(--('Bundle Assignment'!F3:F22=TRUE()),--('Patent Portfolio'!X3:X22="Yes"))/COUNTIF('Bundle Assignment'!F3:F22,TRUE()),0) -> 0.83333333 | G5: =IFERROR(SUMPRODUCT(--('Bundle Assignment'!F3:F22=TRUE()),--('Patent Portfolio'!T3:T22="Yes"))/COUNTIF('Bundle Assignment'!F3:F22,TRUE()),0) -> 0.5 | H5: =IFERROR(SUMPRODUCT(--('Bundle Assignment'!F3:F22=TRUE()),--('Patent Portfolio'!H3:H22>=2))/COUNTIF('Bundle Assignment'!F3:F22,TRUE()),0) -> 0.33333333 | I5: =SUMPRODUCT(--('Bundle Assignment'!F3:F22=TRUE()),--('Patent Portfolio'!L3:L22=3)) -> 1 | J5: =IF(C5<2,"WEAK",IF(AND(C5>=4,D5>=2,E5>=10),"STRONG","MODERATE")) -> MODERATE | K5: =IFERROR(aggregate(5,6,'Patent Portfolio'!AC3:AC22/('Bundle Assignment'!F3:F22=TRUE())),"") | L5: =IFERROR(SUMPRODUCT(--('Bundle Assignment'!F3:F22=TRUE()),--('Patent Portfolio'!AD3:AD22<=1))/COUNTIF('Bundle Assignment'!F3:F22,TRUE()),0) -> 0.25 | M5: =IFERROR(SUMPRODUCT(--('Bundle Assignment'!F3:F22=TRUE()),--('Patent Portfolio'!AK3:AK22<>"None"),--('Patent Portfolio'!AK3:AK22<>""))/COUNTIF('Bundle Assignment'!F3:F22,TRUE()),0) -> 0.58333333 | N5: =IFERROR(SUMPRODUCT(--('Bundle Assignment'!F3:F22=TRUE()),--('Patent Portfolio'!AI3:AI22="Survived"))/COUNTIF('Bundle Assignment'!F3:F22,TRUE()),0) -> 0.16666667 | O5: =IFERROR(SUMPRODUCT(--('Bundle Assignment'!F3:F22=TRUE()),--('Patent Portfolio'!T3:T22="Yes"))/COUNTIF('Bundle Assignment'!F3:F22,TRUE()),0) -> 0.5
A6: 5 | B6: Use-Case | C6: =COUNTIF('Bundle Assignment'!G3:G22,TRUE()) -> 12 | D6: =IFERROR(SUMPRODUCT(--('Bundle Assignment'!G3:G22=TRUE()),('Patent Portfolio'!O3:O22+'Patent Portfolio'!P3:P22)/2)/COUNTIF('Bundle Assignment'!G3:G22,TRUE()),0) -> 1.5833333 | E6: =IFERROR(SUMPRODUCT(--('Bundle Assignment'!G3:G22=TRUE()),'Patent Portfolio'!U3:U22)/COUNTIF('Bundle Assignment'!G3:G22,TRUE()),0) -> 13.166667 | F6: =IFERROR(SUMPRODUCT(--('Bundle Assignment'!G3:G22=TRUE()),--('Patent Portfolio'!X3:X22="Yes"))/COUNTIF('Bundle Assignment'!G3:G22,TRUE()),0) -> 0.83333333 | G6: =IFERROR(SUMPRODUCT(--('Bundle Assignment'!G3:G22=TRUE()),--('Patent Portfolio'!T3:T22="Yes"))/COUNTIF('Bundle Assignment'!G3:G22,TRUE()),0) -> 0.5 | H6: =IFERROR(SUMPRODUCT(--('Bundle Assignment'!G3:G22=TRUE()),--('Patent Portfolio'!H3:H22>=2))/COUNTIF('Bundle Assignment'!G3:G22,TRUE()),0) -> 0.33333333 | I6: =SUMPRODUCT(--('Bundle Assignment'!G3:G22=TRUE()),--('Patent Portfolio'!L3:L22=3)) -> 1 | J6: =IF(C6<2,"WEAK",IF(AND(C6>=4,D6>=2,E6>=10),"STRONG","MODERATE")) -> MODERATE | K6: =IFERROR(aggregate(5,6,'Patent Portfolio'!AC3:AC22/('Bundle Assignment'!G3:G22=TRUE())),"") | L6: =IFERROR(SUMPRODUCT(--('Bundle Assignment'!G3:G22=TRUE()),--('Patent Portfolio'!AD3:AD22<=1))/COUNTIF('Bundle Assignment'!G3:G22,TRUE()),0) -> 0.25 | M6: =IFERROR(SUMPRODUCT(--('Bundle Assignment'!G3:G22=TRUE()),--('Patent Portfolio'!AK3:AK22<>"None"),--('Patent Portfolio'!AK3:AK22<>""))/COUNTIF('Bundle Assignment'!G3:G22,TRUE()),0) -> 0.58333333 | N6: =IFERROR(SUMPRODUCT(--('Bundle Assignment'!G3:G22=TRUE()),--('Patent Portfolio'!AI3:AI22="Survived"))/COUNTIF('Bundle Assignment'!G3:G22,TRUE()),0) -> 0.16666667 | O6: =IFERROR(SUMPRODUCT(--('Bundle Assignment'!G3:G22=TRUE()),--('Patent Portfolio'!T3:T22="Yes"))/COUNTIF('Bundle Assignment'!G3:G22,TRUE()),0) -> 0.5
A7: 6 | B7: Mfg/Process | C7: =COUNTIF('Bundle Assignment'!H3:H22,TRUE()) -> 1 | D7: =IFERROR(SUMPRODUCT(--('Bundle Assignment'!H3:H22=TRUE()),('Patent Portfolio'!O3:O22+'Patent Portfolio'!P3:P22)/2)/COUNTIF('Bundle Assignment'!H3:H22,TRUE()),0) -> 0.5 | E7: =IFERROR(SUMPRODUCT(--('Bundle Assignment'!H3:H22=TRUE()),'Patent Portfolio'!U3:U22)/COUNTIF('Bundle Assignment'!H3:H22,TRUE()),0) -> 13 | F7: =IFERROR(SUMPRODUCT(--('Bundle Assignment'!H3:H22=TRUE()),--('Patent Portfolio'!X3:X22="Yes"))/COUNTIF('Bundle Assignment'!H3:H22,TRUE()),0) -> 1 | G7: =IFERROR(SUMPRODUCT(--('Bundle Assignment'!H3:H22=TRUE()),--('Patent Portfolio'!T3:T22="Yes"))/COUNTIF('Bundle Assignment'!H3:H22,TRUE()),0) -> 1 | H7: =IFERROR(SUMPRODUCT(--('Bundle Assignment'!H3:H22=TRUE()),--('Patent Portfolio'!H3:H22>=2))/COUNTIF('Bundle Assignment'!H3:H22,TRUE()),0) -> 0 | I7: =SUMPRODUCT(--('Bundle Assignment'!H3:H22=TRUE()),--('Patent Portfolio'!L3:L22=3)) -> 0 | J7: =IF(C7<2,"WEAK",IF(AND(C7>=4,D7>=2,E7>=10),"STRONG","MODERATE")) -> WEAK | K7: =IFERROR(aggregate(5,6,'Patent Portfolio'!AC3:AC22/('Bundle Assignment'!H3:H22=TRUE())),"") | L7: =IFERROR(SUMPRODUCT(--('Bundle Assignment'!H3:H22=TRUE()),--('Patent Portfolio'!AD3:AD22<=1))/COUNTIF('Bundle Assignment'!H3:H22,TRUE()),0) -> 0 | M7: =IFERROR(SUMPRODUCT(--('Bundle Assignment'!H3:H22=TRUE()),--('Patent Portfolio'!AK3:AK22<>"None"),--('Patent Portfolio'!AK3:AK22<>""))/COUNTIF('Bundle Assignment'!H3:H22,TRUE()),0) -> 0 | N7: =IFERROR(SUMPRODUCT(--('Bundle Assignment'!H3:H22=TRUE()),--('Patent Portfolio'!AI3:AI22="Survived"))/COUNTIF('Bundle Assignment'!H3:H22,TRUE()),0) -> 0 | O7: =IFERROR(SUMPRODUCT(--('Bundle Assignment'!H3:H22=TRUE()),--('Patent Portfolio'!T3:T22="Yes"))/COUNTIF('Bundle Assignment'!H3:H22,TRUE()),0) -> 1
A8: 7 | B8: Materials | C8: =COUNTIF('Bundle Assignment'!I3:I22,TRUE()) -> 1 | D8: =IFERROR(SUMPRODUCT(--('Bundle Assignment'!I3:I22=TRUE()),('Patent Portfolio'!O3:O22+'Patent Portfolio'!P3:P22)/2)/COUNTIF('Bundle Assignment'!I3:I22,TRUE()),0) -> 1.5 | E8: =IFERROR(SUMPRODUCT(--('Bundle Assignment'!I3:I22=TRUE()),'Patent Portfolio'!U3:U22)/COUNTIF('Bundle Assignment'!I3:I22,TRUE()),0) -> 17 | F8: =IFERROR(SUMPRODUCT(--('Bundle Assignment'!I3:I22=TRUE()),--('Patent Portfolio'!X3:X22="Yes"))/COUNTIF('Bundle Assignment'!I3:I22,TRUE()),0) -> 1 | G8: =IFERROR(SUMPRODUCT(--('Bundle Assignment'!I3:I22=TRUE()),--('Patent Portfolio'!T3:T22="Yes"))/COUNTIF('Bundle Assignment'!I3:I22,TRUE()),0) -> 1 | H8: =IFERROR(SUMPRODUCT(--('Bundle Assignment'!I3:I22=TRUE()),--('Patent Portfolio'!H3:H22>=2))/COUNTIF('Bundle Assignment'!I3:I22,TRUE()),0) -> 0 | I8: =SUMPRODUCT(--('Bundle Assignment'!I3:I22=TRUE()),--('Patent Portfolio'!L3:L22=3)) -> 1 | J8: =IF(C8<2,"WEAK",IF(AND(C8>=4,D8>=2,E8>=10),"STRONG","MODERATE")) -> WEAK | K8: =IFERROR(aggregate(5,6,'Patent Portfolio'!AC3:AC22/('Bundle Assignment'!I3:I22=TRUE())),"") | L8: =IFERROR(SUMPRODUCT(--('Bundle Assignment'!I3:I22=TRUE()),--('Patent Portfolio'!AD3:AD22<=1))/COUNTIF('Bundle Assignment'!I3:I22,TRUE()),0) -> 0 | M8: =IFERROR(SUMPRODUCT(--('Bundle Assignment'!I3:I22=TRUE()),--('Patent Portfolio'!AK3:AK22<>"None"),--('Patent Portfolio'!AK3:AK22<>""))/COUNTIF('Bundle Assignment'!I3:I22,TRUE()),0) -> 1 | N8: =IFERROR(SUMPRODUCT(--('Bundle Assignment'!I3:I22=TRUE()),--('Patent Portfolio'!AI3:AI22="Survived"))/COUNTIF('Bundle Assignment'!I3:I22,TRUE()),0) -> 0 | O8: =IFERROR(SUMPRODUCT(--('Bundle Assignment'!I3:I22=TRUE()),--('Patent Portfolio'!T3:T22="Yes"))/COUNTIF('Bundle Assignment'!I3:I22,TRUE()),0) -> 1
A9: 8 | B9: Algorithm | C9: =COUNTIF('Bundle Assignment'!J3:J22,TRUE()) -> 3 | D9: =IFERROR(SUMPRODUCT(--('Bundle Assignment'!J3:J22=TRUE()),('Patent Portfolio'!O3:O22+'Patent Portfolio'!P3:P22)/2)/COUNTIF('Bundle Assignment'!J3:J22,TRUE()),0) -> 1.1666667 | E9: =IFERROR(SUMPRODUCT(--('Bundle Assignment'!J3:J22=TRUE()),'Patent Portfolio'!U3:U22)/COUNTIF('Bundle Assignment'!J3:J22,TRUE()),0) -> 14 | F9: =IFERROR(SUMPRODUCT(--('Bundle Assignment'!J3:J22=TRUE()),--('Patent Portfolio'!X3:X22="Yes"))/COUNTIF('Bundle Assignment'!J3:J22,TRUE()),0) -> 0.33333333 | G9: =IFERROR(SUMPRODUCT(--('Bundle Assignment'!J3:J22=TRUE()),--('Patent Portfolio'!T3:T22="Yes"))/COUNTIF('Bundle Assignment'!J3:J22,TRUE()),0) -> 0.66666667 | H9: =IFERROR(SUMPRODUCT(--('Bundle Assignment'!J3:J22=TRUE()),--('Patent Portfolio'!H3:H22>=2))/COUNTIF('Bundle Assignment'!J3:J22,TRUE()),0) -> 0 | I9: =SUMPRODUCT(--('Bundle Assignment'!J3:J22=TRUE()),--('Patent Portfolio'!L3:L22=3)) -> 0 | J9: =IF(C9<2,"WEAK",IF(AND(C9>=4,D9>=2,E9>=10),"STRONG","MODERATE")) -> MODERATE | K9: =IFERROR(aggregate(5,6,'Patent Portfolio'!AC3:AC22/('Bundle Assignment'!J3:J22=TRUE())),"") | L9: =IFERROR(SUMPRODUCT(--('Bundle Assignment'!J3:J22=TRUE()),--('Patent Portfolio'!AD3:AD22<=1))/COUNTIF('Bundle Assignment'!J3:J22,TRUE()),0) -> 1 | M9: =IFERROR(SUMPRODUCT(--('Bundle Assignment'!J3:J22=TRUE()),--('Patent Portfolio'!AK3:AK22<>"None"),--('Patent Portfolio'!AK3:AK22<>""))/COUNTIF('Bundle Assignment'!J3:J22,TRUE()),0) -> 0.33333333 | N9: =IFERROR(SUMPRODUCT(--('Bundle Assignment'!J3:J22=TRUE()),--('Patent Portfolio'!AI3:AI22="Survived"))/COUNTIF('Bundle Assignment'!J3:J22,TRUE()),0) -> 0 | O9: =IFERROR(SUMPRODUCT(--('Bundle Assignment'!J3:J22=TRUE()),--('Patent Portfolio'!T3:T22="Yes"))/COUNTIF('Bundle Assignment'!J3:J22,TRUE()),0) -> 0.66666667
A10: 9 | B10: Interop | C10: =COUNTIF('Bundle Assignment'!K3:K22,TRUE()) -> 4 | D10: =IFERROR(SUMPRODUCT(--('Bundle Assignment'!K3:K22=TRUE()),('Patent Portfolio'!O3:O22+'Patent Portfolio'!P3:P22)/2)/COUNTIF('Bundle Assignment'!K3:K22,TRUE()),0) -> 2 | E10: =IFERROR(SUMPRODUCT(--('Bundle Assignment'!K3:K22=TRUE()),'Patent Portfolio'!U3:U22)/COUNTIF('Bundle Assignment'!K3:K22,TRUE()),0) -> 13.25 | F10: =IFERROR(SUMPRODUCT(--('Bundle Assignment'!K3:K22=TRUE()),--('Patent Portfolio'!X3:X22="Yes"))/COUNTIF('Bundle Assignment'!K3:K22,TRUE()),0) -> 1 | G10: =IFERROR(SUMPRODUCT(--('Bundle Assignment'!K3:K22=TRUE()),--('Patent Portfolio'!T3:T22="Yes"))/COUNTIF('Bundle Assignment'!K3:K22,TRUE()),0) -> 0.5 | H10: =IFERROR(SUMPRODUCT(--('Bundle Assignment'!K3:K22=TRUE()),--('Patent Portfolio'!H3:H22>=2))/COUNTIF('Bundle Assignment'!K3:K22,TRUE()),0) -> 1 | I10: =SUMPRODUCT(--('Bundle Assignment'!K3:K22=TRUE()),--('Patent Portfolio'!L3:L22=3)) -> 0 | J10: =IF(C10<2,"WEAK",IF(AND(C10>=4,D10>=2,E10>=10),"STRONG","MODERATE")) -> STRONG | K10: =IFERROR(aggregate(5,6,'Patent Portfolio'!AC3:AC22/('Bundle Assignment'!K3:K22=TRUE())),"") | L10: =IFERROR(SUMPRODUCT(--('Bundle Assignment'!K3:K22=TRUE()),--('Patent Portfolio'!AD3:AD22<=1))/COUNTIF('Bundle Assignment'!K3:K22,TRUE()),0) -> 0 | M10: =IFERROR(SUMPRODUCT(--('Bundle Assignment'!K3:K22=TRUE()),--('Patent Portfolio'!AK3:AK22<>"None"),--('Patent Portfolio'!AK3:AK22<>""))/COUNTIF('Bundle Assignment'!K3:K22,TRUE()),0) -> 0.75 | N10: =IFERROR(SUMPRODUCT(--('Bundle Assignment'!K3:K22=TRUE()),--('Patent Portfolio'!AI3:AI22="Survived"))/COUNTIF('Bundle Assignment'!K3:K22,TRUE()),0) -> 0.5 | O10: =IFERROR(SUMPRODUCT(--('Bundle Assignment'!K3:K22=TRUE()),--('Patent Portfolio'!T3:T22="Yes"))/COUNTIF('Bundle Assignment'!K3:K22,TRUE()),0) -> 0.5
A11: 10 | B11: Generational | C11: =COUNTIF('Bundle Assignment'!L3:L22,TRUE()) -> 12 | D11: =IFERROR(SUMPRODUCT(--('Bundle Assignment'!L3:L22=TRUE()),('Patent Portfolio'!O3:O22+'Patent Portfolio'!P3:P22)/2)/COUNTIF('Bundle Assignment'!L3:L22,TRUE()),0) -> 1.5833333 | E11: =IFERROR(SUMPRODUCT(--('Bundle Assignment'!L3:L22=TRUE()),'Patent Portfolio'!U3:U22)/COUNTIF('Bundle Assignment'!L3:L22,TRUE()),0) -> 13.166667 | F11: =IFERROR(SUMPRODUCT(--('Bundle Assignment'!L3:L22=TRUE()),--('Patent Portfolio'!X3:X22="Yes"))/COUNTIF('Bundle Assignment'!L3:L22,TRUE()),0) -> 0.83333333 | G11: =IFERROR(SUMPRODUCT(--('Bundle Assignment'!L3:L22=TRUE()),--('Patent Portfolio'!T3:T22="Yes"))/COUNTIF('Bundle Assignment'!L3:L22,TRUE()),0) -> 0.5 | H11: =IFERROR(SUMPRODUCT(--('Bundle Assignment'!L3:L22=TRUE()),--('Patent Portfolio'!H3:H22>=2))/COUNTIF('Bundle Assignment'!L3:L22,TRUE()),0) -> 0.33333333 | I11: =SUMPRODUCT(--('Bundle Assignment'!L3:L22=TRUE()),--('Patent Portfolio'!L3:L22=3)) -> 1 | J11: =IF(C11<2,"WEAK",IF(AND(C11>=4,D11>=2,E11>=10),"STRONG","MODERATE")) -> MODERATE | K11: =IFERROR(aggregate(5,6,'Patent Portfolio'!AC3:AC22/('Bundle Assignment'!L3:L22=TRUE())),"") | L11: =IFERROR(SUMPRODUCT(--('Bundle Assignment'!L3:L22=TRUE()),--('Patent Portfolio'!AD3:AD22<=1))/COUNTIF('Bundle Assignment'!L3:L22,TRUE()),0) -> 0.25 | M11: =IFERROR(SUMPRODUCT(--('Bundle Assignment'!L3:L22=TRUE()),--('Patent Portfolio'!AK3:AK22<>"None"),--('Patent Portfolio'!AK3:AK22<>""))/COUNTIF('Bundle Assignment'!L3:L22,TRUE()),0) -> 0.58333333 | N11: =IFERROR(SUMPRODUCT(--('Bundle Assignment'!L3:L22=TRUE()),--('Patent Portfolio'!AI3:AI22="Survived"))/COUNTIF('Bundle Assignment'!L3:L22,TRUE()),0) -> 0.16666667 | O11: =IFERROR(SUMPRODUCT(--('Bundle Assignment'!L3:L22=TRUE()),--('Patent Portfolio'!T3:T22="Yes"))/COUNTIF('Bundle Assignment'!L3:L22,TRUE()),0) -> 0.5
A12: 11 | B12: Claim-Type | C12: =COUNTIF('Bundle Assignment'!M3:M22,TRUE()) -> 12 | D12: =IFERROR(SUMPRODUCT(--('Bundle Assignment'!M3:M22=TRUE()),('Patent Portfolio'!O3:O22+'Patent Portfolio'!P3:P22)/2)/COUNTIF('Bundle Assignment'!M3:M22,TRUE()),0) -> 1.5833333 | E12: =IFERROR(SUMPRODUCT(--('Bundle Assignment'!M3:M22=TRUE()),'Patent Portfolio'!U3:U22)/COUNTIF('Bundle Assignment'!M3:M22,TRUE()),0) -> 13.166667 | F12: =IFERROR(SUMPRODUCT(--('Bundle Assignment'!M3:M22=TRUE()),--('Patent Portfolio'!X3:X22="Yes"))/COUNTIF('Bundle Assignment'!M3:M22,TRUE()),0) -> 0.83333333 | G12: =IFERROR(SUMPRODUCT(--('Bundle Assignment'!M3:M22=TRUE()),--('Patent Portfolio'!T3:T22="Yes"))/COUNTIF('Bundle Assignment'!M3:M22,TRUE()),0) -> 0.5 | H12: =IFERROR(SUMPRODUCT(--('Bundle Assignment'!M3:M22=TRUE()),--('Patent Portfolio'!H3:H22>=2))/COUNTIF('Bundle Assignment'!M3:M22,TRUE()),0) -> 0.33333333 | I12: =SUMPRODUCT(--('Bundle Assignment'!M3:M22=TRUE()),--('Patent Portfolio'!L3:L22=3)) -> 1 | J12: =IF(C12<2,"WEAK",IF(AND(C12>=4,D12>=2,E12>=10),"STRONG","MODERATE")) -> MODERATE | K12: =IFERROR(aggregate(5,6,'Patent Portfolio'!AC3:AC22/('Bundle Assignment'!M3:M22=TRUE())),"") | L12: =IFERROR(SUMPRODUCT(--('Bundle Assignment'!M3:M22=TRUE()),--('Patent Portfolio'!AD3:AD22<=1))/COUNTIF('Bundle Assignment'!M3:M22,TRUE()),0) -> 0.25 | M12: =IFERROR(SUMPRODUCT(--('Bundle Assignment'!M3:M22=TRUE()),--('Patent Portfolio'!AK3:AK22<>"None"),--('Patent Portfolio'!AK3:AK22<>""))/COUNTIF('Bundle Assignment'!M3:M22,TRUE()),0) -> 0.58333333 | N12: =IFERROR(SUMPRODUCT(--('Bundle Assignment'!M3:M22=TRUE()),--('Patent Portfolio'!AI3:AI22="Survived"))/COUNTIF('Bundle Assignment'!M3:M22,TRUE()),0) -> 0.16666667 | O12: =IFERROR(SUMPRODUCT(--('Bundle Assignment'!M3:M22=TRUE()),--('Patent Portfolio'!T3:T22="Yes"))/COUNTIF('Bundle Assignment'!M3:M22,TRUE()),0) -> 0.5
A13: 12 | B13: Detectable | C13: =COUNTIF('Bundle Assignment'!N3:N22,TRUE()) -> 11 | D13: =IFERROR(SUMPRODUCT(--('Bundle Assignment'!N3:N22=TRUE()),('Patent Portfolio'!O3:O22+'Patent Portfolio'!P3:P22)/2)/COUNTIF('Bundle Assignment'!N3:N22,TRUE()),0) -> 1.6818182 | E13: =IFERROR(SUMPRODUCT(--('Bundle Assignment'!N3:N22=TRUE()),'Patent Portfolio'!U3:U22)/COUNTIF('Bundle Assignment'!N3:N22,TRUE()),0) -> 13.181818 | F13: =IFERROR(SUMPRODUCT(--('Bundle Assignment'!N3:N22=TRUE()),--('Patent Portfolio'!X3:X22="Yes"))/COUNTIF('Bundle Assignment'!N3:N22,TRUE()),0) -> 0.81818182 | G13: =IFERROR(SUMPRODUCT(--('Bundle Assignment'!N3:N22=TRUE()),--('Patent Portfolio'!T3:T22="Yes"))/COUNTIF('Bundle Assignment'!N3:N22,TRUE()),0) -> 0.45454545 | H13: =IFERROR(SUMPRODUCT(--('Bundle Assignment'!N3:N22=TRUE()),--('Patent Portfolio'!H3:H22>=2))/COUNTIF('Bundle Assignment'!N3:N22,TRUE()),0) -> 0.36363636 | I13: =SUMPRODUCT(--('Bundle Assignment'!N3:N22=TRUE()),--('Patent Portfolio'!L3:L22=3)) -> 1 | J13: =IF(C13<2,"WEAK",IF(AND(C13>=4,D13>=2,E13>=10),"STRONG","MODERATE")) -> MODERATE | K13: =IFERROR(aggregate(5,6,'Patent Portfolio'!AC3:AC22/('Bundle Assignment'!N3:N22=TRUE())),"") | L13: =IFERROR(SUMPRODUCT(--('Bundle Assignment'!N3:N22=TRUE()),--('Patent Portfolio'!AD3:AD22<=1))/COUNTIF('Bundle Assignment'!N3:N22,TRUE()),0) -> 0.27272727 | M13: =IFERROR(SUMPRODUCT(--('Bundle Assignment'!N3:N22=TRUE()),--('Patent Portfolio'!AK3:AK22<>"None"),--('Patent Portfolio'!AK3:AK22<>""))/COUNTIF('Bundle Assignment'!N3:N22,TRUE()),0) -> 0.63636364 | N13: =IFERROR(SUMPRODUCT(--('Bundle Assignment'!N3:N22=TRUE()),--('Patent Portfolio'!AI3:AI22="Survived"))/COUNTIF('Bundle Assignment'!N3:N22,TRUE()),0) -> 0.18181818 | O13: =IFERROR(SUMPRODUCT(--('Bundle Assignment'!N3:N22=TRUE()),--('Patent Portfolio'!T3:T22="Yes"))/COUNTIF('Bundle Assignment'!N3:N22,TRUE()),0) -> 0.45454545
A14: 13 | B14: Geographic | C14: =COUNTIF('Bundle Assignment'!O3:O22,TRUE()) -> 10 | D14: =IFERROR(SUMPRODUCT(--('Bundle Assignment'!O3:O22=TRUE()),('Patent Portfolio'!O3:O22+'Patent Portfolio'!P3:P22)/2)/COUNTIF('Bundle Assignment'!O3:O22,TRUE()),0) -> 1.7 | E14: =IFERROR(SUMPRODUCT(--('Bundle Assignment'!O3:O22=TRUE()),'Patent Portfolio'!U3:U22)/COUNTIF('Bundle Assignment'!O3:O22,TRUE()),0) -> 13.1 | F14: =IFERROR(SUMPRODUCT(--('Bundle Assignment'!O3:O22=TRUE()),--('Patent Portfolio'!X3:X22="Yes"))/COUNTIF('Bundle Assignment'!O3:O22,TRUE()),0) -> 1 | G14: =IFERROR(SUMPRODUCT(--('Bundle Assignment'!O3:O22=TRUE()),--('Patent Portfolio'!T3:T22="Yes"))/COUNTIF('Bundle Assignment'!O3:O22,TRUE()),0) -> 0.5 | H14: =IFERROR(SUMPRODUCT(--('Bundle Assignment'!O3:O22=TRUE()),--('Patent Portfolio'!H3:H22>=2))/COUNTIF('Bundle Assignment'!O3:O22,TRUE()),0) -> 0.4 | I14: =SUMPRODUCT(--('Bundle Assignment'!O3:O22=TRUE()),--('Patent Portfolio'!L3:L22=3)) -> 1 | J14: =IF(C14<2,"WEAK",IF(AND(C14>=4,D14>=2,E14>=10),"STRONG","MODERATE")) -> MODERATE | K14: =IFERROR(aggregate(5,6,'Patent Portfolio'!AC3:AC22/('Bundle Assignment'!O3:O22=TRUE())),"") | L14: =IFERROR(SUMPRODUCT(--('Bundle Assignment'!O3:O22=TRUE()),--('Patent Portfolio'!AD3:AD22<=1))/COUNTIF('Bundle Assignment'!O3:O22,TRUE()),0) -> 0.1 | M14: =IFERROR(SUMPRODUCT(--('Bundle Assignment'!O3:O22=TRUE()),--('Patent Portfolio'!AK3:AK22<>"None"),--('Patent Portfolio'!AK3:AK22<>""))/COUNTIF('Bundle Assignment'!O3:O22,TRUE()),0) -> 0.7 | N14: =IFERROR(SUMPRODUCT(--('Bundle Assignment'!O3:O22=TRUE()),--('Patent Portfolio'!AI3:AI22="Survived"))/COUNTIF('Bundle Assignment'!O3:O22,TRUE()),0) -> 0.2 | O14: =IFERROR(SUMPRODUCT(--('Bundle Assignment'!O3:O22=TRUE()),--('Patent Portfolio'!T3:T22="Yes"))/COUNTIF('Bundle Assignment'!O3:O22,TRUE()),0) -> 0.5
A15: 14 | B15: Family | C15: =COUNTIF('Bundle Assignment'!P3:P22,TRUE()) -> 12 | D15: =IFERROR(SUMPRODUCT(--('Bundle Assignment'!P3:P22=TRUE()),('Patent Portfolio'!O3:O22+'Patent Portfolio'!P3:P22)/2)/COUNTIF('Bundle Assignment'!P3:P22,TRUE()),0) -> 1.5833333 | E15: =IFERROR(SUMPRODUCT(--('Bundle Assignment'!P3:P22=TRUE()),'Patent Portfolio'!U3:U22)/COUNTIF('Bundle Assignment'!P3:P22,TRUE()),0) -> 13.166667 | F15: =IFERROR(SUMPRODUCT(--('Bundle Assignment'!P3:P22=TRUE()),--('Patent Portfolio'!X3:X22="Yes"))/COUNTIF('Bundle Assignment'!P3:P22,TRUE()),0) -> 0.83333333 | G15: =IFERROR(SUMPRODUCT(--('Bundle Assignment'!P3:P22=TRUE()),--('Patent Portfolio'!T3:T22="Yes"))/COUNTIF('Bundle Assignment'!P3:P22,TRUE()),0) -> 0.5 | H15: =IFERROR(SUMPRODUCT(--('Bundle Assignment'!P3:P22=TRUE()),--('Patent Portfolio'!H3:H22>=2))/COUNTIF('Bundle Assignment'!P3:P22,TRUE()),0) -> 0.33333333 | I15: =SUMPRODUCT(--('Bundle Assignment'!P3:P22=TRUE()),--('Patent Portfolio'!L3:L22=3)) -> 1 | J15: =IF(C15<2,"WEAK",IF(AND(C15>=4,D15>=2,E15>=10),"STRONG","MODERATE")) -> MODERATE | K15: =IFERROR(aggregate(5,6,'Patent Portfolio'!AC3:AC22/('Bundle Assignment'!P3:P22=TRUE())),"") | L15: =IFERROR(SUMPRODUCT(--('Bundle Assignment'!P3:P22=TRUE()),--('Patent Portfolio'!AD3:AD22<=1))/COUNTIF('Bundle Assignment'!P3:P22,TRUE()),0) -> 0.25 | M15: =IFERROR(SUMPRODUCT(--('Bundle Assignment'!P3:P22=TRUE()),--('Patent Portfolio'!AK3:AK22<>"None"),--('Patent Portfolio'!AK3:AK22<>""))/COUNTIF('Bundle Assignment'!P3:P22,TRUE()),0) -> 0.58333333 | N15: =IFERROR(SUMPRODUCT(--('Bundle Assignment'!P3:P22=TRUE()),--('Patent Portfolio'!AI3:AI22="Survived"))/COUNTIF('Bundle Assignment'!P3:P22,TRUE()),0) -> 0.16666667 | O15: =IFERROR(SUMPRODUCT(--('Bundle Assignment'!P3:P22=TRUE()),--('Patent Portfolio'!T3:T22="Yes"))/COUNTIF('Bundle Assignment'!P3:P22,TRUE()),0) -> 0.5
A16: 15 | B16: Lifecycle | C16: =COUNTIF('Bundle Assignment'!Q3:Q22,TRUE()) -> 12 | D16: =IFERROR(SUMPRODUCT(--('Bundle Assignment'!Q3:Q22=TRUE()),('Patent Portfolio'!O3:O22+'Patent Portfolio'!P3:P22)/2)/COUNTIF('Bundle Assignment'!Q3:Q22,TRUE()),0) -> 1.5833333 | E16: =IFERROR(SUMPRODUCT(--('Bundle Assignment'!Q3:Q22=TRUE()),'Patent Portfolio'!U3:U22)/COUNTIF('Bundle Assignment'!Q3:Q22,TRUE()),0) -> 13.166667 | F16: =IFERROR(SUMPRODUCT(--('Bundle Assignment'!Q3:Q22=TRUE()),--('Patent Portfolio'!X3:X22="Yes"))/COUNTIF('Bundle Assignment'!Q3:Q22,TRUE()),0) -> 0.83333333 | G16: =IFERROR(SUMPRODUCT(--('Bundle Assignment'!Q3:Q22=TRUE()),--('Patent Portfolio'!T3:T22="Yes"))/COUNTIF('Bundle Assignment'!Q3:Q22,TRUE()),0) -> 0.5 | H16: =IFERROR(SUMPRODUCT(--('Bundle Assignment'!Q3:Q22=TRUE()),--('Patent Portfolio'!H3:H22>=2))/COUNTIF('Bundle Assignment'!Q3:Q22,TRUE()),0) -> 0.33333333 | I16: =SUMPRODUCT(--('Bundle Assignment'!Q3:Q22=TRUE()),--('Patent Portfolio'!L3:L22=3)) -> 1 | J16: =IF(C16<2,"WEAK",IF(AND(C16>=4,D16>=2,E16>=10),"STRONG","MODERATE")) -> MODERATE | K16: =IFERROR(aggregate(5,6,'Patent Portfolio'!AC3:AC22/('Bundle Assignment'!Q3:Q22=TRUE())),"") | L16: =IFERROR(SUMPRODUCT(--('Bundle Assignment'!Q3:Q22=TRUE()),--('Patent Portfolio'!AD3:AD22<=1))/COUNTIF('Bundle Assignment'!Q3:Q22,TRUE()),0) -> 0.25 | M16: =IFERROR(SUMPRODUCT(--('Bundle Assignment'!Q3:Q22=TRUE()),--('Patent Portfolio'!AK3:AK22<>"None"),--('Patent Portfolio'!AK3:AK22<>""))/COUNTIF('Bundle Assignment'!Q3:Q22,TRUE()),0) -> 0.58333333 | N16: =IFERROR(SUMPRODUCT(--('Bundle Assignment'!Q3:Q22=TRUE()),--('Patent Portfolio'!AI3:AI22="Survived"))/COUNTIF('Bundle Assignment'!Q3:Q22,TRUE()),0) -> 0.16666667 | O16: =IFERROR(SUMPRODUCT(--('Bundle Assignment'!Q3:Q22=TRUE()),--('Patent Portfolio'!T3:T22="Yes"))/COUNTIF('Bundle Assignment'!Q3:Q22,TRUE()),0) -> 0.5
A17: 16 | B17: Foundational+Improvement | C17: =COUNTIF('Bundle Assignment'!R3:R22,TRUE()) -> 13 | D17: =IFERROR(SUMPRODUCT(--('Bundle Assignment'!R3:R22=TRUE()),('Patent Portfolio'!O3:O22+'Patent Portfolio'!P3:P22)/2)/COUNTIF('Bundle Assignment'!R3:R22,TRUE()),0) -> 0.61538462 | E17: =IFERROR(SUMPRODUCT(--('Bundle Assignment'!R3:R22=TRUE()),'Patent Portfolio'!U3:U22)/COUNTIF('Bundle Assignment'!R3:R22,TRUE()),0) -> 5.3846154 | F17: =IFERROR(SUMPRODUCT(--('Bundle Assignment'!R3:R22=TRUE()),--('Patent Portfolio'!X3:X22="Yes"))/COUNTIF('Bundle Assignment'!R3:R22,TRUE()),0) -> 0.23076923 | G17: =IFERROR(SUMPRODUCT(--('Bundle Assignment'!R3:R22=TRUE()),--('Patent Portfolio'!T3:T22="Yes"))/COUNTIF('Bundle Assignment'!R3:R22,TRUE()),0) -> 0.23076923 | H17: =IFERROR(SUMPRODUCT(--('Bundle Assignment'!R3:R22=TRUE()),--('Patent Portfolio'!H3:H22>=2))/COUNTIF('Bundle Assignment'!R3:R22,TRUE()),0) -> 0.15384615 | I17: =SUMPRODUCT(--('Bundle Assignment'!R3:R22=TRUE()),--('Patent Portfolio'!L3:L22=3)) -> 1 | J17: =IF(C17<2,"WEAK",IF(AND(C17>=4,D17>=2,E17>=10),"STRONG","MODERATE")) -> MODERATE | K17: =IFERROR(aggregate(5,6,'Patent Portfolio'!AC3:AC22/('Bundle Assignment'!R3:R22=TRUE())),"") | L17: =IFERROR(SUMPRODUCT(--('Bundle Assignment'!R3:R22=TRUE()),--('Patent Portfolio'!AD3:AD22<=1))/COUNTIF('Bundle Assignment'!R3:R22,TRUE()),0) -> 0.76923077 | M17: =IFERROR(SUMPRODUCT(--('Bundle Assignment'!R3:R22=TRUE()),--('Patent Portfolio'!AK3:AK22<>"None"),--('Patent Portfolio'!AK3:AK22<>""))/COUNTIF('Bundle Assignment'!R3:R22,TRUE()),0) -> 0.15384615 | N17: =IFERROR(SUMPRODUCT(--('Bundle Assignment'!R3:R22=TRUE()),--('Patent Portfolio'!AI3:AI22="Survived"))/COUNTIF('Bundle Assignment'!R3:R22,TRUE()),0) -> 0.076923077 | O17: =IFERROR(SUMPRODUCT(--('Bundle Assignment'!R3:R22=TRUE()),--('Patent Portfolio'!T3:T22="Yes"))/COUNTIF('Bundle Assignment'!R3:R22,TRUE()),0) -> 0.23076923
A18: 17 | B18: Cross-Industry | C18: =COUNTIF('Bundle Assignment'!S3:S22,TRUE()) -> 9 | D18: =IFERROR(SUMPRODUCT(--('Bundle Assignment'!S3:S22=TRUE()),('Patent Portfolio'!O3:O22+'Patent Portfolio'!P3:P22)/2)/COUNTIF('Bundle Assignment'!S3:S22,TRUE()),0) -> 1.6666667 | E18: =IFERROR(SUMPRODUCT(--('Bundle Assignment'!S3:S22=TRUE()),'Patent Portfolio'!U3:U22)/COUNTIF('Bundle Assignment'!S3:S22,TRUE()),0) -> 13.111111 | F18: =IFERROR(SUMPRODUCT(--('Bundle Assignment'!S3:S22=TRUE()),--('Patent Portfolio'!X3:X22="Yes"))/COUNTIF('Bundle Assignment'!S3:S22,TRUE()),0) -> 0.77777778 | G18: =IFERROR(SUMPRODUCT(--('Bundle Assignment'!S3:S22=TRUE()),--('Patent Portfolio'!T3:T22="Yes"))/COUNTIF('Bundle Assignment'!S3:S22,TRUE()),0) -> 0.44444444 | H18: =IFERROR(SUMPRODUCT(--('Bundle Assignment'!S3:S22=TRUE()),--('Patent Portfolio'!H3:H22>=2))/COUNTIF('Bundle Assignment'!S3:S22,TRUE()),0) -> 0.22222222 | I18: =SUMPRODUCT(--('Bundle Assignment'!S3:S22=TRUE()),--('Patent Portfolio'!L3:L22=3)) -> 1 | J18: =IF(C18<2,"WEAK",IF(AND(C18>=4,D18>=2,E18>=10),"STRONG","MODERATE")) -> MODERATE | K18: =IFERROR(aggregate(5,6,'Patent Portfolio'!AC3:AC22/('Bundle Assignment'!S3:S22=TRUE())),"") | L18: =IFERROR(SUMPRODUCT(--('Bundle Assignment'!S3:S22=TRUE()),--('Patent Portfolio'!AD3:AD22<=1))/COUNTIF('Bundle Assignment'!S3:S22,TRUE()),0) -> 0.33333333 | M18: =IFERROR(SUMPRODUCT(--('Bundle Assignment'!S3:S22=TRUE()),--('Patent Portfolio'!AK3:AK22<>"None"),--('Patent Portfolio'!AK3:AK22<>""))/COUNTIF('Bundle Assignment'!S3:S22,TRUE()),0) -> 0.55555556 | N18: =IFERROR(SUMPRODUCT(--('Bundle Assignment'!S3:S22=TRUE()),--('Patent Portfolio'!AI3:AI22="Survived"))/COUNTIF('Bundle Assignment'!S3:S22,TRUE()),0) -> 0.11111111 | O18: =IFERROR(SUMPRODUCT(--('Bundle Assignment'!S3:S22=TRUE()),--('Patent Portfolio'!T3:T22="Yes"))/COUNTIF('Bundle Assignment'!S3:S22,TRUE()),0) -> 0.44444444
A19: 18 | B19: Convergent Theme | C19: =COUNTIF('Bundle Assignment'!T3:T22,TRUE()) -> 4 | D19: =IFERROR(SUMPRODUCT(--('Bundle Assignment'!T3:T22=TRUE()),('Patent Portfolio'!O3:O22+'Patent Portfolio'!P3:P22)/2)/COUNTIF('Bundle Assignment'!T3:T22,TRUE()),0) -> 1.25 | E19: =IFERROR(SUMPRODUCT(--('Bundle Assignment'!T3:T22=TRUE()),'Patent Portfolio'!U3:U22)/COUNTIF('Bundle Assignment'!T3:T22,TRUE()),0) -> 13 | F19: =IFERROR(SUMPRODUCT(--('Bundle Assignment'!T3:T22=TRUE()),--('Patent Portfolio'!X3:X22="Yes"))/COUNTIF('Bundle Assignment'!T3:T22,TRUE()),0) -> 0.5 | G19: =IFERROR(SUMPRODUCT(--('Bundle Assignment'!T3:T22=TRUE()),--('Patent Portfolio'!T3:T22="Yes"))/COUNTIF('Bundle Assignment'!T3:T22,TRUE()),0) -> 0.5 | H19: =IFERROR(SUMPRODUCT(--('Bundle Assignment'!T3:T22=TRUE()),--('Patent Portfolio'!H3:H22>=2))/COUNTIF('Bundle Assignment'!T3:T22,TRUE()),0) -> 0 | I19: =SUMPRODUCT(--('Bundle Assignment'!T3:T22=TRUE()),--('Patent Portfolio'!L3:L22=3)) -> 0 | J19: =IF(C19<2,"WEAK",IF(AND(C19>=4,D19>=2,E19>=10),"STRONG","MODERATE")) -> MODERATE | K19: =IFERROR(aggregate(5,6,'Patent Portfolio'!AC3:AC22/('Bundle Assignment'!T3:T22=TRUE())),"") | L19: =IFERROR(SUMPRODUCT(--('Bundle Assignment'!T3:T22=TRUE()),--('Patent Portfolio'!AD3:AD22<=1))/COUNTIF('Bundle Assignment'!T3:T22,TRUE()),0) -> 0.75 | M19: =IFERROR(SUMPRODUCT(--('Bundle Assignment'!T3:T22=TRUE()),--('Patent Portfolio'!AK3:AK22<>"None"),--('Patent Portfolio'!AK3:AK22<>""))/COUNTIF('Bundle Assignment'!T3:T22,TRUE()),0) -> 0.5 | N19: =IFERROR(SUMPRODUCT(--('Bundle Assignment'!T3:T22=TRUE()),--('Patent Portfolio'!AI3:AI22="Survived"))/COUNTIF('Bundle Assignment'!T3:T22,TRUE()),0) -> 0 | O19: =IFERROR(SUMPRODUCT(--('Bundle Assignment'!T3:T22=TRUE()),--('Patent Portfolio'!T3:T22="Yes"))/COUNTIF('Bundle Assignment'!T3:T22,TRUE()),0) -> 0.5
A20: 19 | B20: Defensive | C20: =COUNTIF('Bundle Assignment'!U3:U22,TRUE()) -> 10 | D20: =IFERROR(SUMPRODUCT(--('Bundle Assignment'!U3:U22=TRUE()),('Patent Portfolio'!O3:O22+'Patent Portfolio'!P3:P22)/2)/COUNTIF('Bundle Assignment'!U3:U22,TRUE()),0) -> 1.75 | E20: =IFERROR(SUMPRODUCT(--('Bundle Assignment'!U3:U22=TRUE()),'Patent Portfolio'!U3:U22)/COUNTIF('Bundle Assignment'!U3:U22,TRUE()),0) -> 13.7 | F20: =IFERROR(SUMPRODUCT(--('Bundle Assignment'!U3:U22=TRUE()),--('Patent Portfolio'!X3:X22="Yes"))/COUNTIF('Bundle Assignment'!U3:U22,TRUE()),0) -> 0.9 | G20: =IFERROR(SUMPRODUCT(--('Bundle Assignment'!U3:U22=TRUE()),--('Patent Portfolio'!T3:T22="Yes"))/COUNTIF('Bundle Assignment'!U3:U22,TRUE()),0) -> 0.5 | H20: =IFERROR(SUMPRODUCT(--('Bundle Assignment'!U3:U22=TRUE()),--('Patent Portfolio'!H3:H22>=2))/COUNTIF('Bundle Assignment'!U3:U22,TRUE()),0) -> 0.4 | I20: =SUMPRODUCT(--('Bundle Assignment'!U3:U22=TRUE()),--('Patent Portfolio'!L3:L22=3)) -> 1 | J20: =IF(C20<2,"WEAK",IF(AND(C20>=4,D20>=2,E20>=10),"STRONG","MODERATE")) -> MODERATE | K20: =IFERROR(aggregate(5,6,'Patent Portfolio'!AC3:AC22/('Bundle Assignment'!U3:U22=TRUE())),"") | L20: =IFERROR(SUMPRODUCT(--('Bundle Assignment'!U3:U22=TRUE()),--('Patent Portfolio'!AD3:AD22<=1))/COUNTIF('Bundle Assignment'!U3:U22,TRUE()),0) -> 0.2 | M20: =IFERROR(SUMPRODUCT(--('Bundle Assignment'!U3:U22=TRUE()),--('Patent Portfolio'!AK3:AK22<>"None"),--('Patent Portfolio'!AK3:AK22<>""))/COUNTIF('Bundle Assignment'!U3:U22,TRUE()),0) -> 0.7 | N20: =IFERROR(SUMPRODUCT(--('Bundle Assignment'!U3:U22=TRUE()),--('Patent Portfolio'!AI3:AI22="Survived"))/COUNTIF('Bundle Assignment'!U3:U22,TRUE()),0) -> 0.2 | O20: =IFERROR(SUMPRODUCT(--('Bundle Assignment'!U3:U22=TRUE()),--('Patent Portfolio'!T3:T22="Yes"))/COUNTIF('Bundle Assignment'!U3:U22,TRUE()),0) -> 0.5
A21: 20 | B21: Whitespace | C21: =COUNTIF('Bundle Assignment'!V3:V22,TRUE()) -> 10 | D21: =IFERROR(SUMPRODUCT(--('Bundle Assignment'!V3:V22=TRUE()),('Patent Portfolio'!O3:O22+'Patent Portfolio'!P3:P22)/2)/COUNTIF('Bundle Assignment'!V3:V22,TRUE()),0) -> 1.7 | E21: =IFERROR(SUMPRODUCT(--('Bundle Assignment'!V3:V22=TRUE()),'Patent Portfolio'!U3:U22)/COUNTIF('Bundle Assignment'!V3:V22,TRUE()),0) -> 13.1 | F21: =IFERROR(SUMPRODUCT(--('Bundle Assignment'!V3:V22=TRUE()),--('Patent Portfolio'!X3:X22="Yes"))/COUNTIF('Bundle Assignment'!V3:V22,TRUE()),0) -> 1 | G21: =IFERROR(SUMPRODUCT(--('Bundle Assignment'!V3:V22=TRUE()),--('Patent Portfolio'!T3:T22="Yes"))/COUNTIF('Bundle Assignment'!V3:V22,TRUE()),0) -> 0.5 | H21: =IFERROR(SUMPRODUCT(--('Bundle Assignment'!V3:V22=TRUE()),--('Patent Portfolio'!H3:H22>=2))/COUNTIF('Bundle Assignment'!V3:V22,TRUE()),0) -> 0.4 | I21: =SUMPRODUCT(--('Bundle Assignment'!V3:V22=TRUE()),--('Patent Portfolio'!L3:L22=3)) -> 1 | J21: =IF(C21<2,"WEAK",IF(AND(C21>=4,D21>=2,E21>=10),"STRONG","MODERATE")) -> MODERATE | K21: =IFERROR(aggregate(5,6,'Patent Portfolio'!AC3:AC22/('Bundle Assignment'!V3:V22=TRUE())),"") | L21: =IFERROR(SUMPRODUCT(--('Bundle Assignment'!V3:V22=TRUE()),--('Patent Portfolio'!AD3:AD22<=1))/COUNTIF('Bundle Assignment'!V3:V22,TRUE()),0) -> 0.1 | M21: =IFERROR(SUMPRODUCT(--('Bundle Assignment'!V3:V22=TRUE()),--('Patent Portfolio'!AK3:AK22<>"None"),--('Patent Portfolio'!AK3:AK22<>""))/COUNTIF('Bundle Assignment'!V3:V22,TRUE()),0) -> 0.7 | N21: =IFERROR(SUMPRODUCT(--('Bundle Assignment'!V3:V22=TRUE()),--('Patent Portfolio'!AI3:AI22="Survived"))/COUNTIF('Bundle Assignment'!V3:V22,TRUE()),0) -> 0.2 | O21: =IFERROR(SUMPRODUCT(--('Bundle Assignment'!V3:V22=TRUE()),--('Patent Portfolio'!T3:T22="Yes"))/COUNTIF('Bundle Assignment'!V3:V22,TRUE()),0) -> 0.5
A22: 21 | B22: Prosecution-Status | C22: =COUNTIF('Bundle Assignment'!W3:W22,TRUE()) -> 6 | D22: =IFERROR(SUMPRODUCT(--('Bundle Assignment'!W3:W22=TRUE()),('Patent Portfolio'!O3:O22+'Patent Portfolio'!P3:P22)/2)/COUNTIF('Bundle Assignment'!W3:W22,TRUE()),0) -> 1.3333333 | E22: =IFERROR(SUMPRODUCT(--('Bundle Assignment'!W3:W22=TRUE()),'Patent Portfolio'!U3:U22)/COUNTIF('Bundle Assignment'!W3:W22,TRUE()),0) -> 15.833333 | F22: =IFERROR(SUMPRODUCT(--('Bundle Assignment'!W3:W22=TRUE()),--('Patent Portfolio'!X3:X22="Yes"))/COUNTIF('Bundle Assignment'!W3:W22,TRUE()),0) -> 0.83333333 | G22: =IFERROR(SUMPRODUCT(--('Bundle Assignment'!W3:W22=TRUE()),--('Patent Portfolio'!T3:T22="Yes"))/COUNTIF('Bundle Assignment'!W3:W22,TRUE()),0) -> 1 | H22: =IFERROR(SUMPRODUCT(--('Bundle Assignment'!W3:W22=TRUE()),--('Patent Portfolio'!H3:H22>=2))/COUNTIF('Bundle Assignment'!W3:W22,TRUE()),0) -> 0.33333333 | I22: =SUMPRODUCT(--('Bundle Assignment'!W3:W22=TRUE()),--('Patent Portfolio'!L3:L22=3)) -> 1 | J22: =IF(C22<2,"WEAK",IF(AND(C22>=4,D22>=2,E22>=10),"STRONG","MODERATE")) -> MODERATE | K22: =IFERROR(aggregate(5,6,'Patent Portfolio'!AC3:AC22/('Bundle Assignment'!W3:W22=TRUE())),"") | L22: =IFERROR(SUMPRODUCT(--('Bundle Assignment'!W3:W22=TRUE()),--('Patent Portfolio'!AD3:AD22<=1))/COUNTIF('Bundle Assignment'!W3:W22,TRUE()),0) -> 0.33333333 | M22: =IFERROR(SUMPRODUCT(--('Bundle Assignment'!W3:W22=TRUE()),--('Patent Portfolio'!AK3:AK22<>"None"),--('Patent Portfolio'!AK3:AK22<>""))/COUNTIF('Bundle Assignment'!W3:W22,TRUE()),0) -> 0.5 | N22: =IFERROR(SUMPRODUCT(--('Bundle Assignment'!W3:W22=TRUE()),--('Patent Portfolio'!AI3:AI22="Survived"))/COUNTIF('Bundle Assignment'!W3:W22,TRUE()),0) -> 0.16666667 | O22: =IFERROR(SUMPRODUCT(--('Bundle Assignment'!W3:W22=TRUE()),--('Patent Portfolio'!T3:T22="Yes"))/COUNTIF('Bundle Assignment'!W3:W22,TRUE()),0) -> 1
A23: 22 | B23: Anchor-and-Halo | C23: =COUNTIF('Bundle Assignment'!X3:X22,TRUE()) -> 10 | D23: =IFERROR(SUMPRODUCT(--('Bundle Assignment'!X3:X22=TRUE()),('Patent Portfolio'!O3:O22+'Patent Portfolio'!P3:P22)/2)/COUNTIF('Bundle Assignment'!X3:X22,TRUE()),0) -> 1.7 | E23: =IFERROR(SUMPRODUCT(--('Bundle Assignment'!X3:X22=TRUE()),'Patent Portfolio'!U3:U22)/COUNTIF('Bundle Assignment'!X3:X22,TRUE()),0) -> 13.1 | F23: =IFERROR(SUMPRODUCT(--('Bundle Assignment'!X3:X22=TRUE()),--('Patent Portfolio'!X3:X22="Yes"))/COUNTIF('Bundle Assignment'!X3:X22,TRUE()),0) -> 1 | G23: =IFERROR(SUMPRODUCT(--('Bundle Assignment'!X3:X22=TRUE()),--('Patent Portfolio'!T3:T22="Yes"))/COUNTIF('Bundle Assignment'!X3:X22,TRUE()),0) -> 0.5 | H23: =IFERROR(SUMPRODUCT(--('Bundle Assignment'!X3:X22=TRUE()),--('Patent Portfolio'!H3:H22>=2))/COUNTIF('Bundle Assignment'!X3:X22,TRUE()),0) -> 0.4 | I23: =SUMPRODUCT(--('Bundle Assignment'!X3:X22=TRUE()),--('Patent Portfolio'!L3:L22=3)) -> 1 | J23: =IF(C23<2,"WEAK",IF(AND(C23>=4,D23>=2,E23>=10),"STRONG","MODERATE")) -> MODERATE | K23: =IFERROR(aggregate(5,6,'Patent Portfolio'!AC3:AC22/('Bundle Assignment'!X3:X22=TRUE())),"") | L23: =IFERROR(SUMPRODUCT(--('Bundle Assignment'!X3:X22=TRUE()),--('Patent Portfolio'!AD3:AD22<=1))/COUNTIF('Bundle Assignment'!X3:X22,TRUE()),0) -> 0.1 | M23: =IFERROR(SUMPRODUCT(--('Bundle Assignment'!X3:X22=TRUE()),--('Patent Portfolio'!AK3:AK22<>"None"),--('Patent Portfolio'!AK3:AK22<>""))/COUNTIF('Bundle Assignment'!X3:X22,TRUE()),0) -> 0.7 | N23: =IFERROR(SUMPRODUCT(--('Bundle Assignment'!X3:X22=TRUE()),--('Patent Portfolio'!AI3:AI22="Survived"))/COUNTIF('Bundle Assignment'!X3:X22,TRUE()),0) -> 0.2 | O23: =IFERROR(SUMPRODUCT(--('Bundle Assignment'!X3:X22=TRUE()),--('Patent Portfolio'!T3:T22="Yes"))/COUNTIF('Bundle Assignment'!X3:X22,TRUE()),0) -> 0.5
A24: 23 | B24: Picket-Fence / Cluster-Around-Standard | C24: =COUNTIF('Bundle Assignment'!Y3:Y22,TRUE()) -> 12 | D24: =IFERROR(SUMPRODUCT(--('Bundle Assignment'!Y3:Y22=TRUE()),('Patent Portfolio'!O3:O22+'Patent Portfolio'!P3:P22)/2)/COUNTIF('Bundle Assignment'!Y3:Y22,TRUE()),0) -> 1.5833333 | E24: =IFERROR(SUMPRODUCT(--('Bundle Assignment'!Y3:Y22=TRUE()),'Patent Portfolio'!U3:U22)/COUNTIF('Bundle Assignment'!Y3:Y22,TRUE()),0) -> 13.166667 | F24: =IFERROR(SUMPRODUCT(--('Bundle Assignment'!Y3:Y22=TRUE()),--('Patent Portfolio'!X3:X22="Yes"))/COUNTIF('Bundle Assignment'!Y3:Y22,TRUE()),0) -> 0.83333333 | G24: =IFERROR(SUMPRODUCT(--('Bundle Assignment'!Y3:Y22=TRUE()),--('Patent Portfolio'!T3:T22="Yes"))/COUNTIF('Bundle Assignment'!Y3:Y22,TRUE()),0) -> 0.5 | H24: =IFERROR(SUMPRODUCT(--('Bundle Assignment'!Y3:Y22=TRUE()),--('Patent Portfolio'!H3:H22>=2))/COUNTIF('Bundle Assignment'!Y3:Y22,TRUE()),0) -> 0.33333333 | I24: =SUMPRODUCT(--('Bundle Assignment'!Y3:Y22=TRUE()),--('Patent Portfolio'!L3:L22=3)) -> 1 | J24: =IF(C24<2,"WEAK",IF(AND(C24>=4,D24>=2,E24>=10),"STRONG","MODERATE")) -> MODERATE | K24: =IFERROR(aggregate(5,6,'Patent Portfolio'!AC3:AC22/('Bundle Assignment'!Y3:Y22=TRUE())),"") | L24: =IFERROR(SUMPRODUCT(--('Bundle Assignment'!Y3:Y22=TRUE()),--('Patent Portfolio'!AD3:AD22<=1))/COUNTIF('Bundle Assignment'!Y3:Y22,TRUE()),0) -> 0.25 | M24: =IFERROR(SUMPRODUCT(--('Bundle Assignment'!Y3:Y22=TRUE()),--('Patent Portfolio'!AK3:AK22<>"None"),--('Patent Portfolio'!AK3:AK22<>""))/COUNTIF('Bundle Assignment'!Y3:Y22,TRUE()),0) -> 0.58333333 | N24: =IFERROR(SUMPRODUCT(--('Bundle Assignment'!Y3:Y22=TRUE()),--('Patent Portfolio'!AI3:AI22="Survived"))/COUNTIF('Bundle Assignment'!Y3:Y22,TRUE()),0) -> 0.16666667 | O24: =IFERROR(SUMPRODUCT(--('Bundle Assignment'!Y3:Y22=TRUE()),--('Patent Portfolio'!T3:T22="Yes"))/COUNTIF('Bundle Assignment'!Y3:Y22,TRUE()),0) -> 0.5
A25: 24 | B25: Strong-Core + Quality-Diluted Tail | C25: =COUNTIF('Bundle Assignment'!Z3:Z22,TRUE()) -> 12 | D25: =IFERROR(SUMPRODUCT(--('Bundle Assignment'!Z3:Z22=TRUE()),('Patent Portfolio'!O3:O22+'Patent Portfolio'!P3:P22)/2)/COUNTIF('Bundle Assignment'!Z3:Z22,TRUE()),0) -> 1.5833333 | E25: =IFERROR(SUMPRODUCT(--('Bundle Assignment'!Z3:Z22=TRUE()),'Patent Portfolio'!U3:U22)/COUNTIF('Bundle Assignment'!Z3:Z22,TRUE()),0) -> 13.166667 | F25: =IFERROR(SUMPRODUCT(--('Bundle Assignment'!Z3:Z22=TRUE()),--('Patent Portfolio'!X3:X22="Yes"))/COUNTIF('Bundle Assignment'!Z3:Z22,TRUE()),0) -> 0.83333333 | G25: =IFERROR(SUMPRODUCT(--('Bundle Assignment'!Z3:Z22=TRUE()),--('Patent Portfolio'!T3:T22="Yes"))/COUNTIF('Bundle Assignment'!Z3:Z22,TRUE()),0) -> 0.5 | H25: =IFERROR(SUMPRODUCT(--('Bundle Assignment'!Z3:Z22=TRUE()),--('Patent Portfolio'!H3:H22>=2))/COUNTIF('Bundle Assignment'!Z3:Z22,TRUE()),0) -> 0.33333333 | I25: =SUMPRODUCT(--('Bundle Assignment'!Z3:Z22=TRUE()),--('Patent Portfolio'!L3:L22=3)) -> 1 | J25: =IF(C25<2,"WEAK",IF(AND(C25>=4,D25>=2,E25>=10),"STRONG","MODERATE")) -> MODERATE | K25: =IFERROR(aggregate(5,6,'Patent Portfolio'!AC3:AC22/('Bundle Assignment'!Z3:Z22=TRUE())),"") | L25: =IFERROR(SUMPRODUCT(--('Bundle Assignment'!Z3:Z22=TRUE()),--('Patent Portfolio'!AD3:AD22<=1))/COUNTIF('Bundle Assignment'!Z3:Z22,TRUE()),0) -> 0.25 | M25: =IFERROR(SUMPRODUCT(--('Bundle Assignment'!Z3:Z22=TRUE()),--('Patent Portfolio'!AK3:AK22<>"None"),--('Patent Portfolio'!AK3:AK22<>""))/COUNTIF('Bundle Assignment'!Z3:Z22,TRUE()),0) -> 0.58333333 | N25: =IFERROR(SUMPRODUCT(--('Bundle Assignment'!Z3:Z22=TRUE()),--('Patent Portfolio'!AI3:AI22="Survived"))/COUNTIF('Bundle Assignment'!Z3:Z22,TRUE()),0) -> 0.16666667 | O25: =IFERROR(SUMPRODUCT(--('Bundle Assignment'!Z3:Z22=TRUE()),--('Patent Portfolio'!T3:T22="Yes"))/COUNTIF('Bundle Assignment'!Z3:Z22,TRUE()),0) -> 0.5
A26: 25 | B26: Continuation-Live / Claim-Tailorable | C26: =COUNTIF('Bundle Assignment'!AA3:AA22,TRUE()) -> 6 | D26: =IFERROR(SUMPRODUCT(--('Bundle Assignment'!AA3:AA22=TRUE()),('Patent Portfolio'!O3:O22+'Patent Portfolio'!P3:P22)/2)/COUNTIF('Bundle Assignment'!AA3:AA22,TRUE()),0) -> 1.3333333 | E26: =IFERROR(SUMPRODUCT(--('Bundle Assignment'!AA3:AA22=TRUE()),'Patent Portfolio'!U3:U22)/COUNTIF('Bundle Assignment'!AA3:AA22,TRUE()),0) -> 15.833333 | F26: =IFERROR(SUMPRODUCT(--('Bundle Assignment'!AA3:AA22=TRUE()),--('Patent Portfolio'!X3:X22="Yes"))/COUNTIF('Bundle Assignment'!AA3:AA22,TRUE()),0) -> 0.83333333 | G26: =IFERROR(SUMPRODUCT(--('Bundle Assignment'!AA3:AA22=TRUE()),--('Patent Portfolio'!T3:T22="Yes"))/COUNTIF('Bundle Assignment'!AA3:AA22,TRUE()),0) -> 1 | H26: =IFERROR(SUMPRODUCT(--('Bundle Assignment'!AA3:AA22=TRUE()),--('Patent Portfolio'!H3:H22>=2))/COUNTIF('Bundle Assignment'!AA3:AA22,TRUE()),0) -> 0.33333333 | I26: =SUMPRODUCT(--('Bundle Assignment'!AA3:AA22=TRUE()),--('Patent Portfolio'!L3:L22=3)) -> 1 | J26: =IF(C26<2,"WEAK",IF(AND(C26>=4,D26>=2,E26>=10),"STRONG","MODERATE")) -> MODERATE | K26: =IFERROR(aggregate(5,6,'Patent Portfolio'!AC3:AC22/('Bundle Assignment'!AA3:AA22=TRUE())),"") | L26: =IFERROR(SUMPRODUCT(--('Bundle Assignment'!AA3:AA22=TRUE()),--('Patent Portfolio'!AD3:AD22<=1))/COUNTIF('Bundle Assignment'!AA3:AA22,TRUE()),0) -> 0.33333333 | M26: =IFERROR(SUMPRODUCT(--('Bundle Assignment'!AA3:AA22=TRUE()),--('Patent Portfolio'!AK3:AK22<>"None"),--('Patent Portfolio'!AK3:AK22<>""))/COUNTIF('Bundle Assignment'!AA3:AA22,TRUE()),0) -> 0.5 | N26: =IFERROR(SUMPRODUCT(--('Bundle Assignment'!AA3:AA22=TRUE()),--('Patent Portfolio'!AI3:AI22="Survived"))/COUNTIF('Bundle Assignment'!AA3:AA22,TRUE()),0) -> 0.16666667 | O26: =IFERROR(SUMPRODUCT(--('Bundle Assignment'!AA3:AA22=TRUE()),--('Patent Portfolio'!T3:T22="Yes"))/COUNTIF('Bundle Assignment'!AA3:AA22,TRUE()),0) -> 1
A27: 26 | B27: EoU-Backed / Litigation-Ready | C27: =COUNTIF('Bundle Assignment'!AB3:AB22,TRUE()) -> 7 | D27: =IFERROR(SUMPRODUCT(--('Bundle Assignment'!AB3:AB22=TRUE()),('Patent Portfolio'!O3:O22+'Patent Portfolio'!P3:P22)/2)/COUNTIF('Bundle Assignment'!AB3:AB22,TRUE()),0) -> 1.8571429 | E27: =IFERROR(SUMPRODUCT(--('Bundle Assignment'!AB3:AB22=TRUE()),'Patent Portfolio'!U3:U22)/COUNTIF('Bundle Assignment'!AB3:AB22,TRUE()),0) -> 12.857143 | F27: =IFERROR(SUMPRODUCT(--('Bundle Assignment'!AB3:AB22=TRUE()),--('Patent Portfolio'!X3:X22="Yes"))/COUNTIF('Bundle Assignment'!AB3:AB22,TRUE()),0) -> 1 | G27: =IFERROR(SUMPRODUCT(--('Bundle Assignment'!AB3:AB22=TRUE()),--('Patent Portfolio'!T3:T22="Yes"))/COUNTIF('Bundle Assignment'!AB3:AB22,TRUE()),0) -> 0.42857143 | H27: =IFERROR(SUMPRODUCT(--('Bundle Assignment'!AB3:AB22=TRUE()),--('Patent Portfolio'!H3:H22>=2))/COUNTIF('Bundle Assignment'!AB3:AB22,TRUE()),0) -> 0.42857143 | I27: =SUMPRODUCT(--('Bundle Assignment'!AB3:AB22=TRUE()),--('Patent Portfolio'!L3:L22=3)) -> 1 | J27: =IF(C27<2,"WEAK",IF(AND(C27>=4,D27>=2,E27>=10),"STRONG","MODERATE")) -> MODERATE | K27: =IFERROR(aggregate(5,6,'Patent Portfolio'!AC3:AC22/('Bundle Assignment'!AB3:AB22=TRUE())),"") | L27: =IFERROR(SUMPRODUCT(--('Bundle Assignment'!AB3:AB22=TRUE()),--('Patent Portfolio'!AD3:AD22<=1))/COUNTIF('Bundle Assignment'!AB3:AB22,TRUE()),0) -> 0.14285714 | M27: =IFERROR(SUMPRODUCT(--('Bundle Assignment'!AB3:AB22=TRUE()),--('Patent Portfolio'!AK3:AK22<>"None"),--('Patent Portfolio'!AK3:AK22<>""))/COUNTIF('Bundle Assignment'!AB3:AB22,TRUE()),0) -> 1 | N27: =IFERROR(SUMPRODUCT(--('Bundle Assignment'!AB3:AB22=TRUE()),--('Patent Portfolio'!AI3:AI22="Survived"))/COUNTIF('Bundle Assignment'!AB3:AB22,TRUE()),0) -> 0.28571429 | O27: =IFERROR(SUMPRODUCT(--('Bundle Assignment'!AB3:AB22=TRUE()),--('Patent Portfolio'!T3:T22="Yes"))/COUNTIF('Bundle Assignment'!AB3:AB22,TRUE()),0) -> 0.42857143
A28: 27 | B28: Survived-Challenge / Battle-Tested | C28: =COUNTIF('Bundle Assignment'!AC3:AC22,TRUE()) -> 2 | D28: =IFERROR(SUMPRODUCT(--('Bundle Assignment'!AC3:AC22=TRUE()),('Patent Portfolio'!O3:O22+'Patent Portfolio'!P3:P22)/2)/COUNTIF('Bundle Assignment'!AC3:AC22,TRUE()),0) -> 2.5 | E28: =IFERROR(SUMPRODUCT(--('Bundle Assignment'!AC3:AC22=TRUE()),'Patent Portfolio'!U3:U22)/COUNTIF('Bundle Assignment'!AC3:AC22,TRUE()),0) -> 11.5 | F28: =IFERROR(SUMPRODUCT(--('Bundle Assignment'!AC3:AC22=TRUE()),--('Patent Portfolio'!X3:X22="Yes"))/COUNTIF('Bundle Assignment'!AC3:AC22,TRUE()),0) -> 1 | G28: =IFERROR(SUMPRODUCT(--('Bundle Assignment'!AC3:AC22=TRUE()),--('Patent Portfolio'!T3:T22="Yes"))/COUNTIF('Bundle Assignment'!AC3:AC22,TRUE()),0) -> 0.5 | H28: =IFERROR(SUMPRODUCT(--('Bundle Assignment'!AC3:AC22=TRUE()),--('Patent Portfolio'!H3:H22>=2))/COUNTIF('Bundle Assignment'!AC3:AC22,TRUE()),0) -> 1 | I28: =SUMPRODUCT(--('Bundle Assignment'!AC3:AC22=TRUE()),--('Patent Portfolio'!L3:L22=3)) -> 0 | J28: =IF(C28<2,"WEAK",IF(AND(C28>=4,D28>=2,E28>=10),"STRONG","MODERATE")) -> MODERATE | K28: =IFERROR(aggregate(5,6,'Patent Portfolio'!AC3:AC22/('Bundle Assignment'!AC3:AC22=TRUE())),"") | L28: =IFERROR(SUMPRODUCT(--('Bundle Assignment'!AC3:AC22=TRUE()),--('Patent Portfolio'!AD3:AD22<=1))/COUNTIF('Bundle Assignment'!AC3:AC22,TRUE()),0) -> 0 | M28: =IFERROR(SUMPRODUCT(--('Bundle Assignment'!AC3:AC22=TRUE()),--('Patent Portfolio'!AK3:AK22<>"None"),--('Patent Portfolio'!AK3:AK22<>""))/COUNTIF('Bundle Assignment'!AC3:AC22,TRUE()),0) -> 1 | N28: =IFERROR(SUMPRODUCT(--('Bundle Assignment'!AC3:AC22=TRUE()),--('Patent Portfolio'!AI3:AI22="Survived"))/COUNTIF('Bundle Assignment'!AC3:AC22,TRUE()),0) -> 1 | O28: =IFERROR(SUMPRODUCT(--('Bundle Assignment'!AC3:AC22=TRUE()),--('Patent Portfolio'!T3:T22="Yes"))/COUNTIF('Bundle Assignment'!AC3:AC22,TRUE()),0) -> 0.5
A29: 28 | B29: Clean-Chain-of-Title | C29: =COUNTIF('Bundle Assignment'!AD3:AD22,TRUE()) -> 9 | D29: =IFERROR(SUMPRODUCT(--('Bundle Assignment'!AD3:AD22=TRUE()),('Patent Portfolio'!O3:O22+'Patent Portfolio'!P3:P22)/2)/COUNTIF('Bundle Assignment'!AD3:AD22,TRUE()),0) -> 1.5555556 | E29: =IFERROR(SUMPRODUCT(--('Bundle Assignment'!AD3:AD22=TRUE()),'Patent Portfolio'!U3:U22)/COUNTIF('Bundle Assignment'!AD3:AD22,TRUE()),0) -> 14.111111 | F29: =IFERROR(SUMPRODUCT(--('Bundle Assignment'!AD3:AD22=TRUE()),--('Patent Portfolio'!X3:X22="Yes"))/COUNTIF('Bundle Assignment'!AD3:AD22,TRUE()),0) -> 0.88888889 | G29: =IFERROR(SUMPRODUCT(--('Bundle Assignment'!AD3:AD22=TRUE()),--('Patent Portfolio'!T3:T22="Yes"))/COUNTIF('Bundle Assignment'!AD3:AD22,TRUE()),0) -> 0.66666667 | H29: =IFERROR(SUMPRODUCT(--('Bundle Assignment'!AD3:AD22=TRUE()),--('Patent Portfolio'!H3:H22>=2))/COUNTIF('Bundle Assignment'!AD3:AD22,TRUE()),0) -> 0.44444444 | I29: =SUMPRODUCT(--('Bundle Assignment'!AD3:AD22=TRUE()),--('Patent Portfolio'!L3:L22=3)) -> 1 | J29: =IF(C29<2,"WEAK",IF(AND(C29>=4,D29>=2,E29>=10),"STRONG","MODERATE")) -> MODERATE | K29: =IFERROR(aggregate(5,6,'Patent Portfolio'!AC3:AC22/('Bundle Assignment'!AD3:AD22=TRUE())),"") | L29: =IFERROR(SUMPRODUCT(--('Bundle Assignment'!AD3:AD22=TRUE()),--('Patent Portfolio'!AD3:AD22<=1))/COUNTIF('Bundle Assignment'!AD3:AD22,TRUE()),0) -> 0.22222222 | M29: =IFERROR(SUMPRODUCT(--('Bundle Assignment'!AD3:AD22=TRUE()),--('Patent Portfolio'!AK3:AK22<>"None"),--('Patent Portfolio'!AK3:AK22<>""))/COUNTIF('Bundle Assignment'!AD3:AD22,TRUE()),0) -> 0.66666667 | N29: =IFERROR(SUMPRODUCT(--('Bundle Assignment'!AD3:AD22=TRUE()),--('Patent Portfolio'!AI3:AI22="Survived"))/COUNTIF('Bundle Assignment'!AD3:AD22,TRUE()),0) -> 0.22222222 | O29: =IFERROR(SUMPRODUCT(--('Bundle Assignment'!AD3:AD22=TRUE()),--('Patent Portfolio'!T3:T22="Yes"))/COUNTIF('Bundle Assignment'!AD3:AD22,TRUE()),0) -> 0.66666667
A30: 29 | B30: High-Citation / Technical-Influence | C30: =COUNTIF('Bundle Assignment'!AE3:AE22,TRUE()) -> 8 | D30: =IFERROR(SUMPRODUCT(--('Bundle Assignment'!AE3:AE22=TRUE()),('Patent Portfolio'!O3:O22+'Patent Portfolio'!P3:P22)/2)/COUNTIF('Bundle Assignment'!AE3:AE22,TRUE()),0) -> 1.6875 | E30: =IFERROR(SUMPRODUCT(--('Bundle Assignment'!AE3:AE22=TRUE()),'Patent Portfolio'!U3:U22)/COUNTIF('Bundle Assignment'!AE3:AE22,TRUE()),0) -> 12.875 | F30: =IFERROR(SUMPRODUCT(--('Bundle Assignment'!AE3:AE22=TRUE()),--('Patent Portfolio'!X3:X22="Yes"))/COUNTIF('Bundle Assignment'!AE3:AE22,TRUE()),0) -> 1 | G30: =IFERROR(SUMPRODUCT(--('Bundle Assignment'!AE3:AE22=TRUE()),--('Patent Portfolio'!T3:T22="Yes"))/COUNTIF('Bundle Assignment'!AE3:AE22,TRUE()),0) -> 0.5 | H30: =IFERROR(SUMPRODUCT(--('Bundle Assignment'!AE3:AE22=TRUE()),--('Patent Portfolio'!H3:H22>=2))/COUNTIF('Bundle Assignment'!AE3:AE22,TRUE()),0) -> 0.375 | I30: =SUMPRODUCT(--('Bundle Assignment'!AE3:AE22=TRUE()),--('Patent Portfolio'!L3:L22=3)) -> 1 | J30: =IF(C30<2,"WEAK",IF(AND(C30>=4,D30>=2,E30>=10),"STRONG","MODERATE")) -> MODERATE | K30: =IFERROR(aggregate(5,6,'Patent Portfolio'!AC3:AC22/('Bundle Assignment'!AE3:AE22=TRUE())),"") | L30: =IFERROR(SUMPRODUCT(--('Bundle Assignment'!AE3:AE22=TRUE()),--('Patent Portfolio'!AD3:AD22<=1))/COUNTIF('Bundle Assignment'!AE3:AE22,TRUE()),0) -> 0.125 | M30: =IFERROR(SUMPRODUCT(--('Bundle Assignment'!AE3:AE22=TRUE()),--('Patent Portfolio'!AK3:AK22<>"None"),--('Patent Portfolio'!AK3:AK22<>""))/COUNTIF('Bundle Assignment'!AE3:AE22,TRUE()),0) -> 0.875 | N30: =IFERROR(SUMPRODUCT(--('Bundle Assignment'!AE3:AE22=TRUE()),--('Patent Portfolio'!AI3:AI22="Survived"))/COUNTIF('Bundle Assignment'!AE3:AE22,TRUE()),0) -> 0.25 | O30: =IFERROR(SUMPRODUCT(--('Bundle Assignment'!AE3:AE22=TRUE()),--('Patent Portfolio'!T3:T22="Yes"))/COUNTIF('Bundle Assignment'!AE3:AE22,TRUE()),0) -> 0.5
A31: 30 | B31: Adjacent-Industry Re-Read | C31: =COUNTIF('Bundle Assignment'!AF3:AF22,TRUE()) -> 9 | D31: =IFERROR(SUMPRODUCT(--('Bundle Assignment'!AF3:AF22=TRUE()),('Patent Portfolio'!O3:O22+'Patent Portfolio'!P3:P22)/2)/COUNTIF('Bundle Assignment'!AF3:AF22,TRUE()),0) -> 1.6666667 | E31: =IFERROR(SUMPRODUCT(--('Bundle Assignment'!AF3:AF22=TRUE()),'Patent Portfolio'!U3:U22)/COUNTIF('Bundle Assignment'!AF3:AF22,TRUE()),0) -> 13.111111 | F31: =IFERROR(SUMPRODUCT(--('Bundle Assignment'!AF3:AF22=TRUE()),--('Patent Portfolio'!X3:X22="Yes"))/COUNTIF('Bundle Assignment'!AF3:AF22,TRUE()),0) -> 0.77777778 | G31: =IFERROR(SUMPRODUCT(--('Bundle Assignment'!AF3:AF22=TRUE()),--('Patent Portfolio'!T3:T22="Yes"))/COUNTIF('Bundle Assignment'!AF3:AF22,TRUE()),0) -> 0.44444444 | H31: =IFERROR(SUMPRODUCT(--('Bundle Assignment'!AF3:AF22=TRUE()),--('Patent Portfolio'!H3:H22>=2))/COUNTIF('Bundle Assignment'!AF3:AF22,TRUE()),0) -> 0.22222222 | I31: =SUMPRODUCT(--('Bundle Assignment'!AF3:AF22=TRUE()),--('Patent Portfolio'!L3:L22=3)) -> 1 | J31: =IF(C31<2,"WEAK",IF(AND(C31>=4,D31>=2,E31>=10),"STRONG","MODERATE")) -> MODERATE | K31: =IFERROR(aggregate(5,6,'Patent Portfolio'!AC3:AC22/('Bundle Assignment'!AF3:AF22=TRUE())),"") | L31: =IFERROR(SUMPRODUCT(--('Bundle Assignment'!AF3:AF22=TRUE()),--('Patent Portfolio'!AD3:AD22<=1))/COUNTIF('Bundle Assignment'!AF3:AF22,TRUE()),0) -> 0.33333333 | M31: =IFERROR(SUMPRODUCT(--('Bundle Assignment'!AF3:AF22=TRUE()),--('Patent Portfolio'!AK3:AK22<>"None"),--('Patent Portfolio'!AK3:AK22<>""))/COUNTIF('Bundle Assignment'!AF3:AF22,TRUE()),0) -> 0.55555556 | N31: =IFERROR(SUMPRODUCT(--('Bundle Assignment'!AF3:AF22=TRUE()),--('Patent Portfolio'!AI3:AI22="Survived"))/COUNTIF('Bundle Assignment'!AF3:AF22,TRUE()),0) -> 0.11111111 | O31: =IFERROR(SUMPRODUCT(--('Bundle Assignment'!AF3:AF22=TRUE()),--('Patent Portfolio'!T3:T22="Yes"))/COUNTIF('Bundle Assignment'!AF3:AF22,TRUE()),0) -> 0.44444444
A32: 31 | B32: Salvage / Defensive-Volume Lot | C32: =COUNTIF('Bundle Assignment'!AG3:AG22,TRUE()) -> 11 | D32: =IFERROR(SUMPRODUCT(--('Bundle Assignment'!AG3:AG22=TRUE()),('Patent Portfolio'!O3:O22+'Patent Portfolio'!P3:P22)/2)/COUNTIF('Bundle Assignment'!AG3:AG22,TRUE()),0) -> 0.31818182 | E32: =IFERROR(SUMPRODUCT(--('Bundle Assignment'!AG3:AG22=TRUE()),'Patent Portfolio'!U3:U22)/COUNTIF('Bundle Assignment'!AG3:AG22,TRUE()),0) -> 3.8181818 | F32: =IFERROR(SUMPRODUCT(--('Bundle Assignment'!AG3:AG22=TRUE()),--('Patent Portfolio'!X3:X22="Yes"))/COUNTIF('Bundle Assignment'!AG3:AG22,TRUE()),0) -> 0.090909091 | G32: =IFERROR(SUMPRODUCT(--('Bundle Assignment'!AG3:AG22=TRUE()),--('Patent Portfolio'!T3:T22="Yes"))/COUNTIF('Bundle Assignment'!AG3:AG22,TRUE()),0) -> 0.18181818 | H32: =IFERROR(SUMPRODUCT(--('Bundle Assignment'!AG3:AG22=TRUE()),--('Patent Portfolio'!H3:H22>=2))/COUNTIF('Bundle Assignment'!AG3:AG22,TRUE()),0) -> 0 | I32: =SUMPRODUCT(--('Bundle Assignment'!AG3:AG22=TRUE()),--('Patent Portfolio'!L3:L22=3)) -> 0 | J32: =IF(C32<2,"WEAK",IF(AND(C32>=4,D32>=2,E32>=10),"STRONG","MODERATE")) -> MODERATE | K32: =IFERROR(aggregate(5,6,'Patent Portfolio'!AC3:AC22/('Bundle Assignment'!AG3:AG22=TRUE())),"") | L32: =IFERROR(SUMPRODUCT(--('Bundle Assignment'!AG3:AG22=TRUE()),--('Patent Portfolio'!AD3:AD22<=1))/COUNTIF('Bundle Assignment'!AG3:AG22,TRUE()),0) -> 1 | M32: =IFERROR(SUMPRODUCT(--('Bundle Assignment'!AG3:AG22=TRUE()),--('Patent Portfolio'!AK3:AK22<>"None"),--('Patent Portfolio'!AK3:AK22<>""))/COUNTIF('Bundle Assignment'!AG3:AG22,TRUE()),0) -> 0.090909091 | N32: =IFERROR(SUMPRODUCT(--('Bundle Assignment'!AG3:AG22=TRUE()),--('Patent Portfolio'!AI3:AI22="Survived"))/COUNTIF('Bundle Assignment'!AG3:AG22,TRUE()),0) -> 0 | O32: =IFERROR(SUMPRODUCT(--('Bundle Assignment'!AG3:AG22=TRUE()),--('Patent Portfolio'!T3:T22="Yes"))/COUNTIF('Bundle Assignment'!AG3:AG22,TRUE()),0) -> 0.18181818
A33: 32 | B33: Pre-Expiry / Last-Window | C33: =COUNTIF('Bundle Assignment'!AH3:AH22,TRUE()) -> 0 | D33: =IFERROR(SUMPRODUCT(--('Bundle Assignment'!AH3:AH22=TRUE()),('Patent Portfolio'!O3:O22+'Patent Portfolio'!P3:P22)/2)/COUNTIF('Bundle Assignment'!AH3:AH22,TRUE()),0) -> 0 | E33: =IFERROR(SUMPRODUCT(--('Bundle Assignment'!AH3:AH22=TRUE()),'Patent Portfolio'!U3:U22)/COUNTIF('Bundle Assignment'!AH3:AH22,TRUE()),0) -> 0 | F33: =IFERROR(SUMPRODUCT(--('Bundle Assignment'!AH3:AH22=TRUE()),--('Patent Portfolio'!X3:X22="Yes"))/COUNTIF('Bundle Assignment'!AH3:AH22,TRUE()),0) -> 0 | G33: =IFERROR(SUMPRODUCT(--('Bundle Assignment'!AH3:AH22=TRUE()),--('Patent Portfolio'!T3:T22="Yes"))/COUNTIF('Bundle Assignment'!AH3:AH22,TRUE()),0) -> 0 | H33: =IFERROR(SUMPRODUCT(--('Bundle Assignment'!AH3:AH22=TRUE()),--('Patent Portfolio'!H3:H22>=2))/COUNTIF('Bundle Assignment'!AH3:AH22,TRUE()),0) -> 0 | I33: =SUMPRODUCT(--('Bundle Assignment'!AH3:AH22=TRUE()),--('Patent Portfolio'!L3:L22=3)) -> 0 | J33: =IF(C33<2,"WEAK",IF(AND(C33>=4,D33>=2,E33>=10),"STRONG","MODERATE")) -> WEAK | K33: =IFERROR(aggregate(5,6,'Patent Portfolio'!AC3:AC22/('Bundle Assignment'!AH3:AH22=TRUE())),"") | L33: =IFERROR(SUMPRODUCT(--('Bundle Assignment'!AH3:AH22=TRUE()),--('Patent Portfolio'!AD3:AD22<=1))/COUNTIF('Bundle Assignment'!AH3:AH22,TRUE()),0) -> 0 | M33: =IFERROR(SUMPRODUCT(--('Bundle Assignment'!AH3:AH22=TRUE()),--('Patent Portfolio'!AK3:AK22<>"None"),--('Patent Portfolio'!AK3:AK22<>""))/COUNTIF('Bundle Assignment'!AH3:AH22,TRUE()),0) -> 0 | N33: =IFERROR(SUMPRODUCT(--('Bundle Assignment'!AH3:AH22=TRUE()),--('Patent Portfolio'!AI3:AI22="Survived"))/COUNTIF('Bundle Assignment'!AH3:AH22,TRUE()),0) -> 0 | O33: =IFERROR(SUMPRODUCT(--('Bundle Assignment'!AH3:AH22=TRUE()),--('Patent Portfolio'!T3:T22="Yes"))/COUNTIF('Bundle Assignment'!AH3:AH22,TRUE()),0) -> 0
A34: 33 | B34: Provenance-Coherent | C34: =COUNTIF('Bundle Assignment'!AI3:AI22,TRUE()) -> 12 | D34: =IFERROR(SUMPRODUCT(--('Bundle Assignment'!AI3:AI22=TRUE()),('Patent Portfolio'!O3:O22+'Patent Portfolio'!P3:P22)/2)/COUNTIF('Bundle Assignment'!AI3:AI22,TRUE()),0) -> 1.5833333 | E34: =IFERROR(SUMPRODUCT(--('Bundle Assignment'!AI3:AI22=TRUE()),'Patent Portfolio'!U3:U22)/COUNTIF('Bundle Assignment'!AI3:AI22,TRUE()),0) -> 13.166667 | F34: =IFERROR(SUMPRODUCT(--('Bundle Assignment'!AI3:AI22=TRUE()),--('Patent Portfolio'!X3:X22="Yes"))/COUNTIF('Bundle Assignment'!AI3:AI22,TRUE()),0) -> 0.83333333 | G34: =IFERROR(SUMPRODUCT(--('Bundle Assignment'!AI3:AI22=TRUE()),--('Patent Portfolio'!T3:T22="Yes"))/COUNTIF('Bundle Assignment'!AI3:AI22,TRUE()),0) -> 0.5 | H34: =IFERROR(SUMPRODUCT(--('Bundle Assignment'!AI3:AI22=TRUE()),--('Patent Portfolio'!H3:H22>=2))/COUNTIF('Bundle Assignment'!AI3:AI22,TRUE()),0) -> 0.33333333 | I34: =SUMPRODUCT(--('Bundle Assignment'!AI3:AI22=TRUE()),--('Patent Portfolio'!L3:L22=3)) -> 1 | J34: =IF(C34<2,"WEAK",IF(AND(C34>=4,D34>=2,E34>=10),"STRONG","MODERATE")) -> MODERATE | K34: =IFERROR(aggregate(5,6,'Patent Portfolio'!AC3:AC22/('Bundle Assignment'!AI3:AI22=TRUE())),"") | L34: =IFERROR(SUMPRODUCT(--('Bundle Assignment'!AI3:AI22=TRUE()),--('Patent Portfolio'!AD3:AD22<=1))/COUNTIF('Bundle Assignment'!AI3:AI22,TRUE()),0) -> 0.25 | M34: =IFERROR(SUMPRODUCT(--('Bundle Assignment'!AI3:AI22=TRUE()),--('Patent Portfolio'!AK3:AK22<>"None"),--('Patent Portfolio'!AK3:AK22<>""))/COUNTIF('Bundle Assignment'!AI3:AI22,TRUE()),0) -> 0.58333333 | N34: =IFERROR(SUMPRODUCT(--('Bundle Assignment'!AI3:AI22=TRUE()),--('Patent Portfolio'!AI3:AI22="Survived"))/COUNTIF('Bundle Assignment'!AI3:AI22,TRUE()),0) -> 0.16666667 | O34: =IFERROR(SUMPRODUCT(--('Bundle Assignment'!AI3:AI22=TRUE()),--('Patent Portfolio'!T3:T22="Yes"))/COUNTIF('Bundle Assignment'!AI3:AI22,TRUE()),0) -> 0.5

Sheet Sample Bundles
A1: BUNDLE A — 5G Wireless PHY SEP Cluster
A2: Value proposition: | B2: Buyer gets standards-relevant assets that any 5G NR implementer must license or design around. High enforcement leverage from teardown-detectable hardware claims, trilateral coverage, and one family with active continuation for claim shaping.
A3: Routing rule: | B3: B1 ≥ 2 AND share B2 = "3GPP 5G NR". (Bundle Rule #2 — Standard-Essential.)
A5: Patent ID | B5: Title | C5: A1 Domain | D5: B2 Standard / G2 Gen. | E5: E4 Term (yrs) | F5: F2 Trilateral
A6: P-001 | B6: Beamforming pilot signaling for 5G NR | C6: Wireless PHY | D6: 3GPP 5G NR | E6: 14 | F6: Yes
A7: P-002 | B7: Polar code decoder architecture | C7: Wireless PHY | D7: 3GPP 5G NR | E7: 13 | F7: Yes
A10: BUNDLE B — Electric Vehicle Powertrain Stack
A11: Value proposition: | B11: "Build-an-EV-powertrain" kit covering battery cell chemistry, pack-level thermal management, and traction inverter control. Cross-subsystem coverage across one product architecture; valuable to an EV OEM, Tier-1 supplier, or cell maker wanting end-to-end FTO.
A12: Routing rule: | B12: Patents collectively span ≥ 3 distinct A4 subsystems of the EV product family. (Bundle Rule #3 — Product Architecture.)
A14: Patent ID | B14: Title | C14: A1 Domain | D14: B2 Standard / G2 Gen. | E14: E4 Term (yrs) | F14: F2 Trilateral
A15: P-004 | B15: Solid-state electrolyte composition for EV batteries | C15: Battery materials | D15: Next-gen | E15: 17 | F15: Yes
A16: P-005 | B16: Battery thermal management with phase-change material | C16: Thermal mgmt | D16: Current | E16: 11 | F16: Yes
A17: P-006 | B17: SiC MOSFET inverter control method | C17: Power electronics | D17: Current | E17: 12 | F17: Yes
A20: BUNDLE C — Edge AI / Computer Vision Convergence
A21: Value proposition: | B21: Thematic bundle aligned with the edge-AI investment narrative. Spans algorithmic optimization (quantization, attention pruning) and applied robotics (visual SLAM). Implementation-agnostic methods deployable across smart cameras, robotics, AR/VR, and on-device inference products.
A22: Routing rule: | B22: Patents share G1 convergence theme tag (Edge AI). (Bundle Rule #18 — Convergent / Emerging Theme.)
A24: Patent ID | B24: Title | C24: A1 Domain | D24: B2 Standard / G2 Gen. | E24: E4 Term (yrs) | F24: F2 Trilateral
A25: P-007 | B25: On-device CNN quantization for low-power inference | C25: CV algorithm | D25: Current | E25: 15 | F25: Yes
A26: P-008 | B26: Transformer attention pruning for vision models | C26: CV algorithm | D26: Next-gen | E26: 19 | F26: No
A27: P-009 | B27: Visual SLAM for indoor robot navigation | C27: Robotics SW | D27: Current | E27: 10 | F27: Yes

Sheet Bundle Composition Strategy
A1: BUNDLE COMPOSITION STRATEGIES
A2: Compositional approaches that sit on top of the 33 bundle types — how to construct, position, and price bundles for a mixed-quality portfolio.
A4: 1. TIERED STRUCTURE (Premium / Standard / Lot)
A5: For each technology domain, build three tiers from the same patent pool:
A6: • Premium tier: only patents with H1≥2 AND avg detectability≥2 AND F2=Yes AND E4≥10. Marketed individually with full claim charts.
A7: • Standard tier: mixed quality, used for thematic / use-case bundles. The workhorses.
A8: • Lot tier: weak, narrow, near-expiry, or unclassified patents — sold as defensive-volume lots.
A9: Value of tiering: isolates strong assets so weak ones do not drag the premium narrative down. Each tier has a distinct buyer profile.
A11: 2. ANCHOR-FIRST BUNDLING
A12: Identify the top 5-10 strongest patents (H1=3, C2≥2, D2≥2). Build each bundle AROUND one anchor; surround it with related supporting patents.
A13: Every bundle must have a "lead patent" the buyer can latch onto. Bundles without an anchor are restructured or moved to the salvage lot.
A15: 3. STORYLINE BUNDLING
... A63: • Is the buyer profile clear? Operating company, NPE, or defensive aggregator — write to that audience.
