Workbook

Sheet README
A1: PATENT PORTFOLIO BUNDLING TEMPLATE
A2: A technical-attribute-based framework for grouping patents into sellable bundles
A4: PURPOSE
A5: Score each patent across technical attributes, then auto-route patents into one or more sellable bundle types based on logical rules. The framework is purely technical — no valuation, no pricing.
A7: SHEETS IN THIS WORKBOOK
A8: 1. README — This page. Overview and instructions.
A9: 2. Attribute Dictionary — Definitions and scoring scales for every attribute.
A10: 3. Patent Portfolio — Master data sheet. One row per patent. Fill this in.
A11: 4. Bundle Rules — The 21 bundle types and the routing rule that qualifies a patent for each.
A12: 5. Bundle Assignment — Auto-computed: which bundles each patent qualifies for.
A13: 6. Bundle Quality Scorecard — Auto-computed: quality indicators per bundle.
A14: 7. Sample Bundles — Worked examples showing how three bundles look in practice.
... A61: Use this sheet as the long-form reference. Keep using the Attribute Dictionary for quick scale/values lookups while entering data on the Patent Portfolio sheet.

Sheet Configuration
A1: CONFIGURATION
A2: Pick a preset, or switch to Edit Mode to override individual values. All Bundle Assignment and Scorecard formulas read from this sheet.
A4: Active Preset: | B4: All ON (default) | E4: ← Pick from Presets sheet. Changing this updates all Active Values below.
A5: Edit Mode: | B5: No | E5: ← Yes = use Manual Override column. No = use selected preset.
A6: Summary: | B6: ="Bundles active: "&COUNTIF(C10:C42,"Yes")&" of 33 | Gates active: "&COUNTIF(C63:C67,"Yes")&" of 5 | "&IF($B$5="Yes","EDIT MODE — using Manual Override values","Using preset: "&$B$4) -> Bundles active: 33 of 33 | Gates active: 5 of 5 | Using preset: All ON (default)
A8: Parameter | B8: Description | C8: Active Value (use this in formulas) | D8: From Preset | E8: Manual Override
A9: BUNDLE TOGGLES (Yes = bundle is active in this analysis)
A10: B1_enabled | B10: Bundle 1 — Tech Domain | C10: =IF($B$5="Yes",E10,D10) -> Yes | D10: =INDEX(Presets!$C$4:$L$4,MATCH($B$4,Presets!$C$1:$L$1,0)) -> Yes | E10: Yes
A11: B2_enabled | B11: Bundle 2 — SEP | C11: =IF($B$5="Yes",E11,D11) -> Yes | D11: =INDEX(Presets!$C$5:$L$5,MATCH($B$4,Presets!$C$1:$L$1,0)) -> Yes | E11: Yes
A12: B3_enabled | B12: Bundle 3 — Product Architecture | C12: =IF($B$5="Yes",E12,D12) -> Yes | D12: =INDEX(Presets!$C$6:$L$6,MATCH($B$4,Presets!$C$1:$L$1,0)) -> Yes | E12: Yes
A13: B4_enabled | B13: Bundle 4 — Stack Layer | C13: =IF($B$5="Yes",E13,D13) -> Yes | D13: =INDEX(Presets!$C$7:$L$7,MATCH($B$4,Presets!$C$1:$L$1,0)) -> Yes | E13: Yes
A14: B5_enabled | B14: Bundle 5 — Use-Case | C14: =IF($B$5="Yes",E14,D14) -> Yes | D14: =INDEX(Presets!$C$8:$L$8,MATCH($B$4,Presets!$C$1:$L$1,0)) -> Yes | E14: Yes
A15: B6_enabled | B15: Bundle 6 — Manufacturing / Process | C15: =IF($B$5="Yes",E15,D15) -> Yes | D15: =INDEX(Presets!$C$9:$L$9,MATCH($B$4,Presets!$C$1:$L$1,0)) -> Yes | E15: Yes
A16: B7_enabled | B16: Bundle 7 — Materials & Chemistry | C16: =IF($B$5="Yes",E16,D16) -> Yes | D16: =INDEX(Presets!$C$10:$L$10,MATCH($B$4,Presets!$C$1:$L$1,0)) -> Yes | E16: Yes
A17: B8_enabled | B17: Bundle 8 — Algorithm / Software | C17: =IF($B$5="Yes",E17,D17) -> Yes | D17: =INDEX(Presets!$C$11:$L$11,MATCH($B$4,Presets!$C$1:$L$1,0)) -> Yes | E17: Yes
A18: B9_enabled | B18: Bundle 9 — Interoperability | C18: =IF($B$5="Yes",E18,D18) -> Yes | D18: =INDEX(Presets!$C$12:$L$12,MATCH($B$4,Presets!$C$1:$L$1,0)) -> Yes | E18: Yes
A19: B10_enabled | B19: Bundle 10 — Generational Roadmap | C19: =IF($B$5="Yes",E19,D19) -> Yes | D19: =INDEX(Presets!$C$13:$L$13,MATCH($B$4,Presets!$C$1:$L$1,0)) -> Yes | E19: Yes
A20: B11_enabled | B20: Bundle 11 — Claim-Type | C20: =IF($B$5="Yes",E20,D20) -> Yes | D20: =INDEX(Presets!$C$14:$L$14,MATCH($B$4,Presets!$C$1:$L$1,0)) -> Yes | E20: Yes
A21: B12_enabled | B21: Bundle 12 — Detectability | C21: =IF($B$5="Yes",E21,D21) -> Yes | D21: =INDEX(Presets!$C$15:$L$15,MATCH($B$4,Presets!$C$1:$L$1,0)) -> Yes | E21: Yes
A22: B13_enabled | B22: Bundle 13 — Geographic | C22: =IF($B$5="Yes",E22,D22) -> Yes | D22: =INDEX(Presets!$C$16:$L$16,MATCH($B$4,Presets!$C$1:$L$1,0)) -> Yes | E22: Yes
A23: B14_enabled | B23: Bundle 14 — Family-Tree | C23: =IF($B$5="Yes",E23,D23) -> Yes | D23: =INDEX(Presets!$C$17:$L$17,MATCH($B$4,Presets!$C$1:$L$1,0)) -> Yes | E23: Yes
A24: B15_enabled | B24: Bundle 15 — Lifecycle / Term | C24: =IF($B$5="Yes",E24,D24) -> Yes | D24: =INDEX(Presets!$C$18:$L$18,MATCH($B$4,Presets!$C$1:$L$1,0)) -> Yes | E24: Yes
A25: B16_enabled | B25: Bundle 16 — Foundational + Improvement | C25: =IF($B$5="Yes",E25,D25) -> Yes | D25: =INDEX(Presets!$C$19:$L$19,MATCH($B$4,Presets!$C$1:$L$1,0)) -> Yes | E25: Yes
A26: B17_enabled | B26: Bundle 17 — Cross-Industry | C26: =IF($B$5="Yes",E26,D26) -> Yes | D26: =INDEX(Presets!$C$20:$L$20,MATCH($B$4,Presets!$C$1:$L$1,0)) -> Yes | E26: Yes
A27: B18_enabled | B27: Bundle 18 — Convergent Theme | C27: =IF($B$5="Yes",E27,D27) -> Yes | D27: =INDEX(Presets!$C$21:$L$21,MATCH($B$4,Presets!$C$1:$L$1,0)) -> Yes | E27: Yes
A28: B19_enabled | B28: Bundle 19 — Defensive / Counter-Assert. | C28: =IF($B$5="Yes",E28,D28) -> Yes | D28: =INDEX(Presets!$C$22:$L$22,MATCH($B$4,Presets!$C$1:$L$1,0)) -> Yes | E28: Yes
A29: B20_enabled | B29: Bundle 20 — Whitespace / Design-Around | C29: =IF($B$5="Yes",E29,D29) -> Yes | D29: =INDEX(Presets!$C$23:$L$23,MATCH($B$4,Presets!$C$1:$L$1,0)) -> Yes | E29: Yes
A30: B21_enabled | B30: Bundle 21 — Prosecution-Status | C30: =IF($B$5="Yes",E30,D30) -> Yes | D30: =INDEX(Presets!$C$24:$L$24,MATCH($B$4,Presets!$C$1:$L$1,0)) -> Yes | E30: Yes
A31: B22_enabled | B31: Bundle 22 — Anchor-and-Halo | C31: =IF($B$5="Yes",E31,D31) -> Yes | D31: =INDEX(Presets!$C$25:$L$25,MATCH($B$4,Presets!$C$1:$L$1,0)) -> Yes | E31: Yes
A32: B23_enabled | B32: Bundle 23 — Picket-Fence | C32: =IF($B$5="Yes",E32,D32) -> Yes | D32: =INDEX(Presets!$C$26:$L$26,MATCH($B$4,Presets!$C$1:$L$1,0)) -> Yes | E32: Yes
A33: B24_enabled | B33: Bundle 24 — Strong-Core + Tail | C33: =IF($B$5="Yes",E33,D33) -> Yes | D33: =INDEX(Presets!$C$27:$L$27,MATCH($B$4,Presets!$C$1:$L$1,0)) -> Yes | E33: Yes
A34: B25_enabled | B34: Bundle 25 — Continuation-Live | C34: =IF($B$5="Yes",E34,D34) -> Yes | D34: =INDEX(Presets!$C$28:$L$28,MATCH($B$4,Presets!$C$1:$L$1,0)) -> Yes | E34: Yes
A35: B26_enabled | B35: Bundle 26 — EoU-Backed | C35: =IF($B$5="Yes",E35,D35) -> Yes | D35: =INDEX(Presets!$C$29:$L$29,MATCH($B$4,Presets!$C$1:$L$1,0)) -> Yes | E35: Yes
A36: B27_enabled | B36: Bundle 27 — Battle-Tested | C36: =IF($B$5="Yes",E36,D36) -> Yes | D36: =INDEX(Presets!$C$30:$L$30,MATCH($B$4,Presets!$C$1:$L$1,0)) -> Yes | E36: Yes
A37: B28_enabled | B37: Bundle 28 — Clean-Title | C37: =IF($B$5="Yes",E37,D37) -> Yes | D37: =INDEX(Presets!$C$31:$L$31,MATCH($B$4,Presets!$C$1:$L$1,0)) -> Yes | E37: Yes
A38: B29_enabled | B38: Bundle 29 — High-Citation | C38: =IF($B$5="Yes",E38,D38) -> Yes | D38: =INDEX(Presets!$C$32:$L$32,MATCH($B$4,Presets!$C$1:$L$1,0)) -> Yes | E38: Yes
A39: B30_enabled | B39: Bundle 30 — Adjacent Re-Read | C39: =IF($B$5="Yes",E39,D39) -> Yes | D39: =INDEX(Presets!$C$33:$L$33,MATCH($B$4,Presets!$C$1:$L$1,0)) -> Yes | E39: Yes
A40: B31_enabled | B40: Bundle 31 — Salvage / Volume Lot | C40: =IF($B$5="Yes",E40,D40) -> Yes | D40: =INDEX(Presets!$C$34:$L$34,MATCH($B$4,Presets!$C$1:$L$1,0)) -> Yes | E40: Yes
A41: B32_enabled | B41: Bundle 32 — Pre-Expiry | C41: =IF($B$5="Yes",E41,D41) -> Yes | D41: =INDEX(Presets!$C$35:$L$35,MATCH($B$4,Presets!$C$1:$L$1,0)) -> Yes | E41: Yes
A42: B33_enabled | B42: Bundle 33 — Provenance-Coherent | C42: =IF($B$5="Yes",E42,D42) -> Yes | D42: =INDEX(Presets!$C$36:$L$36,MATCH($B$4,Presets!$C$1:$L$1,0)) -> Yes | E42: Yes
A43: THRESHOLDS (numeric values referenced in routing rules)
A44: SEP_B1_cutoff | B44: B2 SEP bundle: minimum B1 SEP potential (default 2) | C44: =IF($B$5="Yes",E44,D44) -> 2 | D44: =INDEX(Presets!$C$38:$L$38,MATCH($B$4,Presets!$C$1:$L$1,0)) -> 2 | E44: 2
A45: Interface_B3_cutoff | B45: B9 Interop bundle: minimum B3 interface role (default 2) | C45: =IF($B$5="Yes",E45,D45) -> 2 | D45: =INDEX(Presets!$C$39:$L$39,MATCH($B$4,Presets!$C$1:$L$1,0)) -> 2 | E45: 2
A46: Detect_D1_cutoff | B46: B12 Detectability: D1 external-detect cutoff (default 2) | C46: =IF($B$5="Yes",E46,D46) -> 2 | D46: =INDEX(Presets!$C$40:$L$40,MATCH($B$4,Presets!$C$1:$L$1,0)) -> 2 | E46: 2
A47: Detect_D2_cutoff | B47: B12 Detectability: D2 teardown cutoff (default 2) | C47: =IF($B$5="Yes",E47,D47) -> 2 | D47: =INDEX(Presets!$C$41:$L$41,MATCH($B$4,Presets!$C$1:$L$1,0)) -> 2 | E47: 2
A48: Family_E1_min | B48: B14 Family bundle: minimum E1 family size (default 2) | C48: =IF($B$5="Yes",E48,D48) -> 2 | D48: =INDEX(Presets!$C$42:$L$42,MATCH($B$4,Presets!$C$1:$L$1,0)) -> 2 | E48: 2
A49: CrossIndustry_G3_cutoff | B49: B17 Cross-Industry: minimum G3 cross-industry score (default 2) | C49: =IF($B$5="Yes",E49,D49) -> 2 | D49: =INDEX(Presets!$C$43:$L$43,MATCH($B$4,Presets!$C$1:$L$1,0)) -> 2 | E49: 2
A50: Defensive_D3_cutoff | B50: B19 Defensive: minimum D3 reads-on-products (default 2) | C50: =IF($B$5="Yes",E50,D50) -> 2 | D50: =INDEX(Presets!$C$44:$L$44,MATCH($B$4,Presets!$C$1:$L$1,0)) -> 2 | E50: 2
A51: Whitespace_C4_cutoff | B51: B20 Whitespace: minimum C4 design-around difficulty (default 2) | C51: =IF($B$5="Yes",E51,D51) -> 2 | D51: =INDEX(Presets!$C$45:$L$45,MATCH($B$4,Presets!$C$1:$L$1,0)) -> 2 | E51: 2
A52: Anchor_H1_cutoff | B52: B22 Anchor+Halo: minimum H1 claim strength for anchor (default 2) | C52: =IF($B$5="Yes",E52,D52) -> 2 | D52: =INDEX(Presets!$C$46:$L$46,MATCH($B$4,Presets!$C$1:$L$1,0)) -> 2 | E52: 2
A53: HighCitation_H5_min | B53: B29 High-Citation: minimum H5 forward citations (default 15) | C53: =IF($B$5="Yes",E53,D53) -> 15 | D53: =INDEX(Presets!$C$47:$L$47,MATCH($B$4,Presets!$C$1:$L$1,0)) -> 15 | E53: 15
A54: PreExpiry_min_years | B54: B32 Pre-Expiry: minimum remaining term in years (default 1) | C54: =IF($B$5="Yes",E54,D54) -> 1 | D54: =INDEX(Presets!$C$48:$L$48,MATCH($B$4,Presets!$C$1:$L$1,0)) -> 1 | E54: 1
A55: PreExpiry_max_years | B55: B32 Pre-Expiry: maximum remaining term in years (default 4) | C55: =IF($B$5="Yes",E55,D55) -> 4 | D55: =INDEX(Presets!$C$49:$L$49,MATCH($B$4,Presets!$C$1:$L$1,0)) -> 4 | E55: 4
A56: Salvage_H1_max | B56: B31 Salvage: maximum H1 (default 1) | C56: =IF($B$5="Yes",E56,D56) -> 1 | D56: =INDEX(Presets!$C$50:$L$50,MATCH($B$4,Presets!$C$1:$L$1,0)) -> 1 | E56: 1
A57: Salvage_E4_max | B57: B31 Salvage: maximum remaining term in years (default 5) | C57: =IF($B$5="Yes",E57,D57) -> 5 | D57: =INDEX(Presets!$C$51:$L$51,MATCH($B$4,Presets!$C$1:$L$1,0)) -> 5 | E57: 5
A58: Salvage_H2_max | B58: B31 Salvage: maximum H2 prior-art exposure (default 1) | C58: =IF($B$5="Yes",E58,D58) -> 1 | D58: =INDEX(Presets!$C$52:$L$52,MATCH($B$4,Presets!$C$1:$L$1,0)) -> 1 | E58: 1
A59: Strength_depth_min | B59: Scorecard STRONG flag: minimum coverage depth (default 4) | C59: =IF($B$5="Yes",E59,D59) -> 4 | D59: =INDEX(Presets!$C$53:$L$53,MATCH($B$4,Presets!$C$1:$L$1,0)) -> 4 | E59: 4
A60: Strength_detect_min | B60: Scorecard STRONG flag: minimum avg detectability (default 2) | C60: =IF($B$5="Yes",E60,D60) -> 2 | D60: =INDEX(Presets!$C$54:$L$54,MATCH($B$4,Presets!$C$1:$L$1,0)) -> 2 | E60: 2
A61: Strength_term_min | B61: Scorecard STRONG flag: minimum avg remaining term (default 10) | C61: =IF($B$5="Yes",E61,D61) -> 10 | D61: =INDEX(Presets!$C$55:$L$55,MATCH($B$4,Presets!$C$1:$L$1,0)) -> 10 | E61: 10
A62: QUALITY GATES (Yes = gate column shown on Scorecard)
A63: Gate_WeakestH1 | B63: Show "Weakest H1 in bundle" column | C63: =IF($B$5="Yes",E63,D63) -> Yes | D63: =INDEX(Presets!$C$57:$L$57,MATCH($B$4,Presets!$C$1:$L$1,0)) -> Yes | E63: Yes
A64: Gate_InvalidityExposure | B64: Show "Invalidity exposure %" column | C64: =IF($B$5="Yes",E64,D64) -> Yes | D64: =INDEX(Presets!$C$58:$L$58,MATCH($B$4,Presets!$C$1:$L$1,0)) -> Yes | E64: Yes
A65: Gate_EoUReady | B65: Show "EoU-ready %" column | C65: =IF($B$5="Yes",E65,D65) -> Yes | D65: =INDEX(Presets!$C$59:$L$59,MATCH($B$4,Presets!$C$1:$L$1,0)) -> Yes | E65: Yes
A66: Gate_Survived | B66: Show "Survived %" column | C66: =IF($B$5="Yes",E66,D66) -> Yes | D66: =INDEX(Presets!$C$60:$L$60,MATCH($B$4,Presets!$C$1:$L$1,0)) -> Yes | E66: Yes
A67: Gate_ContOptionality | B67: Show "Continuation-optionality %" column | C67: =IF($B$5="Yes",E67,D67) -> Yes | D67: =INDEX(Presets!$C$61:$L$61,MATCH($B$4,Presets!$C$1:$L$1,0)) -> Yes | E67: Yes

Sheet Presets
A1: Parameter | B1: Description | C1: All ON (default) | D1: NPE / Counter-Assertion | E1: Operating Company / FTO | F1: Defensive Aggregator | G1: Standards Licensee | H1: EV Powertrain Sale | I1: Custom Preset 1 | J1: Custom Preset 2 | K1: Custom Preset 3 | L1: Custom Preset 4
A2: _description | B2: Short description of the preset | C2: Every bundle and gate enabled, all thresholds at default. Baseline view. | D2: Focus on assertion-ready assets: detectability, EoU, survived challenges, defensive reads, salvage lots. | E2: Focus on subsystem coverage, interfaces, claim breadth, continuation optionality. Skips litigation-focused bundles. | F2: Volume-driven: salvage, geographic breadth, claim-type variety, prosecution mix. | G2: Tight focus on standards-essential, interoperability, generational, geographic, battle-tested assets. | H2: EV-focused: subsystems, materials, manufacturing, thermal, generational. Skips wireless/SEP/AI bundles. | I2: (empty — overwrite this column with your own configuration) | J2: (empty — overwrite this column with your own configuration) | K2: (empty — overwrite this column with your own configuration) | L2: (empty — overwrite this column with your own configuration)
A3: BUNDLE TOGGLES (Yes = enabled, No = disabled)
A4: B1_enabled | B4: Bundle 1 — Tech Domain | C4: Yes | D4: No | E4: Yes | F4: Yes | G4: No | H4: Yes | I4: Yes | J4: Yes | K4: Yes | L4: Yes
A5: B2_enabled | B5: Bundle 2 — SEP | C5: Yes | D5: Yes | E5: No | F5: No | G5: Yes | H5: No | I5: Yes | J5: Yes | K5: Yes | L5: Yes
A6: B3_enabled | B6: Bundle 3 — Product Architecture | C6: Yes | D6: No | E6: Yes | F6: No | G6: No | H6: Yes | I6: Yes | J6: Yes | K6: Yes | L6: Yes
A7: B4_enabled | B7: Bundle 4 — Stack Layer | C7: Yes | D7: No | E7: Yes | F7: Yes | G7: No | H7: Yes | I7: Yes | J7: Yes | K7: Yes | L7: Yes
A8: B5_enabled | B8: Bundle 5 — Use-Case | C8: Yes | D8: Yes | E8: Yes | F8: No | G8: No | H8: Yes | I8: Yes | J8: Yes | K8: Yes | L8: Yes
A9: B6_enabled | B9: Bundle 6 — Manufacturing / Process | C9: Yes | D9: No | E9: Yes | F9: No | G9: No | H9: Yes | I9: Yes | J9: Yes | K9: Yes | L9: Yes
A10: B7_enabled | B10: Bundle 7 — Materials & Chemistry | C10: Yes | D10: No | E10: Yes | F10: No | G10: No | H10: Yes | I10: Yes | J10: Yes | K10: Yes | L10: Yes
A11: B8_enabled | B11: Bundle 8 — Algorithm / Software | C11: Yes | D11: No | E11: Yes | F11: No | G11: No | H11: No | I11: Yes | J11: Yes | K11: Yes | L11: Yes
A12: B9_enabled | B12: Bundle 9 — Interoperability | C12: Yes | D12: Yes | E12: Yes | F12: No | G12: Yes | H12: No | I12: Yes | J12: Yes | K12: Yes | L12: Yes
A13: B10_enabled | B13: Bundle 10 — Generational Roadmap | C13: Yes | D13: No | E13: No | F13: Yes | G13: Yes | H13: Yes | I13: Yes | J13: Yes | K13: Yes | L13: Yes
A14: B11_enabled | B14: Bundle 11 — Claim-Type | C14: Yes | D14: Yes | E14: No | F14: Yes | G14: No | H14: No | I14: Yes | J14: Yes | K14: Yes | L14: Yes
A15: B12_enabled | B15: Bundle 12 — Detectability | C15: Yes | D15: Yes | E15: No | F15: No | G15: Yes | H15: No | I15: Yes | J15: Yes | K15: Yes | L15: Yes
... A36: B33_enabled | B36: Bundle 33 — Provenance-Coherent | C36: Yes | D36: No | E36: Yes | F36: No | G36: No | H36: Yes | I36: Yes | J36: Yes | K36: Yes | L36: Yes
A37: THRESHOLDS (numeric values used in routing rules)
A38: SEP_B1_cutoff | B38: B2 SEP bundle: minimum B1 SEP potential (default 2) | C38: 2 | D38: 2 | E38: 2 | F38: 2 | G38: 2 | H38: 2 | I38: 2 | J38: 2 | K38: 2 | L38: 2
A39: Interface_B3_cutoff | B39: B9 Interop bundle: minimum B3 interface role (default 2) | C39: 2 | D39: 2 | E39: 2 | F39: 2 | G39: 2 | H39: 2 | I39: 2 | J39: 2 | K39: 2 | L39: 2
A40: Detect_D1_cutoff | B40: B12 Detectability: D1 external-detect cutoff (default 2) | C40: 2 | D40: 2 | E40: 2 | F40: 2 | G40: 2 | H40: 2 | I40: 2 | J40: 2 | K40: 2 | L40: 2
A41: Detect_D2_cutoff | B41: B12 Detectability: D2 teardown cutoff (default 2) | C41: 2 | D41: 2 | E41: 2 | F41: 2 | G41: 2 | H41: 2 | I41: 2 | J41: 2 | K41: 2 | L41: 2
A42: Family_E1_min | B42: B14 Family bundle: minimum E1 family size (default 2) | C42: 2 | D42: 2 | E42: 3 | F42: 2 | G42: 2 | H42: 2 | I42: 2 | J42: 2 | K42: 2 | L42: 2
A43: CrossIndustry_G3_cutoff | B43: B17 Cross-Industry: minimum G3 cross-industry score (default 2) | C43: 2 | D43: 2 | E43: 2 | F43: 2 | G43: 2 | H43: 2 | I43: 2 | J43: 2 | K43: 2 | L43: 2
A44: Defensive_D3_cutoff | B44: B19 Defensive: minimum D3 reads-on-products (default 2) | C44: 2 | D44: 2 | E44: 2 | F44: 2 | G44: 2 | H44: 2 | I44: 2 | J44: 2 | K44: 2 | L44: 2
A45: Whitespace_C4_cutoff | B45: B20 Whitespace: minimum C4 design-around difficulty (default 2) | C45: 2 | D45: 2 | E45: 2 | F45: 2 | G45: 2 | H45: 2 | I45: 2 | J45: 2 | K45: 2 | L45: 2
A46: Anchor_H1_cutoff | B46: B22 Anchor+Halo: minimum H1 claim strength for anchor (default 2) | C46: 2 | D46: 2 | E46: 2 | F46: 2 | G46: 2 | H46: 2 | I46: 2 | J46: 2 | K46: 2 | L46: 2
A47: HighCitation_H5_min | B47: B29 High-Citation: minimum H5 forward citations (default 15) | C47: 15 | D47: 10 | E47: 15 | F47: 15 | G47: 15 | H47: 15 | I47: 15 | J47: 15 | K47: 15 | L47: 15
A48: PreExpiry_min_years | B48: B32 Pre-Expiry: minimum remaining term in years (default 1) | C48: 1 | D48: 1 | E48: 1 | F48: 1 | G48: 1 | H48: 1 | I48: 1 | J48: 1 | K48: 1 | L48: 1
A49: PreExpiry_max_years | B49: B32 Pre-Expiry: maximum remaining term in years (default 4) | C49: 4 | D49: 4 | E49: 4 | F49: 4 | G49: 4 | H49: 4 | I49: 4 | J49: 4 | K49: 4 | L49: 4
... A55: Strength_term_min | B55: Scorecard STRONG flag: minimum avg remaining term (default 10) | C55: 10 | D55: 10 | E55: 10 | F55: 10 | G55: 10 | H55: 10 | I55: 10 | J55: 10 | K55: 10 | L55: 10
A56: QUALITY GATES (Yes = column shown on Scorecard, No = column blanked)
A57: Gate_WeakestH1 | B57: Show "Weakest H1 in bundle" column | C57: Yes | D57: Yes | E57: Yes | F57: No | G57: Yes | H57: Yes | I57: Yes | J57: Yes | K57: Yes | L57: Yes
A58: Gate_InvalidityExposure | B58: Show "Invalidity exposure %" column | C58: Yes | D58: Yes | E58: Yes | F58: Yes | G58: Yes | H58: Yes | I58: Yes | J58: Yes | K58: Yes | L58: Yes
A59: Gate_EoUReady | B59: Show "EoU-ready %" column | C59: Yes | D59: Yes | E59: No | F59: No | G59: Yes | H59: No | I59: Yes | J59: Yes | K59: Yes | L59: Yes
A60: Gate_Survived | B60: Show "Survived %" column | C60: Yes | D60: Yes | E60: No | F60: No | G60: Yes | H60: No | I60: Yes | J60: Yes | K60: Yes | L60: Yes
A61: Gate_ContOptionality | B61: Show "Continuation-optionality %" column | C61: Yes | D61: No | E61: Yes | F61: No | G61: Yes | H61: Yes | I61: Yes | J61: Yes | K61: Yes | L61: Yes
A64: HOW TO USE THE PRESETS SHEET
A65: • The "Active Preset" dropdown on the Configuration sheet picks one column from this sheet.
A66: • Columns C-H are starter presets — useful as-is or as templates.
A67: • Columns I-L are empty "Custom Preset" slots — overwrite their values to define your own.
A68: • To rename a preset: edit row 1 of its column. The dropdown on the Configuration sheet updates automatically.
A69: • To save your current Configuration as a new preset:
A70: 1. On the Configuration sheet, set Edit Mode = Yes and configure all toggles/thresholds the way you want.
A71: 2. Come back to this sheet. In the Custom Preset column you want to use, paste-special each value section by section, or type values directly.
A72: 3. Rename the column header (row 1) to your preset name.
A73: 4. Back on Configuration: set Edit Mode = No and select your new preset from the dropdown.
A74: • You can add more preset columns by extending to columns M onward — just update the dropdown range on the Configuration sheet.

Sheet Attribute Dictionary
A1: Group | B1: Code | C1: Attribute | D1: Description | E1: Scale / Values | F1: Example
A2: A. Technology Classification | B2: A1 | C2: Primary technology domain | D2: Main CPC/IPC classification or internal taxonomy tag. | E2: Categorical text | F2: Wireless PHY
A3: A. Technology Classification | B3: A2 | C3: Secondary domains | D3: Cross-applicable technical areas the patent also touches. | E3: Comma-separated tags | F3: Beamforming, MIMO
A4: A. Technology Classification | B4: A3 | C4: Stack layer | D4: Horizontal layer of the technology stack. | E4: Hardware / Firmware / OS / Middleware / App / Cloud / UI | F4: Hardware
A5: A. Technology Classification | B5: A4 | C5: Product subsystem | D5: Which subsystem(s) of an end-product it covers. | E5: Free-text / list | F5: Battery management
A6: A. Technology Classification | B6: A5 | C6: Use-case | D6: Real-world problem(s) it solves. | E6: Free-text / list | F6: Indoor positioning
A7: B. Standards & Ecosystem | B7: B1 | C7: SEP potential | D7: Standard-essential potential. | E7: 0 (none) → 3 (declared/strong mapping) | F7: 3
A8: B. Standards & Ecosystem | B8: B2 | C8: Standard tagged | D8: Specific standard(s) the patent maps to. | E8: Categorical text | F8: 3GPP 5G NR
A9: B. Standards & Ecosystem | B9: B3 | C9: Interface role | D9: Role as an interoperability/interface technology. | E9: 0 (internal only) → 3 (mandatory interface) | F9: 2
A10: C. Claim & Scope | B10: C1 | C10: Claim type | D10: Dominant claim type. | E10: Apparatus / Method / System / CRM / Design | F10: Method
A11: C. Claim & Scope | B11: C2 | C11: Claim breadth | D11: How broad/foundational the independent claims are. | E11: 0 (narrow) → 3 (foundational/pioneer) | F11: 2
A12: C. Claim & Scope | B12: C3 | C12: Independent claim count | D12: Number of independent claims. | E12: Integer | F12: 3
... A41: I. Market/Buyer Signals | B41: I4 | C41: Workaround complexity | D41: Engineering effort needed for a competitor to design around the claims. | E41: 0 (trivial) → 3 (deep redesign) | F41: 3

Sheet Attribute Procedure
A1: ATTRIBUTE DERIVATION PROCEDURE
A2: A field-by-field procedure for populating the 40-attribute scoring model from raw patent data. Sits alongside the Attribute Dictionary as the long-form reference.
A3: TYPE LEGEND
A4: Direct lookup | B4: Pull the value straight from a patent document field or database; no judgment required.
A5: Computed | B5: Apply an arithmetic formula or boolean rule to other already-collected fields.
A6: Derived (rubric) | B6: Apply a scoring rubric to claim text or specification language. Requires reading and judgment.
A7: Derived (rubric + SME) | B7: Rubric-based but should be cross-checked with a domain expert or patent counsel.
A9: RECOMMENDED WORKFLOW — 10 steps (run in order; steps 1-3 mostly automatable, steps 4-10 require reading & judgment)
A10: # | B10: Step | C10: What to do | F10: Fields populated
A11: 1 | B11: Pull bibliographic & family data | C11: For each patent: get the front page, claims, abstract, family tree, citations, assignments, and prosecution status. Use Google Patents + Espacenet + USPTO Patent Center. | F11: A1, A2, C1, C3, E1–E5, F1, H5, H6, H8
A12: 2 | B12: Read claims and specification | C12: Read the first independent claim of each patent + the Background / Field-of-Invention. This is the irreplaceable manual step. | F12: A3, A4, A5, C2, C4, B3
A13: 3 | B13: Check SEP declarations | C13: For wireless / video / connectivity patents: check ETSI IPR, IEEE-SA, ITU declarations against the family. | F13: B1, B2
A14: 4 | B14: Score detectability | C14: For each claim, judge external vs. teardown detectability with the rubric. Cross-check teardowns where available. | F14: D1, D2
A15: 5 | B15: Map to products | C15: Identify which commercial products read on each patent. Build a quick read-on list. This is the highest-leverage step for buyer value. | F15: D3, I1
A16: 6 | B16: Compute geography | C16: From the family list, derive trilateral flag and major-market score. | F16: F2, F3 (auto from F1)
A17: 7 | B17: Tag themes and generations | C17: Apply your convergence-theme dictionary and generation labels. | F17: G1, G2, G3
A18: 8 | B18: Quality & vulnerability review | C18: Patent-counsel-grade review: claim strength, prior-art exposure, prosecution estoppel, divided-infringement, litigation history. Most labor-intensive but most decisive for buyer due diligence. | F18: H1, H2, H3, H4, H7
A19: 9 | B19: EoU & encumbrance audit | C19: Check internal claim-chart library; check encumbrance records. | F19: H9, H10
A20: 10 | B20: Market signals review | C20: Implementation maturity (was it productized?), adjacent re-read potential, workaround complexity. SME-driven. | F20: I2, I3, I4
A23: MASTER ATTRIBUTE PROCEDURE TABLE — one row per attribute (40 attributes total)
A24: Grp | B24: Code | C24: Attribute | D24: Type | E24: Where to find | F24: How to derive / compute | G24: Best data source
A25: A | B25: A1 | C25: Primary technology domain | D25: Direct lookup | E25: Front page of the patent: CPC main classification (most specific subgroup), or IPC. Also check the title and abstract for confirmation. | F25: Take the CPC main code and translate it to a human-readable domain tag using a fixed taxonomy (e.g., CPC H04W → "Wireless networking"; CPC H01M → "Battery cells"). Maintain a CPC→tag mapping spreadsheet so values stay consistent across the portfolio. | G25: Google Patents, USPTO PatentsView, Espacenet, EPO Open Patent Services, Lens.org. CPC scheme reference: cpc.uspto.gov
A26: A | B26: A2 | C26: Secondary domains | D26: Direct lookup | E26: CPC classifications other than the main one (front page lists multiple). Also pull keywords from the abstract and the first independent claim. | F26: List every additional CPC subgroup beyond A1. Optionally enrich with 2-3 keyword tags drawn from the abstract (e.g., "MIMO", "beamforming", "edge inference"). | G26: Google Patents, Espacenet, Lens.org. For keyword extraction at scale: use a simple TF-IDF over the abstract against the rest of your portfolio.
A27: A | B27: A3 | C27: Stack layer | D27: Derived (rubric) | E27: Read the first independent claim and the "Field of the Invention" / "Background" section. | F27: Apply a 7-bucket rubric. Hardware: physical device, circuit, or material composition. Firmware: low-level code embedded in hardware. OS: kernel/driver level. Middleware: protocol stacks, libraries, frameworks. App: end-user application logic. Cloud: server-side service or backend. UI: visual interface or interaction pattern. Pick the dominant layer; if the claim mixes layers, pick where the novelty lives. | G27: Patent specification. No external database — judgment-based against the rubric.
A28: A | B28: A4 | C28: Product subsystem | D28: Derived (rubric) | E28: Read the first independent claim, the "Detailed Description" preamble, and any "Embodiments" section listing real-world products. | F28: Map the claim subject matter to a subsystem of an identifiable end product. Example: for an EV — "battery cell", "battery pack", "BMS", "traction inverter", "thermal mgmt", "charging port", "motor", "regen brake controller". Maintain a per-industry subsystem dictionary so tags are consistent. | G28: Patent specification + product architecture knowledge (engineering team / SME input).
A29: A | B29: A5 | C29: Use-case | D29: Derived (rubric) | E29: "Field of the Invention", "Background", and the "Detailed Description" — look for problem statements ("there is a need to...", "addresses the problem of..."). | F29: Phrase the use-case as a customer-facing problem (e.g., "indoor positioning", "battery fast-charging", "fraud detection in payments", "low-latency video streaming"). Maintain a portfolio-wide use-case dictionary; reuse tags rather than coining new ones for each patent. | G29: Patent specification. Use natural-language extraction from the Background section. Cross-check against market reports if needed.
A30: B | B30: B1 | C30: SEP potential | D30: Derived (rubric) | E30: Check (a) SEP databases for any declaration on this family, (b) the claim language for standards-spec phrasing, (c) any prior 3GPP / IEEE / ITU letters of assurance. | F30: Score 0-3. 3: declared SEP in an SSO database, OR claim language directly mirrors a normative spec section. 2: claim reads on a specific clause of a known standard but no formal declaration. 1: standard-adjacent but normative essentiality is debatable. 0: no standard tie. For 5G/Wi-Fi/Bluetooth/USB-C/H.26x patents, always run a claim-vs-spec mapping before assigning ≥2. | G30: ETSI IPR Online Database (search.ipr.etsi.org), IEEE-SA, ITU, IETF declarations, Unified Patents SEP database, IPlytics, Amplified.ai. Pair with claim-charts where available.
A31: B | B31: B2 | C31: Standard tagged | D31: Direct lookup | E31: Same sources as B1. Read the actual SSO declaration if one exists. | F31: Record the exact standard identifier (e.g., "3GPP TS 38.211 (5G NR PHY)", "IEEE 802.11be (Wi-Fi 7)", "USB PD 3.1", "ITU-T H.266/VVC"). If multiple standards are implicated, list all. Blank if B1 = 0. | G31: ETSI IPR database (full declaration text usually names the spec). Otherwise infer from claim text + standards expert review.
A32: B | B32: B3 | C32: Interface role | D32: Derived (rubric) | E32: Read the first independent claim. Look for protocol/handshake/format/connector language. | F32: Score 0-3. 3: claim sits at a mandatory interface between two systems (e.g., wire protocol, connector pinout, RPC format). 2: claim covers a widely-used interoperability mechanism that is not technically mandatory but is de-facto standard. 1: claim involves an interface but the interface is internal to one product. 0: no interface dimension. | G32: Patent specification + SME interpretation. Cross-check whether the interface is named in any public spec.
A33: C | B33: C1 | C33: Claim type | D33: Direct lookup | E33: Read the preamble of each independent claim. | F33: Classify the dominant independent claim type. Apparatus: "an apparatus comprising…", "a device comprising…". Method: "a method comprising the steps of…". System: "a system for X comprising…". CRM: "a non-transitory computer-readable medium storing instructions that, when executed…". Design: design patents (D-numbered, drawings only). If mixed, pick the most enforceable type given the product target. | G33: Patent claims section (always front-of-patent in granted patents).
A34: C | B34: C2 | C34: Claim breadth | D34: Derived (rubric) | E34: Read each independent claim. Count words, count specific limitations, look for "wherein" clauses. | F34: Score 0-3. 3 (pioneer/foundational): few elements, abstract/general language, no narrowing wherein clauses, broad genus. 2 (broad): moderate element count, some structural narrowing. 1 (narrow): many specific element constraints, specific value ranges, named structural features. 0 (very narrow/picture claim): tied to one specific implementation. Rule of thumb: shorter independent claims with fewer limitations are usually broader. | G34: Patent claims + judgment. Tools like ClaimMaster, LexisNexis PatentAdvisor, or simple word-count heuristics can prefilter.
A35: C | B35: C3 | C35: Independent claim count | D35: Direct lookup (count) | E35: Claims section. Independent claims are those that do not refer to another claim ("a method comprising…" rather than "the method of claim 1, wherein…"). | F35: Simple count. Look for claims whose first word is not "The" referring back to a prior claim. | G35: Patent claims section. Most patent APIs (PatentsView, EPO OPS) return claim text in structured form.
... A64: I | B64: I4 | C64: Workaround complexity | D64: Derived (rubric + engineering SME) | E64: Read the claim. Ask an engineer: "If a competitor needed to ship a competing product without infringing, how much redesign is needed?" | F64: Score 0-3. 3: deep redesign — claim covers the natural/efficient approach; alternatives are expensive or technically inferior. 2: significant redesign — alternatives exist but are commercially undesirable. 1: minor redesign — straightforward alternative is available. 0: trivial workaround — designers can easily substitute. Strongly correlates with C4 design-around difficulty but considered separately because C4 is about claim language whereas I4 is about commercial impact. | G64: Patent claims + engineering SME review. The most reliable answer comes from an engineer who has actually shipped products in the space.
A67: DATA SOURCE REFERENCE — free and paid sources used across the procedure
A68: Tier | B68: Source | C68: URL | E68: What it gives you
A69: Free | B69: Google Patents | C69: patents.google.com | E69: Bibliographic, family, citations, claims, full text. Best free starting point.
A70: Free | B70: Espacenet | C70: worldwide.espacenet.com | E70: EPO's global patent search; best for family view (INPADOC).
A71: Free | B71: USPTO Patent Center | C71: patentcenter.uspto.gov | E71: US file wrapper, prosecution history, maintenance fees, assignments.
A72: Free | B72: PatentsView | C72: patentsview.org | E72: USPTO bulk data API. Excellent for programmatic scoring across a portfolio.
A73: Free | B73: Lens.org | C73: lens.org | E73: Free patent + scholarly search; good for forward-citation analysis.
A74: Free | B74: EPO Register | C74: register.epo.org | E74: EP file wrapper, oppositions, renewals.
A75: Free | B75: USPTO PTAB Database | C75: developer.uspto.gov/ptab-api | E75: IPR/PGR/CBM filings and outcomes.
A76: Free | B76: ETSI IPR Database | C76: ipr.etsi.org | E76: SEP declarations for 3GPP / ETSI standards.
A77: Free | B77: USPTO Assignment Search | C77: assignment.uspto.gov | E77: Chain of title for US patents.
A78: Paid | B78: Patsnap | C78: patsnap.com | E78: Integrated platform: family, citations, litigation, valuation. Strong for portfolio-scale analysis.
A79: Paid | B79: Derwent Innovation (Clarivate) | C79: clarivate.com | E79: Premium curated abstracts and family data; strong for prior art.
... A87: Paid | B87: iFixit | C87: ifixit.com | E87: Consumer product teardowns (free + paid tiers).
A90: PRACTICAL NOTES
A91: Scoring consistency
A92: For every 0-3 rubric attribute, calibrate by scoring 5-10 sample patents first as a team, then locking the calibration before processing the rest. Otherwise scores drift across reviewers. Maintain a portfolio-specific data dictionary for A1, A4, A5, G1 so tags are reused rather than re-coined for each patent. Inconsistent tags break the routing rules.
A93: Time and effort allocation
A94: On a 50-patent portfolio: Steps 1-3 (data pull) take ~1 hour total when automated. Steps 4-7 (claim reading, rubric scoring) take ~30 min per patent. Step 8 (quality and vulnerability) takes ~45 min per patent and benefits from patent-counsel involvement. Step 9 (EoU and encumbrance) varies wildly — anywhere from 5 min to several hours depending on internal artifact availability.
A95: Where to invest in claim charts
A96: Don't build EoU claim charts for the whole portfolio. Build them for: anchor patents (H1=3), patents likely to land in EoU-Backed (Bundle 26) or Battle-Tested (Bundle 27), and anything destined for the Premium tier. Charts are expensive — invest them where they shift bundle value the most.
A97: Automation pointers
A98: PatentsView API + Espacenet OPS API together cover ~80% of the Direct Lookup fields programmatically. A simple Python script can populate A1, A2, B2, C1, C3, E1-E5, F1, H5, H6, H8 across the entire Patent Portfolio sheet in one batch. Reserve manual work for the rubric-based and SME-based attributes.
A99: Threshold calibration warning
A100: The numeric thresholds on the Configuration sheet (SEP cutoff, citation minimum, etc.) only make sense if your 0-3 scores are calibrated. If two reviewers would give the same patent different H1 scores, the threshold-based routing produces noise. Run a calibration session before bulk scoring.

Sheet Patent Portfolio
A1: Identification | C1: A. Technology Classification | H1: B. Standards | K1: C. Claim & Scope | O1: D. Detectability | R1: E. Family & Lifecycle | W1: F. Geographic | Z1: G. Strategic | AC1: H. Patent Quality & Vulnerability | AM1: I. Market/Buyer Signals
A2: Patent ID | B2: Title | C2: A1 Primary domain | D2: A2 Secondary domains | E2: A3 Stack layer | F2: A4 Subsystem | G2: A5 Use-case | H2: B1 SEP potential (0-3) | I2: B2 Standard | J2: B3 Interface role (0-3) | K2: C1 Claim type | L2: C2 Claim breadth (0-3) | M2: C3 Indep. claim count | N2: C4 Design-around diff. (0-3) | O2: D1 External detect. (0-3) | P2: D2 Teardown detect. (0-3) | Q2: D3 Reads-on-products (0-3) | R2: E1 Family size | S2: E2 Prosecution | T2: E3 Continuation | U2: E4 Remaining term (yrs) | V2: E5 Maint. status | W2: F1 Jurisdictions | X2: F2 Trilateral (Y/N) | Y2: F3 Major-market score (0-3) | Z2: G1 Convergence theme | AA2: G2 Generation | AB2: G3 Cross-industry (0-3) | AC2: H1 Claim strength (0-3) | AD2: H2 Prior-art exposure (0-3) | AE2: H3 Prosecution risk (0-3) | AF2: H4 Divided-infrgmnt (0-3) | AG2: H5 Fwd citations | AH2: H6 Bwd citations | AI2: H7 Lit/PTAB history | AJ2: H8 Chain-of-title | AK2: H9 EoU available | AL2: H10 Encumbrance | AM2: I1 Product-map conf. (0-3) | AN2: I2 Impl. maturity | AO2: I3 Adjacent re-read (0-3) | AP2: I4 Workaround complex. (0-3)
A3: P-001 | B3: Beamforming pilot signaling for 5G NR | C3: Wireless PHY | D3: MIMO, beamforming | E3: Hardware | F3: Radio frontend | G3: Cellular comms | H3: 3 | I3: 3GPP 5G NR | J3: 3 | K3: Method | L3: 2 | M3: 3 | N3: 3 | O3: 1 | P3: 3 | Q3: 3 | R3: 8 | S3: Granted | T3: Yes | U3: 14 | V3: Active | W3: US, EP, CN, JP, KR | X3: Yes | Y3: 3 | AA3: Current | AB3: 1 | AC3: 3 | AD3: 3 | AE3: 2 | AF3: 3 | AG3: 28 | AH3: 42 | AI3: Survived | AJ3: Clean | AK3: Full | AL3: None | AM3: 3 | AN3: Productized | AO3: 1 | AP3: 3
A4: P-002 | B4: Polar code decoder architecture | C4: Wireless PHY | D4: Error correction | E4: Hardware | F4: Baseband processor | G4: Cellular comms | H4: 3 | I4: 3GPP 5G NR | J4: 2 | K4: Apparatus | L4: 2 | M4: 2 | N4: 2 | O4: 0 | P4: 3 | Q4: 3 | R4: 5 | S4: Granted | T4: No | U4: 13 | V4: Active | W4: US, EP, CN, KR | X4: Yes | Y4: 3 | AA4: Current | AB4: 1 | AC4: 2 | AD4: 2 | AE4: 2 | AF4: 3 | AG4: 18 | AH4: 31 | AI4: None | AJ4: Clean | AK4: Partial | AL4: None | AM4: 3 | AN4: Productized | AO4: 1 | AP4: 2
A5: P-003 | B5: Adaptive Wi-Fi 7 channel sounding | C5: Wireless PHY | D5: OFDMA | E5: Firmware | F5: WLAN module | G5: Indoor connectivity | H5: 2 | I5: IEEE 802.11be | J5: 3 | K5: Method | L5: 1 | M5: 2 | N5: 2 | O5: 1 | P5: 2 | Q5: 2 | R5: 4 | S5: Mixed | T5: Yes | U5: 17 | V5: Active | W5: US, EP, CN | X5: Yes | Y5: 2 | AA5: Next-gen | AB5: 2 | AC5: 2 | AD5: 3 | AE5: 3 | AF5: 2 | AG5: 4 | AH5: 22 | AI5: None | AJ5: Clean | AK5: None | AL5: None | AM5: 2 | AN5: Prototyped | AO5: 2 | AP5: 2
A6: P-004 | B6: Solid-state electrolyte composition for EV batteries | C6: Battery materials | D6: Solid-state, ionics | E6: Hardware | F6: Battery cell | G6: EV propulsion | H6: 0 | J6: 0 | K6: Apparatus | L6: 3 | M6: 4 | N6: 3 | O6: 0 | P6: 3 | Q6: 2 | R6: 6 | S6: Granted | T6: Yes | U6: 17 | V6: Active | W6: US, EP, CN, JP, KR | X6: Yes | Y6: 3 | AA6: Next-gen | AB6: 2 | AC6: 3 | AD6: 3 | AE6: 3 | AF6: 3 | AG6: 35 | AH6: 48 | AI6: None | AJ6: Clean | AK6: Partial | AL6: None | AM6: 2 | AN6: Prototyped | AO6: 3 | AP6: 3
A7: P-005 | B7: Battery thermal management with phase-change material | C7: Thermal mgmt | D7: BMS, materials | E7: Hardware | F7: Battery pack | G7: EV propulsion | H7: 0 | J7: 1 | K7: System | L7: 2 | M7: 3 | N7: 2 | O7: 1 | P7: 3 | Q7: 2 | R7: 3 | S7: Granted | T7: No | U7: 11 | V7: Active | W7: US, EP, CN | X7: Yes | Y7: 2 | AA7: Current | AB7: 2 | AC7: 2 | AD7: 2 | AE7: 2 | AF7: 3 | AG7: 14 | AH7: 27 | AI7: None | AJ7: Clean | AK7: None | AL7: Non-exclusive licensed | AM7: 2 | AN7: Productized | AO7: 2 | AP7: 2
A8: P-006 | B8: SiC MOSFET inverter control method | C8: Power electronics | D8: Wide-bandgap | E8: Firmware | F8: Traction inverter | G8: EV propulsion | H8: 0 | J8: 1 | K8: Method | L8: 2 | M8: 2 | N8: 2 | O8: 1 | P8: 3 | Q8: 3 | R8: 4 | S8: Granted | T8: No | U8: 12 | V8: Active | W8: US, EP, CN, JP | X8: Yes | Y8: 3 | AA8: Current | AB8: 2 | AC8: 2 | AD8: 2 | AE8: 2 | AF8: 3 | AG8: 16 | AH8: 33 | AI8: None | AJ8: Minor gaps | AK8: Partial | AL8: None | AM8: 3 | AN8: Productized | AO8: 2 | AP8: 2
A9: P-007 | B9: On-device CNN quantization for low-power inference | C9: CV algorithm | D9: Edge AI, ML | E9: App | F9: Vision pipeline | G9: Smart cameras | H9: 0 | J9: 0 | K9: CRM | L9: 2 | M9: 3 | N9: 2 | O9: 2 | P9: 1 | Q9: 2 | R9: 5 | S9: Granted | T9: Yes | U9: 15 | V9: Active | W9: US, EP, CN | X9: Yes | Y9: 2 | Z9: Edge AI | AA9: Current | AB9: 3 | AC9: 2 | AD9: 1 | AE9: 2 | AF9: 2 | AG9: 47 | AH9: 26 | AI9: Pending | AJ9: Clean | AK9: Partial | AL9: None | AM9: 2 | AN9: Productized | AO9: 3 | AP9: 2
A10: P-008 | B10: Transformer attention pruning for vision models | C10: CV algorithm | D10: AI optimization | E10: App | F10: Inference engine | G10: Visual analytics | H10: 0 | J10: 0 | K10: Method | L10: 1 | M10: 2 | N10: 1 | O10: 2 | P10: 0 | Q10: 2 | R10: 3 | S10: Pending | T10: Yes | U10: 19 | V10: Active | W10: US, EP | X10: No | Y10: 1 | Z10: Edge AI, AI+health | AA10: Next-gen | AB10: 3 | AC10: 1 | AD10: 1 | AE10: 1 | AF10: 1 | AG10: 8 | AH10: 19 | AI10: None | AJ10: Clean | AK10: None | AL10: None | AM10: 1 | AN10: Idea-only | AO10: 3 | AP10: 1
A11: P-009 | B11: Visual SLAM for indoor robot navigation | C11: Robotics SW | D11: SLAM, CV | E11: Middleware | F11: Navigation stack | G11: Indoor positioning | H11: 0 | J11: 1 | K11: System | L11: 2 | M11: 2 | N11: 2 | O11: 2 | P11: 1 | Q11: 2 | R11: 4 | S11: Granted | T11: No | U11: 10 | V11: Active | W11: US, EP, JP | X11: Yes | Y11: 2 | Z11: Robotics, edge AI | AA11: Current | AB11: 3 | AC11: 2 | AD11: 2 | AE11: 2 | AF11: 2 | AG11: 22 | AH11: 34 | AI11: None | AJ11: Clean | AK11: Partial | AL11: None | AM11: 2 | AN11: Prototyped | AO11: 2 | AP11: 2
A12: P-010 | B12: USB-C power delivery handshake extension | C12: Interconnect | D12: Power delivery | E12: Firmware | F12: Charging interface | G12: Universal charging | H12: 2 | I12: USB PD 3.x | J12: 3 | K12: Method | L12: 1 | M12: 2 | N12: 2 | O12: 3 | P12: 3 | Q12: 3 | R12: 5 | S12: Granted | T12: No | U12: 9 | V12: Active | W12: US, EP, CN, JP, KR | X12: Yes | Y12: 3 | AA12: Current | AB12: 3 | AC12: 2 | AD12: 3 | AE12: 2 | AF12: 3 | AG12: 25 | AH12: 39 | AI12: Survived | AJ12: Clean | AK12: Full | AL12: None | AM12: 3 | AN12: Productized | AO12: 2 | AP12: 2
A13: P-011 | B13: Atomic layer deposition recipe for high-k dielectric | C13: Semiconductor process | D13: ALD, fab | E13: Hardware | F13: Front-end-of-line | G13: IC manufacturing | H13: 0 | J13: 1 | K13: Method | L13: 2 | M13: 3 | N13: 3 | O13: 0 | P13: 1 | Q13: 1 | R13: 6 | S13: Granted | T13: Yes | U13: 13 | V13: Active | W13: US, EP, CN, JP, KR, TW | X13: Yes | Y13: 3 | AA13: Current | AB13: 1 | AC13: 3 | AD13: 2 | AE13: 3 | AF13: 3 | AG13: 19 | AH13: 41 | AI13: None | AJ13: Clean | AK13: None | AL13: None | AM13: 1 | AN13: Productized | AO13: 1 | AP13: 3
A14: P-012 | B14: Predictive maintenance ML for industrial pumps | C14: Industrial AI | D14: Predictive analytics | E14: Cloud | F14: Asset monitoring | G14: Predictive maintenance | H14: 0 | J14: 1 | K14: CRM | L14: 1 | M14: 2 | N14: 1 | O14: 2 | P14: 0 | Q14: 1 | R14: 2 | S14: Granted | T14: No | U14: 8 | V14: Active | W14: US, EP | X14: No | Y14: 1 | Z14: AI+industrial | AA14: Current | AB14: 3 | AC14: 1 | AD14: 1 | AE14: 2 | AF14: 1 | AG14: 5 | AH14: 12 | AI14: None | AJ14: Minor gaps | AK14: None | AL14: None | AM14: 1 | AN14: Idea-only | AO14: 2 | AP14: 1

Sheet Bundle Rules
A1: # | B1: Bundle Type | C1: Value Proposition | D1: Routing Rule (technical qualification) | E1: Primary attributes used
A2: 1 | B2: Technology Domain | C2: Concentrated coverage in one technical field; useful for entering or fortifying a domain position. | D2: Patents share the same A1 (primary domain) tag. | E2: A1
A3: 2 | B3: Standard-Essential (SEP) | C3: Bundle of assets every implementer of the standard must license or design around. | D3: B1 ≥ 2 AND share same B2 standard. | E3: B1, B2
A4: 3 | B4: Product Architecture | C4: "Build a product" kit — full vertical coverage across subsystems of one end-product. | D4: Collectively span ≥ 3 distinct A4 subsystems of one product family. | E4: A4
A5: 4 | B5: Stack Layer | C5: Targets buyers operating at a specific layer of the technology stack. | D5: Patents share the same A3 (stack layer). | E5: A3
A6: 5 | B6: Use-Case / Application | C6: All tools to address one customer problem, even if underlying tech is heterogeneous. | D6: Patents share at least one A5 (use-case) tag. | E6: A5
A7: 6 | B7: Manufacturing / Process | C7: Targets fabs, contract manufacturers, equipment makers needing freedom to operate on production methods. | D7: A1 is a "process" / manufacturing domain (e.g., contains "process" or "fab") AND C1 = Method. | E7: A1, C1
A8: 7 | B8: Materials & Chemistry | C8: Focused IP shield around composition, synthesis, and use of a material system. | D8: A1 is a materials/chemistry domain AND C1 ∈ {Apparatus, Method}. | E8: A1, C1
A9: 8 | B9: Algorithm / Software Method | C9: Implementation-agnostic methods deployable across many products. | D9: A3 ∈ {App, Middleware, Cloud} AND C1 ∈ {Method, CRM}. | E9: A3, C1
A10: 9 | B10: Interoperability / Interface | C10: Critical chokepoints for any player whose product must talk to others. | D10: B3 ≥ 2. | E10: B3
A11: 10 | B11: Generational Roadmap | C11: Buyer picks legacy (cheap defensive) or next-gen (forward-looking offensive). | D11: Group by G2 (Legacy / Current / Next-gen). | E11: G2
A12: 11 | B12: Claim-Type | C12: Different enforcement profiles; buyers pick by litigation/licensing strategy. | D12: Group by C1. | E12: C1
A13: 12 | B13: Detectability | C13: Litigation-ready bundle — infringement is easy to spot. | D13: D1 ≥ 2 OR D2 ≥ 2. | E13: D1, D2
... A34: 33 | B34: Provenance-Coherent | C34: Patents originating from the same R&D program, inventor group, or acquired sub-business. Shared specifications and consistent terminology reduce claim-construction risk. | D34: Patents share A1 AND share A4 (proxy for common provenance in this template). | E34: A1, A4

Sheet Bundle Assignment
A1: Patent | C1: Bundle Qualification (TRUE = patent qualifies for this bundle) | AJ1: Total
A2: Patent ID | B2: Title | C2: =IF(Configuration!$C$10="No","[DISABLED] B1 Tech Domain","B1 Tech Domain") -> B1 Tech Domain | D2: =IF(Configuration!$C$11="No","[DISABLED] B2 SEP","B2 SEP") -> B2 SEP | E2: =IF(Configuration!$C$12="No","[DISABLED] B3 Product Arch","B3 Product Arch") -> B3 Product Arch | F2: =IF(Configuration!$C$13="No","[DISABLED] B4 Stack Layer","B4 Stack Layer") -> B4 Stack Layer | G2: =IF(Configuration!$C$14="No","[DISABLED] B5 Use-Case","B5 Use-Case") -> B5 Use-Case | H2: =IF(Configuration!$C$15="No","[DISABLED] B6 Mfg/Process","B6 Mfg/Process") -> B6 Mfg/Process | I2: =IF(Configuration!$C$16="No","[DISABLED] B7 Materials","B7 Materials") -> B7 Materials | J2: =IF(Configuration!$C$17="No","[DISABLED] B8 Algorithm","B8 Algorithm") -> B8 Algorithm | K2: =IF(Configuration!$C$18="No","[DISABLED] B9 Interop","B9 Interop") -> B9 Interop | L2: =IF(Configuration!$C$19="No","[DISABLED] B10 Generational","B10 Generational") -> B10 Generational | M2: =IF(Configuration!$C$20="No","[DISABLED] B11 Claim-Type","B11 Claim-Type") -> B11 Claim-Type | N2: =IF(Configuration!$C$21="No","[DISABLED] B12 Detectable","B12 Detectable") -> B12 Detectable | O2: =IF(Configuration!$C$22="No","[DISABLED] B13 Geographic","B13 Geographic") -> B13 Geographic | P2: =IF(Configuration!$C$23="No","[DISABLED] B14 Family","B14 Family") -> B14 Family | Q2: =IF(Configuration!$C$24="No","[DISABLED] B15 Lifecycle","B15 Lifecycle") -> B15 Lifecycle | R2: =IF(Configuration!$C$25="No","[DISABLED] B16 Foundational+Improv.","B16 Foundational+Improv.") -> B16 Foundational+Improv. | S2: =IF(Configuration!$C$26="No","[DISABLED] B17 Cross-Industry","B17 Cross-Industry") -> B17 Cross-Industry | T2: =IF(Configuration!$C$27="No","[DISABLED] B18 Convergent Theme","B18 Convergent Theme") -> B18 Convergent Theme | U2: =IF(Configuration!$C$28="No","[DISABLED] B19 Defensive","B19 Defensive") -> B19 Defensive | V2: =IF(Configuration!$C$29="No","[DISABLED] B20 Whitespace","B20 Whitespace") -> B20 Whitespace | W2: =IF(Configuration!$C$30="No","[DISABLED] B21 Prosecution-Status","B21 Prosecution-Status") -> B21 Prosecution-Status | X2: =IF(Configuration!$C$31="No","[DISABLED] B22 Anchor+Halo","B22 Anchor+Halo") -> B22 Anchor+Halo | Y2: =IF(Configuration!$C$32="No","[DISABLED] B23 Picket-Fence","B23 Picket-Fence") -> B23 Picket-Fence | Z2: =IF(Configuration!$C$33="No","[DISABLED] B24 Strong+Tail","B24 Strong+Tail") -> B24 Strong+Tail | AA2: =IF(Configuration!$C$34="No","[DISABLED] B25 Continuation-Live","B25 Continuation-Live") -> B25 Continuation-Live | AB2: =IF(Configuration!$C$35="No","[DISABLED] B26 EoU-Backed","B26 EoU-Backed") -> B26 EoU-Backed | AC2: =IF(Configuration!$C$36="No","[DISABLED] B27 Battle-Tested","B27 Battle-Tested") -> B27 Battle-Tested | AD2: =IF(Configuration!$C$37="No","[DISABLED] B28 Clean-Title","B28 Clean-Title") -> B28 Clean-Title | AE2: =IF(Configuration!$C$38="No","[DISABLED] B29 High-Citation","B29 High-Citation") -> B29 High-Citation | AF2: =IF(Configuration!$C$39="No","[DISABLED] B30 Adjacent Re-Read","B30 Adjacent Re-Read") -> B30 Adjacent Re-Read | AG2: =IF(Configuration!$C$40="No","[DISABLED] B31 Salvage-Volume","B31 Salvage-Volume") -> B31 Salvage-Volume | AH2: =IF(Configuration!$C$41="No","[DISABLED] B32 Pre-Expiry","B32 Pre-Expiry") -> B32 Pre-Expiry | AI2: =IF(Configuration!$C$42="No","[DISABLED] B33 Provenance","B33 Provenance") -> B33 Provenance | AJ2: # of bundles
A3: ='Patent Portfolio'!A3 -> P-001 | B3: ='Patent Portfolio'!B3 -> Beamforming pilot signaling for 5G NR | C3: =IF(Configuration!$C$10="No","",IFERROR(IF('Patent Portfolio'!C3<>"",TRUE(),FALSE()),FALSE())) -> TRUE | D3: =IF(Configuration!$C$11="No","",IFERROR(IF(AND(N('Patent Portfolio'!H3)>=Configuration!$C$44,'Patent Portfolio'!I3<>""),TRUE(),FALSE()),FALSE())) -> TRUE | E3: =IF(Configuration!$C$12="No","",IFERROR(IF('Patent Portfolio'!F3<>"",TRUE(),FALSE()),FALSE())) -> TRUE | F3: =IF(Configuration!$C$13="No","",IFERROR(IF('Patent Portfolio'!E3<>"",TRUE(),FALSE()),FALSE())) -> TRUE | G3: =IF(Configuration!$C$14="No","",IFERROR(IF('Patent Portfolio'!G3<>"",TRUE(),FALSE()),FALSE())) -> TRUE | H3: =IF(Configuration!$C$15="No","",IFERROR(IF(AND(OR(ISNUMBER(SEARCH("process",'Patent Portfolio'!C3)),ISNUMBER(SEARCH("fab",'Patent Portfolio'!C3)),ISNUMBER(SEARCH("manufac",'Patent Portfolio'!C3))),'Patent Portfolio'!K3="Method"),TRUE(),FALSE()),FALSE())) -> FALSE | I3: =IF(Configuration!$C$16="No","",IFERROR(IF(AND(OR(ISNUMBER(SEARCH("material",'Patent Portfolio'!C3)),ISNUMBER(SEARCH("chem",'Patent Portfolio'!C3)),ISNUMBER(SEARCH("battery",'Patent Portfolio'!C3)),ISNUMBER(SEARCH("electrolyte",'Patent Portfolio'!C3)),ISNUMBER(SEARCH("polymer",'Patent Portfolio'!C3))),OR('Patent Portfolio'!K3="Apparatus",'Patent Portfolio'!K3="Method")),TRUE(),FALSE()),FALSE())) -> FALSE | J3: =IF(Configuration!$C$17="No","",IFERROR(IF(AND(OR('Patent Portfolio'!E3="App",'Patent Portfolio'!E3="Middleware",'Patent Portfolio'!E3="Cloud"),OR('Patent Portfolio'!K3="Method",'Patent Portfolio'!K3="CRM")),TRUE(),FALSE()),FALSE())) -> FALSE | K3: =IF(Configuration!$C$18="No","",IFERROR(IF(N('Patent Portfolio'!J3)>=Configuration!$C$45,TRUE(),FALSE()),FALSE())) -> TRUE | L3: =IF(Configuration!$C$19="No","",IFERROR(IF('Patent Portfolio'!AA3<>"",TRUE(),FALSE()),FALSE())) -> TRUE | M3: =IF(Configuration!$C$20="No","",IFERROR(IF('Patent Portfolio'!K3<>"",TRUE(),FALSE()),FALSE())) -> TRUE | N3: =IF(Configuration!$C$21="No","",IFERROR(IF(OR(N('Patent Portfolio'!O3)>=Configuration!$C$46,N('Patent Portfolio'!P3)>=Configuration!$C$47),TRUE(),FALSE()),FALSE())) -> TRUE | O3: =IF(Configuration!$C$22="No","",IFERROR(IF('Patent Portfolio'!X3="Yes",TRUE(),FALSE()),FALSE())) -> TRUE | P3: =IF(Configuration!$C$23="No","",IFERROR(IF(N('Patent Portfolio'!R3)>=Configuration!$C$48,TRUE(),FALSE()),FALSE())) -> TRUE | Q3: =IF(Configuration!$C$24="No","",IFERROR(IF(N('Patent Portfolio'!U3)>0,TRUE(),FALSE()),FALSE())) -> TRUE | R3: =IF(Configuration!$C$25="No","",IFERROR(IF(OR(N('Patent Portfolio'!L3)=3,N('Patent Portfolio'!L3)<=1),TRUE(),FALSE()),FALSE())) -> FALSE | S3: =IF(Configuration!$C$26="No","",IFERROR(IF(N('Patent Portfolio'!AB3)>=Configuration!$C$49,TRUE(),FALSE()),FALSE())) -> FALSE | T3: =IF(Configuration!$C$27="No","",IFERROR(IF('Patent Portfolio'!Z3<>"",TRUE(),FALSE()),FALSE())) -> FALSE | U3: =IF(Configuration!$C$28="No","",IFERROR(IF(N('Patent Portfolio'!Q3)>=Configuration!$C$50,TRUE(),FALSE()),FALSE())) -> TRUE | V3: =IF(Configuration!$C$29="No","",IFERROR(IF(AND(N('Patent Portfolio'!N3)>=Configuration!$C$51,'Patent Portfolio'!C3<>""),TRUE(),FALSE()),FALSE())) -> TRUE | W3: =IF(Configuration!$C$30="No","",IFERROR(IF(OR('Patent Portfolio'!S3="Pending",'Patent Portfolio'!T3="Yes"),TRUE(),FALSE()),FALSE())) -> TRUE | X3: =IF(Configuration!$C$31="No","",IFERROR(IF(AND(N('Patent Portfolio'!AC3)>=Configuration!$C$52,N('Patent Portfolio'!L3)>=1),TRUE(),FALSE()),FALSE())) -> TRUE | Y3: =IF(Configuration!$C$32="No","",IFERROR(IF(AND(N('Patent Portfolio'!N3)>=1,OR('Patent Portfolio'!C3<>"",'Patent Portfolio'!I3<>"")),TRUE(),FALSE()),FALSE())) -> TRUE | Z3: =IF(Configuration!$C$33="No","",IFERROR(IF('Patent Portfolio'!C3<>"",TRUE(),FALSE()),FALSE())) -> TRUE | AA3: =IF(Configuration!$C$34="No","",IFERROR(IF('Patent Portfolio'!T3="Yes",TRUE(),FALSE()),FALSE())) -> TRUE | AB3: =IF(Configuration!$C$35="No","",IFERROR(IF(OR('Patent Portfolio'!AK3="Partial",'Patent Portfolio'!AK3="Full"),TRUE(),FALSE()),FALSE())) -> TRUE | AC3: =IF(Configuration!$C$36="No","",IFERROR(IF('Patent Portfolio'!AI3="Survived",TRUE(),FALSE()),FALSE())) -> TRUE | AD3: =IF(Configuration!$C$37="No","",IFERROR(IF(AND('Patent Portfolio'!AJ3="Clean",'Patent Portfolio'!AL3="None"),TRUE(),FALSE()),FALSE())) -> TRUE | AE3: =IF(Configuration!$C$38="No","",IFERROR(IF(N('Patent Portfolio'!AG3)>=Configuration!$C$53,TRUE(),FALSE()),FALSE())) -> TRUE | AF3: =IF(Configuration!$C$39="No","",IFERROR(IF(AND(N('Patent Portfolio'!AO3)>=2,N('Patent Portfolio'!AB3)>=2),TRUE(),FALSE()),FALSE())) -> FALSE | AG3: =IF(Configuration!$C$40="No","",IFERROR(IF(OR(N('Patent Portfolio'!AC3)<=Configuration!$C$56,N('Patent Portfolio'!U3)<Configuration!$C$57,N('Patent Portfolio'!AD3)<=Configuration!$C$58),TRUE(),FALSE()),FALSE())) -> FALSE | AH3: =IF(Configuration!$C$41="No","",IFERROR(IF(AND(N('Patent Portfolio'!U3)>=Configuration!$C$54,N('Patent Portfolio'!U3)<=Configuration!$C$55),TRUE(),FALSE()),FALSE())) -> FALSE | AI3: =IF(Configuration!$C$42="No","",IFERROR(IF(AND('Patent Portfolio'!C3<>"",'Patent Portfolio'!F3<>""),TRUE(),FALSE()),FALSE())) -> TRUE | AJ3: =COUNTIF(C3:AI3,TRUE()) -> 24
A4: ='Patent Portfolio'!A4 -> P-002 | B4: ='Patent Portfolio'!B4 -> Polar code decoder architecture | C4: =IF(Configuration!$C$10="No","",IFERROR(IF('Patent Portfolio'!C4<>"",TRUE(),FALSE()),FALSE())) -> TRUE | D4: =IF(Configuration!$C$11="No","",IFERROR(IF(AND(N('Patent Portfolio'!H4)>=Configuration!$C$44,'Patent Portfolio'!I4<>""),TRUE(),FALSE()),FALSE())) -> TRUE | E4: =IF(Configuration!$C$12="No","",IFERROR(IF('Patent Portfolio'!F4<>"",TRUE(),FALSE()),FALSE())) -> TRUE | F4: =IF(Configuration!$C$13="No","",IFERROR(IF('Patent Portfolio'!E4<>"",TRUE(),FALSE()),FALSE())) -> TRUE | G4: =IF(Configuration!$C$14="No","",IFERROR(IF('Patent Portfolio'!G4<>"",TRUE(),FALSE()),FALSE())) -> TRUE | H4: =IF(Configuration!$C$15="No","",IFERROR(IF(AND(OR(ISNUMBER(SEARCH("process",'Patent Portfolio'!C4)),ISNUMBER(SEARCH("fab",'Patent Portfolio'!C4)),ISNUMBER(SEARCH("manufac",'Patent Portfolio'!C4))),'Patent Portfolio'!K4="Method"),TRUE(),FALSE()),FALSE())) -> FALSE | I4: =IF(Configuration!$C$16="No","",IFERROR(IF(AND(OR(ISNUMBER(SEARCH("material",'Patent Portfolio'!C4)),ISNUMBER(SEARCH("chem",'Patent Portfolio'!C4)),ISNUMBER(SEARCH("battery",'Patent Portfolio'!C4)),ISNUMBER(SEARCH("electrolyte",'Patent Portfolio'!C4)),ISNUMBER(SEARCH("polymer",'Patent Portfolio'!C4))),OR('Patent Portfolio'!K4="Apparatus",'Patent Portfolio'!K4="Method")),TRUE(),FALSE()),FALSE())) -> FALSE | J4: =IF(Configuration!$C$17="No","",IFERROR(IF(AND(OR('Patent Portfolio'!E4="App",'Patent Portfolio'!E4="Middleware",'Patent Portfolio'!E4="Cloud"),OR('Patent Portfolio'!K4="Method",'Patent Portfolio'!K4="CRM")),TRUE(),FALSE()),FALSE())) -> FALSE | K4: =IF(Configuration!$C$18="No","",IFERROR(IF(N('Patent Portfolio'!J4)>=Configuration!$C$45,TRUE(),FALSE()),FALSE())) -> TRUE | L4: =IF(Configuration!$C$19="No","",IFERROR(IF('Patent Portfolio'!AA4<>"",TRUE(),FALSE()),FALSE())) -> TRUE | M4: =IF(Configuration!$C$20="No","",IFERROR(IF('Patent Portfolio'!K4<>"",TRUE(),FALSE()),FALSE())) -> TRUE | N4: =IF(Configuration!$C$21="No","",IFERROR(IF(OR(N('Patent Portfolio'!O4)>=Configuration!$C$46,N('Patent Portfolio'!P4)>=Configuration!$C$47),TRUE(),FALSE()),FALSE())) -> TRUE | O4: =IF(Configuration!$C$22="No","",IFERROR(IF('Patent Portfolio'!X4="Yes",TRUE(),FALSE()),FALSE())) -> TRUE | P4: =IF(Configuration!$C$23="No","",IFERROR(IF(N('Patent Portfolio'!R4)>=Configuration!$C$48,TRUE(),FALSE()),FALSE())) -> TRUE | Q4: =IF(Configuration!$C$24="No","",IFERROR(IF(N('Patent Portfolio'!U4)>0,TRUE(),FALSE()),FALSE())) -> TRUE | R4: =IF(Configuration!$C$25="No","",IFERROR(IF(OR(N('Patent Portfolio'!L4)=3,N('Patent Portfolio'!L4)<=1),TRUE(),FALSE()),FALSE())) -> FALSE | S4: =IF(Configuration!$C$26="No","",IFERROR(IF(N('Patent Portfolio'!AB4)>=Configuration!$C$49,TRUE(),FALSE()),FALSE())) -> FALSE | T4: =IF(Configuration!$C$27="No","",IFERROR(IF('Patent Portfolio'!Z4<>"",TRUE(),FALSE()),FALSE())) -> FALSE | U4: =IF(Configuration!$C$28="No","",IFERROR(IF(N('Patent Portfolio'!Q4)>=Configuration!$C$50,TRUE(),FALSE()),FALSE())) -> TRUE | V4: =IF(Configuration!$C$29="No","",IFERROR(IF(AND(N('Patent Portfolio'!N4)>=Configuration!$C$51,'Patent Portfolio'!C4<>""),TRUE(),FALSE()),FALSE())) -> TRUE | W4: =IF(Configuration!$C$30="No","",IFERROR(IF(OR('Patent Portfolio'!S4="Pending",'Patent Portfolio'!T4="Yes"),TRUE(),FALSE()),FALSE())) -> FALSE | X4: =IF(Configuration!$C$31="No","",IFERROR(IF(AND(N('Patent Portfolio'!AC4)>=Configuration!$C$52,N('Patent Portfolio'!L4)>=1),TRUE(),FALSE()),FALSE())) -> TRUE | Y4: =IF(Configuration!$C$32="No","",IFERROR(IF(AND(N('Patent Portfolio'!N4)>=1,OR('Patent Portfolio'!C4<>"",'Patent Portfolio'!I4<>"")),TRUE(),FALSE()),FALSE())) -> TRUE | Z4: =IF(Configuration!$C$33="No","",IFERROR(IF('Patent Portfolio'!C4<>"",TRUE(),FALSE()),FALSE())) -> TRUE | AA4: =IF(Configuration!$C$34="No","",IFERROR(IF('Patent Portfolio'!T4="Yes",TRUE(),FALSE()),FALSE())) -> FALSE | AB4: =IF(Configuration!$C$35="No","",IFERROR(IF(OR('Patent Portfolio'!AK4="Partial",'Patent Portfolio'!AK4="Full"),TRUE(),FALSE()),FALSE())) -> TRUE | AC4: =IF(Configuration!$C$36="No","",IFERROR(IF('Patent Portfolio'!AI4="Survived",TRUE(),FALSE()),FALSE())) -> FALSE | AD4: =IF(Configuration!$C$37="No","",IFERROR(IF(AND('Patent Portfolio'!AJ4="Clean",'Patent Portfolio'!AL4="None"),TRUE(),FALSE()),FALSE())) -> TRUE | AE4: =IF(Configuration!$C$38="No","",IFERROR(IF(N('Patent Portfolio'!AG4)>=Configuration!$C$53,TRUE(),FALSE()),FALSE())) -> TRUE | AF4: =IF(Configuration!$C$39="No","",IFERROR(IF(AND(N('Patent Portfolio'!AO4)>=2,N('Patent Portfolio'!AB4)>=2),TRUE(),FALSE()),FALSE())) -> FALSE | AG4: =IF(Configuration!$C$40="No","",IFERROR(IF(OR(N('Patent Portfolio'!AC4)<=Configuration!$C$56,N('Patent Portfolio'!U4)<Configuration!$C$57,N('Patent Portfolio'!AD4)<=Configuration!$C$58),TRUE(),FALSE()),FALSE())) -> FALSE | AH4: =IF(Configuration!$C$41="No","",IFERROR(IF(AND(N('Patent Portfolio'!U4)>=Configuration!$C$54,N('Patent Portfolio'!U4)<=Configuration!$C$55),TRUE(),FALSE()),FALSE())) -> FALSE | AI4: =IF(Configuration!$C$42="No","",IFERROR(IF(AND('Patent Portfolio'!C4<>"",'Patent Portfolio'!F4<>""),TRUE(),FALSE()),FALSE())) -> TRUE | AJ4: =COUNTIF(C4:AI4,TRUE()) -> 21
A5: ='Patent Portfolio'!A5 -> P-003 | B5: ='Patent Portfolio'!B5 -> Adaptive Wi-Fi 7 channel sounding | C5: =IF(Configuration!$C$10="No","",IFERROR(IF('Patent Portfolio'!C5<>"",TRUE(),FALSE()),FALSE())) -> TRUE | D5: =IF(Configuration!$C$11="No","",IFERROR(IF(AND(N('Patent Portfolio'!H5)>=Configuration!$C$44,'Patent Portfolio'!I5<>""),TRUE(),FALSE()),FALSE())) -> TRUE | E5: =IF(Configuration!$C$12="No","",IFERROR(IF('Patent Portfolio'!F5<>"",TRUE(),FALSE()),FALSE())) -> TRUE | F5: =IF(Configuration!$C$13="No","",IFERROR(IF('Patent Portfolio'!E5<>"",TRUE(),FALSE()),FALSE())) -> TRUE | G5: =IF(Configuration!$C$14="No","",IFERROR(IF('Patent Portfolio'!G5<>"",TRUE(),FALSE()),FALSE())) -> TRUE | H5: =IF(Configuration!$C$15="No","",IFERROR(IF(AND(OR(ISNUMBER(SEARCH("process",'Patent Portfolio'!C5)),ISNUMBER(SEARCH("fab",'Patent Portfolio'!C5)),ISNUMBER(SEARCH("manufac",'Patent Portfolio'!C5))),'Patent Portfolio'!K5="Method"),TRUE(),FALSE()),FALSE())) -> FALSE | I5: =IF(Configuration!$C$16="No","",IFERROR(IF(AND(OR(ISNUMBER(SEARCH("material",'Patent Portfolio'!C5)),ISNUMBER(SEARCH("chem",'Patent Portfolio'!C5)),ISNUMBER(SEARCH("battery",'Patent Portfolio'!C5)),ISNUMBER(SEARCH("electrolyte",'Patent Portfolio'!C5)),ISNUMBER(SEARCH("polymer",'Patent Portfolio'!C5))),OR('Patent Portfolio'!K5="Apparatus",'Patent Portfolio'!K5="Method")),TRUE(),FALSE()),FALSE())) -> FALSE | J5: =IF(Configuration!$C$17="No","",IFERROR(IF(AND(OR('Patent Portfolio'!E5="App",'Patent Portfolio'!E5="Middleware",'Patent Portfolio'!E5="Cloud"),OR('Patent Portfolio'!K5="Method",'Patent Portfolio'!K5="CRM")),TRUE(),FALSE()),FALSE())) -> FALSE | K5: =IF(Configuration!$C$18="No","",IFERROR(IF(N('Patent Portfolio'!J5)>=Configuration!$C$45,TRUE(),FALSE()),FALSE())) -> TRUE | L5: =IF(Configuration!$C$19="No","",IFERROR(IF('Patent Portfolio'!AA5<>"",TRUE(),FALSE()),FALSE())) -> TRUE | M5: =IF(Configuration!$C$20="No","",IFERROR(IF('Patent Portfolio'!K5<>"",TRUE(),FALSE()),FALSE())) -> TRUE | N5: =IF(Configuration!$C$21="No","",IFERROR(IF(OR(N('Patent Portfolio'!O5)>=Configuration!$C$46,N('Patent Portfolio'!P5)>=Configuration!$C$47),TRUE(),FALSE()),FALSE())) -> TRUE | O5: =IF(Configuration!$C$22="No","",IFERROR(IF('Patent Portfolio'!X5="Yes",TRUE(),FALSE()),FALSE())) -> TRUE | P5: =IF(Configuration!$C$23="No","",IFERROR(IF(N('Patent Portfolio'!R5)>=Configuration!$C$48,TRUE(),FALSE()),FALSE())) -> TRUE | Q5: =IF(Configuration!$C$24="No","",IFERROR(IF(N('Patent Portfolio'!U5)>0,TRUE(),FALSE()),FALSE())) -> TRUE | R5: =IF(Configuration!$C$25="No","",IFERROR(IF(OR(N('Patent Portfolio'!L5)=3,N('Patent Portfolio'!L5)<=1),TRUE(),FALSE()),FALSE())) -> TRUE | S5: =IF(Configuration!$C$26="No","",IFERROR(IF(N('Patent Portfolio'!AB5)>=Configuration!$C$49,TRUE(),FALSE()),FALSE())) -> TRUE | T5: =IF(Configuration!$C$27="No","",IFERROR(IF('Patent Portfolio'!Z5<>"",TRUE(),FALSE()),FALSE())) -> FALSE | U5: =IF(Configuration!$C$28="No","",IFERROR(IF(N('Patent Portfolio'!Q5)>=Configuration!$C$50,TRUE(),FALSE()),FALSE())) -> TRUE | V5: =IF(Configuration!$C$29="No","",IFERROR(IF(AND(N('Patent Portfolio'!N5)>=Configuration!$C$51,'Patent Portfolio'!C5<>""),TRUE(),FALSE()),FALSE())) -> TRUE | W5: =IF(Configuration!$C$30="No","",IFERROR(IF(OR('Patent Portfolio'!S5="Pending",'Patent Portfolio'!T5="Yes"),TRUE(),FALSE()),FALSE())) -> TRUE | X5: =IF(Configuration!$C$31="No","",IFERROR(IF(AND(N('Patent Portfolio'!AC5)>=Configuration!$C$52,N('Patent Portfolio'!L5)>=1),TRUE(),FALSE()),FALSE())) -> TRUE | Y5: =IF(Configuration!$C$32="No","",IFERROR(IF(AND(N('Patent Portfolio'!N5)>=1,OR('Patent Portfolio'!C5<>"",'Patent Portfolio'!I5<>"")),TRUE(),FALSE()),FALSE())) -> TRUE | Z5: =IF(Configuration!$C$33="No","",IFERROR(IF('Patent Portfolio'!C5<>"",TRUE(),FALSE()),FALSE())) -> TRUE | AA5: =IF(Configuration!$C$34="No","",IFERROR(IF('Patent Portfolio'!T5="Yes",TRUE(),FALSE()),FALSE())) -> TRUE | AB5: =IF(Configuration!$C$35="No","",IFERROR(IF(OR('Patent Portfolio'!AK5="Partial",'Patent Portfolio'!AK5="Full"),TRUE(),FALSE()),FALSE())) -> FALSE | AC5: =IF(Configuration!$C$36="No","",IFERROR(IF('Patent Portfolio'!AI5="Survived",TRUE(),FALSE()),FALSE())) -> FALSE | AD5: =IF(Configuration!$C$37="No","",IFERROR(IF(AND('Patent Portfolio'!AJ5="Clean",'Patent Portfolio'!AL5="None"),TRUE(),FALSE()),FALSE())) -> TRUE | AE5: =IF(Configuration!$C$38="No","",IFERROR(IF(N('Patent Portfolio'!AG5)>=Configuration!$C$53,TRUE(),FALSE()),FALSE())) -> FALSE | AF5: =IF(Configuration!$C$39="No","",IFERROR(IF(AND(N('Patent Portfolio'!AO5)>=2,N('Patent Portfolio'!AB5)>=2),TRUE(),FALSE()),FALSE())) -> TRUE | AG5: =IF(Configuration!$C$40="No","",IFERROR(IF(OR(N('Patent Portfolio'!AC5)<=Configuration!$C$56,N('Patent Portfolio'!U5)<Configuration!$C$57,N('Patent Portfolio'!AD5)<=Configuration!$C$58),TRUE(),FALSE()),FALSE())) -> FALSE | AH5: =IF(Configuration!$C$41="No","",IFERROR(IF(AND(N('Patent Portfolio'!U5)>=Configuration!$C$54,N('Patent Portfolio'!U5)<=Configuration!$C$55),TRUE(),FALSE()),FALSE())) -> FALSE | AI5: =IF(Configuration!$C$42="No","",IFERROR(IF(AND('Patent Portfolio'!C5<>"",'Patent Portfolio'!F5<>""),TRUE(),FALSE()),FALSE())) -> TRUE | AJ5: =COUNTIF(C5:AI5,TRUE()) -> 24
A6: ='Patent Portfolio'!A6 -> P-004 | B6: ='Patent Portfolio'!B6 -> Solid-state electrolyte composition for EV batteries | C6: =IF(Configuration!$C$10="No","",IFERROR(IF('Patent Portfolio'!C6<>"",TRUE(),FALSE()),FALSE())) -> TRUE | D6: =IF(Configuration!$C$11="No","",IFERROR(IF(AND(N('Patent Portfolio'!H6)>=Configuration!$C$44,'Patent Portfolio'!I6<>""),TRUE(),FALSE()),FALSE())) -> FALSE | E6: =IF(Configuration!$C$12="No","",IFERROR(IF('Patent Portfolio'!F6<>"",TRUE(),FALSE()),FALSE())) -> TRUE | F6: =IF(Configuration!$C$13="No","",IFERROR(IF('Patent Portfolio'!E6<>"",TRUE(),FALSE()),FALSE())) -> TRUE | G6: =IF(Configuration!$C$14="No","",IFERROR(IF('Patent Portfolio'!G6<>"",TRUE(),FALSE()),FALSE())) -> TRUE | H6: =IF(Configuration!$C$15="No","",IFERROR(IF(AND(OR(ISNUMBER(SEARCH("process",'Patent Portfolio'!C6)),ISNUMBER(SEARCH("fab",'Patent Portfolio'!C6)),ISNUMBER(SEARCH("manufac",'Patent Portfolio'!C6))),'Patent Portfolio'!K6="Method"),TRUE(),FALSE()),FALSE())) -> FALSE | I6: =IF(Configuration!$C$16="No","",IFERROR(IF(AND(OR(ISNUMBER(SEARCH("material",'Patent Portfolio'!C6)),ISNUMBER(SEARCH("chem",'Patent Portfolio'!C6)),ISNUMBER(SEARCH("battery",'Patent Portfolio'!C6)),ISNUMBER(SEARCH("electrolyte",'Patent Portfolio'!C6)),ISNUMBER(SEARCH("polymer",'Patent Portfolio'!C6))),OR('Patent Portfolio'!K6="Apparatus",'Patent Portfolio'!K6="Method")),TRUE(),FALSE()),FALSE())) -> TRUE | J6: =IF(Configuration!$C$17="No","",IFERROR(IF(AND(OR('Patent Portfolio'!E6="App",'Patent Portfolio'!E6="Middleware",'Patent Portfolio'!E6="Cloud"),OR('Patent Portfolio'!K6="Method",'Patent Portfolio'!K6="CRM")),TRUE(),FALSE()),FALSE())) -> FALSE | K6: =IF(Configuration!$C$18="No","",IFERROR(IF(N('Patent Portfolio'!J6)>=Configuration!$C$45,TRUE(),FALSE()),FALSE())) -> FALSE | L6: =IF(Configuration!$C$19="No","",IFERROR(IF('Patent Portfolio'!AA6<>"",TRUE(),FALSE()),FALSE())) -> TRUE | M6: =IF(Configuration!$C$20="No","",IFERROR(IF('Patent Portfolio'!K6<>"",TRUE(),FALSE()),FALSE())) -> TRUE | N6: =IF(Configuration!$C$21="No","",IFERROR(IF(OR(N('Patent Portfolio'!O6)>=Configuration!$C$46,N('Patent Portfolio'!P6)>=Configuration!$C$47),TRUE(),FALSE()),FALSE())) -> TRUE | O6: =IF(Configuration!$C$22="No","",IFERROR(IF('Patent Portfolio'!X6="Yes",TRUE(),FALSE()),FALSE())) -> TRUE | P6: =IF(Configuration!$C$23="No","",IFERROR(IF(N('Patent Portfolio'!R6)>=Configuration!$C$48,TRUE(),FALSE()),FALSE())) -> TRUE | Q6: =IF(Configuration!$C$24="No","",IFERROR(IF(N('Patent Portfolio'!U6)>0,TRUE(),FALSE()),FALSE())) -> TRUE | R6: =IF(Configuration!$C$25="No","",IFERROR(IF(OR(N('Patent Portfolio'!L6)=3,N('Patent Portfolio'!L6)<=1),TRUE(),FALSE()),FALSE())) -> TRUE | S6: =IF(Configuration!$C$26="No","",IFERROR(IF(N('Patent Portfolio'!AB6)>=Configuration!$C$49,TRUE(),FALSE()),FALSE())) -> TRUE | T6: =IF(Configuration!$C$27="No","",IFERROR(IF('Patent Portfolio'!Z6<>"",TRUE(),FALSE()),FALSE())) -> FALSE | U6: =IF(Configuration!$C$28="No","",IFERROR(IF(N('Patent Portfolio'!Q6)>=Configuration!$C$50,TRUE(),FALSE()),FALSE())) -> TRUE | V6: =IF(Configuration!$C$29="No","",IFERROR(IF(AND(N('Patent Portfolio'!N6)>=Configuration!$C$51,'Patent Portfolio'!C6<>""),TRUE(),FALSE()),FALSE())) -> TRUE | W6: =IF(Configuration!$C$30="No","",IFERROR(IF(OR('Patent Portfolio'!S6="Pending",'Patent Portfolio'!T6="Yes"),TRUE(),FALSE()),FALSE())) -> TRUE | X6: =IF(Configuration!$C$31="No","",IFERROR(IF(AND(N('Patent Portfolio'!AC6)>=Configuration!$C$52,N('Patent Portfolio'!L6)>=1),TRUE(),FALSE()),FALSE())) -> TRUE | Y6: =IF(Configuration!$C$32="No","",IFERROR(IF(AND(N('Patent Portfolio'!N6)>=1,OR('Patent Portfolio'!C6<>"",'Patent Portfolio'!I6<>"")),TRUE(),FALSE()),FALSE())) -> TRUE | Z6: =IF(Configuration!$C$33="No","",IFERROR(IF('Patent Portfolio'!C6<>"",TRUE(),FALSE()),FALSE())) -> TRUE | AA6: =IF(Configuration!$C$34="No","",IFERROR(IF('Patent Portfolio'!T6="Yes",TRUE(),FALSE()),FALSE())) -> TRUE | AB6: =IF(Configuration!$C$35="No","",IFERROR(IF(OR('Patent Portfolio'!AK6="Partial",'Patent Portfolio'!AK6="Full"),TRUE(),FALSE()),FALSE())) -> TRUE | AC6: =IF(Configuration!$C$36="No","",IFERROR(IF('Patent Portfolio'!AI6="Survived",TRUE(),FALSE()),FALSE())) -> FALSE | AD6: =IF(Configuration!$C$37="No","",IFERROR(IF(AND('Patent Portfolio'!AJ6="Clean",'Patent Portfolio'!AL6="None"),TRUE(),FALSE()),FALSE())) -> TRUE | AE6: =IF(Configuration!$C$38="No","",IFERROR(IF(N('Patent Portfolio'!AG6)>=Configuration!$C$53,TRUE(),FALSE()),FALSE())) -> TRUE | AF6: =IF(Configuration!$C$39="No","",IFERROR(IF(AND(N('Patent Portfolio'!AO6)>=2,N('Patent Portfolio'!AB6)>=2),TRUE(),FALSE()),FALSE())) -> TRUE | AG6: =IF(Configuration!$C$40="No","",IFERROR(IF(OR(N('Patent Portfolio'!AC6)<=Configuration!$C$56,N('Patent Portfolio'!U6)<Configuration!$C$57,N('Patent Portfolio'!AD6)<=Configuration!$C$58),TRUE(),FALSE()),FALSE())) -> FALSE | AH6: =IF(Configuration!$C$41="No","",IFERROR(IF(AND(N('Patent Portfolio'!U6)>=Configuration!$C$54,N('Patent Portfolio'!U6)<=Configuration!$C$55),TRUE(),FALSE()),FALSE())) -> FALSE | AI6: =IF(Configuration!$C$42="No","",IFERROR(IF(AND('Patent Portfolio'!C6<>"",'Patent Portfolio'!F6<>""),TRUE(),FALSE()),FALSE())) -> TRUE | AJ6: =COUNTIF(C6:AI6,TRUE()) -> 25
A7: ='Patent Portfolio'!A7 -> P-005 | B7: ='Patent Portfolio'!B7 -> Battery thermal management with phase-change material | C7: =IF(Configuration!$C$10="No","",IFERROR(IF('Patent Portfolio'!C7<>"",TRUE(),FALSE()),FALSE())) -> TRUE | D7: =IF(Configuration!$C$11="No","",IFERROR(IF(AND(N('Patent Portfolio'!H7)>=Configuration!$C$44,'Patent Portfolio'!I7<>""),TRUE(),FALSE()),FALSE())) -> FALSE | E7: =IF(Configuration!$C$12="No","",IFERROR(IF('Patent Portfolio'!F7<>"",TRUE(),FALSE()),FALSE())) -> TRUE | F7: =IF(Configuration!$C$13="No","",IFERROR(IF('Patent Portfolio'!E7<>"",TRUE(),FALSE()),FALSE())) -> TRUE | G7: =IF(Configuration!$C$14="No","",IFERROR(IF('Patent Portfolio'!G7<>"",TRUE(),FALSE()),FALSE())) -> TRUE | H7: =IF(Configuration!$C$15="No","",IFERROR(IF(AND(OR(ISNUMBER(SEARCH("process",'Patent Portfolio'!C7)),ISNUMBER(SEARCH("fab",'Patent Portfolio'!C7)),ISNUMBER(SEARCH("manufac",'Patent Portfolio'!C7))),'Patent Portfolio'!K7="Method"),TRUE(),FALSE()),FALSE())) -> FALSE | I7: =IF(Configuration!$C$16="No","",IFERROR(IF(AND(OR(ISNUMBER(SEARCH("material",'Patent Portfolio'!C7)),ISNUMBER(SEARCH("chem",'Patent Portfolio'!C7)),ISNUMBER(SEARCH("battery",'Patent Portfolio'!C7)),ISNUMBER(SEARCH("electrolyte",'Patent Portfolio'!C7)),ISNUMBER(SEARCH("polymer",'Patent Portfolio'!C7))),OR('Patent Portfolio'!K7="Apparatus",'Patent Portfolio'!K7="Method")),TRUE(),FALSE()),FALSE())) -> FALSE | J7: =IF(Configuration!$C$17="No","",IFERROR(IF(AND(OR('Patent Portfolio'!E7="App",'Patent Portfolio'!E7="Middleware",'Patent Portfolio'!E7="Cloud"),OR('Patent Portfolio'!K7="Method",'Patent Portfolio'!K7="CRM")),TRUE(),FALSE()),FALSE())) -> FALSE | K7: =IF(Configuration!$C$18="No","",IFERROR(IF(N('Patent Portfolio'!J7)>=Configuration!$C$45,TRUE(),FALSE()),FALSE())) -> FALSE | L7: =IF(Configuration!$C$19="No","",IFERROR(IF('Patent Portfolio'!AA7<>"",TRUE(),FALSE()),FALSE())) -> TRUE | M7: =IF(Configuration!$C$20="No","",IFERROR(IF('Patent Portfolio'!K7<>"",TRUE(),FALSE()),FALSE())) -> TRUE | N7: =IF(Configuration!$C$21="No","",IFERROR(IF(OR(N('Patent Portfolio'!O7)>=Configuration!$C$46,N('Patent Portfolio'!P7)>=Configuration!$C$47),TRUE(),FALSE()),FALSE())) -> TRUE | O7: =IF(Configuration!$C$22="No","",IFERROR(IF('Patent Portfolio'!X7="Yes",TRUE(),FALSE()),FALSE())) -> TRUE | P7: =IF(Configuration!$C$23="No","",IFERROR(IF(N('Patent Portfolio'!R7)>=Configuration!$C$48,TRUE(),FALSE()),FALSE())) -> TRUE | Q7: =IF(Configuration!$C$24="No","",IFERROR(IF(N('Patent Portfolio'!U7)>0,TRUE(),FALSE()),FALSE())) -> TRUE | R7: =IF(Configuration!$C$25="No","",IFERROR(IF(OR(N('Patent Portfolio'!L7)=3,N('Patent Portfolio'!L7)<=1),TRUE(),FALSE()),FALSE())) -> FALSE | S7: =IF(Configuration!$C$26="No","",IFERROR(IF(N('Patent Portfolio'!AB7)>=Configuration!$C$49,TRUE(),FALSE()),FALSE())) -> TRUE | T7: =IF(Configuration!$C$27="No","",IFERROR(IF('Patent Portfolio'!Z7<>"",TRUE(),FALSE()),FALSE())) -> FALSE | U7: =IF(Configuration!$C$28="No","",IFERROR(IF(N('Patent Portfolio'!Q7)>=Configuration!$C$50,TRUE(),FALSE()),FALSE())) -> TRUE | V7: =IF(Configuration!$C$29="No","",IFERROR(IF(AND(N('Patent Portfolio'!N7)>=Configuration!$C$51,'Patent Portfolio'!C7<>""),TRUE(),FALSE()),FALSE())) -> TRUE | W7: =IF(Configuration!$C$30="No","",IFERROR(IF(OR('Patent Portfolio'!S7="Pending",'Patent Portfolio'!T7="Yes"),TRUE(),FALSE()),FALSE())) -> FALSE | X7: =IF(Configuration!$C$31="No","",IFERROR(IF(AND(N('Patent Portfolio'!AC7)>=Configuration!$C$52,N('Patent Portfolio'!L7)>=1),TRUE(),FALSE()),FALSE())) -> TRUE | Y7: =IF(Configuration!$C$32="No","",IFERROR(IF(AND(N('Patent Portfolio'!N7)>=1,OR('Patent Portfolio'!C7<>"",'Patent Portfolio'!I7<>"")),TRUE(),FALSE()),FALSE())) -> TRUE | Z7: =IF(Configuration!$C$33="No","",IFERROR(IF('Patent Portfolio'!C7<>"",TRUE(),FALSE()),FALSE())) -> TRUE | AA7: =IF(Configuration!$C$34="No","",IFERROR(IF('Patent Portfolio'!T7="Yes",TRUE(),FALSE()),FALSE())) -> FALSE | AB7: =IF(Configuration!$C$35="No","",IFERROR(IF(OR('Patent Portfolio'!AK7="Partial",'Patent Portfolio'!AK7="Full"),TRUE(),FALSE()),FALSE())) -> FALSE | AC7: =IF(Configuration!$C$36="No","",IFERROR(IF('Patent Portfolio'!AI7="Survived",TRUE(),FALSE()),FALSE())) -> FALSE | AD7: =IF(Configuration!$C$37="No","",IFERROR(IF(AND('Patent Portfolio'!AJ7="Clean",'Patent Portfolio'!AL7="None"),TRUE(),FALSE()),FALSE())) -> FALSE | AE7: =IF(Configuration!$C$38="No","",IFERROR(IF(N('Patent Portfolio'!AG7)>=Configuration!$C$53,TRUE(),FALSE()),FALSE())) -> FALSE | AF7: =IF(Configuration!$C$39="No","",IFERROR(IF(AND(N('Patent Portfolio'!AO7)>=2,N('Patent Portfolio'!AB7)>=2),TRUE(),FALSE()),FALSE())) -> TRUE | AG7: =IF(Configuration!$C$40="No","",IFERROR(IF(OR(N('Patent Portfolio'!AC7)<=Configuration!$C$56,N('Patent Portfolio'!U7)<Configuration!$C$57,N('Patent Portfolio'!AD7)<=Configuration!$C$58),TRUE(),FALSE()),FALSE())) -> FALSE | AH7: =IF(Configuration!$C$41="No","",IFERROR(IF(AND(N('Patent Portfolio'!U7)>=Configuration!$C$54,N('Patent Portfolio'!U7)<=Configuration!$C$55),TRUE(),FALSE()),FALSE())) -> FALSE | AI7: =IF(Configuration!$C$42="No","",IFERROR(IF(AND('Patent Portfolio'!C7<>"",'Patent Portfolio'!F7<>""),TRUE(),FALSE()),FALSE())) -> TRUE | AJ7: =COUNTIF(C7:AI7,TRUE()) -> 18
A8: ='Patent Portfolio'!A8 -> P-006 | B8: ='Patent Portfolio'!B8 -> SiC MOSFET inverter control method | C8: =IF(Configuration!$C$10="No","",IFERROR(IF('Patent Portfolio'!C8<>"",TRUE(),FALSE()),FALSE())) -> TRUE | D8: =IF(Configuration!$C$11="No","",IFERROR(IF(AND(N('Patent Portfolio'!H8)>=Configuration!$C$44,'Patent Portfolio'!I8<>""),TRUE(),FALSE()),FALSE())) -> FALSE | E8: =IF(Configuration!$C$12="No","",IFERROR(IF('Patent Portfolio'!F8<>"",TRUE(),FALSE()),FALSE())) -> TRUE | F8: =IF(Configuration!$C$13="No","",IFERROR(IF('Patent Portfolio'!E8<>"",TRUE(),FALSE()),FALSE())) -> TRUE | G8: =IF(Configuration!$C$14="No","",IFERROR(IF('Patent Portfolio'!G8<>"",TRUE(),FALSE()),FALSE())) -> TRUE | H8: =IF(Configuration!$C$15="No","",IFERROR(IF(AND(OR(ISNUMBER(SEARCH("process",'Patent Portfolio'!C8)),ISNUMBER(SEARCH("fab",'Patent Portfolio'!C8)),ISNUMBER(SEARCH("manufac",'Patent Portfolio'!C8))),'Patent Portfolio'!K8="Method"),TRUE(),FALSE()),FALSE())) -> FALSE | I8: =IF(Configuration!$C$16="No","",IFERROR(IF(AND(OR(ISNUMBER(SEARCH("material",'Patent Portfolio'!C8)),ISNUMBER(SEARCH("chem",'Patent Portfolio'!C8)),ISNUMBER(SEARCH("battery",'Patent Portfolio'!C8)),ISNUMBER(SEARCH("electrolyte",'Patent Portfolio'!C8)),ISNUMBER(SEARCH("polymer",'Patent Portfolio'!C8))),OR('Patent Portfolio'!K8="Apparatus",'Patent Portfolio'!K8="Method")),TRUE(),FALSE()),FALSE())) -> FALSE | J8: =IF(Configuration!$C$17="No","",IFERROR(IF(AND(OR('Patent Portfolio'!E8="App",'Patent Portfolio'!E8="Middleware",'Patent Portfolio'!E8="Cloud"),OR('Patent Portfolio'!K8="Method",'Patent Portfolio'!K8="CRM")),TRUE(),FALSE()),FALSE())) -> FALSE | K8: =IF(Configuration!$C$18="No","",IFERROR(IF(N('Patent Portfolio'!J8)>=Configuration!$C$45,TRUE(),FALSE()),FALSE())) -> FALSE | L8: =IF(Configuration!$C$19="No","",IFERROR(IF('Patent Portfolio'!AA8<>"",TRUE(),FALSE()),FALSE())) -> TRUE | M8: =IF(Configuration!$C$20="No","",IFERROR(IF('Patent Portfolio'!K8<>"",TRUE(),FALSE()),FALSE())) -> TRUE | N8: =IF(Configuration!$C$21="No","",IFERROR(IF(OR(N('Patent Portfolio'!O8)>=Configuration!$C$46,N('Patent Portfolio'!P8)>=Configuration!$C$47),TRUE(),FALSE()),FALSE())) -> TRUE | O8: =IF(Configuration!$C$22="No","",IFERROR(IF('Patent Portfolio'!X8="Yes",TRUE(),FALSE()),FALSE())) -> TRUE | P8: =IF(Configuration!$C$23="No","",IFERROR(IF(N('Patent Portfolio'!R8)>=Configuration!$C$48,TRUE(),FALSE()),FALSE())) -> TRUE | Q8: =IF(Configuration!$C$24="No","",IFERROR(IF(N('Patent Portfolio'!U8)>0,TRUE(),FALSE()),FALSE())) -> TRUE | R8: =IF(Configuration!$C$25="No","",IFERROR(IF(OR(N('Patent Portfolio'!L8)=3,N('Patent Portfolio'!L8)<=1),TRUE(),FALSE()),FALSE())) -> FALSE | S8: =IF(Configuration!$C$26="No","",IFERROR(IF(N('Patent Portfolio'!AB8)>=Configuration!$C$49,TRUE(),FALSE()),FALSE())) -> TRUE | T8: =IF(Configuration!$C$27="No","",IFERROR(IF('Patent Portfolio'!Z8<>"",TRUE(),FALSE()),FALSE())) -> FALSE | U8: =IF(Configuration!$C$28="No","",IFERROR(IF(N('Patent Portfolio'!Q8)>=Configuration!$C$50,TRUE(),FALSE()),FALSE())) -> TRUE | V8: =IF(Configuration!$C$29="No","",IFERROR(IF(AND(N('Patent Portfolio'!N8)>=Configuration!$C$51,'Patent Portfolio'!C8<>""),TRUE(),FALSE()),FALSE())) -> TRUE | W8: =IF(Configuration!$C$30="No","",IFERROR(IF(OR('Patent Portfolio'!S8="Pending",'Patent Portfolio'!T8="Yes"),TRUE(),FALSE()),FALSE())) -> FALSE | X8: =IF(Configuration!$C$31="No","",IFERROR(IF(AND(N('Patent Portfolio'!AC8)>=Configuration!$C$52,N('Patent Portfolio'!L8)>=1),TRUE(),FALSE()),FALSE())) -> TRUE | Y8: =IF(Configuration!$C$32="No","",IFERROR(IF(AND(N('Patent Portfolio'!N8)>=1,OR('Patent Portfolio'!C8<>"",'Patent Portfolio'!I8<>"")),TRUE(),FALSE()),FALSE())) -> TRUE | Z8: =IF(Configuration!$C$33="No","",IFERROR(IF('Patent Portfolio'!C8<>"",TRUE(),FALSE()),FALSE())) -> TRUE | AA8: =IF(Configuration!$C$34="No","",IFERROR(IF('Patent Portfolio'!T8="Yes",TRUE(),FALSE()),FALSE())) -> FALSE | AB8: =IF(Configuration!$C$35="No","",IFERROR(IF(OR('Patent Portfolio'!AK8="Partial",'Patent Portfolio'!AK8="Full"),TRUE(),FALSE()),FALSE())) -> TRUE | AC8: =IF(Configuration!$C$36="No","",IFERROR(IF('Patent Portfolio'!AI8="Survived",TRUE(),FALSE()),FALSE())) -> FALSE | AD8: =IF(Configuration!$C$37="No","",IFERROR(IF(AND('Patent Portfolio'!AJ8="Clean",'Patent Portfolio'!AL8="None"),TRUE(),FALSE()),FALSE())) -> FALSE | AE8: =IF(Configuration!$C$38="No","",IFERROR(IF(N('Patent Portfolio'!AG8)>=Configuration!$C$53,TRUE(),FALSE()),FALSE())) -> TRUE | AF8: =IF(Configuration!$C$39="No","",IFERROR(IF(AND(N('Patent Portfolio'!AO8)>=2,N('Patent Portfolio'!AB8)>=2),TRUE(),FALSE()),FALSE())) -> TRUE | AG8: =IF(Configuration!$C$40="No","",IFERROR(IF(OR(N('Patent Portfolio'!AC8)<=Configuration!$C$56,N('Patent Portfolio'!U8)<Configuration!$C$57,N('Patent Portfolio'!AD8)<=Configuration!$C$58),TRUE(),FALSE()),FALSE())) -> FALSE | AH8: =IF(Configuration!$C$41="No","",IFERROR(IF(AND(N('Patent Portfolio'!U8)>=Configuration!$C$54,N('Patent Portfolio'!U8)<=Configuration!$C$55),TRUE(),FALSE()),FALSE())) -> FALSE | AI8: =IF(Configuration!$C$42="No","",IFERROR(IF(AND('Patent Portfolio'!C8<>"",'Patent Portfolio'!F8<>""),TRUE(),FALSE()),FALSE())) -> TRUE | AJ8: =COUNTIF(C8:AI8,TRUE()) -> 20
A9: ='Patent Portfolio'!A9 -> P-007 | B9: ='Patent Portfolio'!B9 -> On-device CNN quantization for low-power inference | C9: =IF(Configuration!$C$10="No","",IFERROR(IF('Patent Portfolio'!C9<>"",TRUE(),FALSE()),FALSE())) -> TRUE | D9: =IF(Configuration!$C$11="No","",IFERROR(IF(AND(N('Patent Portfolio'!H9)>=Configuration!$C$44,'Patent Portfolio'!I9<>""),TRUE(),FALSE()),FALSE())) -> FALSE | E9: =IF(Configuration!$C$12="No","",IFERROR(IF('Patent Portfolio'!F9<>"",TRUE(),FALSE()),FALSE())) -> TRUE | F9: =IF(Configuration!$C$13="No","",IFERROR(IF('Patent Portfolio'!E9<>"",TRUE(),FALSE()),FALSE())) -> TRUE | G9: =IF(Configuration!$C$14="No","",IFERROR(IF('Patent Portfolio'!G9<>"",TRUE(),FALSE()),FALSE())) -> TRUE | H9: =IF(Configuration!$C$15="No","",IFERROR(IF(AND(OR(ISNUMBER(SEARCH("process",'Patent Portfolio'!C9)),ISNUMBER(SEARCH("fab",'Patent Portfolio'!C9)),ISNUMBER(SEARCH("manufac",'Patent Portfolio'!C9))),'Patent Portfolio'!K9="Method"),TRUE(),FALSE()),FALSE())) -> FALSE | I9: =IF(Configuration!$C$16="No","",IFERROR(IF(AND(OR(ISNUMBER(SEARCH("material",'Patent Portfolio'!C9)),ISNUMBER(SEARCH("chem",'Patent Portfolio'!C9)),ISNUMBER(SEARCH("battery",'Patent Portfolio'!C9)),ISNUMBER(SEARCH("electrolyte",'Patent Portfolio'!C9)),ISNUMBER(SEARCH("polymer",'Patent Portfolio'!C9))),OR('Patent Portfolio'!K9="Apparatus",'Patent Portfolio'!K9="Method")),TRUE(),FALSE()),FALSE())) -> FALSE | J9: =IF(Configuration!$C$17="No","",IFERROR(IF(AND(OR('Patent Portfolio'!E9="App",'Patent Portfolio'!E9="Middleware",'Patent Portfolio'!E9="Cloud"),OR('Patent Portfolio'!K9="Method",'Patent Portfolio'!K9="CRM")),TRUE(),FALSE()),FALSE())) -> TRUE | K9: =IF(Configuration!$C$18="No","",IFERROR(IF(N('Patent Portfolio'!J9)>=Configuration!$C$45,TRUE(),FALSE()),FALSE())) -> FALSE | L9: =IF(Configuration!$C$19="No","",IFERROR(IF('Patent Portfolio'!AA9<>"",TRUE(),FALSE()),FALSE())) -> TRUE | M9: =IF(Configuration!$C$20="No","",IFERROR(IF('Patent Portfolio'!K9<>"",TRUE(),FALSE()),FALSE())) -> TRUE | N9: =IF(Configuration!$C$21="No","",IFERROR(IF(OR(N('Patent Portfolio'!O9)>=Configuration!$C$46,N('Patent Portfolio'!P9)>=Configuration!$C$47),TRUE(),FALSE()),FALSE())) -> TRUE | O9: =IF(Configuration!$C$22="No","",IFERROR(IF('Patent Portfolio'!X9="Yes",TRUE(),FALSE()),FALSE())) -> TRUE | P9: =IF(Configuration!$C$23="No","",IFERROR(IF(N('Patent Portfolio'!R9)>=Configuration!$C$48,TRUE(),FALSE()),FALSE())) -> TRUE | Q9: =IF(Configuration!$C$24="No","",IFERROR(IF(N('Patent Portfolio'!U9)>0,TRUE(),FALSE()),FALSE())) -> TRUE | R9: =IF(Configuration!$C$25="No","",IFERROR(IF(OR(N('Patent Portfolio'!L9)=3,N('Patent Portfolio'!L9)<=1),TRUE(),FALSE()),FALSE())) -> FALSE | S9: =IF(Configuration!$C$26="No","",IFERROR(IF(N('Patent Portfolio'!AB9)>=Configuration!$C$49,TRUE(),FALSE()),FALSE())) -> TRUE | T9: =IF(Configuration!$C$27="No","",IFERROR(IF('Patent Portfolio'!Z9<>"",TRUE(),FALSE()),FALSE())) -> TRUE | U9: =IF(Configuration!$C$28="No","",IFERROR(IF(N('Patent Portfolio'!Q9)>=Configuration!$C$50,TRUE(),FALSE()),FALSE())) -> TRUE | V9: =IF(Configuration!$C$29="No","",IFERROR(IF(AND(N('Patent Portfolio'!N9)>=Configuration!$C$51,'Patent Portfolio'!C9<>""),TRUE(),FALSE()),FALSE())) -> TRUE | W9: =IF(Configuration!$C$30="No","",IFERROR(IF(OR('Patent Portfolio'!S9="Pending",'Patent Portfolio'!T9="Yes"),TRUE(),FALSE()),FALSE())) -> TRUE | X9: =IF(Configuration!$C$31="No","",IFERROR(IF(AND(N('Patent Portfolio'!AC9)>=Configuration!$C$52,N('Patent Portfolio'!L9)>=1),TRUE(),FALSE()),FALSE())) -> TRUE | Y9: =IF(Configuration!$C$32="No","",IFERROR(IF(AND(N('Patent Portfolio'!N9)>=1,OR('Patent Portfolio'!C9<>"",'Patent Portfolio'!I9<>"")),TRUE(),FALSE()),FALSE())) -> TRUE | Z9: =IF(Configuration!$C$33="No","",IFERROR(IF('Patent Portfolio'!C9<>"",TRUE(),FALSE()),FALSE())) -> TRUE | AA9: =IF(Configuration!$C$34="No","",IFERROR(IF('Patent Portfolio'!T9="Yes",TRUE(),FALSE()),FALSE())) -> TRUE | AB9: =IF(Configuration!$C$35="No","",IFERROR(IF(OR('Patent Portfolio'!AK9="Partial",'Patent Portfolio'!AK9="Full"),TRUE(),FALSE()),FALSE())) -> TRUE | AC9: =IF(Configuration!$C$36="No","",IFERROR(IF('Patent Portfolio'!AI9="Survived",TRUE(),FALSE()),FALSE())) -> FALSE | AD9: =IF(Configuration!$C$37="No","",IFERROR(IF(AND('Patent Portfolio'!AJ9="Clean",'Patent Portfolio'!AL9="None"),TRUE(),FALSE()),FALSE())) -> TRUE | AE9: =IF(Configuration!$C$38="No","",IFERROR(IF(N('Patent Portfolio'!AG9)>=Configuration!$C$53,TRUE(),FALSE()),FALSE())) -> TRUE | AF9: =IF(Configuration!$C$39="No","",IFERROR(IF(AND(N('Patent Portfolio'!AO9)>=2,N('Patent Portfolio'!AB9)>=2),TRUE(),FALSE()),FALSE())) -> TRUE | AG9: =IF(Configuration!$C$40="No","",IFERROR(IF(OR(N('Patent Portfolio'!AC9)<=Configuration!$C$56,N('Patent Portfolio'!U9)<Configuration!$C$57,N('Patent Portfolio'!AD9)<=Configuration!$C$58),TRUE(),FALSE()),FALSE())) -> TRUE | AH9: =IF(Configuration!$C$41="No","",IFERROR(IF(AND(N('Patent Portfolio'!U9)>=Configuration!$C$54,N('Patent Portfolio'!U9)<=Configuration!$C$55),TRUE(),FALSE()),FALSE())) -> FALSE | AI9: =IF(Configuration!$C$42="No","",IFERROR(IF(AND('Patent Portfolio'!C9<>"",'Patent Portfolio'!F9<>""),TRUE(),FALSE()),FALSE())) -> TRUE | AJ9: =COUNTIF(C9:AI9,TRUE()) -> 26
A10: ='Patent Portfolio'!A10 -> P-008 | B10: ='Patent Portfolio'!B10 -> Transformer attention pruning for vision models | C10: =IF(Configuration!$C$10="No","",IFERROR(IF('Patent Portfolio'!C10<>"",TRUE(),FALSE()),FALSE())) -> TRUE | D10: =IF(Configuration!$C$11="No","",IFERROR(IF(AND(N('Patent Portfolio'!H10)>=Configuration!$C$44,'Patent Portfolio'!I10<>""),TRUE(),FALSE()),FALSE())) -> FALSE | E10: =IF(Configuration!$C$12="No","",IFERROR(IF('Patent Portfolio'!F10<>"",TRUE(),FALSE()),FALSE())) -> TRUE | F10: =IF(Configuration!$C$13="No","",IFERROR(IF('Patent Portfolio'!E10<>"",TRUE(),FALSE()),FALSE())) -> TRUE | G10: =IF(Configuration!$C$14="No","",IFERROR(IF('Patent Portfolio'!G10<>"",TRUE(),FALSE()),FALSE())) -> TRUE | H10: =IF(Configuration!$C$15="No","",IFERROR(IF(AND(OR(ISNUMBER(SEARCH("process",'Patent Portfolio'!C10)),ISNUMBER(SEARCH("fab",'Patent Portfolio'!C10)),ISNUMBER(SEARCH("manufac",'Patent Portfolio'!C10))),'Patent Portfolio'!K10="Method"),TRUE(),FALSE()),FALSE())) -> FALSE | I10: =IF(Configuration!$C$16="No","",IFERROR(IF(AND(OR(ISNUMBER(SEARCH("material",'Patent Portfolio'!C10)),ISNUMBER(SEARCH("chem",'Patent Portfolio'!C10)),ISNUMBER(SEARCH("battery",'Patent Portfolio'!C10)),ISNUMBER(SEARCH("electrolyte",'Patent Portfolio'!C10)),ISNUMBER(SEARCH("polymer",'Patent Portfolio'!C10))),OR('Patent Portfolio'!K10="Apparatus",'Patent Portfolio'!K10="Method")),TRUE(),FALSE()),FALSE())) -> FALSE | J10: =IF(Configuration!$C$17="No","",IFERROR(IF(AND(OR('Patent Portfolio'!E10="App",'Patent Portfolio'!E10="Middleware",'Patent Portfolio'!E10="Cloud"),OR('Patent Portfolio'!K10="Method",'Patent Portfolio'!K10="CRM")),TRUE(),FALSE()),FALSE())) -> TRUE | K10: =IF(Configuration!$C$18="No","",IFERROR(IF(N('Patent Portfolio'!J10)>=Configuration!$C$45,TRUE(),FALSE()),FALSE())) -> FALSE | L10: =IF(Configuration!$C$19="No","",IFERROR(IF('Patent Portfolio'!AA10<>"",TRUE(),FALSE()),FALSE())) -> TRUE | M10: =IF(Configuration!$C$20="No","",IFERROR(IF('Patent Portfolio'!K10<>"",TRUE(),FALSE()),FALSE())) -> TRUE | N10: =IF(Configuration!$C$21="No","",IFERROR(IF(OR(N('Patent Portfolio'!O10)>=Configuration!$C$46,N('Patent Portfolio'!P10)>=Configuration!$C$47),TRUE(),FALSE()),FALSE())) -> TRUE | O10: =IF(Configuration!$C$22="No","",IFERROR(IF('Patent Portfolio'!X10="Yes",TRUE(),FALSE()),FALSE())) -> FALSE | P10: =IF(Configuration!$C$23="No","",IFERROR(IF(N('Patent Portfolio'!R10)>=Configuration!$C$48,TRUE(),FALSE()),FALSE())) -> TRUE | Q10: =IF(Configuration!$C$24="No","",IFERROR(IF(N('Patent Portfolio'!U10)>0,TRUE(),FALSE()),FALSE())) -> TRUE | R10: =IF(Configuration!$C$25="No","",IFERROR(IF(OR(N('Patent Portfolio'!L10)=3,N('Patent Portfolio'!L10)<=1),TRUE(),FALSE()),FALSE())) -> TRUE | S10: =IF(Configuration!$C$26="No","",IFERROR(IF(N('Patent Portfolio'!AB10)>=Configuration!$C$49,TRUE(),FALSE()),FALSE())) -> TRUE | T10: =IF(Configuration!$C$27="No","",IFERROR(IF('Patent Portfolio'!Z10<>"",TRUE(),FALSE()),FALSE())) -> TRUE | U10: =IF(Configuration!$C$28="No","",IFERROR(IF(N('Patent Portfolio'!Q10)>=Configuration!$C$50,TRUE(),FALSE()),FALSE())) -> TRUE | V10: =IF(Configuration!$C$29="No","",IFERROR(IF(AND(N('Patent Portfolio'!N10)>=Configuration!$C$51,'Patent Portfolio'!C10<>""),TRUE(),FALSE()),FALSE())) -> FALSE | W10: =IF(Configuration!$C$30="No","",IFERROR(IF(OR('Patent Portfolio'!S10="Pending",'Patent Portfolio'!T10="Yes"),TRUE(),FALSE()),FALSE())) -> TRUE | X10: =IF(Configuration!$C$31="No","",IFERROR(IF(AND(N('Patent Portfolio'!AC10)>=Configuration!$C$52,N('Patent Portfolio'!L10)>=1),TRUE(),FALSE()),FALSE())) -> FALSE | Y10: =IF(Configuration!$C$32="No","",IFERROR(IF(AND(N('Patent Portfolio'!N10)>=1,OR('Patent Portfolio'!C10<>"",'Patent Portfolio'!I10<>"")),TRUE(),FALSE()),FALSE())) -> TRUE | Z10: =IF(Configuration!$C$33="No","",IFERROR(IF('Patent Portfolio'!C10<>"",TRUE(),FALSE()),FALSE())) -> TRUE | AA10: =IF(Configuration!$C$34="No","",IFERROR(IF('Patent Portfolio'!T10="Yes",TRUE(),FALSE()),FALSE())) -> TRUE | AB10: =IF(Configuration!$C$35="No","",IFERROR(IF(OR('Patent Portfolio'!AK10="Partial",'Patent Portfolio'!AK10="Full"),TRUE(),FALSE()),FALSE())) -> FALSE | AC10: =IF(Configuration!$C$36="No","",IFERROR(IF('Patent Portfolio'!AI10="Survived",TRUE(),FALSE()),FALSE())) -> FALSE | AD10: =IF(Configuration!$C$37="No","",IFERROR(IF(AND('Patent Portfolio'!AJ10="Clean",'Patent Portfolio'!AL10="None"),TRUE(),FALSE()),FALSE())) -> TRUE | AE10: =IF(Configuration!$C$38="No","",IFERROR(IF(N('Patent Portfolio'!AG10)>=Configuration!$C$53,TRUE(),FALSE()),FALSE())) -> FALSE | AF10: =IF(Configuration!$C$39="No","",IFERROR(IF(AND(N('Patent Portfolio'!AO10)>=2,N('Patent Portfolio'!AB10)>=2),TRUE(),FALSE()),FALSE())) -> TRUE | AG10: =IF(Configuration!$C$40="No","",IFERROR(IF(OR(N('Patent Portfolio'!AC10)<=Configuration!$C$56,N('Patent Portfolio'!U10)<Configuration!$C$57,N('Patent Portfolio'!AD10)<=Configuration!$C$58),TRUE(),FALSE()),FALSE())) -> TRUE | AH10: =IF(Configuration!$C$41="No","",IFERROR(IF(AND(N('Patent Portfolio'!U10)>=Configuration!$C$54,N('Patent Portfolio'!U10)<=Configuration!$C$55),TRUE(),FALSE()),FALSE())) -> FALSE | AI10: =IF(Configuration!$C$42="No","",IFERROR(IF(AND('Patent Portfolio'!C10<>"",'Patent Portfolio'!F10<>""),TRUE(),FALSE()),FALSE())) -> TRUE | AJ10: =COUNTIF(C10:AI10,TRUE()) -> 22
A11: ='Patent Portfolio'!A11 -> P-009 | B11: ='Patent Portfolio'!B11 -> Visual SLAM for indoor robot navigation | C11: =IF(Configuration!$C$10="No","",IFERROR(IF('Patent Portfolio'!C11<>"",TRUE(),FALSE()),FALSE())) -> TRUE | D11: =IF(Configuration!$C$11="No","",IFERROR(IF(AND(N('Patent Portfolio'!H11)>=Configuration!$C$44,'Patent Portfolio'!I11<>""),TRUE(),FALSE()),FALSE())) -> FALSE | E11: =IF(Configuration!$C$12="No","",IFERROR(IF('Patent Portfolio'!F11<>"",TRUE(),FALSE()),FALSE())) -> TRUE | F11: =IF(Configuration!$C$13="No","",IFERROR(IF('Patent Portfolio'!E11<>"",TRUE(),FALSE()),FALSE())) -> TRUE | G11: =IF(Configuration!$C$14="No","",IFERROR(IF('Patent Portfolio'!G11<>"",TRUE(),FALSE()),FALSE())) -> TRUE | H11: =IF(Configuration!$C$15="No","",IFERROR(IF(AND(OR(ISNUMBER(SEARCH("process",'Patent Portfolio'!C11)),ISNUMBER(SEARCH("fab",'Patent Portfolio'!C11)),ISNUMBER(SEARCH("manufac",'Patent Portfolio'!C11))),'Patent Portfolio'!K11="Method"),TRUE(),FALSE()),FALSE())) -> FALSE | I11: =IF(Configuration!$C$16="No","",IFERROR(IF(AND(OR(ISNUMBER(SEARCH("material",'Patent Portfolio'!C11)),ISNUMBER(SEARCH("chem",'Patent Portfolio'!C11)),ISNUMBER(SEARCH("battery",'Patent Portfolio'!C11)),ISNUMBER(SEARCH("electrolyte",'Patent Portfolio'!C11)),ISNUMBER(SEARCH("polymer",'Patent Portfolio'!C11))),OR('Patent Portfolio'!K11="Apparatus",'Patent Portfolio'!K11="Method")),TRUE(),FALSE()),FALSE())) -> FALSE | J11: =IF(Configuration!$C$17="No","",IFERROR(IF(AND(OR('Patent Portfolio'!E11="App",'Patent Portfolio'!E11="Middleware",'Patent Portfolio'!E11="Cloud"),OR('Patent Portfolio'!K11="Method",'Patent Portfolio'!K11="CRM")),TRUE(),FALSE()),FALSE())) -> FALSE | K11: =IF(Configuration!$C$18="No","",IFERROR(IF(N('Patent Portfolio'!J11)>=Configuration!$C$45,TRUE(),FALSE()),FALSE())) -> FALSE | L11: =IF(Configuration!$C$19="No","",IFERROR(IF('Patent Portfolio'!AA11<>"",TRUE(),FALSE()),FALSE())) -> TRUE | M11: =IF(Configuration!$C$20="No","",IFERROR(IF('Patent Portfolio'!K11<>"",TRUE(),FALSE()),FALSE())) -> TRUE | N11: =IF(Configuration!$C$21="No","",IFERROR(IF(OR(N('Patent Portfolio'!O11)>=Configuration!$C$46,N('Patent Portfolio'!P11)>=Configuration!$C$47),TRUE(),FALSE()),FALSE())) -> TRUE | O11: =IF(Configuration!$C$22="No","",IFERROR(IF('Patent Portfolio'!X11="Yes",TRUE(),FALSE()),FALSE())) -> TRUE | P11: =IF(Configuration!$C$23="No","",IFERROR(IF(N('Patent Portfolio'!R11)>=Configuration!$C$48,TRUE(),FALSE()),FALSE())) -> TRUE | Q11: =IF(Configuration!$C$24="No","",IFERROR(IF(N('Patent Portfolio'!U11)>0,TRUE(),FALSE()),FALSE())) -> TRUE | R11: =IF(Configuration!$C$25="No","",IFERROR(IF(OR(N('Patent Portfolio'!L11)=3,N('Patent Portfolio'!L11)<=1),TRUE(),FALSE()),FALSE())) -> FALSE | S11: =IF(Configuration!$C$26="No","",IFERROR(IF(N('Patent Portfolio'!AB11)>=Configuration!$C$49,TRUE(),FALSE()),FALSE())) -> TRUE | T11: =IF(Configuration!$C$27="No","",IFERROR(IF('Patent Portfolio'!Z11<>"",TRUE(),FALSE()),FALSE())) -> TRUE | U11: =IF(Configuration!$C$28="No","",IFERROR(IF(N('Patent Portfolio'!Q11)>=Configuration!$C$50,TRUE(),FALSE()),FALSE())) -> TRUE | V11: =IF(Configuration!$C$29="No","",IFERROR(IF(AND(N('Patent Portfolio'!N11)>=Configuration!$C$51,'Patent Portfolio'!C11<>""),TRUE(),FALSE()),FALSE())) -> TRUE | W11: =IF(Configuration!$C$30="No","",IFERROR(IF(OR('Patent Portfolio'!S11="Pending",'Patent Portfolio'!T11="Yes"),TRUE(),FALSE()),FALSE())) -> FALSE | X11: =IF(Configuration!$C$31="No","",IFERROR(IF(AND(N('Patent Portfolio'!AC11)>=Configuration!$C$52,N('Patent Portfolio'!L11)>=1),TRUE(),FALSE()),FALSE())) -> TRUE | Y11: =IF(Configuration!$C$32="No","",IFERROR(IF(AND(N('Patent Portfolio'!N11)>=1,OR('Patent Portfolio'!C11<>"",'Patent Portfolio'!I11<>"")),TRUE(),FALSE()),FALSE())) -> TRUE | Z11: =IF(Configuration!$C$33="No","",IFERROR(IF('Patent Portfolio'!C11<>"",TRUE(),FALSE()),FALSE())) -> TRUE | AA11: =IF(Configuration!$C$34="No","",IFERROR(IF('Patent Portfolio'!T11="Yes",TRUE(),FALSE()),FALSE())) -> FALSE | AB11: =IF(Configuration!$C$35="No","",IFERROR(IF(OR('Patent Portfolio'!AK11="Partial",'Patent Portfolio'!AK11="Full"),TRUE(),FALSE()),FALSE())) -> TRUE | AC11: =IF(Configuration!$C$36="No","",IFERROR(IF('Patent Portfolio'!AI11="Survived",TRUE(),FALSE()),FALSE())) -> FALSE | AD11: =IF(Configuration!$C$37="No","",IFERROR(IF(AND('Patent Portfolio'!AJ11="Clean",'Patent Portfolio'!AL11="None"),TRUE(),FALSE()),FALSE())) -> TRUE | AE11: =IF(Configuration!$C$38="No","",IFERROR(IF(N('Patent Portfolio'!AG11)>=Configuration!$C$53,TRUE(),FALSE()),FALSE())) -> TRUE | AF11: =IF(Configuration!$C$39="No","",IFERROR(IF(AND(N('Patent Portfolio'!AO11)>=2,N('Patent Portfolio'!AB11)>=2),TRUE(),FALSE()),FALSE())) -> TRUE | AG11: =IF(Configuration!$C$40="No","",IFERROR(IF(OR(N('Patent Portfolio'!AC11)<=Configuration!$C$56,N('Patent Portfolio'!U11)<Configuration!$C$57,N('Patent Portfolio'!AD11)<=Configuration!$C$58),TRUE(),FALSE()),FALSE())) -> FALSE | AH11: =IF(Configuration!$C$41="No","",IFERROR(IF(AND(N('Patent Portfolio'!U11)>=Configuration!$C$54,N('Patent Portfolio'!U11)<=Configuration!$C$55),TRUE(),FALSE()),FALSE())) -> FALSE | AI11: =IF(Configuration!$C$42="No","",IFERROR(IF(AND('Patent Portfolio'!C11<>"",'Patent Portfolio'!F11<>""),TRUE(),FALSE()),FALSE())) -> TRUE | AJ11: =COUNTIF(C11:AI11,TRUE()) -> 22
A12: ='Patent Portfolio'!A12 -> P-010 | B12: ='Patent Portfolio'!B12 -> USB-C power delivery handshake extension | C12: =IF(Configuration!$C$10="No","",IFERROR(IF('Patent Portfolio'!C12<>"",TRUE(),FALSE()),FALSE())) -> TRUE | D12: =IF(Configuration!$C$11="No","",IFERROR(IF(AND(N('Patent Portfolio'!H12)>=Configuration!$C$44,'Patent Portfolio'!I12<>""),TRUE(),FALSE()),FALSE())) -> TRUE | E12: =IF(Configuration!$C$12="No","",IFERROR(IF('Patent Portfolio'!F12<>"",TRUE(),FALSE()),FALSE())) -> TRUE | F12: =IF(Configuration!$C$13="No","",IFERROR(IF('Patent Portfolio'!E12<>"",TRUE(),FALSE()),FALSE())) -> TRUE | G12: =IF(Configuration!$C$14="No","",IFERROR(IF('Patent Portfolio'!G12<>"",TRUE(),FALSE()),FALSE())) -> TRUE | H12: =IF(Configuration!$C$15="No","",IFERROR(IF(AND(OR(ISNUMBER(SEARCH("process",'Patent Portfolio'!C12)),ISNUMBER(SEARCH("fab",'Patent Portfolio'!C12)),ISNUMBER(SEARCH("manufac",'Patent Portfolio'!C12))),'Patent Portfolio'!K12="Method"),TRUE(),FALSE()),FALSE())) -> FALSE | I12: =IF(Configuration!$C$16="No","",IFERROR(IF(AND(OR(ISNUMBER(SEARCH("material",'Patent Portfolio'!C12)),ISNUMBER(SEARCH("chem",'Patent Portfolio'!C12)),ISNUMBER(SEARCH("battery",'Patent Portfolio'!C12)),ISNUMBER(SEARCH("electrolyte",'Patent Portfolio'!C12)),ISNUMBER(SEARCH("polymer",'Patent Portfolio'!C12))),OR('Patent Portfolio'!K12="Apparatus",'Patent Portfolio'!K12="Method")),TRUE(),FALSE()),FALSE())) -> FALSE | J12: =IF(Configuration!$C$17="No","",IFERROR(IF(AND(OR('Patent Portfolio'!E12="App",'Patent Portfolio'!E12="Middleware",'Patent Portfolio'!E12="Cloud"),OR('Patent Portfolio'!K12="Method",'Patent Portfolio'!K12="CRM")),TRUE(),FALSE()),FALSE())) -> FALSE | K12: =IF(Configuration!$C$18="No","",IFERROR(IF(N('Patent Portfolio'!J12)>=Configuration!$C$45,TRUE(),FALSE()),FALSE())) -> TRUE | L12: =IF(Configuration!$C$19="No","",IFERROR(IF('Patent Portfolio'!AA12<>"",TRUE(),FALSE()),FALSE())) -> TRUE | M12: =IF(Configuration!$C$20="No","",IFERROR(IF('Patent Portfolio'!K12<>"",TRUE(),FALSE()),FALSE())) -> TRUE | N12: =IF(Configuration!$C$21="No","",IFERROR(IF(OR(N('Patent Portfolio'!O12)>=Configuration!$C$46,N('Patent Portfolio'!P12)>=Configuration!$C$47),TRUE(),FALSE()),FALSE())) -> TRUE | O12: =IF(Configuration!$C$22="No","",IFERROR(IF('Patent Portfolio'!X12="Yes",TRUE(),FALSE()),FALSE())) -> TRUE | P12: =IF(Configuration!$C$23="No","",IFERROR(IF(N('Patent Portfolio'!R12)>=Configuration!$C$48,TRUE(),FALSE()),FALSE())) -> TRUE | Q12: =IF(Configuration!$C$24="No","",IFERROR(IF(N('Patent Portfolio'!U12)>0,TRUE(),FALSE()),FALSE())) -> TRUE | R12: =IF(Configuration!$C$25="No","",IFERROR(IF(OR(N('Patent Portfolio'!L12)=3,N('Patent Portfolio'!L12)<=1),TRUE(),FALSE()),FALSE())) -> TRUE | S12: =IF(Configuration!$C$26="No","",IFERROR(IF(N('Patent Portfolio'!AB12)>=Configuration!$C$49,TRUE(),FALSE()),FALSE())) -> TRUE | T12: =IF(Configuration!$C$27="No","",IFERROR(IF('Patent Portfolio'!Z12<>"",TRUE(),FALSE()),FALSE())) -> FALSE | U12: =IF(Configuration!$C$28="No","",IFERROR(IF(N('Patent Portfolio'!Q12)>=Configuration!$C$50,TRUE(),FALSE()),FALSE())) -> TRUE | V12: =IF(Configuration!$C$29="No","",IFERROR(IF(AND(N('Patent Portfolio'!N12)>=Configuration!$C$51,'Patent Portfolio'!C12<>""),TRUE(),FALSE()),FALSE())) -> TRUE | W12: =IF(Configuration!$C$30="No","",IFERROR(IF(OR('Patent Portfolio'!S12="Pending",'Patent Portfolio'!T12="Yes"),TRUE(),FALSE()),FALSE())) -> FALSE | X12: =IF(Configuration!$C$31="No","",IFERROR(IF(AND(N('Patent Portfolio'!AC12)>=Configuration!$C$52,N('Patent Portfolio'!L12)>=1),TRUE(),FALSE()),FALSE())) -> TRUE | Y12: =IF(Configuration!$C$32="No","",IFERROR(IF(AND(N('Patent Portfolio'!N12)>=1,OR('Patent Portfolio'!C12<>"",'Patent Portfolio'!I12<>"")),TRUE(),FALSE()),FALSE())) -> TRUE | Z12: =IF(Configuration!$C$33="No","",IFERROR(IF('Patent Portfolio'!C12<>"",TRUE(),FALSE()),FALSE())) -> TRUE | AA12: =IF(Configuration!$C$34="No","",IFERROR(IF('Patent Portfolio'!T12="Yes",TRUE(),FALSE()),FALSE())) -> FALSE | AB12: =IF(Configuration!$C$35="No","",IFERROR(IF(OR('Patent Portfolio'!AK12="Partial",'Patent Portfolio'!AK12="Full"),TRUE(),FALSE()),FALSE())) -> TRUE | AC12: =IF(Configuration!$C$36="No","",IFERROR(IF('Patent Portfolio'!AI12="Survived",TRUE(),FALSE()),FALSE())) -> TRUE | AD12: =IF(Configuration!$C$37="No","",IFERROR(IF(AND('Patent Portfolio'!AJ12="Clean",'Patent Portfolio'!AL12="None"),TRUE(),FALSE()),FALSE())) -> TRUE | AE12: =IF(Configuration!$C$38="No","",IFERROR(IF(N('Patent Portfolio'!AG12)>=Configuration!$C$53,TRUE(),FALSE()),FALSE())) -> TRUE | AF12: =IF(Configuration!$C$39="No","",IFERROR(IF(AND(N('Patent Portfolio'!AO12)>=2,N('Patent Portfolio'!AB12)>=2),TRUE(),FALSE()),FALSE())) -> TRUE | AG12: =IF(Configuration!$C$40="No","",IFERROR(IF(OR(N('Patent Portfolio'!AC12)<=Configuration!$C$56,N('Patent Portfolio'!U12)<Configuration!$C$57,N('Patent Portfolio'!AD12)<=Configuration!$C$58),TRUE(),FALSE()),FALSE())) -> FALSE | AH12: =IF(Configuration!$C$41="No","",IFERROR(IF(AND(N('Patent Portfolio'!U12)>=Configuration!$C$54,N('Patent Portfolio'!U12)<=Configuration!$C$55),TRUE(),FALSE()),FALSE())) -> FALSE | AI12: =IF(Configuration!$C$42="No","",IFERROR(IF(AND('Patent Portfolio'!C12<>"",'Patent Portfolio'!F12<>""),TRUE(),FALSE()),FALSE())) -> TRUE | AJ12: =COUNTIF(C12:AI12,TRUE()) -> 25
A13: ='Patent Portfolio'!A13 -> P-011 | B13: ='Patent Portfolio'!B13 -> Atomic layer deposition recipe for high-k dielectric | C13: =IF(Configuration!$C$10="No","",IFERROR(IF('Patent Portfolio'!C13<>"",TRUE(),FALSE()),FALSE())) -> TRUE | D13: =IF(Configuration!$C$11="No","",IFERROR(IF(AND(N('Patent Portfolio'!H13)>=Configuration!$C$44,'Patent Portfolio'!I13<>""),TRUE(),FALSE()),FALSE())) -> FALSE | E13: =IF(Configuration!$C$12="No","",IFERROR(IF('Patent Portfolio'!F13<>"",TRUE(),FALSE()),FALSE())) -> TRUE | F13: =IF(Configuration!$C$13="No","",IFERROR(IF('Patent Portfolio'!E13<>"",TRUE(),FALSE()),FALSE())) -> TRUE | G13: =IF(Configuration!$C$14="No","",IFERROR(IF('Patent Portfolio'!G13<>"",TRUE(),FALSE()),FALSE())) -> TRUE | H13: =IF(Configuration!$C$15="No","",IFERROR(IF(AND(OR(ISNUMBER(SEARCH("process",'Patent Portfolio'!C13)),ISNUMBER(SEARCH("fab",'Patent Portfolio'!C13)),ISNUMBER(SEARCH("manufac",'Patent Portfolio'!C13))),'Patent Portfolio'!K13="Method"),TRUE(),FALSE()),FALSE())) -> TRUE | I13: =IF(Configuration!$C$16="No","",IFERROR(IF(AND(OR(ISNUMBER(SEARCH("material",'Patent Portfolio'!C13)),ISNUMBER(SEARCH("chem",'Patent Portfolio'!C13)),ISNUMBER(SEARCH("battery",'Patent Portfolio'!C13)),ISNUMBER(SEARCH("electrolyte",'Patent Portfolio'!C13)),ISNUMBER(SEARCH("polymer",'Patent Portfolio'!C13))),OR('Patent Portfolio'!K13="Apparatus",'Patent Portfolio'!K13="Method")),TRUE(),FALSE()),FALSE())) -> FALSE | J13: =IF(Configuration!$C$17="No","",IFERROR(IF(AND(OR('Patent Portfolio'!E13="App",'Patent Portfolio'!E13="Middleware",'Patent Portfolio'!E13="Cloud"),OR('Patent Portfolio'!K13="Method",'Patent Portfolio'!K13="CRM")),TRUE(),FALSE()),FALSE())) -> FALSE | K13: =IF(Configuration!$C$18="No","",IFERROR(IF(N('Patent Portfolio'!J13)>=Configuration!$C$45,TRUE(),FALSE()),FALSE())) -> FALSE | L13: =IF(Configuration!$C$19="No","",IFERROR(IF('Patent Portfolio'!AA13<>"",TRUE(),FALSE()),FALSE())) -> TRUE | M13: =IF(Configuration!$C$20="No","",IFERROR(IF('Patent Portfolio'!K13<>"",TRUE(),FALSE()),FALSE())) -> TRUE | N13: =IF(Configuration!$C$21="No","",IFERROR(IF(OR(N('Patent Portfolio'!O13)>=Configuration!$C$46,N('Patent Portfolio'!P13)>=Configuration!$C$47),TRUE(),FALSE()),FALSE())) -> FALSE | O13: =IF(Configuration!$C$22="No","",IFERROR(IF('Patent Portfolio'!X13="Yes",TRUE(),FALSE()),FALSE())) -> TRUE | P13: =IF(Configuration!$C$23="No","",IFERROR(IF(N('Patent Portfolio'!R13)>=Configuration!$C$48,TRUE(),FALSE()),FALSE())) -> TRUE | Q13: =IF(Configuration!$C$24="No","",IFERROR(IF(N('Patent Portfolio'!U13)>0,TRUE(),FALSE()),FALSE())) -> TRUE | R13: =IF(Configuration!$C$25="No","",IFERROR(IF(OR(N('Patent Portfolio'!L13)=3,N('Patent Portfolio'!L13)<=1),TRUE(),FALSE()),FALSE())) -> FALSE | S13: =IF(Configuration!$C$26="No","",IFERROR(IF(N('Patent Portfolio'!AB13)>=Configuration!$C$49,TRUE(),FALSE()),FALSE())) -> FALSE | T13: =IF(Configuration!$C$27="No","",IFERROR(IF('Patent Portfolio'!Z13<>"",TRUE(),FALSE()),FALSE())) -> FALSE | U13: =IF(Configuration!$C$28="No","",IFERROR(IF(N('Patent Portfolio'!Q13)>=Configuration!$C$50,TRUE(),FALSE()),FALSE())) -> FALSE | V13: =IF(Configuration!$C$29="No","",IFERROR(IF(AND(N('Patent Portfolio'!N13)>=Configuration!$C$51,'Patent Portfolio'!C13<>""),TRUE(),FALSE()),FALSE())) -> TRUE | W13: =IF(Configuration!$C$30="No","",IFERROR(IF(OR('Patent Portfolio'!S13="Pending",'Patent Portfolio'!T13="Yes"),TRUE(),FALSE()),FALSE())) -> TRUE | X13: =IF(Configuration!$C$31="No","",IFERROR(IF(AND(N('Patent Portfolio'!AC13)>=Configuration!$C$52,N('Patent Portfolio'!L13)>=1),TRUE(),FALSE()),FALSE())) -> TRUE | Y13: =IF(Configuration!$C$32="No","",IFERROR(IF(AND(N('Patent Portfolio'!N13)>=1,OR('Patent Portfolio'!C13<>"",'Patent Portfolio'!I13<>"")),TRUE(),FALSE()),FALSE())) -> TRUE | Z13: =IF(Configuration!$C$33="No","",IFERROR(IF('Patent Portfolio'!C13<>"",TRUE(),FALSE()),FALSE())) -> TRUE | AA13: =IF(Configuration!$C$34="No","",IFERROR(IF('Patent Portfolio'!T13="Yes",TRUE(),FALSE()),FALSE())) -> TRUE | AB13: =IF(Configuration!$C$35="No","",IFERROR(IF(OR('Patent Portfolio'!AK13="Partial",'Patent Portfolio'!AK13="Full"),TRUE(),FALSE()),FALSE())) -> FALSE | AC13: =IF(Configuration!$C$36="No","",IFERROR(IF('Patent Portfolio'!AI13="Survived",TRUE(),FALSE()),FALSE())) -> FALSE | AD13: =IF(Configuration!$C$37="No","",IFERROR(IF(AND('Patent Portfolio'!AJ13="Clean",'Patent Portfolio'!AL13="None"),TRUE(),FALSE()),FALSE())) -> TRUE | AE13: =IF(Configuration!$C$38="No","",IFERROR(IF(N('Patent Portfolio'!AG13)>=Configuration!$C$53,TRUE(),FALSE()),FALSE())) -> TRUE | AF13: =IF(Configuration!$C$39="No","",IFERROR(IF(AND(N('Patent Portfolio'!AO13)>=2,N('Patent Portfolio'!AB13)>=2),TRUE(),FALSE()),FALSE())) -> FALSE | AG13: =IF(Configuration!$C$40="No","",IFERROR(IF(OR(N('Patent Portfolio'!AC13)<=Configuration!$C$56,N('Patent Portfolio'!U13)<Configuration!$C$57,N('Patent Portfolio'!AD13)<=Configuration!$C$58),TRUE(),FALSE()),FALSE())) -> FALSE | AH13: =IF(Configuration!$C$41="No","",IFERROR(IF(AND(N('Patent Portfolio'!U13)>=Configuration!$C$54,N('Patent Portfolio'!U13)<=Configuration!$C$55),TRUE(),FALSE()),FALSE())) -> FALSE | AI13: =IF(Configuration!$C$42="No","",IFERROR(IF(AND('Patent Portfolio'!C13<>"",'Patent Portfolio'!F13<>""),TRUE(),FALSE()),FALSE())) -> TRUE | AJ13: =COUNTIF(C13:AI13,TRUE()) -> 19
A14: ='Patent Portfolio'!A14 -> P-012 | B14: ='Patent Portfolio'!B14 -> Predictive maintenance ML for industrial pumps | C14: =IF(Configuration!$C$10="No","",IFERROR(IF('Patent Portfolio'!C14<>"",TRUE(),FALSE()),FALSE())) -> TRUE | D14: =IF(Configuration!$C$11="No","",IFERROR(IF(AND(N('Patent Portfolio'!H14)>=Configuration!$C$44,'Patent Portfolio'!I14<>""),TRUE(),FALSE()),FALSE())) -> FALSE | E14: =IF(Configuration!$C$12="No","",IFERROR(IF('Patent Portfolio'!F14<>"",TRUE(),FALSE()),FALSE())) -> TRUE | F14: =IF(Configuration!$C$13="No","",IFERROR(IF('Patent Portfolio'!E14<>"",TRUE(),FALSE()),FALSE())) -> TRUE | G14: =IF(Configuration!$C$14="No","",IFERROR(IF('Patent Portfolio'!G14<>"",TRUE(),FALSE()),FALSE())) -> TRUE | H14: =IF(Configuration!$C$15="No","",IFERROR(IF(AND(OR(ISNUMBER(SEARCH("process",'Patent Portfolio'!C14)),ISNUMBER(SEARCH("fab",'Patent Portfolio'!C14)),ISNUMBER(SEARCH("manufac",'Patent Portfolio'!C14))),'Patent Portfolio'!K14="Method"),TRUE(),FALSE()),FALSE())) -> FALSE | I14: =IF(Configuration!$C$16="No","",IFERROR(IF(AND(OR(ISNUMBER(SEARCH("material",'Patent Portfolio'!C14)),ISNUMBER(SEARCH("chem",'Patent Portfolio'!C14)),ISNUMBER(SEARCH("battery",'Patent Portfolio'!C14)),ISNUMBER(SEARCH("electrolyte",'Patent Portfolio'!C14)),ISNUMBER(SEARCH("polymer",'Patent Portfolio'!C14))),OR('Patent Portfolio'!K14="Apparatus",'Patent Portfolio'!K14="Method")),TRUE(),FALSE()),FALSE())) -> FALSE | J14: =IF(Configuration!$C$17="No","",IFERROR(IF(AND(OR('Patent Portfolio'!E14="App",'Patent Portfolio'!E14="Middleware",'Patent Portfolio'!E14="Cloud"),OR('Patent Portfolio'!K14="Method",'Patent Portfolio'!K14="CRM")),TRUE(),FALSE()),FALSE())) -> TRUE | K14: =IF(Configuration!$C$18="No","",IFERROR(IF(N('Patent Portfolio'!J14)>=Configuration!$C$45,TRUE(),FALSE()),FALSE())) -> FALSE | L14: =IF(Configuration!$C$19="No","",IFERROR(IF('Patent Portfolio'!AA14<>"",TRUE(),FALSE()),FALSE())) -> TRUE | M14: =IF(Configuration!$C$20="No","",IFERROR(IF('Patent Portfolio'!K14<>"",TRUE(),FALSE()),FALSE())) -> TRUE | N14: =IF(Configuration!$C$21="No","",IFERROR(IF(OR(N('Patent Portfolio'!O14)>=Configuration!$C$46,N('Patent Portfolio'!P14)>=Configuration!$C$47),TRUE(),FALSE()),FALSE())) -> TRUE | O14: =IF(Configuration!$C$22="No","",IFERROR(IF('Patent Portfolio'!X14="Yes",TRUE(),FALSE()),FALSE())) -> FALSE | P14: =IF(Configuration!$C$23="No","",IFERROR(IF(N('Patent Portfolio'!R14)>=Configuration!$C$48,TRUE(),FALSE()),FALSE())) -> TRUE | Q14: =IF(Configuration!$C$24="No","",IFERROR(IF(N('Patent Portfolio'!U14)>0,TRUE(),FALSE()),FALSE())) -> TRUE | R14: =IF(Configuration!$C$25="No","",IFERROR(IF(OR(N('Patent Portfolio'!L14)=3,N('Patent Portfolio'!L14)<=1),TRUE(),FALSE()),FALSE())) -> TRUE | S14: =IF(Configuration!$C$26="No","",IFERROR(IF(N('Patent Portfolio'!AB14)>=Configuration!$C$49,TRUE(),FALSE()),FALSE())) -> TRUE | T14: =IF(Configuration!$C$27="No","",IFERROR(IF('Patent Portfolio'!Z14<>"",TRUE(),FALSE()),FALSE())) -> TRUE | U14: =IF(Configuration!$C$28="No","",IFERROR(IF(N('Patent Portfolio'!Q14)>=Configuration!$C$50,TRUE(),FALSE()),FALSE())) -> FALSE | V14: =IF(Configuration!$C$29="No","",IFERROR(IF(AND(N('Patent Portfolio'!N14)>=Configuration!$C$51,'Patent Portfolio'!C14<>""),TRUE(),FALSE()),FALSE())) -> FALSE | W14: =IF(Configuration!$C$30="No","",IFERROR(IF(OR('Patent Portfolio'!S14="Pending",'Patent Portfolio'!T14="Yes"),TRUE(),FALSE()),FALSE())) -> FALSE | X14: =IF(Configuration!$C$31="No","",IFERROR(IF(AND(N('Patent Portfolio'!AC14)>=Configuration!$C$52,N('Patent Portfolio'!L14)>=1),TRUE(),FALSE()),FALSE())) -> FALSE | Y14: =IF(Configuration!$C$32="No","",IFERROR(IF(AND(N('Patent Portfolio'!N14)>=1,OR('Patent Portfolio'!C14<>"",'Patent Portfolio'!I14<>"")),TRUE(),FALSE()),FALSE())) -> TRUE | Z14: =IF(Configuration!$C$33="No","",IFERROR(IF('Patent Portfolio'!C14<>"",TRUE(),FALSE()),FALSE())) -> TRUE | AA14: =IF(Configuration!$C$34="No","",IFERROR(IF('Patent Portfolio'!T14="Yes",TRUE(),FALSE()),FALSE())) -> FALSE | AB14: =IF(Configuration!$C$35="No","",IFERROR(IF(OR('Patent Portfolio'!AK14="Partial",'Patent Portfolio'!AK14="Full"),TRUE(),FALSE()),FALSE())) -> FALSE | AC14: =IF(Configuration!$C$36="No","",IFERROR(IF('Patent Portfolio'!AI14="Survived",TRUE(),FALSE()),FALSE())) -> FALSE | AD14: =IF(Configuration!$C$37="No","",IFERROR(IF(AND('Patent Portfolio'!AJ14="Clean",'Patent Portfolio'!AL14="None"),TRUE(),FALSE()),FALSE())) -> FALSE | AE14: =IF(Configuration!$C$38="No","",IFERROR(IF(N('Patent Portfolio'!AG14)>=Configuration!$C$53,TRUE(),FALSE()),FALSE())) -> FALSE | AF14: =IF(Configuration!$C$39="No","",IFERROR(IF(AND(N('Patent Portfolio'!AO14)>=2,N('Patent Portfolio'!AB14)>=2),TRUE(),FALSE()),FALSE())) -> TRUE | AG14: =IF(Configuration!$C$40="No","",IFERROR(IF(OR(N('Patent Portfolio'!AC14)<=Configuration!$C$56,N('Patent Portfolio'!U14)<Configuration!$C$57,N('Patent Portfolio'!AD14)<=Configuration!$C$58),TRUE(),FALSE()),FALSE())) -> TRUE | AH14: =IF(Configuration!$C$41="No","",IFERROR(IF(AND(N('Patent Portfolio'!U14)>=Configuration!$C$54,N('Patent Portfolio'!U14)<=Configuration!$C$55),TRUE(),FALSE()),FALSE())) -> FALSE | AI14: =IF(Configuration!$C$42="No","",IFERROR(IF(AND('Patent Portfolio'!C14<>"",'Patent Portfolio'!F14<>""),TRUE(),FALSE()),FALSE())) -> TRUE | AJ14: =COUNTIF(C14:AI14,TRUE()) -> 18
... A22: ='Patent Portfolio'!A22 -> 0 | B22: ='Patent Portfolio'!B22 -> 0 | C22: =IF(Configuration!$C$10="No","",IFERROR(IF('Patent Portfolio'!C22<>"",TRUE(),FALSE()),FALSE())) -> FALSE | D22: =IF(Configuration!$C$11="No","",IFERROR(IF(AND(N('Patent Portfolio'!H22)>=Configuration!$C$44,'Patent Portfolio'!I22<>""),TRUE(),FALSE()),FALSE())) -> FALSE | E22: =IF(Configuration!$C$12="No","",IFERROR(IF('Patent Portfolio'!F22<>"",TRUE(),FALSE()),FALSE())) -> FALSE | F22: =IF(Configuration!$C$13="No","",IFERROR(IF('Patent Portfolio'!E22<>"",TRUE(),FALSE()),FALSE())) -> FALSE | G22: =IF(Configuration!$C$14="No","",IFERROR(IF('Patent Portfolio'!G22<>"",TRUE(),FALSE()),FALSE())) -> FALSE | H22: =IF(Configuration!$C$15="No","",IFERROR(IF(AND(OR(ISNUMBER(SEARCH("process",'Patent Portfolio'!C22)),ISNUMBER(SEARCH("fab",'Patent Portfolio'!C22)),ISNUMBER(SEARCH("manufac",'Patent Portfolio'!C22))),'Patent Portfolio'!K22="Method"),TRUE(),FALSE()),FALSE())) -> FALSE | I22: =IF(Configuration!$C$16="No","",IFERROR(IF(AND(OR(ISNUMBER(SEARCH("material",'Patent Portfolio'!C22)),ISNUMBER(SEARCH("chem",'Patent Portfolio'!C22)),ISNUMBER(SEARCH("battery",'Patent Portfolio'!C22)),ISNUMBER(SEARCH("electrolyte",'Patent Portfolio'!C22)),ISNUMBER(SEARCH("polymer",'Patent Portfolio'!C22))),OR('Patent Portfolio'!K22="Apparatus",'Patent Portfolio'!K22="Method")),TRUE(),FALSE()),FALSE())) -> FALSE | J22: =IF(Configuration!$C$17="No","",IFERROR(IF(AND(OR('Patent Portfolio'!E22="App",'Patent Portfolio'!E22="Middleware",'Patent Portfolio'!E22="Cloud"),OR('Patent Portfolio'!K22="Method",'Patent Portfolio'!K22="CRM")),TRUE(),FALSE()),FALSE())) -> FALSE | K22: =IF(Configuration!$C$18="No","",IFERROR(IF(N('Patent Portfolio'!J22)>=Configuration!$C$45,TRUE(),FALSE()),FALSE())) -> FALSE | L22: =IF(Configuration!$C$19="No","",IFERROR(IF('Patent Portfolio'!AA22<>"",TRUE(),FALSE()),FALSE())) -> FALSE | M22: =IF(Configuration!$C$20="No","",IFERROR(IF('Patent Portfolio'!K22<>"",TRUE(),FALSE()),FALSE())) -> FALSE | N22: =IF(Configuration!$C$21="No","",IFERROR(IF(OR(N('Patent Portfolio'!O22)>=Configuration!$C$46,N('Patent Portfolio'!P22)>=Configuration!$C$47),TRUE(),FALSE()),FALSE())) -> FALSE | O22: =IF(Configuration!$C$22="No","",IFERROR(IF('Patent Portfolio'!X22="Yes",TRUE(),FALSE()),FALSE())) -> FALSE | P22: =IF(Configuration!$C$23="No","",IFERROR(IF(N('Patent Portfolio'!R22)>=Configuration!$C$48,TRUE(),FALSE()),FALSE())) -> FALSE | Q22: =IF(Configuration!$C$24="No","",IFERROR(IF(N('Patent Portfolio'!U22)>0,TRUE(),FALSE()),FALSE())) -> FALSE | R22: =IF(Configuration!$C$25="No","",IFERROR(IF(OR(N('Patent Portfolio'!L22)=3,N('Patent Portfolio'!L22)<=1),TRUE(),FALSE()),FALSE())) -> TRUE | S22: =IF(Configuration!$C$26="No","",IFERROR(IF(N('Patent Portfolio'!AB22)>=Configuration!$C$49,TRUE(),FALSE()),FALSE())) -> FALSE | T22: =IF(Configuration!$C$27="No","",IFERROR(IF('Patent Portfolio'!Z22<>"",TRUE(),FALSE()),FALSE())) -> FALSE | U22: =IF(Configuration!$C$28="No","",IFERROR(IF(N('Patent Portfolio'!Q22)>=Configuration!$C$50,TRUE(),FALSE()),FALSE())) -> FALSE | V22: =IF(Configuration!$C$29="No","",IFERROR(IF(AND(N('Patent Portfolio'!N22)>=Configuration!$C$51,'Patent Portfolio'!C22<>""),TRUE(),FALSE()),FALSE())) -> FALSE | W22: =IF(Configuration!$C$30="No","",IFERROR(IF(OR('Patent Portfolio'!S22="Pending",'Patent Portfolio'!T22="Yes"),TRUE(),FALSE()),FALSE())) -> FALSE | X22: =IF(Configuration!$C$31="No","",IFERROR(IF(AND(N('Patent Portfolio'!AC22)>=Configuration!$C$52,N('Patent Portfolio'!L22)>=1),TRUE(),FALSE()),FALSE())) -> FALSE | Y22: =IF(Configuration!$C$32="No","",IFERROR(IF(AND(N('Patent Portfolio'!N22)>=1,OR('Patent Portfolio'!C22<>"",'Patent Portfolio'!I22<>"")),TRUE(),FALSE()),FALSE())) -> FALSE | Z22: =IF(Configuration!$C$33="No","",IFERROR(IF('Patent Portfolio'!C22<>"",TRUE(),FALSE()),FALSE())) -> FALSE | AA22: =IF(Configuration!$C$34="No","",IFERROR(IF('Patent Portfolio'!T22="Yes",TRUE(),FALSE()),FALSE())) -> FALSE | AB22: =IF(Configuration!$C$35="No","",IFERROR(IF(OR('Patent Portfolio'!AK22="Partial",'Patent Portfolio'!AK22="Full"),TRUE(),FALSE()),FALSE())) -> FALSE | AC22: =IF(Configuration!$C$36="No","",IFERROR(IF('Patent Portfolio'!AI22="Survived",TRUE(),FALSE()),FALSE())) -> FALSE | AD22: =IF(Configuration!$C$37="No","",IFERROR(IF(AND('Patent Portfolio'!AJ22="Clean",'Patent Portfolio'!AL22="None"),TRUE(),FALSE()),FALSE())) -> FALSE | AE22: =IF(Configuration!$C$38="No","",IFERROR(IF(N('Patent Portfolio'!AG22)>=Configuration!$C$53,TRUE(),FALSE()),FALSE())) -> FALSE | AF22: =IF(Configuration!$C$39="No","",IFERROR(IF(AND(N('Patent Portfolio'!AO22)>=2,N('Patent Portfolio'!AB22)>=2),TRUE(),FALSE()),FALSE())) -> FALSE | AG22: =IF(Configuration!$C$40="No","",IFERROR(IF(OR(N('Patent Portfolio'!AC22)<=Configuration!$C$56,N('Patent Portfolio'!U22)<Configuration!$C$57,N('Patent Portfolio'!AD22)<=Configuration!$C$58),TRUE(),FALSE()),FALSE())) -> TRUE | AH22: =IF(Configuration!$C$41="No","",IFERROR(IF(AND(N('Patent Portfolio'!U22)>=Configuration!$C$54,N('Patent Portfolio'!U22)<=Configuration!$C$55),TRUE(),FALSE()),FALSE())) -> FALSE | AI22: =IF(Configuration!$C$42="No","",IFERROR(IF(AND('Patent Portfolio'!C22<>"",'Patent Portfolio'!F22<>""),TRUE(),FALSE()),FALSE())) -> FALSE | AJ22: =COUNTIF(C22:AI22,TRUE()) -> 2

Sheet Bundle Quality Scorecard
A1: # | B1: Bundle Type | C1: Coverage depth (# patents) | D1: Avg Detectability (D1+D2)/2 | E1: Avg Remaining Term (E4) | F1: Trilateral % (F2=Yes) | G1: Continuation % (E3=Yes) | H1: % SEP-flagged (B1≥2) | I1: Pioneer count (C2=3) | J1: Strength flag | K1: =IF(Configuration!$C$63="No","[DISABLED] Weakest H1 (min in bundle)","Weakest H1 (min in bundle)") -> Weakest H1 (min in bundle) | L1: =IF(Configuration!$C$64="No","[DISABLED] Invalidity exposure % (H2≤1)","Invalidity exposure % (H2≤1)") -> Invalidity exposure % (H2≤1) | M1: =IF(Configuration!$C$65="No","[DISABLED] EoU-ready % (H9≠None)","EoU-ready % (H9≠None)") -> EoU-ready % (H9≠None) | N1: =IF(Configuration!$C$66="No","[DISABLED] Survived % (H7=Survived)","Survived % (H7=Survived)") -> Survived % (H7=Survived) | O1: =IF(Configuration!$C$67="No","[DISABLED] Continuation-optionality %","Continuation-optionality %") -> Continuation-optionality %
A2: 1 | B2: =IF(Configuration!$C$10="No","[DISABLED] Tech Domain","Tech Domain") -> Tech Domain | C2: =IF(Configuration!$C$10="No","",COUNTIF('Bundle Assignment'!C3:C22,TRUE())) -> 12 | D2: =IF(Configuration!$C$10="No","",IFERROR(SUMPRODUCT(--('Bundle Assignment'!C3:C22=TRUE()),('Patent Portfolio'!O3:O22+'Patent Portfolio'!P3:P22)/2)/COUNTIF('Bundle Assignment'!C3:C22,TRUE()),0)) -> 1.5833333 | E2: =IF(Configuration!$C$10="No","",IFERROR(SUMPRODUCT(--('Bundle Assignment'!C3:C22=TRUE()),'Patent Portfolio'!U3:U22)/COUNTIF('Bundle Assignment'!C3:C22,TRUE()),0)) -> 13.166667 | F2: =IF(Configuration!$C$10="No","",IFERROR(SUMPRODUCT(--('Bundle Assignment'!C3:C22=TRUE()),--('Patent Portfolio'!X3:X22="Yes"))/COUNTIF('Bundle Assignment'!C3:C22,TRUE()),0)) -> 0.83333333 | G2: =IF(Configuration!$C$10="No","",IFERROR(SUMPRODUCT(--('Bundle Assignment'!C3:C22=TRUE()),--('Patent Portfolio'!T3:T22="Yes"))/COUNTIF('Bundle Assignment'!C3:C22,TRUE()),0)) -> 0.5 | H2: =IF(Configuration!$C$10="No","",IFERROR(SUMPRODUCT(--('Bundle Assignment'!C3:C22=TRUE()),--('Patent Portfolio'!H3:H22>=2))/COUNTIF('Bundle Assignment'!C3:C22,TRUE()),0)) -> 0.33333333 | I2: =IF(Configuration!$C$10="No","",SUMPRODUCT(--('Bundle Assignment'!C3:C22=TRUE()),--('Patent Portfolio'!L3:L22=3))) -> 1 | J2: =IF(Configuration!$C$10="No","",IF(C2<2,"WEAK",IF(AND(C2>=Configuration!$C$59,D2>=Configuration!$C$60,E2>=Configuration!$C$61),"STRONG","MODERATE"))) -> MODERATE | K2: =IF(Configuration!$C$10="No","",IF(Configuration!$C$63="No","",IFERROR(aggregate(5,6,'Patent Portfolio'!AC3:AC22/('Bundle Assignment'!C3:C22=TRUE())),""))) | L2: =IF(Configuration!$C$10="No","",IF(Configuration!$C$64="No","",IFERROR(SUMPRODUCT(--('Bundle Assignment'!C3:C22=TRUE()),--('Patent Portfolio'!AD3:AD22<=1))/COUNTIF('Bundle Assignment'!C3:C22,TRUE()),0))) -> 0.25 | M2: =IF(Configuration!$C$10="No","",IF(Configuration!$C$65="No","",IFERROR(SUMPRODUCT(--('Bundle Assignment'!C3:C22=TRUE()),--('Patent Portfolio'!AK3:AK22<>"None"),--('Patent Portfolio'!AK3:AK22<>""))/COUNTIF('Bundle Assignment'!C3:C22,TRUE()),0))) -> 0.58333333 | N2: =IF(Configuration!$C$10="No","",IF(Configuration!$C$66="No","",IFERROR(SUMPRODUCT(--('Bundle Assignment'!C3:C22=TRUE()),--('Patent Portfolio'!AI3:AI22="Survived"))/COUNTIF('Bundle Assignment'!C3:C22,TRUE()),0))) -> 0.16666667 | O2: =IF(Configuration!$C$10="No","",IF(Configuration!$C$67="No","",IFERROR(SUMPRODUCT(--('Bundle Assignment'!C3:C22=TRUE()),--('Patent Portfolio'!T3:T22="Yes"))/COUNTIF('Bundle Assignment'!C3:C22,TRUE()),0))) -> 0.5
A3: 2 | B3: =IF(Configuration!$C$11="No","[DISABLED] SEP","SEP") -> SEP | C3: =IF(Configuration!$C$11="No","",COUNTIF('Bundle Assignment'!D3:D22,TRUE())) -> 4 | D3: =IF(Configuration!$C$11="No","",IFERROR(SUMPRODUCT(--('Bundle Assignment'!D3:D22=TRUE()),('Patent Portfolio'!O3:O22+'Patent Portfolio'!P3:P22)/2)/COUNTIF('Bundle Assignment'!D3:D22,TRUE()),0)) -> 2 | E3: =IF(Configuration!$C$11="No","",IFERROR(SUMPRODUCT(--('Bundle Assignment'!D3:D22=TRUE()),'Patent Portfolio'!U3:U22)/COUNTIF('Bundle Assignment'!D3:D22,TRUE()),0)) -> 13.25 | F3: =IF(Configuration!$C$11="No","",IFERROR(SUMPRODUCT(--('Bundle Assignment'!D3:D22=TRUE()),--('Patent Portfolio'!X3:X22="Yes"))/COUNTIF('Bundle Assignment'!D3:D22,TRUE()),0)) -> 1 | G3: =IF(Configuration!$C$11="No","",IFERROR(SUMPRODUCT(--('Bundle Assignment'!D3:D22=TRUE()),--('Patent Portfolio'!T3:T22="Yes"))/COUNTIF('Bundle Assignment'!D3:D22,TRUE()),0)) -> 0.5 | H3: =IF(Configuration!$C$11="No","",IFERROR(SUMPRODUCT(--('Bundle Assignment'!D3:D22=TRUE()),--('Patent Portfolio'!H3:H22>=2))/COUNTIF('Bundle Assignment'!D3:D22,TRUE()),0)) -> 1 | I3: =IF(Configuration!$C$11="No","",SUMPRODUCT(--('Bundle Assignment'!D3:D22=TRUE()),--('Patent Portfolio'!L3:L22=3))) -> 0 | J3: =IF(Configuration!$C$11="No","",IF(C3<2,"WEAK",IF(AND(C3>=Configuration!$C$59,D3>=Configuration!$C$60,E3>=Configuration!$C$61),"STRONG","MODERATE"))) -> STRONG | K3: =IF(Configuration!$C$11="No","",IF(Configuration!$C$63="No","",IFERROR(aggregate(5,6,'Patent Portfolio'!AC3:AC22/('Bundle Assignment'!D3:D22=TRUE())),""))) | L3: =IF(Configuration!$C$11="No","",IF(Configuration!$C$64="No","",IFERROR(SUMPRODUCT(--('Bundle Assignment'!D3:D22=TRUE()),--('Patent Portfolio'!AD3:AD22<=1))/COUNTIF('Bundle Assignment'!D3:D22,TRUE()),0))) -> 0 | M3: =IF(Configuration!$C$11="No","",IF(Configuration!$C$65="No","",IFERROR(SUMPRODUCT(--('Bundle Assignment'!D3:D22=TRUE()),--('Patent Portfolio'!AK3:AK22<>"None"),--('Patent Portfolio'!AK3:AK22<>""))/COUNTIF('Bundle Assignment'!D3:D22,TRUE()),0))) -> 0.75 | N3: =IF(Configuration!$C$11="No","",IF(Configuration!$C$66="No","",IFERROR(SUMPRODUCT(--('Bundle Assignment'!D3:D22=TRUE()),--('Patent Portfolio'!AI3:AI22="Survived"))/COUNTIF('Bundle Assignment'!D3:D22,TRUE()),0))) -> 0.5 | O3: =IF(Configuration!$C$11="No","",IF(Configuration!$C$67="No","",IFERROR(SUMPRODUCT(--('Bundle Assignment'!D3:D22=TRUE()),--('Patent Portfolio'!T3:T22="Yes"))/COUNTIF('Bundle Assignment'!D3:D22,TRUE()),0))) -> 0.5
A4: 3 | B4: =IF(Configuration!$C$12="No","[DISABLED] Product Architecture","Product Architecture") -> Product Architecture | C4: =IF(Configuration!$C$12="No","",COUNTIF('Bundle Assignment'!E3:E22,TRUE())) -> 12 | D4: =IF(Configuration!$C$12="No","",IFERROR(SUMPRODUCT(--('Bundle Assignment'!E3:E22=TRUE()),('Patent Portfolio'!O3:O22+'Patent Portfolio'!P3:P22)/2)/COUNTIF('Bundle Assignment'!E3:E22,TRUE()),0)) -> 1.5833333 | E4: =IF(Configuration!$C$12="No","",IFERROR(SUMPRODUCT(--('Bundle Assignment'!E3:E22=TRUE()),'Patent Portfolio'!U3:U22)/COUNTIF('Bundle Assignment'!E3:E22,TRUE()),0)) -> 13.166667 | F4: =IF(Configuration!$C$12="No","",IFERROR(SUMPRODUCT(--('Bundle Assignment'!E3:E22=TRUE()),--('Patent Portfolio'!X3:X22="Yes"))/COUNTIF('Bundle Assignment'!E3:E22,TRUE()),0)) -> 0.83333333 | G4: =IF(Configuration!$C$12="No","",IFERROR(SUMPRODUCT(--('Bundle Assignment'!E3:E22=TRUE()),--('Patent Portfolio'!T3:T22="Yes"))/COUNTIF('Bundle Assignment'!E3:E22,TRUE()),0)) -> 0.5 | H4: =IF(Configuration!$C$12="No","",IFERROR(SUMPRODUCT(--('Bundle Assignment'!E3:E22=TRUE()),--('Patent Portfolio'!H3:H22>=2))/COUNTIF('Bundle Assignment'!E3:E22,TRUE()),0)) -> 0.33333333 | I4: =IF(Configuration!$C$12="No","",SUMPRODUCT(--('Bundle Assignment'!E3:E22=TRUE()),--('Patent Portfolio'!L3:L22=3))) -> 1 | J4: =IF(Configuration!$C$12="No","",IF(C4<2,"WEAK",IF(AND(C4>=Configuration!$C$59,D4>=Configuration!$C$60,E4>=Configuration!$C$61),"STRONG","MODERATE"))) -> MODERATE | K4: =IF(Configuration!$C$12="No","",IF(Configuration!$C$63="No","",IFERROR(aggregate(5,6,'Patent Portfolio'!AC3:AC22/('Bundle Assignment'!E3:E22=TRUE())),""))) | L4: =IF(Configuration!$C$12="No","",IF(Configuration!$C$64="No","",IFERROR(SUMPRODUCT(--('Bundle Assignment'!E3:E22=TRUE()),--('Patent Portfolio'!AD3:AD22<=1))/COUNTIF('Bundle Assignment'!E3:E22,TRUE()),0))) -> 0.25 | M4: =IF(Configuration!$C$12="No","",IF(Configuration!$C$65="No","",IFERROR(SUMPRODUCT(--('Bundle Assignment'!E3:E22=TRUE()),--('Patent Portfolio'!AK3:AK22<>"None"),--('Patent Portfolio'!AK3:AK22<>""))/COUNTIF('Bundle Assignment'!E3:E22,TRUE()),0))) -> 0.58333333 | N4: =IF(Configuration!$C$12="No","",IF(Configuration!$C$66="No","",IFERROR(SUMPRODUCT(--('Bundle Assignment'!E3:E22=TRUE()),--('Patent Portfolio'!AI3:AI22="Survived"))/COUNTIF('Bundle Assignment'!E3:E22,TRUE()),0))) -> 0.16666667 | O4: =IF(Configuration!$C$12="No","",IF(Configuration!$C$67="No","",IFERROR(SUMPRODUCT(--('Bundle Assignment'!E3:E22=TRUE()),--('Patent Portfolio'!T3:T22="Yes"))/COUNTIF('Bundle Assignment'!E3:E22,TRUE()),0))) -> 0.5
A5: 4 | B5: =IF(Configuration!$C$13="No","[DISABLED] Stack Layer","Stack Layer") -> Stack Layer | C5: =IF(Configuration!$C$13="No","",COUNTIF('Bundle Assignment'!F3:F22,TRUE())) -> 12 | D5: =IF(Configuration!$C$13="No","",IFERROR(SUMPRODUCT(--('Bundle Assignment'!F3:F22=TRUE()),('Patent Portfolio'!O3:O22+'Patent Portfolio'!P3:P22)/2)/COUNTIF('Bundle Assignment'!F3:F22,TRUE()),0)) -> 1.5833333 | E5: =IF(Configuration!$C$13="No","",IFERROR(SUMPRODUCT(--('Bundle Assignment'!F3:F22=TRUE()),'Patent Portfolio'!U3:U22)/COUNTIF('Bundle Assignment'!F3:F22,TRUE()),0)) -> 13.166667 | F5: =IF(Configuration!$C$13="No","",IFERROR(SUMPRODUCT(--('Bundle Assignment'!F3:F22=TRUE()),--('Patent Portfolio'!X3:X22="Yes"))/COUNTIF('Bundle Assignment'!F3:F22,TRUE()),0)) -> 0.83333333 | G5: =IF(Configuration!$C$13="No","",IFERROR(SUMPRODUCT(--('Bundle Assignment'!F3:F22=TRUE()),--('Patent Portfolio'!T3:T22="Yes"))/COUNTIF('Bundle Assignment'!F3:F22,TRUE()),0)) -> 0.5 | H5: =IF(Configuration!$C$13="No","",IFERROR(SUMPRODUCT(--('Bundle Assignment'!F3:F22=TRUE()),--('Patent Portfolio'!H3:H22>=2))/COUNTIF('Bundle Assignment'!F3:F22,TRUE()),0)) -> 0.33333333 | I5: =IF(Configuration!$C$13="No","",SUMPRODUCT(--('Bundle Assignment'!F3:F22=TRUE()),--('Patent Portfolio'!L3:L22=3))) -> 1 | J5: =IF(Configuration!$C$13="No","",IF(C5<2,"WEAK",IF(AND(C5>=Configuration!$C$59,D5>=Configuration!$C$60,E5>=Configuration!$C$61),"STRONG","MODERATE"))) -> MODERATE | K5: =IF(Configuration!$C$13="No","",IF(Configuration!$C$63="No","",IFERROR(aggregate(5,6,'Patent Portfolio'!AC3:AC22/('Bundle Assignment'!F3:F22=TRUE())),""))) | L5: =IF(Configuration!$C$13="No","",IF(Configuration!$C$64="No","",IFERROR(SUMPRODUCT(--('Bundle Assignment'!F3:F22=TRUE()),--('Patent Portfolio'!AD3:AD22<=1))/COUNTIF('Bundle Assignment'!F3:F22,TRUE()),0))) -> 0.25 | M5: =IF(Configuration!$C$13="No","",IF(Configuration!$C$65="No","",IFERROR(SUMPRODUCT(--('Bundle Assignment'!F3:F22=TRUE()),--('Patent Portfolio'!AK3:AK22<>"None"),--('Patent Portfolio'!AK3:AK22<>""))/COUNTIF('Bundle Assignment'!F3:F22,TRUE()),0))) -> 0.58333333 | N5: =IF(Configuration!$C$13="No","",IF(Configuration!$C$66="No","",IFERROR(SUMPRODUCT(--('Bundle Assignment'!F3:F22=TRUE()),--('Patent Portfolio'!AI3:AI22="Survived"))/COUNTIF('Bundle Assignment'!F3:F22,TRUE()),0))) -> 0.16666667 | O5: =IF(Configuration!$C$13="No","",IF(Configuration!$C$67="No","",IFERROR(SUMPRODUCT(--('Bundle Assignment'!F3:F22=TRUE()),--('Patent Portfolio'!T3:T22="Yes"))/COUNTIF('Bundle Assignment'!F3:F22,TRUE()),0))) -> 0.5
A6: 5 | B6: =IF(Configuration!$C$14="No","[DISABLED] Use-Case","Use-Case") -> Use-Case | C6: =IF(Configuration!$C$14="No","",COUNTIF('Bundle Assignment'!G3:G22,TRUE())) -> 12 | D6: =IF(Configuration!$C$14="No","",IFERROR(SUMPRODUCT(--('Bundle Assignment'!G3:G22=TRUE()),('Patent Portfolio'!O3:O22+'Patent Portfolio'!P3:P22)/2)/COUNTIF('Bundle Assignment'!G3:G22,TRUE()),0)) -> 1.5833333 | E6: =IF(Configuration!$C$14="No","",IFERROR(SUMPRODUCT(--('Bundle Assignment'!G3:G22=TRUE()),'Patent Portfolio'!U3:U22)/COUNTIF('Bundle Assignment'!G3:G22,TRUE()),0)) -> 13.166667 | F6: =IF(Configuration!$C$14="No","",IFERROR(SUMPRODUCT(--('Bundle Assignment'!G3:G22=TRUE()),--('Patent Portfolio'!X3:X22="Yes"))/COUNTIF('Bundle Assignment'!G3:G22,TRUE()),0)) -> 0.83333333 | G6: =IF(Configuration!$C$14="No","",IFERROR(SUMPRODUCT(--('Bundle Assignment'!G3:G22=TRUE()),--('Patent Portfolio'!T3:T22="Yes"))/COUNTIF('Bundle Assignment'!G3:G22,TRUE()),0)) -> 0.5 | H6: =IF(Configuration!$C$14="No","",IFERROR(SUMPRODUCT(--('Bundle Assignment'!G3:G22=TRUE()),--('Patent Portfolio'!H3:H22>=2))/COUNTIF('Bundle Assignment'!G3:G22,TRUE()),0)) -> 0.33333333 | I6: =IF(Configuration!$C$14="No","",SUMPRODUCT(--('Bundle Assignment'!G3:G22=TRUE()),--('Patent Portfolio'!L3:L22=3))) -> 1 | J6: =IF(Configuration!$C$14="No","",IF(C6<2,"WEAK",IF(AND(C6>=Configuration!$C$59,D6>=Configuration!$C$60,E6>=Configuration!$C$61),"STRONG","MODERATE"))) -> MODERATE | K6: =IF(Configuration!$C$14="No","",IF(Configuration!$C$63="No","",IFERROR(aggregate(5,6,'Patent Portfolio'!AC3:AC22/('Bundle Assignment'!G3:G22=TRUE())),""))) | L6: =IF(Configuration!$C$14="No","",IF(Configuration!$C$64="No","",IFERROR(SUMPRODUCT(--('Bundle Assignment'!G3:G22=TRUE()),--('Patent Portfolio'!AD3:AD22<=1))/COUNTIF('Bundle Assignment'!G3:G22,TRUE()),0))) -> 0.25 | M6: =IF(Configuration!$C$14="No","",IF(Configuration!$C$65="No","",IFERROR(SUMPRODUCT(--('Bundle Assignment'!G3:G22=TRUE()),--('Patent Portfolio'!AK3:AK22<>"None"),--('Patent Portfolio'!AK3:AK22<>""))/COUNTIF('Bundle Assignment'!G3:G22,TRUE()),0))) -> 0.58333333 | N6: =IF(Configuration!$C$14="No","",IF(Configuration!$C$66="No","",IFERROR(SUMPRODUCT(--('Bundle Assignment'!G3:G22=TRUE()),--('Patent Portfolio'!AI3:AI22="Survived"))/COUNTIF('Bundle Assignment'!G3:G22,TRUE()),0))) -> 0.16666667 | O6: =IF(Configuration!$C$14="No","",IF(Configuration!$C$67="No","",IFERROR(SUMPRODUCT(--('Bundle Assignment'!G3:G22=TRUE()),--('Patent Portfolio'!T3:T22="Yes"))/COUNTIF('Bundle Assignment'!G3:G22,TRUE()),0))) -> 0.5
A7: 6 | B7: =IF(Configuration!$C$15="No","[DISABLED] Manufacturing / Process","Manufacturing / Process") -> Manufacturing / Process | C7: =IF(Configuration!$C$15="No","",COUNTIF('Bundle Assignment'!H3:H22,TRUE())) -> 1 | D7: =IF(Configuration!$C$15="No","",IFERROR(SUMPRODUCT(--('Bundle Assignment'!H3:H22=TRUE()),('Patent Portfolio'!O3:O22+'Patent Portfolio'!P3:P22)/2)/COUNTIF('Bundle Assignment'!H3:H22,TRUE()),0)) -> 0.5 | E7: =IF(Configuration!$C$15="No","",IFERROR(SUMPRODUCT(--('Bundle Assignment'!H3:H22=TRUE()),'Patent Portfolio'!U3:U22)/COUNTIF('Bundle Assignment'!H3:H22,TRUE()),0)) -> 13 | F7: =IF(Configuration!$C$15="No","",IFERROR(SUMPRODUCT(--('Bundle Assignment'!H3:H22=TRUE()),--('Patent Portfolio'!X3:X22="Yes"))/COUNTIF('Bundle Assignment'!H3:H22,TRUE()),0)) -> 1 | G7: =IF(Configuration!$C$15="No","",IFERROR(SUMPRODUCT(--('Bundle Assignment'!H3:H22=TRUE()),--('Patent Portfolio'!T3:T22="Yes"))/COUNTIF('Bundle Assignment'!H3:H22,TRUE()),0)) -> 1 | H7: =IF(Configuration!$C$15="No","",IFERROR(SUMPRODUCT(--('Bundle Assignment'!H3:H22=TRUE()),--('Patent Portfolio'!H3:H22>=2))/COUNTIF('Bundle Assignment'!H3:H22,TRUE()),0)) -> 0 | I7: =IF(Configuration!$C$15="No","",SUMPRODUCT(--('Bundle Assignment'!H3:H22=TRUE()),--('Patent Portfolio'!L3:L22=3))) -> 0 | J7: =IF(Configuration!$C$15="No","",IF(C7<2,"WEAK",IF(AND(C7>=Configuration!$C$59,D7>=Configuration!$C$60,E7>=Configuration!$C$61),"STRONG","MODERATE"))) -> WEAK | K7: =IF(Configuration!$C$15="No","",IF(Configuration!$C$63="No","",IFERROR(aggregate(5,6,'Patent Portfolio'!AC3:AC22/('Bundle Assignment'!H3:H22=TRUE())),""))) | L7: =IF(Configuration!$C$15="No","",IF(Configuration!$C$64="No","",IFERROR(SUMPRODUCT(--('Bundle Assignment'!H3:H22=TRUE()),--('Patent Portfolio'!AD3:AD22<=1))/COUNTIF('Bundle Assignment'!H3:H22,TRUE()),0))) -> 0 | M7: =IF(Configuration!$C$15="No","",IF(Configuration!$C$65="No","",IFERROR(SUMPRODUCT(--('Bundle Assignment'!H3:H22=TRUE()),--('Patent Portfolio'!AK3:AK22<>"None"),--('Patent Portfolio'!AK3:AK22<>""))/COUNTIF('Bundle Assignment'!H3:H22,TRUE()),0))) -> 0 | N7: =IF(Configuration!$C$15="No","",IF(Configuration!$C$66="No","",IFERROR(SUMPRODUCT(--('Bundle Assignment'!H3:H22=TRUE()),--('Patent Portfolio'!AI3:AI22="Survived"))/COUNTIF('Bundle Assignment'!H3:H22,TRUE()),0))) -> 0 | O7: =IF(Configuration!$C$15="No","",IF(Configuration!$C$67="No","",IFERROR(SUMPRODUCT(--('Bundle Assignment'!H3:H22=TRUE()),--('Patent Portfolio'!T3:T22="Yes"))/COUNTIF('Bundle Assignment'!H3:H22,TRUE()),0))) -> 1
A8: 7 | B8: =IF(Configuration!$C$16="No","[DISABLED] Materials & Chemistry","Materials & Chemistry") -> Materials & Chemistry | C8: =IF(Configuration!$C$16="No","",COUNTIF('Bundle Assignment'!I3:I22,TRUE())) -> 1 | D8: =IF(Configuration!$C$16="No","",IFERROR(SUMPRODUCT(--('Bundle Assignment'!I3:I22=TRUE()),('Patent Portfolio'!O3:O22+'Patent Portfolio'!P3:P22)/2)/COUNTIF('Bundle Assignment'!I3:I22,TRUE()),0)) -> 1.5 | E8: =IF(Configuration!$C$16="No","",IFERROR(SUMPRODUCT(--('Bundle Assignment'!I3:I22=TRUE()),'Patent Portfolio'!U3:U22)/COUNTIF('Bundle Assignment'!I3:I22,TRUE()),0)) -> 17 | F8: =IF(Configuration!$C$16="No","",IFERROR(SUMPRODUCT(--('Bundle Assignment'!I3:I22=TRUE()),--('Patent Portfolio'!X3:X22="Yes"))/COUNTIF('Bundle Assignment'!I3:I22,TRUE()),0)) -> 1 | G8: =IF(Configuration!$C$16="No","",IFERROR(SUMPRODUCT(--('Bundle Assignment'!I3:I22=TRUE()),--('Patent Portfolio'!T3:T22="Yes"))/COUNTIF('Bundle Assignment'!I3:I22,TRUE()),0)) -> 1 | H8: =IF(Configuration!$C$16="No","",IFERROR(SUMPRODUCT(--('Bundle Assignment'!I3:I22=TRUE()),--('Patent Portfolio'!H3:H22>=2))/COUNTIF('Bundle Assignment'!I3:I22,TRUE()),0)) -> 0 | I8: =IF(Configuration!$C$16="No","",SUMPRODUCT(--('Bundle Assignment'!I3:I22=TRUE()),--('Patent Portfolio'!L3:L22=3))) -> 1 | J8: =IF(Configuration!$C$16="No","",IF(C8<2,"WEAK",IF(AND(C8>=Configuration!$C$59,D8>=Configuration!$C$60,E8>=Configuration!$C$61),"STRONG","MODERATE"))) -> WEAK | K8: =IF(Configuration!$C$16="No","",IF(Configuration!$C$63="No","",IFERROR(aggregate(5,6,'Patent Portfolio'!AC3:AC22/('Bundle Assignment'!I3:I22=TRUE())),""))) | L8: =IF(Configuration!$C$16="No","",IF(Configuration!$C$64="No","",IFERROR(SUMPRODUCT(--('Bundle Assignment'!I3:I22=TRUE()),--('Patent Portfolio'!AD3:AD22<=1))/COUNTIF('Bundle Assignment'!I3:I22,TRUE()),0))) -> 0 | M8: =IF(Configuration!$C$16="No","",IF(Configuration!$C$65="No","",IFERROR(SUMPRODUCT(--('Bundle Assignment'!I3:I22=TRUE()),--('Patent Portfolio'!AK3:AK22<>"None"),--('Patent Portfolio'!AK3:AK22<>""))/COUNTIF('Bundle Assignment'!I3:I22,TRUE()),0))) -> 1 | N8: =IF(Configuration!$C$16="No","",IF(Configuration!$C$66="No","",IFERROR(SUMPRODUCT(--('Bundle Assignment'!I3:I22=TRUE()),--('Patent Portfolio'!AI3:AI22="Survived"))/COUNTIF('Bundle Assignment'!I3:I22,TRUE()),0))) -> 0 | O8: =IF(Configuration!$C$16="No","",IF(Configuration!$C$67="No","",IFERROR(SUMPRODUCT(--('Bundle Assignment'!I3:I22=TRUE()),--('Patent Portfolio'!T3:T22="Yes"))/COUNTIF('Bundle Assignment'!I3:I22,TRUE()),0))) -> 1
A9: 8 | B9: =IF(Configuration!$C$17="No","[DISABLED] Algorithm / Software","Algorithm / Software") -> Algorithm / Software | C9: =IF(Configuration!$C$17="No","",COUNTIF('Bundle Assignment'!J3:J22,TRUE())) -> 3 | D9: =IF(Configuration!$C$17="No","",IFERROR(SUMPRODUCT(--('Bundle Assignment'!J3:J22=TRUE()),('Patent Portfolio'!O3:O22+'Patent Portfolio'!P3:P22)/2)/COUNTIF('Bundle Assignment'!J3:J22,TRUE()),0)) -> 1.1666667 | E9: =IF(Configuration!$C$17="No","",IFERROR(SUMPRODUCT(--('Bundle Assignment'!J3:J22=TRUE()),'Patent Portfolio'!U3:U22)/COUNTIF('Bundle Assignment'!J3:J22,TRUE()),0)) -> 14 | F9: =IF(Configuration!$C$17="No","",IFERROR(SUMPRODUCT(--('Bundle Assignment'!J3:J22=TRUE()),--('Patent Portfolio'!X3:X22="Yes"))/COUNTIF('Bundle Assignment'!J3:J22,TRUE()),0)) -> 0.33333333 | G9: =IF(Configuration!$C$17="No","",IFERROR(SUMPRODUCT(--('Bundle Assignment'!J3:J22=TRUE()),--('Patent Portfolio'!T3:T22="Yes"))/COUNTIF('Bundle Assignment'!J3:J22,TRUE()),0)) -> 0.66666667 | H9: =IF(Configuration!$C$17="No","",IFERROR(SUMPRODUCT(--('Bundle Assignment'!J3:J22=TRUE()),--('Patent Portfolio'!H3:H22>=2))/COUNTIF('Bundle Assignment'!J3:J22,TRUE()),0)) -> 0 | I9: =IF(Configuration!$C$17="No","",SUMPRODUCT(--('Bundle Assignment'!J3:J22=TRUE()),--('Patent Portfolio'!L3:L22=3))) -> 0 | J9: =IF(Configuration!$C$17="No","",IF(C9<2,"WEAK",IF(AND(C9>=Configuration!$C$59,D9>=Configuration!$C$60,E9>=Configuration!$C$61),"STRONG","MODERATE"))) -> MODERATE | K9: =IF(Configuration!$C$17="No","",IF(Configuration!$C$63="No","",IFERROR(aggregate(5,6,'Patent Portfolio'!AC3:AC22/('Bundle Assignment'!J3:J22=TRUE())),""))) | L9: =IF(Configuration!$C$17="No","",IF(Configuration!$C$64="No","",IFERROR(SUMPRODUCT(--('Bundle Assignment'!J3:J22=TRUE()),--('Patent Portfolio'!AD3:AD22<=1))/COUNTIF('Bundle Assignment'!J3:J22,TRUE()),0))) -> 1 | M9: =IF(Configuration!$C$17="No","",IF(Configuration!$C$65="No","",IFERROR(SUMPRODUCT(--('Bundle Assignment'!J3:J22=TRUE()),--('Patent Portfolio'!AK3:AK22<>"None"),--('Patent Portfolio'!AK3:AK22<>""))/COUNTIF('Bundle Assignment'!J3:J22,TRUE()),0))) -> 0.33333333 | N9: =IF(Configuration!$C$17="No","",IF(Configuration!$C$66="No","",IFERROR(SUMPRODUCT(--('Bundle Assignment'!J3:J22=TRUE()),--('Patent Portfolio'!AI3:AI22="Survived"))/COUNTIF('Bundle Assignment'!J3:J22,TRUE()),0))) -> 0 | O9: =IF(Configuration!$C$17="No","",IF(Configuration!$C$67="No","",IFERROR(SUMPRODUCT(--('Bundle Assignment'!J3:J22=TRUE()),--('Patent Portfolio'!T3:T22="Yes"))/COUNTIF('Bundle Assignment'!J3:J22,TRUE()),0))) -> 0.66666667
A10: 9 | B10: =IF(Configuration!$C$18="No","[DISABLED] Interoperability","Interoperability") -> Interoperability | C10: =IF(Configuration!$C$18="No","",COUNTIF('Bundle Assignment'!K3:K22,TRUE())) -> 4 | D10: =IF(Configuration!$C$18="No","",IFERROR(SUMPRODUCT(--('Bundle Assignment'!K3:K22=TRUE()),('Patent Portfolio'!O3:O22+'Patent Portfolio'!P3:P22)/2)/COUNTIF('Bundle Assignment'!K3:K22,TRUE()),0)) -> 2 | E10: =IF(Configuration!$C$18="No","",IFERROR(SUMPRODUCT(--('Bundle Assignment'!K3:K22=TRUE()),'Patent Portfolio'!U3:U22)/COUNTIF('Bundle Assignment'!K3:K22,TRUE()),0)) -> 13.25 | F10: =IF(Configuration!$C$18="No","",IFERROR(SUMPRODUCT(--('Bundle Assignment'!K3:K22=TRUE()),--('Patent Portfolio'!X3:X22="Yes"))/COUNTIF('Bundle Assignment'!K3:K22,TRUE()),0)) -> 1 | G10: =IF(Configuration!$C$18="No","",IFERROR(SUMPRODUCT(--('Bundle Assignment'!K3:K22=TRUE()),--('Patent Portfolio'!T3:T22="Yes"))/COUNTIF('Bundle Assignment'!K3:K22,TRUE()),0)) -> 0.5 | H10: =IF(Configuration!$C$18="No","",IFERROR(SUMPRODUCT(--('Bundle Assignment'!K3:K22=TRUE()),--('Patent Portfolio'!H3:H22>=2))/COUNTIF('Bundle Assignment'!K3:K22,TRUE()),0)) -> 1 | I10: =IF(Configuration!$C$18="No","",SUMPRODUCT(--('Bundle Assignment'!K3:K22=TRUE()),--('Patent Portfolio'!L3:L22=3))) -> 0 | J10: =IF(Configuration!$C$18="No","",IF(C10<2,"WEAK",IF(AND(C10>=Configuration!$C$59,D10>=Configuration!$C$60,E10>=Configuration!$C$61),"STRONG","MODERATE"))) -> STRONG | K10: =IF(Configuration!$C$18="No","",IF(Configuration!$C$63="No","",IFERROR(aggregate(5,6,'Patent Portfolio'!AC3:AC22/('Bundle Assignment'!K3:K22=TRUE())),""))) | L10: =IF(Configuration!$C$18="No","",IF(Configuration!$C$64="No","",IFERROR(SUMPRODUCT(--('Bundle Assignment'!K3:K22=TRUE()),--('Patent Portfolio'!AD3:AD22<=1))/COUNTIF('Bundle Assignment'!K3:K22,TRUE()),0))) -> 0 | M10: =IF(Configuration!$C$18="No","",IF(Configuration!$C$65="No","",IFERROR(SUMPRODUCT(--('Bundle Assignment'!K3:K22=TRUE()),--('Patent Portfolio'!AK3:AK22<>"None"),--('Patent Portfolio'!AK3:AK22<>""))/COUNTIF('Bundle Assignment'!K3:K22,TRUE()),0))) -> 0.75 | N10: =IF(Configuration!$C$18="No","",IF(Configuration!$C$66="No","",IFERROR(SUMPRODUCT(--('Bundle Assignment'!K3:K22=TRUE()),--('Patent Portfolio'!AI3:AI22="Survived"))/COUNTIF('Bundle Assignment'!K3:K22,TRUE()),0))) -> 0.5 | O10: =IF(Configuration!$C$18="No","",IF(Configuration!$C$67="No","",IFERROR(SUMPRODUCT(--('Bundle Assignment'!K3:K22=TRUE()),--('Patent Portfolio'!T3:T22="Yes"))/COUNTIF('Bundle Assignment'!K3:K22,TRUE()),0))) -> 0.5
A11: 10 | B11: =IF(Configuration!$C$19="No","[DISABLED] Generational Roadmap","Generational Roadmap") -> Generational Roadmap | C11: =IF(Configuration!$C$19="No","",COUNTIF('Bundle Assignment'!L3:L22,TRUE())) -> 12 | D11: =IF(Configuration!$C$19="No","",IFERROR(SUMPRODUCT(--('Bundle Assignment'!L3:L22=TRUE()),('Patent Portfolio'!O3:O22+'Patent Portfolio'!P3:P22)/2)/COUNTIF('Bundle Assignment'!L3:L22,TRUE()),0)) -> 1.5833333 | E11: =IF(Configuration!$C$19="No","",IFERROR(SUMPRODUCT(--('Bundle Assignment'!L3:L22=TRUE()),'Patent Portfolio'!U3:U22)/COUNTIF('Bundle Assignment'!L3:L22,TRUE()),0)) -> 13.166667 | F11: =IF(Configuration!$C$19="No","",IFERROR(SUMPRODUCT(--('Bundle Assignment'!L3:L22=TRUE()),--('Patent Portfolio'!X3:X22="Yes"))/COUNTIF('Bundle Assignment'!L3:L22,TRUE()),0)) -> 0.83333333 | G11: =IF(Configuration!$C$19="No","",IFERROR(SUMPRODUCT(--('Bundle Assignment'!L3:L22=TRUE()),--('Patent Portfolio'!T3:T22="Yes"))/COUNTIF('Bundle Assignment'!L3:L22,TRUE()),0)) -> 0.5 | H11: =IF(Configuration!$C$19="No","",IFERROR(SUMPRODUCT(--('Bundle Assignment'!L3:L22=TRUE()),--('Patent Portfolio'!H3:H22>=2))/COUNTIF('Bundle Assignment'!L3:L22,TRUE()),0)) -> 0.33333333 | I11: =IF(Configuration!$C$19="No","",SUMPRODUCT(--('Bundle Assignment'!L3:L22=TRUE()),--('Patent Portfolio'!L3:L22=3))) -> 1 | J11: =IF(Configuration!$C$19="No","",IF(C11<2,"WEAK",IF(AND(C11>=Configuration!$C$59,D11>=Configuration!$C$60,E11>=Configuration!$C$61),"STRONG","MODERATE"))) -> MODERATE | K11: =IF(Configuration!$C$19="No","",IF(Configuration!$C$63="No","",IFERROR(aggregate(5,6,'Patent Portfolio'!AC3:AC22/('Bundle Assignment'!L3:L22=TRUE())),""))) | L11: =IF(Configuration!$C$19="No","",IF(Configuration!$C$64="No","",IFERROR(SUMPRODUCT(--('Bundle Assignment'!L3:L22=TRUE()),--('Patent Portfolio'!AD3:AD22<=1))/COUNTIF('Bundle Assignment'!L3:L22,TRUE()),0))) -> 0.25 | M11: =IF(Configuration!$C$19="No","",IF(Configuration!$C$65="No","",IFERROR(SUMPRODUCT(--('Bundle Assignment'!L3:L22=TRUE()),--('Patent Portfolio'!AK3:AK22<>"None"),--('Patent Portfolio'!AK3:AK22<>""))/COUNTIF('Bundle Assignment'!L3:L22,TRUE()),0))) -> 0.58333333 | N11: =IF(Configuration!$C$19="No","",IF(Configuration!$C$66="No","",IFERROR(SUMPRODUCT(--('Bundle Assignment'!L3:L22=TRUE()),--('Patent Portfolio'!AI3:AI22="Survived"))/COUNTIF('Bundle Assignment'!L3:L22,TRUE()),0))) -> 0.16666667 | O11: =IF(Configuration!$C$19="No","",IF(Configuration!$C$67="No","",IFERROR(SUMPRODUCT(--('Bundle Assignment'!L3:L22=TRUE()),--('Patent Portfolio'!T3:T22="Yes"))/COUNTIF('Bundle Assignment'!L3:L22,TRUE()),0))) -> 0.5
A12: 11 | B12: =IF(Configuration!$C$20="No","[DISABLED] Claim-Type","Claim-Type") -> Claim-Type | C12: =IF(Configuration!$C$20="No","",COUNTIF('Bundle Assignment'!M3:M22,TRUE())) -> 12 | D12: =IF(Configuration!$C$20="No","",IFERROR(SUMPRODUCT(--('Bundle Assignment'!M3:M22=TRUE()),('Patent Portfolio'!O3:O22+'Patent Portfolio'!P3:P22)/2)/COUNTIF('Bundle Assignment'!M3:M22,TRUE()),0)) -> 1.5833333 | E12: =IF(Configuration!$C$20="No","",IFERROR(SUMPRODUCT(--('Bundle Assignment'!M3:M22=TRUE()),'Patent Portfolio'!U3:U22)/COUNTIF('Bundle Assignment'!M3:M22,TRUE()),0)) -> 13.166667 | F12: =IF(Configuration!$C$20="No","",IFERROR(SUMPRODUCT(--('Bundle Assignment'!M3:M22=TRUE()),--('Patent Portfolio'!X3:X22="Yes"))/COUNTIF('Bundle Assignment'!M3:M22,TRUE()),0)) -> 0.83333333 | G12: =IF(Configuration!$C$20="No","",IFERROR(SUMPRODUCT(--('Bundle Assignment'!M3:M22=TRUE()),--('Patent Portfolio'!T3:T22="Yes"))/COUNTIF('Bundle Assignment'!M3:M22,TRUE()),0)) -> 0.5 | H12: =IF(Configuration!$C$20="No","",IFERROR(SUMPRODUCT(--('Bundle Assignment'!M3:M22=TRUE()),--('Patent Portfolio'!H3:H22>=2))/COUNTIF('Bundle Assignment'!M3:M22,TRUE()),0)) -> 0.33333333 | I12: =IF(Configuration!$C$20="No","",SUMPRODUCT(--('Bundle Assignment'!M3:M22=TRUE()),--('Patent Portfolio'!L3:L22=3))) -> 1 | J12: =IF(Configuration!$C$20="No","",IF(C12<2,"WEAK",IF(AND(C12>=Configuration!$C$59,D12>=Configuration!$C$60,E12>=Configuration!$C$61),"STRONG","MODERATE"))) -> MODERATE | K12: =IF(Configuration!$C$20="No","",IF(Configuration!$C$63="No","",IFERROR(aggregate(5,6,'Patent Portfolio'!AC3:AC22/('Bundle Assignment'!M3:M22=TRUE())),""))) | L12: =IF(Configuration!$C$20="No","",IF(Configuration!$C$64="No","",IFERROR(SUMPRODUCT(--('Bundle Assignment'!M3:M22=TRUE()),--('Patent Portfolio'!AD3:AD22<=1))/COUNTIF('Bundle Assignment'!M3:M22,TRUE()),0))) -> 0.25 | M12: =IF(Configuration!$C$20="No","",IF(Configuration!$C$65="No","",IFERROR(SUMPRODUCT(--('Bundle Assignment'!M3:M22=TRUE()),--('Patent Portfolio'!AK3:AK22<>"None"),--('Patent Portfolio'!AK3:AK22<>""))/COUNTIF('Bundle Assignment'!M3:M22,TRUE()),0))) -> 0.58333333 | N12: =IF(Configuration!$C$20="No","",IF(Configuration!$C$66="No","",IFERROR(SUMPRODUCT(--('Bundle Assignment'!M3:M22=TRUE()),--('Patent Portfolio'!AI3:AI22="Survived"))/COUNTIF('Bundle Assignment'!M3:M22,TRUE()),0))) -> 0.16666667 | O12: =IF(Configuration!$C$20="No","",IF(Configuration!$C$67="No","",IFERROR(SUMPRODUCT(--('Bundle Assignment'!M3:M22=TRUE()),--('Patent Portfolio'!T3:T22="Yes"))/COUNTIF('Bundle Assignment'!M3:M22,TRUE()),0))) -> 0.5
A13: 12 | B13: =IF(Configuration!$C$21="No","[DISABLED] Detectability","Detectability") -> Detectability | C13: =IF(Configuration!$C$21="No","",COUNTIF('Bundle Assignment'!N3:N22,TRUE())) -> 11 | D13: =IF(Configuration!$C$21="No","",IFERROR(SUMPRODUCT(--('Bundle Assignment'!N3:N22=TRUE()),('Patent Portfolio'!O3:O22+'Patent Portfolio'!P3:P22)/2)/COUNTIF('Bundle Assignment'!N3:N22,TRUE()),0)) -> 1.6818182 | E13: =IF(Configuration!$C$21="No","",IFERROR(SUMPRODUCT(--('Bundle Assignment'!N3:N22=TRUE()),'Patent Portfolio'!U3:U22)/COUNTIF('Bundle Assignment'!N3:N22,TRUE()),0)) -> 13.181818 | F13: =IF(Configuration!$C$21="No","",IFERROR(SUMPRODUCT(--('Bundle Assignment'!N3:N22=TRUE()),--('Patent Portfolio'!X3:X22="Yes"))/COUNTIF('Bundle Assignment'!N3:N22,TRUE()),0)) -> 0.81818182 | G13: =IF(Configuration!$C$21="No","",IFERROR(SUMPRODUCT(--('Bundle Assignment'!N3:N22=TRUE()),--('Patent Portfolio'!T3:T22="Yes"))/COUNTIF('Bundle Assignment'!N3:N22,TRUE()),0)) -> 0.45454545 | H13: =IF(Configuration!$C$21="No","",IFERROR(SUMPRODUCT(--('Bundle Assignment'!N3:N22=TRUE()),--('Patent Portfolio'!H3:H22>=2))/COUNTIF('Bundle Assignment'!N3:N22,TRUE()),0)) -> 0.36363636 | I13: =IF(Configuration!$C$21="No","",SUMPRODUCT(--('Bundle Assignment'!N3:N22=TRUE()),--('Patent Portfolio'!L3:L22=3))) -> 1 | J13: =IF(Configuration!$C$21="No","",IF(C13<2,"WEAK",IF(AND(C13>=Configuration!$C$59,D13>=Configuration!$C$60,E13>=Configuration!$C$61),"STRONG","MODERATE"))) -> MODERATE | K13: =IF(Configuration!$C$21="No","",IF(Configuration!$C$63="No","",IFERROR(aggregate(5,6,'Patent Portfolio'!AC3:AC22/('Bundle Assignment'!N3:N22=TRUE())),""))) | L13: =IF(Configuration!$C$21="No","",IF(Configuration!$C$64="No","",IFERROR(SUMPRODUCT(--('Bundle Assignment'!N3:N22=TRUE()),--('Patent Portfolio'!AD3:AD22<=1))/COUNTIF('Bundle Assignment'!N3:N22,TRUE()),0))) -> 0.27272727 | M13: =IF(Configuration!$C$21="No","",IF(Configuration!$C$65="No","",IFERROR(SUMPRODUCT(--('Bundle Assignment'!N3:N22=TRUE()),--('Patent Portfolio'!AK3:AK22<>"None"),--('Patent Portfolio'!AK3:AK22<>""))/COUNTIF('Bundle Assignment'!N3:N22,TRUE()),0))) -> 0.63636364 | N13: =IF(Configuration!$C$21="No","",IF(Configuration!$C$66="No","",IFERROR(SUMPRODUCT(--('Bundle Assignment'!N3:N22=TRUE()),--('Patent Portfolio'!AI3:AI22="Survived"))/COUNTIF('Bundle Assignment'!N3:N22,TRUE()),0))) -> 0.18181818 | O13: =IF(Configuration!$C$21="No","",IF(Configuration!$C$67="No","",IFERROR(SUMPRODUCT(--('Bundle Assignment'!N3:N22=TRUE()),--('Patent Portfolio'!T3:T22="Yes"))/COUNTIF('Bundle Assignment'!N3:N22,TRUE()),0))) -> 0.45454545
A14: 13 | B14: =IF(Configuration!$C$22="No","[DISABLED] Geographic","Geographic") -> Geographic | C14: =IF(Configuration!$C$22="No","",COUNTIF('Bundle Assignment'!O3:O22,TRUE())) -> 10 | D14: =IF(Configuration!$C$22="No","",IFERROR(SUMPRODUCT(--('Bundle Assignment'!O3:O22=TRUE()),('Patent Portfolio'!O3:O22+'Patent Portfolio'!P3:P22)/2)/COUNTIF('Bundle Assignment'!O3:O22,TRUE()),0)) -> 1.7 | E14: =IF(Configuration!$C$22="No","",IFERROR(SUMPRODUCT(--('Bundle Assignment'!O3:O22=TRUE()),'Patent Portfolio'!U3:U22)/COUNTIF('Bundle Assignment'!O3:O22,TRUE()),0)) -> 13.1 | F14: =IF(Configuration!$C$22="No","",IFERROR(SUMPRODUCT(--('Bundle Assignment'!O3:O22=TRUE()),--('Patent Portfolio'!X3:X22="Yes"))/COUNTIF('Bundle Assignment'!O3:O22,TRUE()),0)) -> 1 | G14: =IF(Configuration!$C$22="No","",IFERROR(SUMPRODUCT(--('Bundle Assignment'!O3:O22=TRUE()),--('Patent Portfolio'!T3:T22="Yes"))/COUNTIF('Bundle Assignment'!O3:O22,TRUE()),0)) -> 0.5 | H14: =IF(Configuration!$C$22="No","",IFERROR(SUMPRODUCT(--('Bundle Assignment'!O3:O22=TRUE()),--('Patent Portfolio'!H3:H22>=2))/COUNTIF('Bundle Assignment'!O3:O22,TRUE()),0)) -> 0.4 | I14: =IF(Configuration!$C$22="No","",SUMPRODUCT(--('Bundle Assignment'!O3:O22=TRUE()),--('Patent Portfolio'!L3:L22=3))) -> 1 | J14: =IF(Configuration!$C$22="No","",IF(C14<2,"WEAK",IF(AND(C14>=Configuration!$C$59,D14>=Configuration!$C$60,E14>=Configuration!$C$61),"STRONG","MODERATE"))) -> MODERATE | K14: =IF(Configuration!$C$22="No","",IF(Configuration!$C$63="No","",IFERROR(aggregate(5,6,'Patent Portfolio'!AC3:AC22/('Bundle Assignment'!O3:O22=TRUE())),""))) | L14: =IF(Configuration!$C$22="No","",IF(Configuration!$C$64="No","",IFERROR(SUMPRODUCT(--('Bundle Assignment'!O3:O22=TRUE()),--('Patent Portfolio'!AD3:AD22<=1))/COUNTIF('Bundle Assignment'!O3:O22,TRUE()),0))) -> 0.1 | M14: =IF(Configuration!$C$22="No","",IF(Configuration!$C$65="No","",IFERROR(SUMPRODUCT(--('Bundle Assignment'!O3:O22=TRUE()),--('Patent Portfolio'!AK3:AK22<>"None"),--('Patent Portfolio'!AK3:AK22<>""))/COUNTIF('Bundle Assignment'!O3:O22,TRUE()),0))) -> 0.7 | N14: =IF(Configuration!$C$22="No","",IF(Configuration!$C$66="No","",IFERROR(SUMPRODUCT(--('Bundle Assignment'!O3:O22=TRUE()),--('Patent Portfolio'!AI3:AI22="Survived"))/COUNTIF('Bundle Assignment'!O3:O22,TRUE()),0))) -> 0.2 | O14: =IF(Configuration!$C$22="No","",IF(Configuration!$C$67="No","",IFERROR(SUMPRODUCT(--('Bundle Assignment'!O3:O22=TRUE()),--('Patent Portfolio'!T3:T22="Yes"))/COUNTIF('Bundle Assignment'!O3:O22,TRUE()),0))) -> 0.5
A15: 14 | B15: =IF(Configuration!$C$23="No","[DISABLED] Family-Tree","Family-Tree") -> Family-Tree | C15: =IF(Configuration!$C$23="No","",COUNTIF('Bundle Assignment'!P3:P22,TRUE())) -> 12 | D15: =IF(Configuration!$C$23="No","",IFERROR(SUMPRODUCT(--('Bundle Assignment'!P3:P22=TRUE()),('Patent Portfolio'!O3:O22+'Patent Portfolio'!P3:P22)/2)/COUNTIF('Bundle Assignment'!P3:P22,TRUE()),0)) -> 1.5833333 | E15: =IF(Configuration!$C$23="No","",IFERROR(SUMPRODUCT(--('Bundle Assignment'!P3:P22=TRUE()),'Patent Portfolio'!U3:U22)/COUNTIF('Bundle Assignment'!P3:P22,TRUE()),0)) -> 13.166667 | F15: =IF(Configuration!$C$23="No","",IFERROR(SUMPRODUCT(--('Bundle Assignment'!P3:P22=TRUE()),--('Patent Portfolio'!X3:X22="Yes"))/COUNTIF('Bundle Assignment'!P3:P22,TRUE()),0)) -> 0.83333333 | G15: =IF(Configuration!$C$23="No","",IFERROR(SUMPRODUCT(--('Bundle Assignment'!P3:P22=TRUE()),--('Patent Portfolio'!T3:T22="Yes"))/COUNTIF('Bundle Assignment'!P3:P22,TRUE()),0)) -> 0.5 | H15: =IF(Configuration!$C$23="No","",IFERROR(SUMPRODUCT(--('Bundle Assignment'!P3:P22=TRUE()),--('Patent Portfolio'!H3:H22>=2))/COUNTIF('Bundle Assignment'!P3:P22,TRUE()),0)) -> 0.33333333 | I15: =IF(Configuration!$C$23="No","",SUMPRODUCT(--('Bundle Assignment'!P3:P22=TRUE()),--('Patent Portfolio'!L3:L22=3))) -> 1 | J15: =IF(Configuration!$C$23="No","",IF(C15<2,"WEAK",IF(AND(C15>=Configuration!$C$59,D15>=Configuration!$C$60,E15>=Configuration!$C$61),"STRONG","MODERATE"))) -> MODERATE | K15: =IF(Configuration!$C$23="No","",IF(Configuration!$C$63="No","",IFERROR(aggregate(5,6,'Patent Portfolio'!AC3:AC22/('Bundle Assignment'!P3:P22=TRUE())),""))) | L15: =IF(Configuration!$C$23="No","",IF(Configuration!$C$64="No","",IFERROR(SUMPRODUCT(--('Bundle Assignment'!P3:P22=TRUE()),--('Patent Portfolio'!AD3:AD22<=1))/COUNTIF('Bundle Assignment'!P3:P22,TRUE()),0))) -> 0.25 | M15: =IF(Configuration!$C$23="No","",IF(Configuration!$C$65="No","",IFERROR(SUMPRODUCT(--('Bundle Assignment'!P3:P22=TRUE()),--('Patent Portfolio'!AK3:AK22<>"None"),--('Patent Portfolio'!AK3:AK22<>""))/COUNTIF('Bundle Assignment'!P3:P22,TRUE()),0))) -> 0.58333333 | N15: =IF(Configuration!$C$23="No","",IF(Configuration!$C$66="No","",IFERROR(SUMPRODUCT(--('Bundle Assignment'!P3:P22=TRUE()),--('Patent Portfolio'!AI3:AI22="Survived"))/COUNTIF('Bundle Assignment'!P3:P22,TRUE()),0))) -> 0.16666667 | O15: =IF(Configuration!$C$23="No","",IF(Configuration!$C$67="No","",IFERROR(SUMPRODUCT(--('Bundle Assignment'!P3:P22=TRUE()),--('Patent Portfolio'!T3:T22="Yes"))/COUNTIF('Bundle Assignment'!P3:P22,TRUE()),0))) -> 0.5
A16: 15 | B16: =IF(Configuration!$C$24="No","[DISABLED] Lifecycle / Term","Lifecycle / Term") -> Lifecycle / Term | C16: =IF(Configuration!$C$24="No","",COUNTIF('Bundle Assignment'!Q3:Q22,TRUE())) -> 12 | D16: =IF(Configuration!$C$24="No","",IFERROR(SUMPRODUCT(--('Bundle Assignment'!Q3:Q22=TRUE()),('Patent Portfolio'!O3:O22+'Patent Portfolio'!P3:P22)/2)/COUNTIF('Bundle Assignment'!Q3:Q22,TRUE()),0)) -> 1.5833333 | E16: =IF(Configuration!$C$24="No","",IFERROR(SUMPRODUCT(--('Bundle Assignment'!Q3:Q22=TRUE()),'Patent Portfolio'!U3:U22)/COUNTIF('Bundle Assignment'!Q3:Q22,TRUE()),0)) -> 13.166667 | F16: =IF(Configuration!$C$24="No","",IFERROR(SUMPRODUCT(--('Bundle Assignment'!Q3:Q22=TRUE()),--('Patent Portfolio'!X3:X22="Yes"))/COUNTIF('Bundle Assignment'!Q3:Q22,TRUE()),0)) -> 0.83333333 | G16: =IF(Configuration!$C$24="No","",IFERROR(SUMPRODUCT(--('Bundle Assignment'!Q3:Q22=TRUE()),--('Patent Portfolio'!T3:T22="Yes"))/COUNTIF('Bundle Assignment'!Q3:Q22,TRUE()),0)) -> 0.5 | H16: =IF(Configuration!$C$24="No","",IFERROR(SUMPRODUCT(--('Bundle Assignment'!Q3:Q22=TRUE()),--('Patent Portfolio'!H3:H22>=2))/COUNTIF('Bundle Assignment'!Q3:Q22,TRUE()),0)) -> 0.33333333 | I16: =IF(Configuration!$C$24="No","",SUMPRODUCT(--('Bundle Assignment'!Q3:Q22=TRUE()),--('Patent Portfolio'!L3:L22=3))) -> 1 | J16: =IF(Configuration!$C$24="No","",IF(C16<2,"WEAK",IF(AND(C16>=Configuration!$C$59,D16>=Configuration!$C$60,E16>=Configuration!$C$61),"STRONG","MODERATE"))) -> MODERATE | K16: =IF(Configuration!$C$24="No","",IF(Configuration!$C$63="No","",IFERROR(aggregate(5,6,'Patent Portfolio'!AC3:AC22/('Bundle Assignment'!Q3:Q22=TRUE())),""))) | L16: =IF(Configuration!$C$24="No","",IF(Configuration!$C$64="No","",IFERROR(SUMPRODUCT(--('Bundle Assignment'!Q3:Q22=TRUE()),--('Patent Portfolio'!AD3:AD22<=1))/COUNTIF('Bundle Assignment'!Q3:Q22,TRUE()),0))) -> 0.25 | M16: =IF(Configuration!$C$24="No","",IF(Configuration!$C$65="No","",IFERROR(SUMPRODUCT(--('Bundle Assignment'!Q3:Q22=TRUE()),--('Patent Portfolio'!AK3:AK22<>"None"),--('Patent Portfolio'!AK3:AK22<>""))/COUNTIF('Bundle Assignment'!Q3:Q22,TRUE()),0))) -> 0.58333333 | N16: =IF(Configuration!$C$24="No","",IF(Configuration!$C$66="No","",IFERROR(SUMPRODUCT(--('Bundle Assignment'!Q3:Q22=TRUE()),--('Patent Portfolio'!AI3:AI22="Survived"))/COUNTIF('Bundle Assignment'!Q3:Q22,TRUE()),0))) -> 0.16666667 | O16: =IF(Configuration!$C$24="No","",IF(Configuration!$C$67="No","",IFERROR(SUMPRODUCT(--('Bundle Assignment'!Q3:Q22=TRUE()),--('Patent Portfolio'!T3:T22="Yes"))/COUNTIF('Bundle Assignment'!Q3:Q22,TRUE()),0))) -> 0.5
A17: 16 | B17: =IF(Configuration!$C$25="No","[DISABLED] Foundational + Improvement","Foundational + Improvement") -> Foundational + Improvement | C17: =IF(Configuration!$C$25="No","",COUNTIF('Bundle Assignment'!R3:R22,TRUE())) -> 13 | D17: =IF(Configuration!$C$25="No","",IFERROR(SUMPRODUCT(--('Bundle Assignment'!R3:R22=TRUE()),('Patent Portfolio'!O3:O22+'Patent Portfolio'!P3:P22)/2)/COUNTIF('Bundle Assignment'!R3:R22,TRUE()),0)) -> 0.61538462 | E17: =IF(Configuration!$C$25="No","",IFERROR(SUMPRODUCT(--('Bundle Assignment'!R3:R22=TRUE()),'Patent Portfolio'!U3:U22)/COUNTIF('Bundle Assignment'!R3:R22,TRUE()),0)) -> 5.3846154 | F17: =IF(Configuration!$C$25="No","",IFERROR(SUMPRODUCT(--('Bundle Assignment'!R3:R22=TRUE()),--('Patent Portfolio'!X3:X22="Yes"))/COUNTIF('Bundle Assignment'!R3:R22,TRUE()),0)) -> 0.23076923 | G17: =IF(Configuration!$C$25="No","",IFERROR(SUMPRODUCT(--('Bundle Assignment'!R3:R22=TRUE()),--('Patent Portfolio'!T3:T22="Yes"))/COUNTIF('Bundle Assignment'!R3:R22,TRUE()),0)) -> 0.23076923 | H17: =IF(Configuration!$C$25="No","",IFERROR(SUMPRODUCT(--('Bundle Assignment'!R3:R22=TRUE()),--('Patent Portfolio'!H3:H22>=2))/COUNTIF('Bundle Assignment'!R3:R22,TRUE()),0)) -> 0.15384615 | I17: =IF(Configuration!$C$25="No","",SUMPRODUCT(--('Bundle Assignment'!R3:R22=TRUE()),--('Patent Portfolio'!L3:L22=3))) -> 1 | J17: =IF(Configuration!$C$25="No","",IF(C17<2,"WEAK",IF(AND(C17>=Configuration!$C$59,D17>=Configuration!$C$60,E17>=Configuration!$C$61),"STRONG","MODERATE"))) -> MODERATE | K17: =IF(Configuration!$C$25="No","",IF(Configuration!$C$63="No","",IFERROR(aggregate(5,6,'Patent Portfolio'!AC3:AC22/('Bundle Assignment'!R3:R22=TRUE())),""))) | L17: =IF(Configuration!$C$25="No","",IF(Configuration!$C$64="No","",IFERROR(SUMPRODUCT(--('Bundle Assignment'!R3:R22=TRUE()),--('Patent Portfolio'!AD3:AD22<=1))/COUNTIF('Bundle Assignment'!R3:R22,TRUE()),0))) -> 0.76923077 | M17: =IF(Configuration!$C$25="No","",IF(Configuration!$C$65="No","",IFERROR(SUMPRODUCT(--('Bundle Assignment'!R3:R22=TRUE()),--('Patent Portfolio'!AK3:AK22<>"None"),--('Patent Portfolio'!AK3:AK22<>""))/COUNTIF('Bundle Assignment'!R3:R22,TRUE()),0))) -> 0.15384615 | N17: =IF(Configuration!$C$25="No","",IF(Configuration!$C$66="No","",IFERROR(SUMPRODUCT(--('Bundle Assignment'!R3:R22=TRUE()),--('Patent Portfolio'!AI3:AI22="Survived"))/COUNTIF('Bundle Assignment'!R3:R22,TRUE()),0))) -> 0.076923077 | O17: =IF(Configuration!$C$25="No","",IF(Configuration!$C$67="No","",IFERROR(SUMPRODUCT(--('Bundle Assignment'!R3:R22=TRUE()),--('Patent Portfolio'!T3:T22="Yes"))/COUNTIF('Bundle Assignment'!R3:R22,TRUE()),0))) -> 0.23076923
A18: 17 | B18: =IF(Configuration!$C$26="No","[DISABLED] Cross-Industry","Cross-Industry") -> Cross-Industry | C18: =IF(Configuration!$C$26="No","",COUNTIF('Bundle Assignment'!S3:S22,TRUE())) -> 9 | D18: =IF(Configuration!$C$26="No","",IFERROR(SUMPRODUCT(--('Bundle Assignment'!S3:S22=TRUE()),('Patent Portfolio'!O3:O22+'Patent Portfolio'!P3:P22)/2)/COUNTIF('Bundle Assignment'!S3:S22,TRUE()),0)) -> 1.6666667 | E18: =IF(Configuration!$C$26="No","",IFERROR(SUMPRODUCT(--('Bundle Assignment'!S3:S22=TRUE()),'Patent Portfolio'!U3:U22)/COUNTIF('Bundle Assignment'!S3:S22,TRUE()),0)) -> 13.111111 | F18: =IF(Configuration!$C$26="No","",IFERROR(SUMPRODUCT(--('Bundle Assignment'!S3:S22=TRUE()),--('Patent Portfolio'!X3:X22="Yes"))/COUNTIF('Bundle Assignment'!S3:S22,TRUE()),0)) -> 0.77777778 | G18: =IF(Configuration!$C$26="No","",IFERROR(SUMPRODUCT(--('Bundle Assignment'!S3:S22=TRUE()),--('Patent Portfolio'!T3:T22="Yes"))/COUNTIF('Bundle Assignment'!S3:S22,TRUE()),0)) -> 0.44444444 | H18: =IF(Configuration!$C$26="No","",IFERROR(SUMPRODUCT(--('Bundle Assignment'!S3:S22=TRUE()),--('Patent Portfolio'!H3:H22>=2))/COUNTIF('Bundle Assignment'!S3:S22,TRUE()),0)) -> 0.22222222 | I18: =IF(Configuration!$C$26="No","",SUMPRODUCT(--('Bundle Assignment'!S3:S22=TRUE()),--('Patent Portfolio'!L3:L22=3))) -> 1 | J18: =IF(Configuration!$C$26="No","",IF(C18<2,"WEAK",IF(AND(C18>=Configuration!$C$59,D18>=Configuration!$C$60,E18>=Configuration!$C$61),"STRONG","MODERATE"))) -> MODERATE | K18: =IF(Configuration!$C$26="No","",IF(Configuration!$C$63="No","",IFERROR(aggregate(5,6,'Patent Portfolio'!AC3:AC22/('Bundle Assignment'!S3:S22=TRUE())),""))) | L18: =IF(Configuration!$C$26="No","",IF(Configuration!$C$64="No","",IFERROR(SUMPRODUCT(--('Bundle Assignment'!S3:S22=TRUE()),--('Patent Portfolio'!AD3:AD22<=1))/COUNTIF('Bundle Assignment'!S3:S22,TRUE()),0))) -> 0.33333333 | M18: =IF(Configuration!$C$26="No","",IF(Configuration!$C$65="No","",IFERROR(SUMPRODUCT(--('Bundle Assignment'!S3:S22=TRUE()),--('Patent Portfolio'!AK3:AK22<>"None"),--('Patent Portfolio'!AK3:AK22<>""))/COUNTIF('Bundle Assignment'!S3:S22,TRUE()),0))) -> 0.55555556 | N18: =IF(Configuration!$C$26="No","",IF(Configuration!$C$66="No","",IFERROR(SUMPRODUCT(--('Bundle Assignment'!S3:S22=TRUE()),--('Patent Portfolio'!AI3:AI22="Survived"))/COUNTIF('Bundle Assignment'!S3:S22,TRUE()),0))) -> 0.11111111 | O18: =IF(Configuration!$C$26="No","",IF(Configuration!$C$67="No","",IFERROR(SUMPRODUCT(--('Bundle Assignment'!S3:S22=TRUE()),--('Patent Portfolio'!T3:T22="Yes"))/COUNTIF('Bundle Assignment'!S3:S22,TRUE()),0))) -> 0.44444444
A19: 18 | B19: =IF(Configuration!$C$27="No","[DISABLED] Convergent Theme","Convergent Theme") -> Convergent Theme | C19: =IF(Configuration!$C$27="No","",COUNTIF('Bundle Assignment'!T3:T22,TRUE())) -> 4 | D19: =IF(Configuration!$C$27="No","",IFERROR(SUMPRODUCT(--('Bundle Assignment'!T3:T22=TRUE()),('Patent Portfolio'!O3:O22+'Patent Portfolio'!P3:P22)/2)/COUNTIF('Bundle Assignment'!T3:T22,TRUE()),0)) -> 1.25 | E19: =IF(Configuration!$C$27="No","",IFERROR(SUMPRODUCT(--('Bundle Assignment'!T3:T22=TRUE()),'Patent Portfolio'!U3:U22)/COUNTIF('Bundle Assignment'!T3:T22,TRUE()),0)) -> 13 | F19: =IF(Configuration!$C$27="No","",IFERROR(SUMPRODUCT(--('Bundle Assignment'!T3:T22=TRUE()),--('Patent Portfolio'!X3:X22="Yes"))/COUNTIF('Bundle Assignment'!T3:T22,TRUE()),0)) -> 0.5 | G19: =IF(Configuration!$C$27="No","",IFERROR(SUMPRODUCT(--('Bundle Assignment'!T3:T22=TRUE()),--('Patent Portfolio'!T3:T22="Yes"))/COUNTIF('Bundle Assignment'!T3:T22,TRUE()),0)) -> 0.5 | H19: =IF(Configuration!$C$27="No","",IFERROR(SUMPRODUCT(--('Bundle Assignment'!T3:T22=TRUE()),--('Patent Portfolio'!H3:H22>=2))/COUNTIF('Bundle Assignment'!T3:T22,TRUE()),0)) -> 0 | I19: =IF(Configuration!$C$27="No","",SUMPRODUCT(--('Bundle Assignment'!T3:T22=TRUE()),--('Patent Portfolio'!L3:L22=3))) -> 0 | J19: =IF(Configuration!$C$27="No","",IF(C19<2,"WEAK",IF(AND(C19>=Configuration!$C$59,D19>=Configuration!$C$60,E19>=Configuration!$C$61),"STRONG","MODERATE"))) -> MODERATE | K19: =IF(Configuration!$C$27="No","",IF(Configuration!$C$63="No","",IFERROR(aggregate(5,6,'Patent Portfolio'!AC3:AC22/('Bundle Assignment'!T3:T22=TRUE())),""))) | L19: =IF(Configuration!$C$27="No","",IF(Configuration!$C$64="No","",IFERROR(SUMPRODUCT(--('Bundle Assignment'!T3:T22=TRUE()),--('Patent Portfolio'!AD3:AD22<=1))/COUNTIF('Bundle Assignment'!T3:T22,TRUE()),0))) -> 0.75 | M19: =IF(Configuration!$C$27="No","",IF(Configuration!$C$65="No","",IFERROR(SUMPRODUCT(--('Bundle Assignment'!T3:T22=TRUE()),--('Patent Portfolio'!AK3:AK22<>"None"),--('Patent Portfolio'!AK3:AK22<>""))/COUNTIF('Bundle Assignment'!T3:T22,TRUE()),0))) -> 0.5 | N19: =IF(Configuration!$C$27="No","",IF(Configuration!$C$66="No","",IFERROR(SUMPRODUCT(--('Bundle Assignment'!T3:T22=TRUE()),--('Patent Portfolio'!AI3:AI22="Survived"))/COUNTIF('Bundle Assignment'!T3:T22,TRUE()),0))) -> 0 | O19: =IF(Configuration!$C$27="No","",IF(Configuration!$C$67="No","",IFERROR(SUMPRODUCT(--('Bundle Assignment'!T3:T22=TRUE()),--('Patent Portfolio'!T3:T22="Yes"))/COUNTIF('Bundle Assignment'!T3:T22,TRUE()),0))) -> 0.5
A20: 19 | B20: =IF(Configuration!$C$28="No","[DISABLED] Defensive / Counter-Assert.","Defensive / Counter-Assert.") -> Defensive / Counter-Assert. | C20: =IF(Configuration!$C$28="No","",COUNTIF('Bundle Assignment'!U3:U22,TRUE())) -> 10 | D20: =IF(Configuration!$C$28="No","",IFERROR(SUMPRODUCT(--('Bundle Assignment'!U3:U22=TRUE()),('Patent Portfolio'!O3:O22+'Patent Portfolio'!P3:P22)/2)/COUNTIF('Bundle Assignment'!U3:U22,TRUE()),0)) -> 1.75 | E20: =IF(Configuration!$C$28="No","",IFERROR(SUMPRODUCT(--('Bundle Assignment'!U3:U22=TRUE()),'Patent Portfolio'!U3:U22)/COUNTIF('Bundle Assignment'!U3:U22,TRUE()),0)) -> 13.7 | F20: =IF(Configuration!$C$28="No","",IFERROR(SUMPRODUCT(--('Bundle Assignment'!U3:U22=TRUE()),--('Patent Portfolio'!X3:X22="Yes"))/COUNTIF('Bundle Assignment'!U3:U22,TRUE()),0)) -> 0.9 | G20: =IF(Configuration!$C$28="No","",IFERROR(SUMPRODUCT(--('Bundle Assignment'!U3:U22=TRUE()),--('Patent Portfolio'!T3:T22="Yes"))/COUNTIF('Bundle Assignment'!U3:U22,TRUE()),0)) -> 0.5 | H20: =IF(Configuration!$C$28="No","",IFERROR(SUMPRODUCT(--('Bundle Assignment'!U3:U22=TRUE()),--('Patent Portfolio'!H3:H22>=2))/COUNTIF('Bundle Assignment'!U3:U22,TRUE()),0)) -> 0.4 | I20: =IF(Configuration!$C$28="No","",SUMPRODUCT(--('Bundle Assignment'!U3:U22=TRUE()),--('Patent Portfolio'!L3:L22=3))) -> 1 | J20: =IF(Configuration!$C$28="No","",IF(C20<2,"WEAK",IF(AND(C20>=Configuration!$C$59,D20>=Configuration!$C$60,E20>=Configuration!$C$61),"STRONG","MODERATE"))) -> MODERATE | K20: =IF(Configuration!$C$28="No","",IF(Configuration!$C$63="No","",IFERROR(aggregate(5,6,'Patent Portfolio'!AC3:AC22/('Bundle Assignment'!U3:U22=TRUE())),""))) | L20: =IF(Configuration!$C$28="No","",IF(Configuration!$C$64="No","",IFERROR(SUMPRODUCT(--('Bundle Assignment'!U3:U22=TRUE()),--('Patent Portfolio'!AD3:AD22<=1))/COUNTIF('Bundle Assignment'!U3:U22,TRUE()),0))) -> 0.2 | M20: =IF(Configuration!$C$28="No","",IF(Configuration!$C$65="No","",IFERROR(SUMPRODUCT(--('Bundle Assignment'!U3:U22=TRUE()),--('Patent Portfolio'!AK3:AK22<>"None"),--('Patent Portfolio'!AK3:AK22<>""))/COUNTIF('Bundle Assignment'!U3:U22,TRUE()),0))) -> 0.7 | N20: =IF(Configuration!$C$28="No","",IF(Configuration!$C$66="No","",IFERROR(SUMPRODUCT(--('Bundle Assignment'!U3:U22=TRUE()),--('Patent Portfolio'!AI3:AI22="Survived"))/COUNTIF('Bundle Assignment'!U3:U22,TRUE()),0))) -> 0.2 | O20: =IF(Configuration!$C$28="No","",IF(Configuration!$C$67="No","",IFERROR(SUMPRODUCT(--('Bundle Assignment'!U3:U22=TRUE()),--('Patent Portfolio'!T3:T22="Yes"))/COUNTIF('Bundle Assignment'!U3:U22,TRUE()),0))) -> 0.5
A21: 20 | B21: =IF(Configuration!$C$29="No","[DISABLED] Whitespace / Design-Around","Whitespace / Design-Around") -> Whitespace / Design-Around | C21: =IF(Configuration!$C$29="No","",COUNTIF('Bundle Assignment'!V3:V22,TRUE())) -> 10 | D21: =IF(Configuration!$C$29="No","",IFERROR(SUMPRODUCT(--('Bundle Assignment'!V3:V22=TRUE()),('Patent Portfolio'!O3:O22+'Patent Portfolio'!P3:P22)/2)/COUNTIF('Bundle Assignment'!V3:V22,TRUE()),0)) -> 1.7 | E21: =IF(Configuration!$C$29="No","",IFERROR(SUMPRODUCT(--('Bundle Assignment'!V3:V22=TRUE()),'Patent Portfolio'!U3:U22)/COUNTIF('Bundle Assignment'!V3:V22,TRUE()),0)) -> 13.1 | F21: =IF(Configuration!$C$29="No","",IFERROR(SUMPRODUCT(--('Bundle Assignment'!V3:V22=TRUE()),--('Patent Portfolio'!X3:X22="Yes"))/COUNTIF('Bundle Assignment'!V3:V22,TRUE()),0)) -> 1 | G21: =IF(Configuration!$C$29="No","",IFERROR(SUMPRODUCT(--('Bundle Assignment'!V3:V22=TRUE()),--('Patent Portfolio'!T3:T22="Yes"))/COUNTIF('Bundle Assignment'!V3:V22,TRUE()),0)) -> 0.5 | H21: =IF(Configuration!$C$29="No","",IFERROR(SUMPRODUCT(--('Bundle Assignment'!V3:V22=TRUE()),--('Patent Portfolio'!H3:H22>=2))/COUNTIF('Bundle Assignment'!V3:V22,TRUE()),0)) -> 0.4 | I21: =IF(Configuration!$C$29="No","",SUMPRODUCT(--('Bundle Assignment'!V3:V22=TRUE()),--('Patent Portfolio'!L3:L22=3))) -> 1 | J21: =IF(Configuration!$C$29="No","",IF(C21<2,"WEAK",IF(AND(C21>=Configuration!$C$59,D21>=Configuration!$C$60,E21>=Configuration!$C$61),"STRONG","MODERATE"))) -> MODERATE | K21: =IF(Configuration!$C$29="No","",IF(Configuration!$C$63="No","",IFERROR(aggregate(5,6,'Patent Portfolio'!AC3:AC22/('Bundle Assignment'!V3:V22=TRUE())),""))) | L21: =IF(Configuration!$C$29="No","",IF(Configuration!$C$64="No","",IFERROR(SUMPRODUCT(--('Bundle Assignment'!V3:V22=TRUE()),--('Patent Portfolio'!AD3:AD22<=1))/COUNTIF('Bundle Assignment'!V3:V22,TRUE()),0))) -> 0.1 | M21: =IF(Configuration!$C$29="No","",IF(Configuration!$C$65="No","",IFERROR(SUMPRODUCT(--('Bundle Assignment'!V3:V22=TRUE()),--('Patent Portfolio'!AK3:AK22<>"None"),--('Patent Portfolio'!AK3:AK22<>""))/COUNTIF('Bundle Assignment'!V3:V22,TRUE()),0))) -> 0.7 | N21: =IF(Configuration!$C$29="No","",IF(Configuration!$C$66="No","",IFERROR(SUMPRODUCT(--('Bundle Assignment'!V3:V22=TRUE()),--('Patent Portfolio'!AI3:AI22="Survived"))/COUNTIF('Bundle Assignment'!V3:V22,TRUE()),0))) -> 0.2 | O21: =IF(Configuration!$C$29="No","",IF(Configuration!$C$67="No","",IFERROR(SUMPRODUCT(--('Bundle Assignment'!V3:V22=TRUE()),--('Patent Portfolio'!T3:T22="Yes"))/COUNTIF('Bundle Assignment'!V3:V22,TRUE()),0))) -> 0.5
A22: 21 | B22: =IF(Configuration!$C$30="No","[DISABLED] Prosecution-Status","Prosecution-Status") -> Prosecution-Status | C22: =IF(Configuration!$C$30="No","",COUNTIF('Bundle Assignment'!W3:W22,TRUE())) -> 6 | D22: =IF(Configuration!$C$30="No","",IFERROR(SUMPRODUCT(--('Bundle Assignment'!W3:W22=TRUE()),('Patent Portfolio'!O3:O22+'Patent Portfolio'!P3:P22)/2)/COUNTIF('Bundle Assignment'!W3:W22,TRUE()),0)) -> 1.3333333 | E22: =IF(Configuration!$C$30="No","",IFERROR(SUMPRODUCT(--('Bundle Assignment'!W3:W22=TRUE()),'Patent Portfolio'!U3:U22)/COUNTIF('Bundle Assignment'!W3:W22,TRUE()),0)) -> 15.833333 | F22: =IF(Configuration!$C$30="No","",IFERROR(SUMPRODUCT(--('Bundle Assignment'!W3:W22=TRUE()),--('Patent Portfolio'!X3:X22="Yes"))/COUNTIF('Bundle Assignment'!W3:W22,TRUE()),0)) -> 0.83333333 | G22: =IF(Configuration!$C$30="No","",IFERROR(SUMPRODUCT(--('Bundle Assignment'!W3:W22=TRUE()),--('Patent Portfolio'!T3:T22="Yes"))/COUNTIF('Bundle Assignment'!W3:W22,TRUE()),0)) -> 1 | H22: =IF(Configuration!$C$30="No","",IFERROR(SUMPRODUCT(--('Bundle Assignment'!W3:W22=TRUE()),--('Patent Portfolio'!H3:H22>=2))/COUNTIF('Bundle Assignment'!W3:W22,TRUE()),0)) -> 0.33333333 | I22: =IF(Configuration!$C$30="No","",SUMPRODUCT(--('Bundle Assignment'!W3:W22=TRUE()),--('Patent Portfolio'!L3:L22=3))) -> 1 | J22: =IF(Configuration!$C$30="No","",IF(C22<2,"WEAK",IF(AND(C22>=Configuration!$C$59,D22>=Configuration!$C$60,E22>=Configuration!$C$61),"STRONG","MODERATE"))) -> MODERATE | K22: =IF(Configuration!$C$30="No","",IF(Configuration!$C$63="No","",IFERROR(aggregate(5,6,'Patent Portfolio'!AC3:AC22/('Bundle Assignment'!W3:W22=TRUE())),""))) | L22: =IF(Configuration!$C$30="No","",IF(Configuration!$C$64="No","",IFERROR(SUMPRODUCT(--('Bundle Assignment'!W3:W22=TRUE()),--('Patent Portfolio'!AD3:AD22<=1))/COUNTIF('Bundle Assignment'!W3:W22,TRUE()),0))) -> 0.33333333 | M22: =IF(Configuration!$C$30="No","",IF(Configuration!$C$65="No","",IFERROR(SUMPRODUCT(--('Bundle Assignment'!W3:W22=TRUE()),--('Patent Portfolio'!AK3:AK22<>"None"),--('Patent Portfolio'!AK3:AK22<>""))/COUNTIF('Bundle Assignment'!W3:W22,TRUE()),0))) -> 0.5 | N22: =IF(Configuration!$C$30="No","",IF(Configuration!$C$66="No","",IFERROR(SUMPRODUCT(--('Bundle Assignment'!W3:W22=TRUE()),--('Patent Portfolio'!AI3:AI22="Survived"))/COUNTIF('Bundle Assignment'!W3:W22,TRUE()),0))) -> 0.16666667 | O22: =IF(Configuration!$C$30="No","",IF(Configuration!$C$67="No","",IFERROR(SUMPRODUCT(--('Bundle Assignment'!W3:W22=TRUE()),--('Patent Portfolio'!T3:T22="Yes"))/COUNTIF('Bundle Assignment'!W3:W22,TRUE()),0))) -> 1
A23: 22 | B23: =IF(Configuration!$C$31="No","[DISABLED] Anchor-and-Halo","Anchor-and-Halo") -> Anchor-and-Halo | C23: =IF(Configuration!$C$31="No","",COUNTIF('Bundle Assignment'!X3:X22,TRUE())) -> 10 | D23: =IF(Configuration!$C$31="No","",IFERROR(SUMPRODUCT(--('Bundle Assignment'!X3:X22=TRUE()),('Patent Portfolio'!O3:O22+'Patent Portfolio'!P3:P22)/2)/COUNTIF('Bundle Assignment'!X3:X22,TRUE()),0)) -> 1.7 | E23: =IF(Configuration!$C$31="No","",IFERROR(SUMPRODUCT(--('Bundle Assignment'!X3:X22=TRUE()),'Patent Portfolio'!U3:U22)/COUNTIF('Bundle Assignment'!X3:X22,TRUE()),0)) -> 13.1 | F23: =IF(Configuration!$C$31="No","",IFERROR(SUMPRODUCT(--('Bundle Assignment'!X3:X22=TRUE()),--('Patent Portfolio'!X3:X22="Yes"))/COUNTIF('Bundle Assignment'!X3:X22,TRUE()),0)) -> 1 | G23: =IF(Configuration!$C$31="No","",IFERROR(SUMPRODUCT(--('Bundle Assignment'!X3:X22=TRUE()),--('Patent Portfolio'!T3:T22="Yes"))/COUNTIF('Bundle Assignment'!X3:X22,TRUE()),0)) -> 0.5 | H23: =IF(Configuration!$C$31="No","",IFERROR(SUMPRODUCT(--('Bundle Assignment'!X3:X22=TRUE()),--('Patent Portfolio'!H3:H22>=2))/COUNTIF('Bundle Assignment'!X3:X22,TRUE()),0)) -> 0.4 | I23: =IF(Configuration!$C$31="No","",SUMPRODUCT(--('Bundle Assignment'!X3:X22=TRUE()),--('Patent Portfolio'!L3:L22=3))) -> 1 | J23: =IF(Configuration!$C$31="No","",IF(C23<2,"WEAK",IF(AND(C23>=Configuration!$C$59,D23>=Configuration!$C$60,E23>=Configuration!$C$61),"STRONG","MODERATE"))) -> MODERATE | K23: =IF(Configuration!$C$31="No","",IF(Configuration!$C$63="No","",IFERROR(aggregate(5,6,'Patent Portfolio'!AC3:AC22/('Bundle Assignment'!X3:X22=TRUE())),""))) | L23: =IF(Configuration!$C$31="No","",IF(Configuration!$C$64="No","",IFERROR(SUMPRODUCT(--('Bundle Assignment'!X3:X22=TRUE()),--('Patent Portfolio'!AD3:AD22<=1))/COUNTIF('Bundle Assignment'!X3:X22,TRUE()),0))) -> 0.1 | M23: =IF(Configuration!$C$31="No","",IF(Configuration!$C$65="No","",IFERROR(SUMPRODUCT(--('Bundle Assignment'!X3:X22=TRUE()),--('Patent Portfolio'!AK3:AK22<>"None"),--('Patent Portfolio'!AK3:AK22<>""))/COUNTIF('Bundle Assignment'!X3:X22,TRUE()),0))) -> 0.7 | N23: =IF(Configuration!$C$31="No","",IF(Configuration!$C$66="No","",IFERROR(SUMPRODUCT(--('Bundle Assignment'!X3:X22=TRUE()),--('Patent Portfolio'!AI3:AI22="Survived"))/COUNTIF('Bundle Assignment'!X3:X22,TRUE()),0))) -> 0.2 | O23: =IF(Configuration!$C$31="No","",IF(Configuration!$C$67="No","",IFERROR(SUMPRODUCT(--('Bundle Assignment'!X3:X22=TRUE()),--('Patent Portfolio'!T3:T22="Yes"))/COUNTIF('Bundle Assignment'!X3:X22,TRUE()),0))) -> 0.5
A24: 23 | B24: =IF(Configuration!$C$32="No","[DISABLED] Picket-Fence","Picket-Fence") -> Picket-Fence | C24: =IF(Configuration!$C$32="No","",COUNTIF('Bundle Assignment'!Y3:Y22,TRUE())) -> 12 | D24: =IF(Configuration!$C$32="No","",IFERROR(SUMPRODUCT(--('Bundle Assignment'!Y3:Y22=TRUE()),('Patent Portfolio'!O3:O22+'Patent Portfolio'!P3:P22)/2)/COUNTIF('Bundle Assignment'!Y3:Y22,TRUE()),0)) -> 1.5833333 | E24: =IF(Configuration!$C$32="No","",IFERROR(SUMPRODUCT(--('Bundle Assignment'!Y3:Y22=TRUE()),'Patent Portfolio'!U3:U22)/COUNTIF('Bundle Assignment'!Y3:Y22,TRUE()),0)) -> 13.166667 | F24: =IF(Configuration!$C$32="No","",IFERROR(SUMPRODUCT(--('Bundle Assignment'!Y3:Y22=TRUE()),--('Patent Portfolio'!X3:X22="Yes"))/COUNTIF('Bundle Assignment'!Y3:Y22,TRUE()),0)) -> 0.83333333 | G24: =IF(Configuration!$C$32="No","",IFERROR(SUMPRODUCT(--('Bundle Assignment'!Y3:Y22=TRUE()),--('Patent Portfolio'!T3:T22="Yes"))/COUNTIF('Bundle Assignment'!Y3:Y22,TRUE()),0)) -> 0.5 | H24: =IF(Configuration!$C$32="No","",IFERROR(SUMPRODUCT(--('Bundle Assignment'!Y3:Y22=TRUE()),--('Patent Portfolio'!H3:H22>=2))/COUNTIF('Bundle Assignment'!Y3:Y22,TRUE()),0)) -> 0.33333333 | I24: =IF(Configuration!$C$32="No","",SUMPRODUCT(--('Bundle Assignment'!Y3:Y22=TRUE()),--('Patent Portfolio'!L3:L22=3))) -> 1 | J24: =IF(Configuration!$C$32="No","",IF(C24<2,"WEAK",IF(AND(C24>=Configuration!$C$59,D24>=Configuration!$C$60,E24>=Configuration!$C$61),"STRONG","MODERATE"))) -> MODERATE | K24: =IF(Configuration!$C$32="No","",IF(Configuration!$C$63="No","",IFERROR(aggregate(5,6,'Patent Portfolio'!AC3:AC22/('Bundle Assignment'!Y3:Y22=TRUE())),""))) | L24: =IF(Configuration!$C$32="No","",IF(Configuration!$C$64="No","",IFERROR(SUMPRODUCT(--('Bundle Assignment'!Y3:Y22=TRUE()),--('Patent Portfolio'!AD3:AD22<=1))/COUNTIF('Bundle Assignment'!Y3:Y22,TRUE()),0))) -> 0.25 | M24: =IF(Configuration!$C$32="No","",IF(Configuration!$C$65="No","",IFERROR(SUMPRODUCT(--('Bundle Assignment'!Y3:Y22=TRUE()),--('Patent Portfolio'!AK3:AK22<>"None"),--('Patent Portfolio'!AK3:AK22<>""))/COUNTIF('Bundle Assignment'!Y3:Y22,TRUE()),0))) -> 0.58333333 | N24: =IF(Configuration!$C$32="No","",IF(Configuration!$C$66="No","",IFERROR(SUMPRODUCT(--('Bundle Assignment'!Y3:Y22=TRUE()),--('Patent Portfolio'!AI3:AI22="Survived"))/COUNTIF('Bundle Assignment'!Y3:Y22,TRUE()),0))) -> 0.16666667 | O24: =IF(Configuration!$C$32="No","",IF(Configuration!$C$67="No","",IFERROR(SUMPRODUCT(--('Bundle Assignment'!Y3:Y22=TRUE()),--('Patent Portfolio'!T3:T22="Yes"))/COUNTIF('Bundle Assignment'!Y3:Y22,TRUE()),0))) -> 0.5
A25: 24 | B25: =IF(Configuration!$C$33="No","[DISABLED] Strong-Core + Tail","Strong-Core + Tail") -> Strong-Core + Tail | C25: =IF(Configuration!$C$33="No","",COUNTIF('Bundle Assignment'!Z3:Z22,TRUE())) -> 12 | D25: =IF(Configuration!$C$33="No","",IFERROR(SUMPRODUCT(--('Bundle Assignment'!Z3:Z22=TRUE()),('Patent Portfolio'!O3:O22+'Patent Portfolio'!P3:P22)/2)/COUNTIF('Bundle Assignment'!Z3:Z22,TRUE()),0)) -> 1.5833333 | E25: =IF(Configuration!$C$33="No","",IFERROR(SUMPRODUCT(--('Bundle Assignment'!Z3:Z22=TRUE()),'Patent Portfolio'!U3:U22)/COUNTIF('Bundle Assignment'!Z3:Z22,TRUE()),0)) -> 13.166667 | F25: =IF(Configuration!$C$33="No","",IFERROR(SUMPRODUCT(--('Bundle Assignment'!Z3:Z22=TRUE()),--('Patent Portfolio'!X3:X22="Yes"))/COUNTIF('Bundle Assignment'!Z3:Z22,TRUE()),0)) -> 0.83333333 | G25: =IF(Configuration!$C$33="No","",IFERROR(SUMPRODUCT(--('Bundle Assignment'!Z3:Z22=TRUE()),--('Patent Portfolio'!T3:T22="Yes"))/COUNTIF('Bundle Assignment'!Z3:Z22,TRUE()),0)) -> 0.5 | H25: =IF(Configuration!$C$33="No","",IFERROR(SUMPRODUCT(--('Bundle Assignment'!Z3:Z22=TRUE()),--('Patent Portfolio'!H3:H22>=2))/COUNTIF('Bundle Assignment'!Z3:Z22,TRUE()),0)) -> 0.33333333 | I25: =IF(Configuration!$C$33="No","",SUMPRODUCT(--('Bundle Assignment'!Z3:Z22=TRUE()),--('Patent Portfolio'!L3:L22=3))) -> 1 | J25: =IF(Configuration!$C$33="No","",IF(C25<2,"WEAK",IF(AND(C25>=Configuration!$C$59,D25>=Configuration!$C$60,E25>=Configuration!$C$61),"STRONG","MODERATE"))) -> MODERATE | K25: =IF(Configuration!$C$33="No","",IF(Configuration!$C$63="No","",IFERROR(aggregate(5,6,'Patent Portfolio'!AC3:AC22/('Bundle Assignment'!Z3:Z22=TRUE())),""))) | L25: =IF(Configuration!$C$33="No","",IF(Configuration!$C$64="No","",IFERROR(SUMPRODUCT(--('Bundle Assignment'!Z3:Z22=TRUE()),--('Patent Portfolio'!AD3:AD22<=1))/COUNTIF('Bundle Assignment'!Z3:Z22,TRUE()),0))) -> 0.25 | M25: =IF(Configuration!$C$33="No","",IF(Configuration!$C$65="No","",IFERROR(SUMPRODUCT(--('Bundle Assignment'!Z3:Z22=TRUE()),--('Patent Portfolio'!AK3:AK22<>"None"),--('Patent Portfolio'!AK3:AK22<>""))/COUNTIF('Bundle Assignment'!Z3:Z22,TRUE()),0))) -> 0.58333333 | N25: =IF(Configuration!$C$33="No","",IF(Configuration!$C$66="No","",IFERROR(SUMPRODUCT(--('Bundle Assignment'!Z3:Z22=TRUE()),--('Patent Portfolio'!AI3:AI22="Survived"))/COUNTIF('Bundle Assignment'!Z3:Z22,TRUE()),0))) -> 0.16666667 | O25: =IF(Configuration!$C$33="No","",IF(Configuration!$C$67="No","",IFERROR(SUMPRODUCT(--('Bundle Assignment'!Z3:Z22=TRUE()),--('Patent Portfolio'!T3:T22="Yes"))/COUNTIF('Bundle Assignment'!Z3:Z22,TRUE()),0))) -> 0.5
A26: 25 | B26: =IF(Configuration!$C$34="No","[DISABLED] Continuation-Live","Continuation-Live") -> Continuation-Live | C26: =IF(Configuration!$C$34="No","",COUNTIF('Bundle Assignment'!AA3:AA22,TRUE())) -> 6 | D26: =IF(Configuration!$C$34="No","",IFERROR(SUMPRODUCT(--('Bundle Assignment'!AA3:AA22=TRUE()),('Patent Portfolio'!O3:O22+'Patent Portfolio'!P3:P22)/2)/COUNTIF('Bundle Assignment'!AA3:AA22,TRUE()),0)) -> 1.3333333 | E26: =IF(Configuration!$C$34="No","",IFERROR(SUMPRODUCT(--('Bundle Assignment'!AA3:AA22=TRUE()),'Patent Portfolio'!U3:U22)/COUNTIF('Bundle Assignment'!AA3:AA22,TRUE()),0)) -> 15.833333 | F26: =IF(Configuration!$C$34="No","",IFERROR(SUMPRODUCT(--('Bundle Assignment'!AA3:AA22=TRUE()),--('Patent Portfolio'!X3:X22="Yes"))/COUNTIF('Bundle Assignment'!AA3:AA22,TRUE()),0)) -> 0.83333333 | G26: =IF(Configuration!$C$34="No","",IFERROR(SUMPRODUCT(--('Bundle Assignment'!AA3:AA22=TRUE()),--('Patent Portfolio'!T3:T22="Yes"))/COUNTIF('Bundle Assignment'!AA3:AA22,TRUE()),0)) -> 1 | H26: =IF(Configuration!$C$34="No","",IFERROR(SUMPRODUCT(--('Bundle Assignment'!AA3:AA22=TRUE()),--('Patent Portfolio'!H3:H22>=2))/COUNTIF('Bundle Assignment'!AA3:AA22,TRUE()),0)) -> 0.33333333 | I26: =IF(Configuration!$C$34="No","",SUMPRODUCT(--('Bundle Assignment'!AA3:AA22=TRUE()),--('Patent Portfolio'!L3:L22=3))) -> 1 | J26: =IF(Configuration!$C$34="No","",IF(C26<2,"WEAK",IF(AND(C26>=Configuration!$C$59,D26>=Configuration!$C$60,E26>=Configuration!$C$61),"STRONG","MODERATE"))) -> MODERATE | K26: =IF(Configuration!$C$34="No","",IF(Configuration!$C$63="No","",IFERROR(aggregate(5,6,'Patent Portfolio'!AC3:AC22/('Bundle Assignment'!AA3:AA22=TRUE())),""))) | L26: =IF(Configuration!$C$34="No","",IF(Configuration!$C$64="No","",IFERROR(SUMPRODUCT(--('Bundle Assignment'!AA3:AA22=TRUE()),--('Patent Portfolio'!AD3:AD22<=1))/COUNTIF('Bundle Assignment'!AA3:AA22,TRUE()),0))) -> 0.33333333 | M26: =IF(Configuration!$C$34="No","",IF(Configuration!$C$65="No","",IFERROR(SUMPRODUCT(--('Bundle Assignment'!AA3:AA22=TRUE()),--('Patent Portfolio'!AK3:AK22<>"None"),--('Patent Portfolio'!AK3:AK22<>""))/COUNTIF('Bundle Assignment'!AA3:AA22,TRUE()),0))) -> 0.5 | N26: =IF(Configuration!$C$34="No","",IF(Configuration!$C$66="No","",IFERROR(SUMPRODUCT(--('Bundle Assignment'!AA3:AA22=TRUE()),--('Patent Portfolio'!AI3:AI22="Survived"))/COUNTIF('Bundle Assignment'!AA3:AA22,TRUE()),0))) -> 0.16666667 | O26: =IF(Configuration!$C$34="No","",IF(Configuration!$C$67="No","",IFERROR(SUMPRODUCT(--('Bundle Assignment'!AA3:AA22=TRUE()),--('Patent Portfolio'!T3:T22="Yes"))/COUNTIF('Bundle Assignment'!AA3:AA22,TRUE()),0))) -> 1
A27: 26 | B27: =IF(Configuration!$C$35="No","[DISABLED] EoU-Backed","EoU-Backed") -> EoU-Backed | C27: =IF(Configuration!$C$35="No","",COUNTIF('Bundle Assignment'!AB3:AB22,TRUE())) -> 7 | D27: =IF(Configuration!$C$35="No","",IFERROR(SUMPRODUCT(--('Bundle Assignment'!AB3:AB22=TRUE()),('Patent Portfolio'!O3:O22+'Patent Portfolio'!P3:P22)/2)/COUNTIF('Bundle Assignment'!AB3:AB22,TRUE()),0)) -> 1.8571429 | E27: =IF(Configuration!$C$35="No","",IFERROR(SUMPRODUCT(--('Bundle Assignment'!AB3:AB22=TRUE()),'Patent Portfolio'!U3:U22)/COUNTIF('Bundle Assignment'!AB3:AB22,TRUE()),0)) -> 12.857143 | F27: =IF(Configuration!$C$35="No","",IFERROR(SUMPRODUCT(--('Bundle Assignment'!AB3:AB22=TRUE()),--('Patent Portfolio'!X3:X22="Yes"))/COUNTIF('Bundle Assignment'!AB3:AB22,TRUE()),0)) -> 1 | G27: =IF(Configuration!$C$35="No","",IFERROR(SUMPRODUCT(--('Bundle Assignment'!AB3:AB22=TRUE()),--('Patent Portfolio'!T3:T22="Yes"))/COUNTIF('Bundle Assignment'!AB3:AB22,TRUE()),0)) -> 0.42857143 | H27: =IF(Configuration!$C$35="No","",IFERROR(SUMPRODUCT(--('Bundle Assignment'!AB3:AB22=TRUE()),--('Patent Portfolio'!H3:H22>=2))/COUNTIF('Bundle Assignment'!AB3:AB22,TRUE()),0)) -> 0.42857143 | I27: =IF(Configuration!$C$35="No","",SUMPRODUCT(--('Bundle Assignment'!AB3:AB22=TRUE()),--('Patent Portfolio'!L3:L22=3))) -> 1 | J27: =IF(Configuration!$C$35="No","",IF(C27<2,"WEAK",IF(AND(C27>=Configuration!$C$59,D27>=Configuration!$C$60,E27>=Configuration!$C$61),"STRONG","MODERATE"))) -> MODERATE | K27: =IF(Configuration!$C$35="No","",IF(Configuration!$C$63="No","",IFERROR(aggregate(5,6,'Patent Portfolio'!AC3:AC22/('Bundle Assignment'!AB3:AB22=TRUE())),""))) | L27: =IF(Configuration!$C$35="No","",IF(Configuration!$C$64="No","",IFERROR(SUMPRODUCT(--('Bundle Assignment'!AB3:AB22=TRUE()),--('Patent Portfolio'!AD3:AD22<=1))/COUNTIF('Bundle Assignment'!AB3:AB22,TRUE()),0))) -> 0.14285714 | M27: =IF(Configuration!$C$35="No","",IF(Configuration!$C$65="No","",IFERROR(SUMPRODUCT(--('Bundle Assignment'!AB3:AB22=TRUE()),--('Patent Portfolio'!AK3:AK22<>"None"),--('Patent Portfolio'!AK3:AK22<>""))/COUNTIF('Bundle Assignment'!AB3:AB22,TRUE()),0))) -> 1 | N27: =IF(Configuration!$C$35="No","",IF(Configuration!$C$66="No","",IFERROR(SUMPRODUCT(--('Bundle Assignment'!AB3:AB22=TRUE()),--('Patent Portfolio'!AI3:AI22="Survived"))/COUNTIF('Bundle Assignment'!AB3:AB22,TRUE()),0))) -> 0.28571429 | O27: =IF(Configuration!$C$35="No","",IF(Configuration!$C$67="No","",IFERROR(SUMPRODUCT(--('Bundle Assignment'!AB3:AB22=TRUE()),--('Patent Portfolio'!T3:T22="Yes"))/COUNTIF('Bundle Assignment'!AB3:AB22,TRUE()),0))) -> 0.42857143
A28: 27 | B28: =IF(Configuration!$C$36="No","[DISABLED] Battle-Tested","Battle-Tested") -> Battle-Tested | C28: =IF(Configuration!$C$36="No","",COUNTIF('Bundle Assignment'!AC3:AC22,TRUE())) -> 2 | D28: =IF(Configuration!$C$36="No","",IFERROR(SUMPRODUCT(--('Bundle Assignment'!AC3:AC22=TRUE()),('Patent Portfolio'!O3:O22+'Patent Portfolio'!P3:P22)/2)/COUNTIF('Bundle Assignment'!AC3:AC22,TRUE()),0)) -> 2.5 | E28: =IF(Configuration!$C$36="No","",IFERROR(SUMPRODUCT(--('Bundle Assignment'!AC3:AC22=TRUE()),'Patent Portfolio'!U3:U22)/COUNTIF('Bundle Assignment'!AC3:AC22,TRUE()),0)) -> 11.5 | F28: =IF(Configuration!$C$36="No","",IFERROR(SUMPRODUCT(--('Bundle Assignment'!AC3:AC22=TRUE()),--('Patent Portfolio'!X3:X22="Yes"))/COUNTIF('Bundle Assignment'!AC3:AC22,TRUE()),0)) -> 1 | G28: =IF(Configuration!$C$36="No","",IFERROR(SUMPRODUCT(--('Bundle Assignment'!AC3:AC22=TRUE()),--('Patent Portfolio'!T3:T22="Yes"))/COUNTIF('Bundle Assignment'!AC3:AC22,TRUE()),0)) -> 0.5 | H28: =IF(Configuration!$C$36="No","",IFERROR(SUMPRODUCT(--('Bundle Assignment'!AC3:AC22=TRUE()),--('Patent Portfolio'!H3:H22>=2))/COUNTIF('Bundle Assignment'!AC3:AC22,TRUE()),0)) -> 1 | I28: =IF(Configuration!$C$36="No","",SUMPRODUCT(--('Bundle Assignment'!AC3:AC22=TRUE()),--('Patent Portfolio'!L3:L22=3))) -> 0 | J28: =IF(Configuration!$C$36="No","",IF(C28<2,"WEAK",IF(AND(C28>=Configuration!$C$59,D28>=Configuration!$C$60,E28>=Configuration!$C$61),"STRONG","MODERATE"))) -> MODERATE | K28: =IF(Configuration!$C$36="No","",IF(Configuration!$C$63="No","",IFERROR(aggregate(5,6,'Patent Portfolio'!AC3:AC22/('Bundle Assignment'!AC3:AC22=TRUE())),""))) | L28: =IF(Configuration!$C$36="No","",IF(Configuration!$C$64="No","",IFERROR(SUMPRODUCT(--('Bundle Assignment'!AC3:AC22=TRUE()),--('Patent Portfolio'!AD3:AD22<=1))/COUNTIF('Bundle Assignment'!AC3:AC22,TRUE()),0))) -> 0 | M28: =IF(Configuration!$C$36="No","",IF(Configuration!$C$65="No","",IFERROR(SUMPRODUCT(--('Bundle Assignment'!AC3:AC22=TRUE()),--('Patent Portfolio'!AK3:AK22<>"None"),--('Patent Portfolio'!AK3:AK22<>""))/COUNTIF('Bundle Assignment'!AC3:AC22,TRUE()),0))) -> 1 | N28: =IF(Configuration!$C$36="No","",IF(Configuration!$C$66="No","",IFERROR(SUMPRODUCT(--('Bundle Assignment'!AC3:AC22=TRUE()),--('Patent Portfolio'!AI3:AI22="Survived"))/COUNTIF('Bundle Assignment'!AC3:AC22,TRUE()),0))) -> 1 | O28: =IF(Configuration!$C$36="No","",IF(Configuration!$C$67="No","",IFERROR(SUMPRODUCT(--('Bundle Assignment'!AC3:AC22=TRUE()),--('Patent Portfolio'!T3:T22="Yes"))/COUNTIF('Bundle Assignment'!AC3:AC22,TRUE()),0))) -> 0.5
A29: 28 | B29: =IF(Configuration!$C$37="No","[DISABLED] Clean-Title","Clean-Title") -> Clean-Title | C29: =IF(Configuration!$C$37="No","",COUNTIF('Bundle Assignment'!AD3:AD22,TRUE())) -> 9 | D29: =IF(Configuration!$C$37="No","",IFERROR(SUMPRODUCT(--('Bundle Assignment'!AD3:AD22=TRUE()),('Patent Portfolio'!O3:O22+'Patent Portfolio'!P3:P22)/2)/COUNTIF('Bundle Assignment'!AD3:AD22,TRUE()),0)) -> 1.5555556 | E29: =IF(Configuration!$C$37="No","",IFERROR(SUMPRODUCT(--('Bundle Assignment'!AD3:AD22=TRUE()),'Patent Portfolio'!U3:U22)/COUNTIF('Bundle Assignment'!AD3:AD22,TRUE()),0)) -> 14.111111 | F29: =IF(Configuration!$C$37="No","",IFERROR(SUMPRODUCT(--('Bundle Assignment'!AD3:AD22=TRUE()),--('Patent Portfolio'!X3:X22="Yes"))/COUNTIF('Bundle Assignment'!AD3:AD22,TRUE()),0)) -> 0.88888889 | G29: =IF(Configuration!$C$37="No","",IFERROR(SUMPRODUCT(--('Bundle Assignment'!AD3:AD22=TRUE()),--('Patent Portfolio'!T3:T22="Yes"))/COUNTIF('Bundle Assignment'!AD3:AD22,TRUE()),0)) -> 0.66666667 | H29: =IF(Configuration!$C$37="No","",IFERROR(SUMPRODUCT(--('Bundle Assignment'!AD3:AD22=TRUE()),--('Patent Portfolio'!H3:H22>=2))/COUNTIF('Bundle Assignment'!AD3:AD22,TRUE()),0)) -> 0.44444444 | I29: =IF(Configuration!$C$37="No","",SUMPRODUCT(--('Bundle Assignment'!AD3:AD22=TRUE()),--('Patent Portfolio'!L3:L22=3))) -> 1 | J29: =IF(Configuration!$C$37="No","",IF(C29<2,"WEAK",IF(AND(C29>=Configuration!$C$59,D29>=Configuration!$C$60,E29>=Configuration!$C$61),"STRONG","MODERATE"))) -> MODERATE | K29: =IF(Configuration!$C$37="No","",IF(Configuration!$C$63="No","",IFERROR(aggregate(5,6,'Patent Portfolio'!AC3:AC22/('Bundle Assignment'!AD3:AD22=TRUE())),""))) | L29: =IF(Configuration!$C$37="No","",IF(Configuration!$C$64="No","",IFERROR(SUMPRODUCT(--('Bundle Assignment'!AD3:AD22=TRUE()),--('Patent Portfolio'!AD3:AD22<=1))/COUNTIF('Bundle Assignment'!AD3:AD22,TRUE()),0))) -> 0.22222222 | M29: =IF(Configuration!$C$37="No","",IF(Configuration!$C$65="No","",IFERROR(SUMPRODUCT(--('Bundle Assignment'!AD3:AD22=TRUE()),--('Patent Portfolio'!AK3:AK22<>"None"),--('Patent Portfolio'!AK3:AK22<>""))/COUNTIF('Bundle Assignment'!AD3:AD22,TRUE()),0))) -> 0.66666667 | N29: =IF(Configuration!$C$37="No","",IF(Configuration!$C$66="No","",IFERROR(SUMPRODUCT(--('Bundle Assignment'!AD3:AD22=TRUE()),--('Patent Portfolio'!AI3:AI22="Survived"))/COUNTIF('Bundle Assignment'!AD3:AD22,TRUE()),0))) -> 0.22222222 | O29: =IF(Configuration!$C$37="No","",IF(Configuration!$C$67="No","",IFERROR(SUMPRODUCT(--('Bundle Assignment'!AD3:AD22=TRUE()),--('Patent Portfolio'!T3:T22="Yes"))/COUNTIF('Bundle Assignment'!AD3:AD22,TRUE()),0))) -> 0.66666667
A30: 29 | B30: =IF(Configuration!$C$38="No","[DISABLED] High-Citation","High-Citation") -> High-Citation | C30: =IF(Configuration!$C$38="No","",COUNTIF('Bundle Assignment'!AE3:AE22,TRUE())) -> 8 | D30: =IF(Configuration!$C$38="No","",IFERROR(SUMPRODUCT(--('Bundle Assignment'!AE3:AE22=TRUE()),('Patent Portfolio'!O3:O22+'Patent Portfolio'!P3:P22)/2)/COUNTIF('Bundle Assignment'!AE3:AE22,TRUE()),0)) -> 1.6875 | E30: =IF(Configuration!$C$38="No","",IFERROR(SUMPRODUCT(--('Bundle Assignment'!AE3:AE22=TRUE()),'Patent Portfolio'!U3:U22)/COUNTIF('Bundle Assignment'!AE3:AE22,TRUE()),0)) -> 12.875 | F30: =IF(Configuration!$C$38="No","",IFERROR(SUMPRODUCT(--('Bundle Assignment'!AE3:AE22=TRUE()),--('Patent Portfolio'!X3:X22="Yes"))/COUNTIF('Bundle Assignment'!AE3:AE22,TRUE()),0)) -> 1 | G30: =IF(Configuration!$C$38="No","",IFERROR(SUMPRODUCT(--('Bundle Assignment'!AE3:AE22=TRUE()),--('Patent Portfolio'!T3:T22="Yes"))/COUNTIF('Bundle Assignment'!AE3:AE22,TRUE()),0)) -> 0.5 | H30: =IF(Configuration!$C$38="No","",IFERROR(SUMPRODUCT(--('Bundle Assignment'!AE3:AE22=TRUE()),--('Patent Portfolio'!H3:H22>=2))/COUNTIF('Bundle Assignment'!AE3:AE22,TRUE()),0)) -> 0.375 | I30: =IF(Configuration!$C$38="No","",SUMPRODUCT(--('Bundle Assignment'!AE3:AE22=TRUE()),--('Patent Portfolio'!L3:L22=3))) -> 1 | J30: =IF(Configuration!$C$38="No","",IF(C30<2,"WEAK",IF(AND(C30>=Configuration!$C$59,D30>=Configuration!$C$60,E30>=Configuration!$C$61),"STRONG","MODERATE"))) -> MODERATE | K30: =IF(Configuration!$C$38="No","",IF(Configuration!$C$63="No","",IFERROR(aggregate(5,6,'Patent Portfolio'!AC3:AC22/('Bundle Assignment'!AE3:AE22=TRUE())),""))) | L30: =IF(Configuration!$C$38="No","",IF(Configuration!$C$64="No","",IFERROR(SUMPRODUCT(--('Bundle Assignment'!AE3:AE22=TRUE()),--('Patent Portfolio'!AD3:AD22<=1))/COUNTIF('Bundle Assignment'!AE3:AE22,TRUE()),0))) -> 0.125 | M30: =IF(Configuration!$C$38="No","",IF(Configuration!$C$65="No","",IFERROR(SUMPRODUCT(--('Bundle Assignment'!AE3:AE22=TRUE()),--('Patent Portfolio'!AK3:AK22<>"None"),--('Patent Portfolio'!AK3:AK22<>""))/COUNTIF('Bundle Assignment'!AE3:AE22,TRUE()),0))) -> 0.875 | N30: =IF(Configuration!$C$38="No","",IF(Configuration!$C$66="No","",IFERROR(SUMPRODUCT(--('Bundle Assignment'!AE3:AE22=TRUE()),--('Patent Portfolio'!AI3:AI22="Survived"))/COUNTIF('Bundle Assignment'!AE3:AE22,TRUE()),0))) -> 0.25 | O30: =IF(Configuration!$C$38="No","",IF(Configuration!$C$67="No","",IFERROR(SUMPRODUCT(--('Bundle Assignment'!AE3:AE22=TRUE()),--('Patent Portfolio'!T3:T22="Yes"))/COUNTIF('Bundle Assignment'!AE3:AE22,TRUE()),0))) -> 0.5
A31: 30 | B31: =IF(Configuration!$C$39="No","[DISABLED] Adjacent Re-Read","Adjacent Re-Read") -> Adjacent Re-Read | C31: =IF(Configuration!$C$39="No","",COUNTIF('Bundle Assignment'!AF3:AF22,TRUE())) -> 9 | D31: =IF(Configuration!$C$39="No","",IFERROR(SUMPRODUCT(--('Bundle Assignment'!AF3:AF22=TRUE()),('Patent Portfolio'!O3:O22+'Patent Portfolio'!P3:P22)/2)/COUNTIF('Bundle Assignment'!AF3:AF22,TRUE()),0)) -> 1.6666667 | E31: =IF(Configuration!$C$39="No","",IFERROR(SUMPRODUCT(--('Bundle Assignment'!AF3:AF22=TRUE()),'Patent Portfolio'!U3:U22)/COUNTIF('Bundle Assignment'!AF3:AF22,TRUE()),0)) -> 13.111111 | F31: =IF(Configuration!$C$39="No","",IFERROR(SUMPRODUCT(--('Bundle Assignment'!AF3:AF22=TRUE()),--('Patent Portfolio'!X3:X22="Yes"))/COUNTIF('Bundle Assignment'!AF3:AF22,TRUE()),0)) -> 0.77777778 | G31: =IF(Configuration!$C$39="No","",IFERROR(SUMPRODUCT(--('Bundle Assignment'!AF3:AF22=TRUE()),--('Patent Portfolio'!T3:T22="Yes"))/COUNTIF('Bundle Assignment'!AF3:AF22,TRUE()),0)) -> 0.44444444 | H31: =IF(Configuration!$C$39="No","",IFERROR(SUMPRODUCT(--('Bundle Assignment'!AF3:AF22=TRUE()),--('Patent Portfolio'!H3:H22>=2))/COUNTIF('Bundle Assignment'!AF3:AF22,TRUE()),0)) -> 0.22222222 | I31: =IF(Configuration!$C$39="No","",SUMPRODUCT(--('Bundle Assignment'!AF3:AF22=TRUE()),--('Patent Portfolio'!L3:L22=3))) -> 1 | J31: =IF(Configuration!$C$39="No","",IF(C31<2,"WEAK",IF(AND(C31>=Configuration!$C$59,D31>=Configuration!$C$60,E31>=Configuration!$C$61),"STRONG","MODERATE"))) -> MODERATE | K31: =IF(Configuration!$C$39="No","",IF(Configuration!$C$63="No","",IFERROR(aggregate(5,6,'Patent Portfolio'!AC3:AC22/('Bundle Assignment'!AF3:AF22=TRUE())),""))) | L31: =IF(Configuration!$C$39="No","",IF(Configuration!$C$64="No","",IFERROR(SUMPRODUCT(--('Bundle Assignment'!AF3:AF22=TRUE()),--('Patent Portfolio'!AD3:AD22<=1))/COUNTIF('Bundle Assignment'!AF3:AF22,TRUE()),0))) -> 0.33333333 | M31: =IF(Configuration!$C$39="No","",IF(Configuration!$C$65="No","",IFERROR(SUMPRODUCT(--('Bundle Assignment'!AF3:AF22=TRUE()),--('Patent Portfolio'!AK3:AK22<>"None"),--('Patent Portfolio'!AK3:AK22<>""))/COUNTIF('Bundle Assignment'!AF3:AF22,TRUE()),0))) -> 0.55555556 | N31: =IF(Configuration!$C$39="No","",IF(Configuration!$C$66="No","",IFERROR(SUMPRODUCT(--('Bundle Assignment'!AF3:AF22=TRUE()),--('Patent Portfolio'!AI3:AI22="Survived"))/COUNTIF('Bundle Assignment'!AF3:AF22,TRUE()),0))) -> 0.11111111 | O31: =IF(Configuration!$C$39="No","",IF(Configuration!$C$67="No","",IFERROR(SUMPRODUCT(--('Bundle Assignment'!AF3:AF22=TRUE()),--('Patent Portfolio'!T3:T22="Yes"))/COUNTIF('Bundle Assignment'!AF3:AF22,TRUE()),0))) -> 0.44444444
A32: 31 | B32: =IF(Configuration!$C$40="No","[DISABLED] Salvage / Volume Lot","Salvage / Volume Lot") -> Salvage / Volume Lot | C32: =IF(Configuration!$C$40="No","",COUNTIF('Bundle Assignment'!AG3:AG22,TRUE())) -> 11 | D32: =IF(Configuration!$C$40="No","",IFERROR(SUMPRODUCT(--('Bundle Assignment'!AG3:AG22=TRUE()),('Patent Portfolio'!O3:O22+'Patent Portfolio'!P3:P22)/2)/COUNTIF('Bundle Assignment'!AG3:AG22,TRUE()),0)) -> 0.31818182 | E32: =IF(Configuration!$C$40="No","",IFERROR(SUMPRODUCT(--('Bundle Assignment'!AG3:AG22=TRUE()),'Patent Portfolio'!U3:U22)/COUNTIF('Bundle Assignment'!AG3:AG22,TRUE()),0)) -> 3.8181818 | F32: =IF(Configuration!$C$40="No","",IFERROR(SUMPRODUCT(--('Bundle Assignment'!AG3:AG22=TRUE()),--('Patent Portfolio'!X3:X22="Yes"))/COUNTIF('Bundle Assignment'!AG3:AG22,TRUE()),0)) -> 0.090909091 | G32: =IF(Configuration!$C$40="No","",IFERROR(SUMPRODUCT(--('Bundle Assignment'!AG3:AG22=TRUE()),--('Patent Portfolio'!T3:T22="Yes"))/COUNTIF('Bundle Assignment'!AG3:AG22,TRUE()),0)) -> 0.18181818 | H32: =IF(Configuration!$C$40="No","",IFERROR(SUMPRODUCT(--('Bundle Assignment'!AG3:AG22=TRUE()),--('Patent Portfolio'!H3:H22>=2))/COUNTIF('Bundle Assignment'!AG3:AG22,TRUE()),0)) -> 0 | I32: =IF(Configuration!$C$40="No","",SUMPRODUCT(--('Bundle Assignment'!AG3:AG22=TRUE()),--('Patent Portfolio'!L3:L22=3))) -> 0 | J32: =IF(Configuration!$C$40="No","",IF(C32<2,"WEAK",IF(AND(C32>=Configuration!$C$59,D32>=Configuration!$C$60,E32>=Configuration!$C$61),"STRONG","MODERATE"))) -> MODERATE | K32: =IF(Configuration!$C$40="No","",IF(Configuration!$C$63="No","",IFERROR(aggregate(5,6,'Patent Portfolio'!AC3:AC22/('Bundle Assignment'!AG3:AG22=TRUE())),""))) | L32: =IF(Configuration!$C$40="No","",IF(Configuration!$C$64="No","",IFERROR(SUMPRODUCT(--('Bundle Assignment'!AG3:AG22=TRUE()),--('Patent Portfolio'!AD3:AD22<=1))/COUNTIF('Bundle Assignment'!AG3:AG22,TRUE()),0))) -> 1 | M32: =IF(Configuration!$C$40="No","",IF(Configuration!$C$65="No","",IFERROR(SUMPRODUCT(--('Bundle Assignment'!AG3:AG22=TRUE()),--('Patent Portfolio'!AK3:AK22<>"None"),--('Patent Portfolio'!AK3:AK22<>""))/COUNTIF('Bundle Assignment'!AG3:AG22,TRUE()),0))) -> 0.090909091 | N32: =IF(Configuration!$C$40="No","",IF(Configuration!$C$66="No","",IFERROR(SUMPRODUCT(--('Bundle Assignment'!AG3:AG22=TRUE()),--('Patent Portfolio'!AI3:AI22="Survived"))/COUNTIF('Bundle Assignment'!AG3:AG22,TRUE()),0))) -> 0 | O32: =IF(Configuration!$C$40="No","",IF(Configuration!$C$67="No","",IFERROR(SUMPRODUCT(--('Bundle Assignment'!AG3:AG22=TRUE()),--('Patent Portfolio'!T3:T22="Yes"))/COUNTIF('Bundle Assignment'!AG3:AG22,TRUE()),0))) -> 0.18181818
